Workbook

Sheet journals
C1: eco_bus | F1: eco | H1: fin | J1: bus | L1: man
A2: journal | B2: publisher | C2: pub | D2: score | E2: rank | F2: score | G2: rank | H2: score | I2: rank | J2: score | K2: rank | L2: score | M2: rank | N2: wc1 | O2: wc2 | P2: wc3 | Q2: wc4 | R2: wc5 | S2: wc6
A3: QUARTERLY JOURNAL OF ECONOMICS | B3: OXFORD UNIV PRESS INC | C3: =IFERROR(VLOOKUP(A3,[1]eco_bus_journals!$B:$D,3,0),"") -> 40 | D3: =IFERROR(ROUND(VLOOKUP(A3,[1]eco_bus_journals!$B:$X,4,0),2),"") -> 10 | E3: =_xlfn.RANK.EQ(D3,D:D) -> 1 | F3: =IFERROR(ROUND(VLOOKUP(A3,[1]eco_journals!B:E,4,0),2),"") -> 10 | G3: =IFERROR(_xlfn.RANK.EQ(F3,F:F),"") -> 1 | H3: =IFERROR(ROUND(VLOOKUP(A3,[1]fin_journals!B:E,4,0),2),"") | I3: =IFERROR(_xlfn.RANK.EQ(H3,H:H),"") | J3: =IFERROR(ROUND(VLOOKUP(A3,[1]bus_journals!B:E,4,0),2),"") | K3: =IFERROR(_xlfn.RANK.EQ(J3,J:J),"") | L3: =IFERROR(ROUND(VLOOKUP(A3,[1]man_journals!B:E,4,0),2),"") | M3: =IFERROR(_xlfn.RANK.EQ(L3,L:L),"") | N3: ECONOMICS
A4: AMERICAN ECONOMIC REVIEW | B4: AMER ECONOMIC ASSOC | C4: =IFERROR(VLOOKUP(A4,[1]eco_bus_journals!$B:$D,3,0),"") -> 116 | D4: =IFERROR(ROUND(VLOOKUP(A4,[1]eco_bus_journals!$B:$X,4,0),2),"") -> 6.51 | E4: =_xlfn.RANK.EQ(D4,D:D) -> 2 | F4: =IFERROR(ROUND(VLOOKUP(A4,[1]eco_journals!B:E,4,0),2),"") -> 6.48 | G4: =IFERROR(_xlfn.RANK.EQ(F4,F:F),"") -> 2 | H4: =IFERROR(ROUND(VLOOKUP(A4,[1]fin_journals!B:E,4,0),2),"") | I4: =IFERROR(_xlfn.RANK.EQ(H4,H:H),"") | J4: =IFERROR(ROUND(VLOOKUP(A4,[1]bus_journals!B:E,4,0),2),"") | K4: =IFERROR(_xlfn.RANK.EQ(J4,J:J),"") | L4: =IFERROR(ROUND(VLOOKUP(A4,[1]man_journals!B:E,4,0),2),"") | M4: =IFERROR(_xlfn.RANK.EQ(L4,L:L),"") | N4: ECONOMICS
A5: JOURNAL OF POLITICAL ECONOMY | B5: UNIV CHICAGO PRESS | C5: =IFERROR(VLOOKUP(A5,[1]eco_bus_journals!$B:$D,3,0),"") -> 110 | D5: =IFERROR(ROUND(VLOOKUP(A5,[1]eco_bus_journals!$B:$X,4,0),2),"") -> 4.65 | E5: =_xlfn.RANK.EQ(D5,D:D) -> 4 | F5: =IFERROR(ROUND(VLOOKUP(A5,[1]eco_journals!B:E,4,0),2),"") -> 4.67 | G5: =IFERROR(_xlfn.RANK.EQ(F5,F:F),"") -> 3 | H5: =IFERROR(ROUND(VLOOKUP(A5,[1]fin_journals!B:E,4,0),2),"") | I5: =IFERROR(_xlfn.RANK.EQ(H5,H:H),"") | J5: =IFERROR(ROUND(VLOOKUP(A5,[1]bus_journals!B:E,4,0),2),"") | K5: =IFERROR(_xlfn.RANK.EQ(J5,J:J),"") | L5: =IFERROR(ROUND(VLOOKUP(A5,[1]man_journals!B:E,4,0),2),"") | M5: =IFERROR(_xlfn.RANK.EQ(L5,L:L),"") | N5: ECONOMICS
A6: REVIEW OF ECONOMIC STUDIES | B6: OXFORD UNIV PRESS | C6: =IFERROR(VLOOKUP(A6,[1]eco_bus_journals!$B:$D,3,0),"") -> 80 | D6: =IFERROR(ROUND(VLOOKUP(A6,[1]eco_bus_journals!$B:$X,4,0),2),"") -> 4.32 | E6: =_xlfn.RANK.EQ(D6,D:D) -> 6 | F6: =IFERROR(ROUND(VLOOKUP(A6,[1]eco_journals!B:E,4,0),2),"") -> 4.38 | G6: =IFERROR(_xlfn.RANK.EQ(F6,F:F),"") -> 4 | H6: =IFERROR(ROUND(VLOOKUP(A6,[1]fin_journals!B:E,4,0),2),"") | I6: =IFERROR(_xlfn.RANK.EQ(H6,H:H),"") | J6: =IFERROR(ROUND(VLOOKUP(A6,[1]bus_journals!B:E,4,0),2),"") | K6: =IFERROR(_xlfn.RANK.EQ(J6,J:J),"") | L6: =IFERROR(ROUND(VLOOKUP(A6,[1]man_journals!B:E,4,0),2),"") | M6: =IFERROR(_xlfn.RANK.EQ(L6,L:L),"") | N6: ECONOMICS
A7: ECONOMETRICA | B7: WILEY | C7: =IFERROR(VLOOKUP(A7,[1]eco_bus_journals!$B:$D,3,0),"") -> 76 | D7: =IFERROR(ROUND(VLOOKUP(A7,[1]eco_bus_journals!$B:$X,4,0),2),"") -> 4.53 | E7: =_xlfn.RANK.EQ(D7,D:D) -> 5 | F7: =IFERROR(ROUND(VLOOKUP(A7,[1]eco_journals!B:E,4,0),2),"") -> 4.38 | G7: =IFERROR(_xlfn.RANK.EQ(F7,F:F),"") -> 4 | H7: =IFERROR(ROUND(VLOOKUP(A7,[1]fin_journals!B:E,4,0),2),"") | I7: =IFERROR(_xlfn.RANK.EQ(H7,H:H),"") | J7: =IFERROR(ROUND(VLOOKUP(A7,[1]bus_journals!B:E,4,0),2),"") | K7: =IFERROR(_xlfn.RANK.EQ(J7,J:J),"") | L7: =IFERROR(ROUND(VLOOKUP(A7,[1]man_journals!B:E,4,0),2),"") | M7: =IFERROR(_xlfn.RANK.EQ(L7,L:L),"") | N7: ECONOMICS | O7: MATHEMATICS, INTERDISCIPLINARY APPLICATIONS | P7: SOCIAL SCIENCES, MATHEMATICAL METHODS | Q7: STATISTICS & PROBABILITY
A8: NBER MACROECONOMICS ANNUAL | B8: UNIV CHICAGO PRESS | C8: =IFERROR(VLOOKUP(A8,[1]eco_bus_journals!$B:$D,3,0),"") -> 7 | D8: =IFERROR(ROUND(VLOOKUP(A8,[1]eco_bus_journals!$B:$X,4,0),2),"") -> 4.25 | E8: =_xlfn.RANK.EQ(D8,D:D) -> 7 | F8: =IFERROR(ROUND(VLOOKUP(A8,[1]eco_journals!B:E,4,0),2),"") -> 4.36 | G8: =IFERROR(_xlfn.RANK.EQ(F8,F:F),"") -> 6 | H8: =IFERROR(ROUND(VLOOKUP(A8,[1]fin_journals!B:E,4,0),2),"") | I8: =IFERROR(_xlfn.RANK.EQ(H8,H:H),"") | J8: =IFERROR(ROUND(VLOOKUP(A8,[1]bus_journals!B:E,4,0),2),"") | K8: =IFERROR(_xlfn.RANK.EQ(J8,J:J),"") | L8: =IFERROR(ROUND(VLOOKUP(A8,[1]man_journals!B:E,4,0),2),"") | M8: =IFERROR(_xlfn.RANK.EQ(L8,L:L),"") | N8: ECONOMICS
A9: ACADEMY OF MANAGEMENT ANNALS | B9: ACAD MANAGEMENT | C9: =IFERROR(VLOOKUP(A9,[1]eco_bus_journals!$B:$D,3,0),"") -> 31 | D9: =IFERROR(ROUND(VLOOKUP(A9,[1]eco_bus_journals!$B:$X,4,0),2),"") -> 4.71 | E9: =_xlfn.RANK.EQ(D9,D:D) -> 3 | F9: =IFERROR(ROUND(VLOOKUP(A9,[1]eco_journals!B:E,4,0),2),"") | G9: =IFERROR(_xlfn.RANK.EQ(F9,F:F),"") | H9: =IFERROR(ROUND(VLOOKUP(A9,[1]fin_journals!B:E,4,0),2),"") | I9: =IFERROR(_xlfn.RANK.EQ(H9,H:H),"") | J9: =IFERROR(ROUND(VLOOKUP(A9,[1]bus_journals!B:E,4,0),2),"") -> 10 | K9: =IFERROR(_xlfn.RANK.EQ(J9,J:J),"") -> 1 | L9: =IFERROR(ROUND(VLOOKUP(A9,[1]man_journals!B:E,4,0),2),"") -> 10 | M9: =IFERROR(_xlfn.RANK.EQ(L9,L:L),"") -> 1 | N9: BUSINESS | O9: MANAGEMENT
A10: JOURNAL OF FINANCE | B10: WILEY | C10: =IFERROR(VLOOKUP(A10,[1]eco_bus_journals!$B:$D,3,0),"") -> 73 | D10: =IFERROR(ROUND(VLOOKUP(A10,[1]eco_bus_journals!$B:$X,4,0),2),"") -> 3.84 | E10: =_xlfn.RANK.EQ(D10,D:D) -> 9 | F10: =IFERROR(ROUND(VLOOKUP(A10,[1]eco_journals!B:E,4,0),2),"") -> 3.01 | G10: =IFERROR(_xlfn.RANK.EQ(F10,F:F),"") -> 11 | H10: =IFERROR(ROUND(VLOOKUP(A10,[1]fin_journals!B:E,4,0),2),"") -> 10 | I10: =IFERROR(_xlfn.RANK.EQ(H10,H:H),"") -> 1 | J10: =IFERROR(ROUND(VLOOKUP(A10,[1]bus_journals!B:E,4,0),2),"") | K10: =IFERROR(_xlfn.RANK.EQ(J10,J:J),"") | L10: =IFERROR(ROUND(VLOOKUP(A10,[1]man_journals!B:E,4,0),2),"") | M10: =IFERROR(_xlfn.RANK.EQ(L10,L:L),"") | N10: FINANCE | O10: ECONOMICS
A11: JOURNAL OF ECONOMIC LITERATURE | B11: AMER ECONOMIC ASSOC | C11: =IFERROR(VLOOKUP(A11,[1]eco_bus_journals!$B:$D,3,0),"") -> 16 | D11: =IFERROR(ROUND(VLOOKUP(A11,[1]eco_bus_journals!$B:$X,4,0),2),"") -> 4.14 | E11: =_xlfn.RANK.EQ(D11,D:D) -> 8 | F11: =IFERROR(ROUND(VLOOKUP(A11,[1]eco_journals!B:E,4,0),2),"") -> 4.1 | G11: =IFERROR(_xlfn.RANK.EQ(F11,F:F),"") -> 7 | H11: =IFERROR(ROUND(VLOOKUP(A11,[1]fin_journals!B:E,4,0),2),"") | I11: =IFERROR(_xlfn.RANK.EQ(H11,H:H),"") | J11: =IFERROR(ROUND(VLOOKUP(A11,[1]bus_journals!B:E,4,0),2),"") | K11: =IFERROR(_xlfn.RANK.EQ(J11,J:J),"") | L11: =IFERROR(ROUND(VLOOKUP(A11,[1]man_journals!B:E,4,0),2),"") | M11: =IFERROR(_xlfn.RANK.EQ(L11,L:L),"") | N11: ECONOMICS
A12: AMERICAN ECONOMIC REVIEW-INSIGHTS | B12: AMER ECONOMIC ASSOC | C12: =IFERROR(VLOOKUP(A12,[1]eco_bus_journals!$B:$D,3,0),"") -> 32 | D12: =IFERROR(ROUND(VLOOKUP(A12,[1]eco_bus_journals!$B:$X,4,0),2),"") -> 3.72 | E12: =_xlfn.RANK.EQ(D12,D:D) -> 10 | F12: =IFERROR(ROUND(VLOOKUP(A12,[1]eco_journals!B:E,4,0),2),"") -> 3.72 | G12: =IFERROR(_xlfn.RANK.EQ(F12,F:F),"") -> 8 | H12: =IFERROR(ROUND(VLOOKUP(A12,[1]fin_journals!B:E,4,0),2),"") | I12: =IFERROR(_xlfn.RANK.EQ(H12,H:H),"") | J12: =IFERROR(ROUND(VLOOKUP(A12,[1]bus_journals!B:E,4,0),2),"") | K12: =IFERROR(_xlfn.RANK.EQ(J12,J:J),"") | L12: =IFERROR(ROUND(VLOOKUP(A12,[1]man_journals!B:E,4,0),2),"") | M12: =IFERROR(_xlfn.RANK.EQ(L12,L:L),"") | N12: ECONOMICS
A13: BROOKINGS PAPERS ON ECONOMIC ACTIVITY | B13: JOHNS HOPKINS UNIV PRESS | C13: =IFERROR(VLOOKUP(A13,[1]eco_bus_journals!$B:$D,3,0),"") -> 24 | D13: =IFERROR(ROUND(VLOOKUP(A13,[1]eco_bus_journals!$B:$X,4,0),2),"") -> 3.63 | E13: =_xlfn.RANK.EQ(D13,D:D) -> 12 | F13: =IFERROR(ROUND(VLOOKUP(A13,[1]eco_journals!B:E,4,0),2),"") -> 3.69 | G13: =IFERROR(_xlfn.RANK.EQ(F13,F:F),"") -> 9 | H13: =IFERROR(ROUND(VLOOKUP(A13,[1]fin_journals!B:E,4,0),2),"") | I13: =IFERROR(_xlfn.RANK.EQ(H13,H:H),"") | J13: =IFERROR(ROUND(VLOOKUP(A13,[1]bus_journals!B:E,4,0),2),"") | K13: =IFERROR(_xlfn.RANK.EQ(J13,J:J),"") | L13: =IFERROR(ROUND(VLOOKUP(A13,[1]man_journals!B:E,4,0),2),"") | M13: =IFERROR(_xlfn.RANK.EQ(L13,L:L),"") | N13: ECONOMICS
A14: REVIEW OF FINANCIAL STUDIES | B14: OXFORD UNIV PRESS INC | C14: =IFERROR(VLOOKUP(A14,[1]eco_bus_journals!$B:$D,3,0),"") -> 141 | D14: =IFERROR(ROUND(VLOOKUP(A14,[1]eco_bus_journals!$B:$X,4,0),2),"") -> 3.16 | E14: =_xlfn.RANK.EQ(D14,D:D) -> 13 | F14: =IFERROR(ROUND(VLOOKUP(A14,[1]eco_journals!B:E,4,0),2),"") -> 2.23 | G14: =IFERROR(_xlfn.RANK.EQ(F14,F:F),"") -> 18 | H14: =IFERROR(ROUND(VLOOKUP(A14,[1]fin_journals!B:E,4,0),2),"") -> 9.15 | I14: =IFERROR(_xlfn.RANK.EQ(H14,H:H),"") -> 3 | J14: =IFERROR(ROUND(VLOOKUP(A14,[1]bus_journals!B:E,4,0),2),"") | K14: =IFERROR(_xlfn.RANK.EQ(J14,J:J),"") | L14: =IFERROR(ROUND(VLOOKUP(A14,[1]man_journals!B:E,4,0),2),"") | M14: =IFERROR(_xlfn.RANK.EQ(L14,L:L),"") | N14: FINANCE | O14: ECONOMICS
A15: ADMINISTRATIVE SCIENCE QUARTERLY | B15: SAGE PUBLICATIONS | C15: =IFERROR(VLOOKUP(A15,[1]eco_bus_journals!$B:$D,3,0),"") -> 39 | D15: =IFERROR(ROUND(VLOOKUP(A15,[1]eco_bus_journals!$B:$X,4,0),2),"") -> 3.66 | E15: =_xlfn.RANK.EQ(D15,D:D) -> 11 | F15: =IFERROR(ROUND(VLOOKUP(A15,[1]eco_journals!B:E,4,0),2),"") | G15: =IFERROR(_xlfn.RANK.EQ(F15,F:F),"") | H15: =IFERROR(ROUND(VLOOKUP(A15,[1]fin_journals!B:E,4,0),2),"") | I15: =IFERROR(_xlfn.RANK.EQ(H15,H:H),"") | J15: =IFERROR(ROUND(VLOOKUP(A15,[1]bus_journals!B:E,4,0),2),"") -> 8.4 | K15: =IFERROR(_xlfn.RANK.EQ(J15,J:J),"") -> 3 | L15: =IFERROR(ROUND(VLOOKUP(A15,[1]man_journals!B:E,4,0),2),"") -> 7.8 | M15: =IFERROR(_xlfn.RANK.EQ(L15,L:L),"") -> 2 | N15: BUSINESS | O15: MANAGEMENT
A16: AMERICAN ECONOMIC JOURNAL-APPLIED ECONOMICS | B16: AMER ECONOMIC ASSOC | C16: =IFERROR(VLOOKUP(A16,[1]eco_bus_journals!$B:$D,3,0),"") -> 43 | D16: =IFERROR(ROUND(VLOOKUP(A16,[1]eco_bus_journals!$B:$X,4,0),2),"") -> 3.11 | E16: =_xlfn.RANK.EQ(D16,D:D) -> 14 | F16: =IFERROR(ROUND(VLOOKUP(A16,[1]eco_journals!B:E,4,0),2),"") -> 3.22 | G16: =IFERROR(_xlfn.RANK.EQ(F16,F:F),"") -> 10 | H16: =IFERROR(ROUND(VLOOKUP(A16,[1]fin_journals!B:E,4,0),2),"") | I16: =IFERROR(_xlfn.RANK.EQ(H16,H:H),"") | J16: =IFERROR(ROUND(VLOOKUP(A16,[1]bus_journals!B:E,4,0),2),"") | K16: =IFERROR(_xlfn.RANK.EQ(J16,J:J),"") | L16: =IFERROR(ROUND(VLOOKUP(A16,[1]man_journals!B:E,4,0),2),"") | M16: =IFERROR(_xlfn.RANK.EQ(L16,L:L),"") | N16: ECONOMICS
A17: AMERICAN ECONOMIC JOURNAL-MACROECONOMICS | B17: AMER ECONOMIC ASSOC | C17: =IFERROR(VLOOKUP(A17,[1]eco_bus_journals!$B:$D,3,0),"") -> 38 | D17: =IFERROR(ROUND(VLOOKUP(A17,[1]eco_bus_journals!$B:$X,4,0),2),"") -> 2.8 | E17: =_xlfn.RANK.EQ(D17,D:D) -> 17 | F17: =IFERROR(ROUND(VLOOKUP(A17,[1]eco_journals!B:E,4,0),2),"") -> 2.91 | G17: =IFERROR(_xlfn.RANK.EQ(F17,F:F),"") -> 12 | H17: =IFERROR(ROUND(VLOOKUP(A17,[1]fin_journals!B:E,4,0),2),"") | I17: =IFERROR(_xlfn.RANK.EQ(H17,H:H),"") | J17: =IFERROR(ROUND(VLOOKUP(A17,[1]bus_journals!B:E,4,0),2),"") | K17: =IFERROR(_xlfn.RANK.EQ(J17,J:J),"") | L17: =IFERROR(ROUND(VLOOKUP(A17,[1]man_journals!B:E,4,0),2),"") | M17: =IFERROR(_xlfn.RANK.EQ(L17,L:L),"") | N17: ECONOMICS
A18: JOURNAL OF LABOR ECONOMICS | B18: UNIV CHICAGO PRESS | C18: =IFERROR(VLOOKUP(A18,[1]eco_bus_journals!$B:$D,3,0),"") -> 32 | D18: =IFERROR(ROUND(VLOOKUP(A18,[1]eco_bus_journals!$B:$X,4,0),2),"") -> 2.96 | E18: =_xlfn.RANK.EQ(D18,D:D) -> 15 | F18: =IFERROR(ROUND(VLOOKUP(A18,[1]eco_journals!B:E,4,0),2),"") -> 2.9 | G18: =IFERROR(_xlfn.RANK.EQ(F18,F:F),"") -> 13 | H18: =IFERROR(ROUND(VLOOKUP(A18,[1]fin_journals!B:E,4,0),2),"") | I18: =IFERROR(_xlfn.RANK.EQ(H18,H:H),"") | J18: =IFERROR(ROUND(VLOOKUP(A18,[1]bus_journals!B:E,4,0),2),"") | K18: =IFERROR(_xlfn.RANK.EQ(J18,J:J),"") | L18: =IFERROR(ROUND(VLOOKUP(A18,[1]man_journals!B:E,4,0),2),"") | M18: =IFERROR(_xlfn.RANK.EQ(L18,L:L),"") | N18: ECONOMICS | O18: INDUSTRIAL RELATIONS & LABOR
A19: JOURNAL OF FINANCIAL ECONOMICS | B19: ELSEVIER | C19: =IFERROR(VLOOKUP(A19,[1]eco_bus_journals!$B:$D,3,0),"") -> 152 | D19: =IFERROR(ROUND(VLOOKUP(A19,[1]eco_bus_journals!$B:$X,4,0),2),"") -> 2.65 | E19: =_xlfn.RANK.EQ(D19,D:D) -> 20 | F19: =IFERROR(ROUND(VLOOKUP(A19,[1]eco_journals!B:E,4,0),2),"") -> 1.77 | G19: =IFERROR(_xlfn.RANK.EQ(F19,F:F),"") -> 20 | H19: =IFERROR(ROUND(VLOOKUP(A19,[1]fin_journals!B:E,4,0),2),"") -> 7.81 | I19: =IFERROR(_xlfn.RANK.EQ(H19,H:H),"") -> 5 | J19: =IFERROR(ROUND(VLOOKUP(A19,[1]bus_journals!B:E,4,0),2),"") | K19: =IFERROR(_xlfn.RANK.EQ(J19,J:J),"") | L19: =IFERROR(ROUND(VLOOKUP(A19,[1]man_journals!B:E,4,0),2),"") | M19: =IFERROR(_xlfn.RANK.EQ(L19,L:L),"") | N19: FINANCE | O19: ECONOMICS
A20: JOURNAL OF MARKETING | B20: SAGE PUBLICATIONS | C20: =IFERROR(VLOOKUP(A20,[1]eco_bus_journals!$B:$D,3,0),"") -> 65 | D20: =IFERROR(ROUND(VLOOKUP(A20,[1]eco_bus_journals!$B:$X,4,0),2),"") -> 2.72 | E20: =_xlfn.RANK.EQ(D20,D:D) -> 18 | F20: =IFERROR(ROUND(VLOOKUP(A20,[1]eco_journals!B:E,4,0),2),"") | G20: =IFERROR(_xlfn.RANK.EQ(F20,F:F),"") | H20: =IFERROR(ROUND(VLOOKUP(A20,[1]fin_journals!B:E,4,0),2),"") | I20: =IFERROR(_xlfn.RANK.EQ(H20,H:H),"") | J20: =IFERROR(ROUND(VLOOKUP(A20,[1]bus_journals!B:E,4,0),2),"") -> 9.17 | K20: =IFERROR(_xlfn.RANK.EQ(J20,J:J),"") -> 2 | L20: =IFERROR(ROUND(VLOOKUP(A20,[1]man_journals!B:E,4,0),2),"") | M20: =IFERROR(_xlfn.RANK.EQ(L20,L:L),"") | N20: BUSINESS
A21: JOURNAL OF ECONOMIC PERSPECTIVES | B21: AMER ECONOMIC ASSOC | C21: =IFERROR(VLOOKUP(A21,[1]eco_bus_journals!$B:$D,3,0),"") -> 41 | D21: =IFERROR(ROUND(VLOOKUP(A21,[1]eco_bus_journals!$B:$X,4,0),2),"") -> 2.81 | E21: =_xlfn.RANK.EQ(D21,D:D) -> 16 | F21: =IFERROR(ROUND(VLOOKUP(A21,[1]eco_journals!B:E,4,0),2),"") -> 2.67 | G21: =IFERROR(_xlfn.RANK.EQ(F21,F:F),"") -> 14 | H21: =IFERROR(ROUND(VLOOKUP(A21,[1]fin_journals!B:E,4,0),2),"") | I21: =IFERROR(_xlfn.RANK.EQ(H21,H:H),"") | J21: =IFERROR(ROUND(VLOOKUP(A21,[1]bus_journals!B:E,4,0),2),"") | K21: =IFERROR(_xlfn.RANK.EQ(J21,J:J),"") | L21: =IFERROR(ROUND(VLOOKUP(A21,[1]man_journals!B:E,4,0),2),"") | M21: =IFERROR(_xlfn.RANK.EQ(L21,L:L),"") | N21: ECONOMICS
A22: REVIEW OF ECONOMICS AND STATISTICS | B22: MIT PRESS | C22: =IFERROR(VLOOKUP(A22,[1]eco_bus_journals!$B:$D,3,0),"") -> 65 | D22: =IFERROR(ROUND(VLOOKUP(A22,[1]eco_bus_journals!$B:$X,4,0),2),"") -> 2.68 | E22: =_xlfn.RANK.EQ(D22,D:D) -> 19 | F22: =IFERROR(ROUND(VLOOKUP(A22,[1]eco_journals!B:E,4,0),2),"") -> 2.65 | G22: =IFERROR(_xlfn.RANK.EQ(F22,F:F),"") -> 15 | H22: =IFERROR(ROUND(VLOOKUP(A22,[1]fin_journals!B:E,4,0),2),"") | I22: =IFERROR(_xlfn.RANK.EQ(H22,H:H),"") | J22: =IFERROR(ROUND(VLOOKUP(A22,[1]bus_journals!B:E,4,0),2),"") | K22: =IFERROR(_xlfn.RANK.EQ(J22,J:J),"") | L22: =IFERROR(ROUND(VLOOKUP(A22,[1]man_journals!B:E,4,0),2),"") | M22: =IFERROR(_xlfn.RANK.EQ(L22,L:L),"") | N22: ECONOMICS | O22: SOCIAL SCIENCES, MATHEMATICAL METHODS
A23: AMERICAN ECONOMIC JOURNAL-ECONOMIC POLICY | B23: AMER ECONOMIC ASSOC | C23: =IFERROR(VLOOKUP(A23,[1]eco_bus_journals!$B:$D,3,0),"") -> 51 | D23: =IFERROR(ROUND(VLOOKUP(A23,[1]eco_bus_journals!$B:$X,4,0),2),"") -> 2.6 | E23: =_xlfn.RANK.EQ(D23,D:D) -> 21 | F23: =IFERROR(ROUND(VLOOKUP(A23,[1]eco_journals!B:E,4,0),2),"") -> 2.58 | G23: =IFERROR(_xlfn.RANK.EQ(F23,F:F),"") -> 16 | H23: =IFERROR(ROUND(VLOOKUP(A23,[1]fin_journals!B:E,4,0),2),"") | I23: =IFERROR(_xlfn.RANK.EQ(H23,H:H),"") | J23: =IFERROR(ROUND(VLOOKUP(A23,[1]bus_journals!B:E,4,0),2),"") | K23: =IFERROR(_xlfn.RANK.EQ(J23,J:J),"") | L23: =IFERROR(ROUND(VLOOKUP(A23,[1]man_journals!B:E,4,0),2),"") | M23: =IFERROR(_xlfn.RANK.EQ(L23,L:L),"") | N23: ECONOMICS
A24: ANNUAL REVIEW OF ECONOMICS | B24: ANNUAL REVIEWS | C24: =IFERROR(VLOOKUP(A24,[1]eco_bus_journals!$B:$D,3,0),"") -> 31 | D24: =IFERROR(ROUND(VLOOKUP(A24,[1]eco_bus_journals!$B:$X,4,0),2),"") -> 2.48 | E24: =_xlfn.RANK.EQ(D24,D:D) -> 23 | F24: =IFERROR(ROUND(VLOOKUP(A24,[1]eco_journals!B:E,4,0),2),"") -> 2.52 | G24: =IFERROR(_xlfn.RANK.EQ(F24,F:F),"") -> 17 | H24: =IFERROR(ROUND(VLOOKUP(A24,[1]fin_journals!B:E,4,0),2),"") | I24: =IFERROR(_xlfn.RANK.EQ(H24,H:H),"") | J24: =IFERROR(ROUND(VLOOKUP(A24,[1]bus_journals!B:E,4,0),2),"") | K24: =IFERROR(_xlfn.RANK.EQ(J24,J:J),"") | L24: =IFERROR(ROUND(VLOOKUP(A24,[1]man_journals!B:E,4,0),2),"") | M24: =IFERROR(_xlfn.RANK.EQ(L24,L:L),"") | N24: ECONOMICS
A25: ACADEMY OF MANAGEMENT JOURNAL | B25: ACAD MANAGEMENT | C25: =IFERROR(VLOOKUP(A25,[1]eco_bus_journals!$B:$D,3,0),"") -> 71 | D25: =IFERROR(ROUND(VLOOKUP(A25,[1]eco_bus_journals!$B:$X,4,0),2),"") -> 2.49 | E25: =_xlfn.RANK.EQ(D25,D:D) -> 22 | F25: =IFERROR(ROUND(VLOOKUP(A25,[1]eco_journals!B:E,4,0),2),"") | G25: =IFERROR(_xlfn.RANK.EQ(F25,F:F),"") | H25: =IFERROR(ROUND(VLOOKUP(A25,[1]fin_journals!B:E,4,0),2),"") | I25: =IFERROR(_xlfn.RANK.EQ(H25,H:H),"") | J25: =IFERROR(ROUND(VLOOKUP(A25,[1]bus_journals!B:E,4,0),2),"") -> 5.72 | K25: =IFERROR(_xlfn.RANK.EQ(J25,J:J),"") -> 5 | L25: =IFERROR(ROUND(VLOOKUP(A25,[1]man_journals!B:E,4,0),2),"") -> 5.22 | M25: =IFERROR(_xlfn.RANK.EQ(L25,L:L),"") -> 3 | N25: BUSINESS | O25: MANAGEMENT
A26: JOURNAL OF ACCOUNTING & ECONOMICS | B26: ELSEVIER | C26: =IFERROR(VLOOKUP(A26,[1]eco_bus_journals!$B:$D,3,0),"") -> 35 | D26: =IFERROR(ROUND(VLOOKUP(A26,[1]eco_bus_journals!$B:$X,4,0),2),"") -> 2.39 | E26: =_xlfn.RANK.EQ(D26,D:D) -> 24 | F26: =IFERROR(ROUND(VLOOKUP(A26,[1]eco_journals!B:E,4,0),2),"") -> 0.85 | G26: =IFERROR(_xlfn.RANK.EQ(F26,F:F),"") -> 38 | H26: =IFERROR(ROUND(VLOOKUP(A26,[1]fin_journals!B:E,4,0),2),"") -> 9.36 | I26: =IFERROR(_xlfn.RANK.EQ(H26,H:H),"") -> 2 | J26: =IFERROR(ROUND(VLOOKUP(A26,[1]bus_journals!B:E,4,0),2),"") | K26: =IFERROR(_xlfn.RANK.EQ(J26,J:J),"") | L26: =IFERROR(ROUND(VLOOKUP(A26,[1]man_journals!B:E,4,0),2),"") | M26: =IFERROR(_xlfn.RANK.EQ(L26,L:L),"") | N26: FINANCE | O26: ECONOMICS
A27: JOURNAL OF PUBLIC ECONOMICS | B27: ELSEVIER | C27: =IFERROR(VLOOKUP(A27,[1]eco_bus_journals!$B:$D,3,0),"") -> 133 | D27: =IFERROR(ROUND(VLOOKUP(A27,[1]eco_bus_journals!$B:$X,4,0),2),"") -> 2.16 | E27: =_xlfn.RANK.EQ(D27,D:D) -> 25 | F27: =IFERROR(ROUND(VLOOKUP(A27,[1]eco_journals!B:E,4,0),2),"") -> 2.16 | G27: =IFERROR(_xlfn.RANK.EQ(F27,F:F),"") -> 19 | H27: =IFERROR(ROUND(VLOOKUP(A27,[1]fin_journals!B:E,4,0),2),"") | I27: =IFERROR(_xlfn.RANK.EQ(H27,H:H),"") | J27: =IFERROR(ROUND(VLOOKUP(A27,[1]bus_journals!B:E,4,0),2),"") | K27: =IFERROR(_xlfn.RANK.EQ(J27,J:J),"") | L27: =IFERROR(ROUND(VLOOKUP(A27,[1]man_journals!B:E,4,0),2),"") | M27: =IFERROR(_xlfn.RANK.EQ(L27,L:L),"") | N27: ECONOMICS
A28: JOURNAL OF ACCOUNTING RESEARCH | B28: WILEY | C28: =IFERROR(VLOOKUP(A28,[1]eco_bus_journals!$B:$D,3,0),"") -> 34 | D28: =IFERROR(ROUND(VLOOKUP(A28,[1]eco_bus_journals!$B:$X,4,0),2),"") -> 2.16 | E28: =_xlfn.RANK.EQ(D28,D:D) -> 25 | F28: =IFERROR(ROUND(VLOOKUP(A28,[1]eco_journals!B:E,4,0),2),"") | G28: =IFERROR(_xlfn.RANK.EQ(F28,F:F),"") | H28: =IFERROR(ROUND(VLOOKUP(A28,[1]fin_journals!B:E,4,0),2),"") -> 8.64 | I28: =IFERROR(_xlfn.RANK.EQ(H28,H:H),"") -> 4 | J28: =IFERROR(ROUND(VLOOKUP(A28,[1]bus_journals!B:E,4,0),2),"") | K28: =IFERROR(_xlfn.RANK.EQ(J28,J:J),"") | L28: =IFERROR(ROUND(VLOOKUP(A28,[1]man_journals!B:E,4,0),2),"") | M28: =IFERROR(_xlfn.RANK.EQ(L28,L:L),"") | N28: FINANCE
A29: ACADEMY OF MANAGEMENT REVIEW | B29: ACAD MANAGEMENT | C29: =IFERROR(VLOOKUP(A29,[1]eco_bus_journals!$B:$D,3,0),"") -> 40 | D29: =IFERROR(ROUND(VLOOKUP(A29,[1]eco_bus_journals!$B:$X,4,0),2),"") -> 2.1 | E29: =_xlfn.RANK.EQ(D29,D:D) -> 27 | F29: =IFERROR(ROUND(VLOOKUP(A29,[1]eco_journals!B:E,4,0),2),"") | G29: =IFERROR(_xlfn.RANK.EQ(F29,F:F),"") | H29: =IFERROR(ROUND(VLOOKUP(A29,[1]fin_journals!B:E,4,0),2),"") | I29: =IFERROR(_xlfn.RANK.EQ(H29,H:H),"") | J29: =IFERROR(ROUND(VLOOKUP(A29,[1]bus_journals!B:E,4,0),2),"") -> 4.98 | K29: =IFERROR(_xlfn.RANK.EQ(J29,J:J),"") -> 6 | L29: =IFERROR(ROUND(VLOOKUP(A29,[1]man_journals!B:E,4,0),2),"") -> 4.66 | M29: =IFERROR(_xlfn.RANK.EQ(L29,L:L),"") -> 4 | N29: BUSINESS | O29: MANAGEMENT
A30: STRATEGIC MANAGEMENT JOURNAL | B30: WILEY | C30: =IFERROR(VLOOKUP(A30,[1]eco_bus_journals!$B:$D,3,0),"") -> 121 | D30: =IFERROR(ROUND(VLOOKUP(A30,[1]eco_bus_journals!$B:$X,4,0),2),"") -> 2.03 | E30: =_xlfn.RANK.EQ(D30,D:D) -> 28 | F30: =IFERROR(ROUND(VLOOKUP(A30,[1]eco_journals!B:E,4,0),2),"") | G30: =IFERROR(_xlfn.RANK.EQ(F30,F:F),"") | H30: =IFERROR(ROUND(VLOOKUP(A30,[1]fin_journals!B:E,4,0),2),"") | I30: =IFERROR(_xlfn.RANK.EQ(H30,H:H),"") | J30: =IFERROR(ROUND(VLOOKUP(A30,[1]bus_journals!B:E,4,0),2),"") -> 4.79 | K30: =IFERROR(_xlfn.RANK.EQ(J30,J:J),"") -> 7 | L30: =IFERROR(ROUND(VLOOKUP(A30,[1]man_journals!B:E,4,0),2),"") -> 3.86 | M30: =IFERROR(_xlfn.RANK.EQ(L30,L:L),"") -> 6 | N30: BUSINESS | O30: MANAGEMENT
A31: JOURNAL OF MANAGEMENT | B31: SAGE PUBLICATIONS | C31: =IFERROR(VLOOKUP(A31,[1]eco_bus_journals!$B:$D,3,0),"") -> 88 | D31: =IFERROR(ROUND(VLOOKUP(A31,[1]eco_bus_journals!$B:$X,4,0),2),"") -> 1.92 | E31: =_xlfn.RANK.EQ(D31,D:D) -> 29 | F31: =IFERROR(ROUND(VLOOKUP(A31,[1]eco_journals!B:E,4,0),2),"") | G31: =IFERROR(_xlfn.RANK.EQ(F31,F:F),"") | H31: =IFERROR(ROUND(VLOOKUP(A31,[1]fin_journals!B:E,4,0),2),"") | I31: =IFERROR(_xlfn.RANK.EQ(H31,H:H),"") | J31: =IFERROR(ROUND(VLOOKUP(A31,[1]bus_journals!B:E,4,0),2),"") -> 4.66 | K31: =IFERROR(_xlfn.RANK.EQ(J31,J:J),"") -> 8 | L31: =IFERROR(ROUND(VLOOKUP(A31,[1]man_journals!B:E,4,0),2),"") -> 3.83 | M31: =IFERROR(_xlfn.RANK.EQ(L31,L:L),"") -> 7 | N31: BUSINESS | O31: MANAGEMENT | P31: PSYCHOLOGY, APPLIED
A32: ACADEMY OF MANAGEMENT PERSPECTIVES | B32: ACAD MANAGEMENT | C32: =IFERROR(VLOOKUP(A32,[1]eco_bus_journals!$B:$D,3,0),"") -> 30 | D32: =IFERROR(ROUND(VLOOKUP(A32,[1]eco_bus_journals!$B:$X,4,0),2),"") -> 1.76 | E32: =_xlfn.RANK.EQ(D32,D:D) -> 31 | F32: =IFERROR(ROUND(VLOOKUP(A32,[1]eco_journals!B:E,4,0),2),"") | G32: =IFERROR(_xlfn.RANK.EQ(F32,F:F),"") | H32: =IFERROR(ROUND(VLOOKUP(A32,[1]fin_journals!B:E,4,0),2),"") | I32: =IFERROR(_xlfn.RANK.EQ(H32,H:H),"") | J32: =IFERROR(ROUND(VLOOKUP(A32,[1]bus_journals!B:E,4,0),2),"") -> 4.38 | K32: =IFERROR(_xlfn.RANK.EQ(J32,J:J),"") -> 10 | L32: =IFERROR(ROUND(VLOOKUP(A32,[1]man_journals!B:E,4,0),2),"") -> 3.43 | M32: =IFERROR(_xlfn.RANK.EQ(L32,L:L),"") -> 8 | N32: BUSINESS | O32: MANAGEMENT
A33: JOURNAL OF THE ACADEMY OF MARKETING SCIENCE | B33: SPRINGER | C33: =IFERROR(VLOOKUP(A33,[1]eco_bus_journals!$B:$D,3,0),"") -> 71 | D33: =IFERROR(ROUND(VLOOKUP(A33,[1]eco_bus_journals!$B:$X,4,0),2),"") -> 1.89 | E33: =_xlfn.RANK.EQ(D33,D:D) -> 30 | F33: =IFERROR(ROUND(VLOOKUP(A33,[1]eco_journals!B:E,4,0),2),"") | G33: =IFERROR(_xlfn.RANK.EQ(F33,F:F),"") | H33: =IFERROR(ROUND(VLOOKUP(A33,[1]fin_journals!B:E,4,0),2),"") | I33: =IFERROR(_xlfn.RANK.EQ(H33,H:H),"") | J33: =IFERROR(ROUND(VLOOKUP(A33,[1]bus_journals!B:E,4,0),2),"") -> 6.26 | K33: =IFERROR(_xlfn.RANK.EQ(J33,J:J),"") -> 4 | L33: =IFERROR(ROUND(VLOOKUP(A33,[1]man_journals!B:E,4,0),2),"") | M33: =IFERROR(_xlfn.RANK.EQ(L33,L:L),"") | N33: BUSINESS
A34: PROCEEDINGS OF THE NATIONAL ACADEMY OF SCIENCES OF THE UNITED STATES OF AMERICA | B34: NATL ACAD SCIENCES | C34: =IFERROR(VLOOKUP(A34,[1]eco_bus_journals!$B:$D,3,0),"") -> 44 | D34: =IFERROR(ROUND(VLOOKUP(A34,[1]eco_bus_journals!$B:$X,4,0),2),"") -> 1.69 | E34: =_xlfn.RANK.EQ(D34,D:D) -> 34 | F34: =IFERROR(ROUND(VLOOKUP(A34,[1]eco_journals!B:E,4,0),2),"") | G34: =IFERROR(_xlfn.RANK.EQ(F34,F:F),"") | H34: =IFERROR(ROUND(VLOOKUP(A34,[1]fin_journals!B:E,4,0),2),"") | I34: =IFERROR(_xlfn.RANK.EQ(H34,H:H),"") | J34: =IFERROR(ROUND(VLOOKUP(A34,[1]bus_journals!B:E,4,0),2),"") | K34: =IFERROR(_xlfn.RANK.EQ(J34,J:J),"") | L34: =IFERROR(ROUND(VLOOKUP(A34,[1]man_journals!B:E,4,0),2),"") | M34: =IFERROR(_xlfn.RANK.EQ(L34,L:L),"") | N34: MULTIDISCIPLINARY SCIENCES
A35: REVIEW OF FINANCE | B35: OXFORD UNIV PRESS | C35: =IFERROR(VLOOKUP(A35,[1]eco_bus_journals!$B:$D,3,0),"") -> 17 | D35: =IFERROR(ROUND(VLOOKUP(A35,[1]eco_bus_journals!$B:$X,4,0),2),"") -> 1.66 | E35: =_xlfn.RANK.EQ(D35,D:D) -> 35 | F35: =IFERROR(ROUND(VLOOKUP(A35,[1]eco_journals!B:E,4,0),2),"") -> 0.91 | G35: =IFERROR(_xlfn.RANK.EQ(F35,F:F),"") -> 35 | H35: =IFERROR(ROUND(VLOOKUP(A35,[1]fin_journals!B:E,4,0),2),"") -> 4.36 | I35: =IFERROR(_xlfn.RANK.EQ(H35,H:H),"") -> 9 | J35: =IFERROR(ROUND(VLOOKUP(A35,[1]bus_journals!B:E,4,0),2),"") | K35: =IFERROR(_xlfn.RANK.EQ(J35,J:J),"") | L35: =IFERROR(ROUND(VLOOKUP(A35,[1]man_journals!B:E,4,0),2),"") | M35: =IFERROR(_xlfn.RANK.EQ(L35,L:L),"") | N35: FINANCE | O35: ECONOMICS
A36: JOURNAL OF FINANCIAL INTERMEDIATION | B36: ELSEVIER | C36: =IFERROR(VLOOKUP(A36,[1]eco_bus_journals!$B:$D,3,0),"") -> 26 | D36: =IFERROR(ROUND(VLOOKUP(A36,[1]eco_bus_journals!$B:$X,4,0),2),"") -> 1.71 | E36: =_xlfn.RANK.EQ(D36,D:D) -> 33 | F36: =IFERROR(ROUND(VLOOKUP(A36,[1]eco_journals!B:E,4,0),2),"") | G36: =IFERROR(_xlfn.RANK.EQ(F36,F:F),"") | H36: =IFERROR(ROUND(VLOOKUP(A36,[1]fin_journals!B:E,4,0),2),"") -> 4.97 | I36: =IFERROR(_xlfn.RANK.EQ(H36,H:H),"") -> 8 | J36: =IFERROR(ROUND(VLOOKUP(A36,[1]bus_journals!B:E,4,0),2),"") | K36: =IFERROR(_xlfn.RANK.EQ(J36,J:J),"") | L36: =IFERROR(ROUND(VLOOKUP(A36,[1]man_journals!B:E,4,0),2),"") | M36: =IFERROR(_xlfn.RANK.EQ(L36,L:L),"") | N36: FINANCE
A37: REVIEW OF ACCOUNTING STUDIES | B37: SPRINGER | C37: =IFERROR(VLOOKUP(A37,[1]eco_bus_journals!$B:$D,3,0),"") -> 51 | D37: =IFERROR(ROUND(VLOOKUP(A37,[1]eco_bus_journals!$B:$X,4,0),2),"") -> 1.73 | E37: =_xlfn.RANK.EQ(D37,D:D) -> 32 | F37: =IFERROR(ROUND(VLOOKUP(A37,[1]eco_journals!B:E,4,0),2),"") | G37: =IFERROR(_xlfn.RANK.EQ(F37,F:F),"") | H37: =IFERROR(ROUND(VLOOKUP(A37,[1]fin_journals!B:E,4,0),2),"") -> 6.32 | I37: =IFERROR(_xlfn.RANK.EQ(H37,H:H),"") -> 6 | J37: =IFERROR(ROUND(VLOOKUP(A37,[1]bus_journals!B:E,4,0),2),"") | K37: =IFERROR(_xlfn.RANK.EQ(J37,J:J),"") | L37: =IFERROR(ROUND(VLOOKUP(A37,[1]man_journals!B:E,4,0),2),"") | M37: =IFERROR(_xlfn.RANK.EQ(L37,L:L),"") | N37: FINANCE
A38: MARKETING SCIENCE | B38: INFORMS | C38: =IFERROR(VLOOKUP(A38,[1]eco_bus_journals!$B:$D,3,0),"") -> 57 | D38: =IFERROR(ROUND(VLOOKUP(A38,[1]eco_bus_journals!$B:$X,4,0),2),"") -> 1.61 | E38: =_xlfn.RANK.EQ(D38,D:D) -> 38 | F38: =IFERROR(ROUND(VLOOKUP(A38,[1]eco_journals!B:E,4,0),2),"") | G38: =IFERROR(_xlfn.RANK.EQ(F38,F:F),"") | H38: =IFERROR(ROUND(VLOOKUP(A38,[1]fin_journals!B:E,4,0),2),"") | I38: =IFERROR(_xlfn.RANK.EQ(H38,H:H),"") | J38: =IFERROR(ROUND(VLOOKUP(A38,[1]bus_journals!B:E,4,0),2),"") -> 3.64 | K38: =IFERROR(_xlfn.RANK.EQ(J38,J:J),"") -> 21 | L38: =IFERROR(ROUND(VLOOKUP(A38,[1]man_journals!B:E,4,0),2),"") | M38: =IFERROR(_xlfn.RANK.EQ(L38,L:L),"") | N38: BUSINESS
A39: JOURNAL OF THE EUROPEAN ECONOMIC ASSOCIATION | B39: OXFORD UNIV PRESS | C39: =IFERROR(VLOOKUP(A39,[1]eco_bus_journals!$B:$D,3,0),"") -> 84 | D39: =IFERROR(ROUND(VLOOKUP(A39,[1]eco_bus_journals!$B:$X,4,0),2),"") -> 1.64 | E39: =_xlfn.RANK.EQ(D39,D:D) -> 36 | F39: =IFERROR(ROUND(VLOOKUP(A39,[1]eco_journals!B:E,4,0),2),"") -> 1.74 | G39: =IFERROR(_xlfn.RANK.EQ(F39,F:F),"") -> 21 | H39: =IFERROR(ROUND(VLOOKUP(A39,[1]fin_journals!B:E,4,0),2),"") | I39: =IFERROR(_xlfn.RANK.EQ(H39,H:H),"") | J39: =IFERROR(ROUND(VLOOKUP(A39,[1]bus_journals!B:E,4,0),2),"") | K39: =IFERROR(_xlfn.RANK.EQ(J39,J:J),"") | L39: =IFERROR(ROUND(VLOOKUP(A39,[1]man_journals!B:E,4,0),2),"") | M39: =IFERROR(_xlfn.RANK.EQ(L39,L:L),"") | N39: ECONOMICS
A40: JOURNAL OF MONETARY ECONOMICS | B40: ELSEVIER | C40: =IFERROR(VLOOKUP(A40,[1]eco_bus_journals!$B:$D,3,0),"") -> 102 | D40: =IFERROR(ROUND(VLOOKUP(A40,[1]eco_bus_journals!$B:$X,4,0),2),"") -> 1.58 | E40: =_xlfn.RANK.EQ(D40,D:D) -> 39 | F40: =IFERROR(ROUND(VLOOKUP(A40,[1]eco_journals!B:E,4,0),2),"") -> 1.58 | G40: =IFERROR(_xlfn.RANK.EQ(F40,F:F),"") -> 22 | H40: =IFERROR(ROUND(VLOOKUP(A40,[1]fin_journals!B:E,4,0),2),"") -> 2.17 | I40: =IFERROR(_xlfn.RANK.EQ(H40,H:H),"") -> 15 | J40: =IFERROR(ROUND(VLOOKUP(A40,[1]bus_journals!B:E,4,0),2),"") | K40: =IFERROR(_xlfn.RANK.EQ(J40,J:J),"") | L40: =IFERROR(ROUND(VLOOKUP(A40,[1]man_journals!B:E,4,0),2),"") | M40: =IFERROR(_xlfn.RANK.EQ(L40,L:L),"") | N40: FINANCE | O40: ECONOMICS
A41: JOURNAL OF MANAGEMENT STUDIES | B41: WILEY | C41: =IFERROR(VLOOKUP(A41,[1]eco_bus_journals!$B:$D,3,0),"") -> 93 | D41: =IFERROR(ROUND(VLOOKUP(A41,[1]eco_bus_journals!$B:$X,4,0),2),"") -> 1.63 | E41: =_xlfn.RANK.EQ(D41,D:D) -> 37 | F41: =IFERROR(ROUND(VLOOKUP(A41,[1]eco_journals!B:E,4,0),2),"") | G41: =IFERROR(_xlfn.RANK.EQ(F41,F:F),"") | H41: =IFERROR(ROUND(VLOOKUP(A41,[1]fin_journals!B:E,4,0),2),"") | I41: =IFERROR(_xlfn.RANK.EQ(H41,H:H),"") | J41: =IFERROR(ROUND(VLOOKUP(A41,[1]bus_journals!B:E,4,0),2),"") -> 4.19 | K41: =IFERROR(_xlfn.RANK.EQ(J41,J:J),"") -> 14 | L41: =IFERROR(ROUND(VLOOKUP(A41,[1]man_journals!B:E,4,0),2),"") -> 3.26 | M41: =IFERROR(_xlfn.RANK.EQ(L41,L:L),"") -> 11 | N41: BUSINESS | O41: MANAGEMENT
A42: ACADEMY OF MANAGEMENT DISCOVERIES | B42: ACAD MANAGEMENT | C42: =IFERROR(VLOOKUP(A42,[1]eco_bus_journals!$B:$D,3,0),"") -> 32 | D42: =IFERROR(ROUND(VLOOKUP(A42,[1]eco_bus_journals!$B:$X,4,0),2),"") -> 1.55 | E42: =_xlfn.RANK.EQ(D42,D:D) -> 41 | F42: =IFERROR(ROUND(VLOOKUP(A42,[1]eco_journals!B:E,4,0),2),"") | G42: =IFERROR(_xlfn.RANK.EQ(F42,F:F),"") | H42: =IFERROR(ROUND(VLOOKUP(A42,[1]fin_journals!B:E,4,0),2),"") | I42: =IFERROR(_xlfn.RANK.EQ(H42,H:H),"") | J42: =IFERROR(ROUND(VLOOKUP(A42,[1]bus_journals!B:E,4,0),2),"") | K42: =IFERROR(_xlfn.RANK.EQ(J42,J:J),"") | L42: =IFERROR(ROUND(VLOOKUP(A42,[1]man_journals!B:E,4,0),2),"") -> 3.29 | M42: =IFERROR(_xlfn.RANK.EQ(L42,L:L),"") -> 10 | N42: MANAGEMENT
A43: MANAGEMENT SCIENCE | B43: INFORMS | C43: =IFERROR(VLOOKUP(A43,[1]eco_bus_journals!$B:$D,3,0),"") -> 294 | D43: =IFERROR(ROUND(VLOOKUP(A43,[1]eco_bus_journals!$B:$X,4,0),2),"") -> 1.55 | E43: =_xlfn.RANK.EQ(D43,D:D) -> 41 | F43: =IFERROR(ROUND(VLOOKUP(A43,[1]eco_journals!B:E,4,0),2),"") | G43: =IFERROR(_xlfn.RANK.EQ(F43,F:F),"") | H43: =IFERROR(ROUND(VLOOKUP(A43,[1]fin_journals!B:E,4,0),2),"") | I43: =IFERROR(_xlfn.RANK.EQ(H43,H:H),"") | J43: =IFERROR(ROUND(VLOOKUP(A43,[1]bus_journals!B:E,4,0),2),"") | K43: =IFERROR(_xlfn.RANK.EQ(J43,J:J),"") | L43: =IFERROR(ROUND(VLOOKUP(A43,[1]man_journals!B:E,4,0),2),"") -> 1.69 | M43: =IFERROR(_xlfn.RANK.EQ(L43,L:L),"") -> 30 | N43: MANAGEMENT | O43: OPERATIONS RESEARCH & MANAGEMENT SCIENCE
A44: ACCOUNTING REVIEW | B44: AMER ACCOUNTING ASSOC | C44: =IFERROR(VLOOKUP(A44,[1]eco_bus_journals!$B:$D,3,0),"") -> 92 | D44: =IFERROR(ROUND(VLOOKUP(A44,[1]eco_bus_journals!$B:$X,4,0),2),"") -> 1.49 | E44: =_xlfn.RANK.EQ(D44,D:D) -> 44 | F44: =IFERROR(ROUND(VLOOKUP(A44,[1]eco_journals!B:E,4,0),2),"") | G44: =IFERROR(_xlfn.RANK.EQ(F44,F:F),"") | H44: =IFERROR(ROUND(VLOOKUP(A44,[1]fin_journals!B:E,4,0),2),"") -> 5.84 | I44: =IFERROR(_xlfn.RANK.EQ(H44,H:H),"") -> 7 | J44: =IFERROR(ROUND(VLOOKUP(A44,[1]bus_journals!B:E,4,0),2),"") | K44: =IFERROR(_xlfn.RANK.EQ(J44,J:J),"") | L44: =IFERROR(ROUND(VLOOKUP(A44,[1]man_journals!B:E,4,0),2),"") | M44: =IFERROR(_xlfn.RANK.EQ(L44,L:L),"") | N44: FINANCE
A45: IMF ECONOMIC REVIEW | B45: PALGRAVE MACMILLAN LTD | C45: =IFERROR(VLOOKUP(A45,[1]eco_bus_journals!$B:$D,3,0),"") -> 21 | D45: =IFERROR(ROUND(VLOOKUP(A45,[1]eco_bus_journals!$B:$X,4,0),2),"") -> 1.42 | E45: =_xlfn.RANK.EQ(D45,D:D) -> 47 | F45: =IFERROR(ROUND(VLOOKUP(A45,[1]eco_journals!B:E,4,0),2),"") -> 1.23 | G45: =IFERROR(_xlfn.RANK.EQ(F45,F:F),"") -> 24 | H45: =IFERROR(ROUND(VLOOKUP(A45,[1]fin_journals!B:E,4,0),2),"") -> 2.23 | I45: =IFERROR(_xlfn.RANK.EQ(H45,H:H),"") -> 14 | J45: =IFERROR(ROUND(VLOOKUP(A45,[1]bus_journals!B:E,4,0),2),"") | K45: =IFERROR(_xlfn.RANK.EQ(J45,J:J),"") | L45: =IFERROR(ROUND(VLOOKUP(A45,[1]man_journals!B:E,4,0),2),"") | M45: =IFERROR(_xlfn.RANK.EQ(L45,L:L),"") | N45: FINANCE | O45: ECONOMICS
A46: JOURNAL OF INTERNATIONAL BUSINESS STUDIES | B46: PALGRAVE MACMILLAN LTD | C46: =IFERROR(VLOOKUP(A46,[1]eco_bus_journals!$B:$D,3,0),"") -> 92 | D46: =IFERROR(ROUND(VLOOKUP(A46,[1]eco_bus_journals!$B:$X,4,0),2),"") -> 1.38 | E46: =_xlfn.RANK.EQ(D46,D:D) -> 50 | F46: =IFERROR(ROUND(VLOOKUP(A46,[1]eco_journals!B:E,4,0),2),"") | G46: =IFERROR(_xlfn.RANK.EQ(F46,F:F),"") | H46: =IFERROR(ROUND(VLOOKUP(A46,[1]fin_journals!B:E,4,0),2),"") | I46: =IFERROR(_xlfn.RANK.EQ(H46,H:H),"") | J46: =IFERROR(ROUND(VLOOKUP(A46,[1]bus_journals!B:E,4,0),2),"") -> 3.77 | K46: =IFERROR(_xlfn.RANK.EQ(J46,J:J),"") -> 20 | L46: =IFERROR(ROUND(VLOOKUP(A46,[1]man_journals!B:E,4,0),2),"") -> 2.22 | M46: =IFERROR(_xlfn.RANK.EQ(L46,L:L),"") -> 20 | N46: BUSINESS | O46: MANAGEMENT
A47: JOURNAL OF PRODUCT INNOVATION MANAGEMENT | B47: WILEY | C47: =IFERROR(VLOOKUP(A47,[1]eco_bus_journals!$B:$D,3,0),"") -> 25 | D47: =IFERROR(ROUND(VLOOKUP(A47,[1]eco_bus_journals!$B:$X,4,0),2),"") -> 1.5 | E47: =_xlfn.RANK.EQ(D47,D:D) -> 43 | F47: =IFERROR(ROUND(VLOOKUP(A47,[1]eco_journals!B:E,4,0),2),"") | G47: =IFERROR(_xlfn.RANK.EQ(F47,F:F),"") | H47: =IFERROR(ROUND(VLOOKUP(A47,[1]fin_journals!B:E,4,0),2),"") | I47: =IFERROR(_xlfn.RANK.EQ(H47,H:H),"") | J47: =IFERROR(ROUND(VLOOKUP(A47,[1]bus_journals!B:E,4,0),2),"") -> 4.2 | K47: =IFERROR(_xlfn.RANK.EQ(J47,J:J),"") -> 13 | L47: =IFERROR(ROUND(VLOOKUP(A47,[1]man_journals!B:E,4,0),2),"") -> 3.14 | M47: =IFERROR(_xlfn.RANK.EQ(L47,L:L),"") -> 13 | N47: BUSINESS | O47: ENGINEERING, INDUSTRIAL | P47: MANAGEMENT
A48: JOURNAL OF MARKETING RESEARCH | B48: SAGE PUBLICATIONS | C48: =IFERROR(VLOOKUP(A48,[1]eco_bus_journals!$B:$D,3,0),"") -> 71 | D48: =IFERROR(ROUND(VLOOKUP(A48,[1]eco_bus_journals!$B:$X,4,0),2),"") -> 1.45 | E48: =_xlfn.RANK.EQ(D48,D:D) -> 45 | F48: =IFERROR(ROUND(VLOOKUP(A48,[1]eco_journals!B:E,4,0),2),"") | G48: =IFERROR(_xlfn.RANK.EQ(F48,F:F),"") | H48: =IFERROR(ROUND(VLOOKUP(A48,[1]fin_journals!B:E,4,0),2),"") | I48: =IFERROR(_xlfn.RANK.EQ(H48,H:H),"") | J48: =IFERROR(ROUND(VLOOKUP(A48,[1]bus_journals!B:E,4,0),2),"") -> 4.48 | K48: =IFERROR(_xlfn.RANK.EQ(J48,J:J),"") -> 9 | L48: =IFERROR(ROUND(VLOOKUP(A48,[1]man_journals!B:E,4,0),2),"") | M48: =IFERROR(_xlfn.RANK.EQ(L48,L:L),"") | N48: BUSINESS
A49: ENTREPRENEURSHIP THEORY AND PRACTICE | B49: SAGE PUBLICATIONS | C49: =IFERROR(VLOOKUP(A49,[1]eco_bus_journals!$B:$D,3,0),"") -> 91 | D49: =IFERROR(ROUND(VLOOKUP(A49,[1]eco_bus_journals!$B:$X,4,0),2),"") -> 1.42 | E49: =_xlfn.RANK.EQ(D49,D:D) -> 47 | F49: =IFERROR(ROUND(VLOOKUP(A49,[1]eco_journals!B:E,4,0),2),"") | G49: =IFERROR(_xlfn.RANK.EQ(F49,F:F),"") | H49: =IFERROR(ROUND(VLOOKUP(A49,[1]fin_journals!B:E,4,0),2),"") | I49: =IFERROR(_xlfn.RANK.EQ(H49,H:H),"") | J49: =IFERROR(ROUND(VLOOKUP(A49,[1]bus_journals!B:E,4,0),2),"") -> 4.02 | K49: =IFERROR(_xlfn.RANK.EQ(J49,J:J),"") -> 17 | L49: =IFERROR(ROUND(VLOOKUP(A49,[1]man_journals!B:E,4,0),2),"") | M49: =IFERROR(_xlfn.RANK.EQ(L49,L:L),"") | N49: BUSINESS
A50: JOURNAL OF SERVICE RESEARCH | B50: SAGE PUBLICATIONS | C50: =IFERROR(VLOOKUP(A50,[1]eco_bus_journals!$B:$D,3,0),"") -> 42 | D50: =IFERROR(ROUND(VLOOKUP(A50,[1]eco_bus_journals!$B:$X,4,0),2),"") -> 1.4 | E50: =_xlfn.RANK.EQ(D50,D:D) -> 49 | F50: =IFERROR(ROUND(VLOOKUP(A50,[1]eco_journals!B:E,4,0),2),"") | G50: =IFERROR(_xlfn.RANK.EQ(F50,F:F),"") | H50: =IFERROR(ROUND(VLOOKUP(A50,[1]fin_journals!B:E,4,0),2),"") | I50: =IFERROR(_xlfn.RANK.EQ(H50,H:H),"") | J50: =IFERROR(ROUND(VLOOKUP(A50,[1]bus_journals!B:E,4,0),2),"") -> 4.34 | K50: =IFERROR(_xlfn.RANK.EQ(J50,J:J),"") -> 11 | L50: =IFERROR(ROUND(VLOOKUP(A50,[1]man_journals!B:E,4,0),2),"") | M50: =IFERROR(_xlfn.RANK.EQ(L50,L:L),"") | N50: BUSINESS
A51: ORGANIZATION SCIENCE | B51: INFORMS | C51: =IFERROR(VLOOKUP(A51,[1]eco_bus_journals!$B:$D,3,0),"") -> 74 | D51: =IFERROR(ROUND(VLOOKUP(A51,[1]eco_bus_journals!$B:$X,4,0),2),"") -> 1.58 | E51: =_xlfn.RANK.EQ(D51,D:D) -> 39 | F51: =IFERROR(ROUND(VLOOKUP(A51,[1]eco_journals!B:E,4,0),2),"") | G51: =IFERROR(_xlfn.RANK.EQ(F51,F:F),"") | H51: =IFERROR(ROUND(VLOOKUP(A51,[1]fin_journals!B:E,4,0),2),"") | I51: =IFERROR(_xlfn.RANK.EQ(H51,H:H),"") | J51: =IFERROR(ROUND(VLOOKUP(A51,[1]bus_journals!B:E,4,0),2),"") | K51: =IFERROR(_xlfn.RANK.EQ(J51,J:J),"") | L51: =IFERROR(ROUND(VLOOKUP(A51,[1]man_journals!B:E,4,0),2),"") -> 3.42 | M51: =IFERROR(_xlfn.RANK.EQ(L51,L:L),"") -> 9 | N51: MANAGEMENT
A52: JOURNAL OF BUSINESS VENTURING | B52: ELSEVIER | C52: =IFERROR(VLOOKUP(A52,[1]eco_bus_journals!$B:$D,3,0),"") -> 60 | D52: =IFERROR(ROUND(VLOOKUP(A52,[1]eco_bus_journals!$B:$X,4,0),2),"") -> 1.43 | E52: =_xlfn.RANK.EQ(D52,D:D) -> 46 | F52: =IFERROR(ROUND(VLOOKUP(A52,[1]eco_journals!B:E,4,0),2),"") | G52: =IFERROR(_xlfn.RANK.EQ(F52,F:F),"") | H52: =IFERROR(ROUND(VLOOKUP(A52,[1]fin_journals!B:E,4,0),2),"") | I52: =IFERROR(_xlfn.RANK.EQ(H52,H:H),"") | J52: =IFERROR(ROUND(VLOOKUP(A52,[1]bus_journals!B:E,4,0),2),"") -> 4.13 | K52: =IFERROR(_xlfn.RANK.EQ(J52,J:J),"") -> 16 | L52: =IFERROR(ROUND(VLOOKUP(A52,[1]man_journals!B:E,4,0),2),"") | M52: =IFERROR(_xlfn.RANK.EQ(L52,L:L),"") | N52: BUSINESS
A53: STRATEGIC ENTREPRENEURSHIP JOURNAL | B53: WILEY | C53: =IFERROR(VLOOKUP(A53,[1]eco_bus_journals!$B:$D,3,0),"") -> 45 | D53: =IFERROR(ROUND(VLOOKUP(A53,[1]eco_bus_journals!$B:$X,4,0),2),"") -> 1.37 | E53: =_xlfn.RANK.EQ(D53,D:D) -> 52 | F53: =IFERROR(ROUND(VLOOKUP(A53,[1]eco_journals!B:E,4,0),2),"") | G53: =IFERROR(_xlfn.RANK.EQ(F53,F:F),"") | H53: =IFERROR(ROUND(VLOOKUP(A53,[1]fin_journals!B:E,4,0),2),"") | I53: =IFERROR(_xlfn.RANK.EQ(H53,H:H),"") | J53: =IFERROR(ROUND(VLOOKUP(A53,[1]bus_journals!B:E,4,0),2),"") -> 3.85 | K53: =IFERROR(_xlfn.RANK.EQ(J53,J:J),"") -> 19 | L53: =IFERROR(ROUND(VLOOKUP(A53,[1]man_journals!B:E,4,0),2),"") -> 2.64 | M53: =IFERROR(_xlfn.RANK.EQ(L53,L:L),"") -> 15 | N53: BUSINESS | O53: MANAGEMENT
A54: JOURNAL OF INTERNATIONAL ECONOMICS | B54: ELSEVIER | C54: =IFERROR(VLOOKUP(A54,[1]eco_bus_journals!$B:$D,3,0),"") -> 92 | D54: =IFERROR(ROUND(VLOOKUP(A54,[1]eco_bus_journals!$B:$X,4,0),2),"") -> 1.24 | E54: =_xlfn.RANK.EQ(D54,D:D) -> 57 | F54: =IFERROR(ROUND(VLOOKUP(A54,[1]eco_journals!B:E,4,0),2),"") -> 1.21 | G54: =IFERROR(_xlfn.RANK.EQ(F54,F:F),"") -> 25 | H54: =IFERROR(ROUND(VLOOKUP(A54,[1]fin_journals!B:E,4,0),2),"") | I54: =IFERROR(_xlfn.RANK.EQ(H54,H:H),"") | J54: =IFERROR(ROUND(VLOOKUP(A54,[1]bus_journals!B:E,4,0),2),"") | K54: =IFERROR(_xlfn.RANK.EQ(J54,J:J),"") | L54: =IFERROR(ROUND(VLOOKUP(A54,[1]man_journals!B:E,4,0),2),"") | M54: =IFERROR(_xlfn.RANK.EQ(L54,L:L),"") | N54: ECONOMICS
A55: JOURNAL OF SUPPLY CHAIN MANAGEMENT | B55: WILEY | C55: =IFERROR(VLOOKUP(A55,[1]eco_bus_journals!$B:$D,3,0),"") -> 25 | D55: =IFERROR(ROUND(VLOOKUP(A55,[1]eco_bus_journals!$B:$X,4,0),2),"") -> 1.38 | E55: =_xlfn.RANK.EQ(D55,D:D) -> 50 | F55: =IFERROR(ROUND(VLOOKUP(A55,[1]eco_journals!B:E,4,0),2),"") | G55: =IFERROR(_xlfn.RANK.EQ(F55,F:F),"") | H55: =IFERROR(ROUND(VLOOKUP(A55,[1]fin_journals!B:E,4,0),2),"") | I55: =IFERROR(_xlfn.RANK.EQ(H55,H:H),"") | J55: =IFERROR(ROUND(VLOOKUP(A55,[1]bus_journals!B:E,4,0),2),"") | K55: =IFERROR(_xlfn.RANK.EQ(J55,J:J),"") | L55: =IFERROR(ROUND(VLOOKUP(A55,[1]man_journals!B:E,4,0),2),"") -> 3.24 | M55: =IFERROR(_xlfn.RANK.EQ(L55,L:L),"") -> 12 | N55: MANAGEMENT
A56: QUANTITATIVE ECONOMICS | B56: WILEY | C56: =IFERROR(VLOOKUP(A56,[1]eco_bus_journals!$B:$D,3,0),"") -> 40 | D56: =IFERROR(ROUND(VLOOKUP(A56,[1]eco_bus_journals!$B:$X,4,0),2),"") -> 1.29 | E56: =_xlfn.RANK.EQ(D56,D:D) -> 54 | F56: =IFERROR(ROUND(VLOOKUP(A56,[1]eco_journals!B:E,4,0),2),"") -> 1.34 | G56: =IFERROR(_xlfn.RANK.EQ(F56,F:F),"") -> 23 | H56: =IFERROR(ROUND(VLOOKUP(A56,[1]fin_journals!B:E,4,0),2),"") | I56: =IFERROR(_xlfn.RANK.EQ(H56,H:H),"") | J56: =IFERROR(ROUND(VLOOKUP(A56,[1]bus_journals!B:E,4,0),2),"") | K56: =IFERROR(_xlfn.RANK.EQ(J56,J:J),"") | L56: =IFERROR(ROUND(VLOOKUP(A56,[1]man_journals!B:E,4,0),2),"") | M56: =IFERROR(_xlfn.RANK.EQ(L56,L:L),"") | N56: ECONOMICS
A57: ORGANIZATIONAL RESEARCH METHODS | B57: SAGE PUBLICATIONS | C57: =IFERROR(VLOOKUP(A57,[1]eco_bus_journals!$B:$D,3,0),"") -> 58 | D57: =IFERROR(ROUND(VLOOKUP(A57,[1]eco_bus_journals!$B:$X,4,0),2),"") -> 1.27 | E57: =_xlfn.RANK.EQ(D57,D:D) -> 55 | F57: =IFERROR(ROUND(VLOOKUP(A57,[1]eco_journals!B:E,4,0),2),"") | G57: =IFERROR(_xlfn.RANK.EQ(F57,F:F),"") | H57: =IFERROR(ROUND(VLOOKUP(A57,[1]fin_journals!B:E,4,0),2),"") | I57: =IFERROR(_xlfn.RANK.EQ(H57,H:H),"") | J57: =IFERROR(ROUND(VLOOKUP(A57,[1]bus_journals!B:E,4,0),2),"") | K57: =IFERROR(_xlfn.RANK.EQ(J57,J:J),"") | L57: =IFERROR(ROUND(VLOOKUP(A57,[1]man_journals!B:E,4,0),2),"") -> 2.76 | M57: =IFERROR(_xlfn.RANK.EQ(L57,L:L),"") -> 14 | N57: MANAGEMENT | O57: PSYCHOLOGY, APPLIED
A58: CALIFORNIA MANAGEMENT REVIEW | B58: SAGE PUBLICATIONS | C58: =IFERROR(VLOOKUP(A58,[1]eco_bus_journals!$B:$D,3,0),"") -> 31 | D58: =IFERROR(ROUND(VLOOKUP(A58,[1]eco_bus_journals!$B:$X,4,0),2),"") -> 1.27 | E58: =_xlfn.RANK.EQ(D58,D:D) -> 55 | F58: =IFERROR(ROUND(VLOOKUP(A58,[1]eco_journals!B:E,4,0),2),"") | G58: =IFERROR(_xlfn.RANK.EQ(F58,F:F),"") | H58: =IFERROR(ROUND(VLOOKUP(A58,[1]fin_journals!B:E,4,0),2),"") | I58: =IFERROR(_xlfn.RANK.EQ(H58,H:H),"") | J58: =IFERROR(ROUND(VLOOKUP(A58,[1]bus_journals!B:E,4,0),2),"") -> 3.32 | K58: =IFERROR(_xlfn.RANK.EQ(J58,J:J),"") -> 22 | L58: =IFERROR(ROUND(VLOOKUP(A58,[1]man_journals!B:E,4,0),2),"") -> 2.36 | M58: =IFERROR(_xlfn.RANK.EQ(L58,L:L),"") -> 19 | N58: BUSINESS | O58: MANAGEMENT
A59: INTERNATIONAL JOURNAL OF MANAGEMENT REVIEWS | B59: WILEY | C59: =IFERROR(VLOOKUP(A59,[1]eco_bus_journals!$B:$D,3,0),"") -> 21 | D59: =IFERROR(ROUND(VLOOKUP(A59,[1]eco_bus_journals!$B:$X,4,0),2),"") -> 1.31 | E59: =_xlfn.RANK.EQ(D59,D:D) -> 53 | F59: =IFERROR(ROUND(VLOOKUP(A59,[1]eco_journals!B:E,4,0),2),"") | G59: =IFERROR(_xlfn.RANK.EQ(F59,F:F),"") | H59: =IFERROR(ROUND(VLOOKUP(A59,[1]fin_journals!B:E,4,0),2),"") | I59: =IFERROR(_xlfn.RANK.EQ(H59,H:H),"") | J59: =IFERROR(ROUND(VLOOKUP(A59,[1]bus_journals!B:E,4,0),2),"") -> 2.93 | K59: =IFERROR(_xlfn.RANK.EQ(J59,J:J),"") -> 25 | L59: =IFERROR(ROUND(VLOOKUP(A59,[1]man_journals!B:E,4,0),2),"") -> 2.64 | M59: =IFERROR(_xlfn.RANK.EQ(L59,L:L),"") -> 15 | N59: BUSINESS | O59: MANAGEMENT
A60: JOURNAL OF CONSUMER RESEARCH | B60: OXFORD UNIV PRESS INC | C60: =IFERROR(VLOOKUP(A60,[1]eco_bus_journals!$B:$D,3,0),"") -> 48 | D60: =IFERROR(ROUND(VLOOKUP(A60,[1]eco_bus_journals!$B:$X,4,0),2),"") -> 1.22 | E60: =_xlfn.RANK.EQ(D60,D:D) -> 58 | F60: =IFERROR(ROUND(VLOOKUP(A60,[1]eco_journals!B:E,4,0),2),"") | G60: =IFERROR(_xlfn.RANK.EQ(F60,F:F),"") | H60: =IFERROR(ROUND(VLOOKUP(A60,[1]fin_journals!B:E,4,0),2),"") | I60: =IFERROR(_xlfn.RANK.EQ(H60,H:H),"") | J60: =IFERROR(ROUND(VLOOKUP(A60,[1]bus_journals!B:E,4,0),2),"") -> 4.29 | K60: =IFERROR(_xlfn.RANK.EQ(J60,J:J),"") -> 12 | L60: =IFERROR(ROUND(VLOOKUP(A60,[1]man_journals!B:E,4,0),2),"") | M60: =IFERROR(_xlfn.RANK.EQ(L60,L:L),"") | N60: BUSINESS
A61: JOURNAL OF URBAN ECONOMICS | B61: ELSEVIER | C61: =IFERROR(VLOOKUP(A61,[1]eco_bus_journals!$B:$D,3,0),"") -> 39 | D61: =IFERROR(ROUND(VLOOKUP(A61,[1]eco_bus_journals!$B:$X,4,0),2),"") -> 1.2 | E61: =_xlfn.RANK.EQ(D61,D:D) -> 60 | F61: =IFERROR(ROUND(VLOOKUP(A61,[1]eco_journals!B:E,4,0),2),"") -> 1.2 | G61: =IFERROR(_xlfn.RANK.EQ(F61,F:F),"") -> 26 | H61: =IFERROR(ROUND(VLOOKUP(A61,[1]fin_journals!B:E,4,0),2),"") | I61: =IFERROR(_xlfn.RANK.EQ(H61,H:H),"") | J61: =IFERROR(ROUND(VLOOKUP(A61,[1]bus_journals!B:E,4,0),2),"") | K61: =IFERROR(_xlfn.RANK.EQ(J61,J:J),"") | L61: =IFERROR(ROUND(VLOOKUP(A61,[1]man_journals!B:E,4,0),2),"") | M61: =IFERROR(_xlfn.RANK.EQ(L61,L:L),"") | N61: ECONOMICS | O61: URBAN STUDIES
A62: GLOBAL STRATEGY JOURNAL | B62: WILEY | C62: =IFERROR(VLOOKUP(A62,[1]eco_bus_journals!$B:$D,3,0),"") -> 33 | D62: =IFERROR(ROUND(VLOOKUP(A62,[1]eco_bus_journals!$B:$X,4,0),2),"") -> 1.08 | E62: =_xlfn.RANK.EQ(D62,D:D) -> 69 | F62: =IFERROR(ROUND(VLOOKUP(A62,[1]eco_journals!B:E,4,0),2),"") | G62: =IFERROR(_xlfn.RANK.EQ(F62,F:F),"") | H62: =IFERROR(ROUND(VLOOKUP(A62,[1]fin_journals!B:E,4,0),2),"") | I62: =IFERROR(_xlfn.RANK.EQ(H62,H:H),"") | J62: =IFERROR(ROUND(VLOOKUP(A62,[1]bus_journals!B:E,4,0),2),"") -> 3.08 | K62: =IFERROR(_xlfn.RANK.EQ(J62,J:J),"") -> 24 | L62: =IFERROR(ROUND(VLOOKUP(A62,[1]man_journals!B:E,4,0),2),"") -> 1.76 | M62: =IFERROR(_xlfn.RANK.EQ(L62,L:L),"") -> 28 | N62: BUSINESS | O62: MANAGEMENT
A63: JOURNAL OF HUMAN RESOURCES | B63: UNIV WISCONSIN PRESS | C63: =IFERROR(VLOOKUP(A63,[1]eco_bus_journals!$B:$D,3,0),"") -> 39 | D63: =IFERROR(ROUND(VLOOKUP(A63,[1]eco_bus_journals!$B:$X,4,0),2),"") -> 1.19 | E63: =_xlfn.RANK.EQ(D63,D:D) -> 61 | F63: =IFERROR(ROUND(VLOOKUP(A63,[1]eco_journals!B:E,4,0),2),"") -> 1.17 | G63: =IFERROR(_xlfn.RANK.EQ(F63,F:F),"") -> 28 | H63: =IFERROR(ROUND(VLOOKUP(A63,[1]fin_journals!B:E,4,0),2),"") | I63: =IFERROR(_xlfn.RANK.EQ(H63,H:H),"") | J63: =IFERROR(ROUND(VLOOKUP(A63,[1]bus_journals!B:E,4,0),2),"") | K63: =IFERROR(_xlfn.RANK.EQ(J63,J:J),"") | L63: =IFERROR(ROUND(VLOOKUP(A63,[1]man_journals!B:E,4,0),2),"") | M63: =IFERROR(_xlfn.RANK.EQ(L63,L:L),"") | N63: ECONOMICS | O63: INDUSTRIAL RELATIONS & LABOR
A64: JOURNAL OF INTERACTIVE MARKETING | B64: SAGE PUBLICATIONS | C64: =IFERROR(VLOOKUP(A64,[1]eco_bus_journals!$B:$D,3,0),"") -> 32 | D64: =IFERROR(ROUND(VLOOKUP(A64,[1]eco_bus_journals!$B:$X,4,0),2),"") -> 1.21 | E64: =_xlfn.RANK.EQ(D64,D:D) -> 59 | F64: =IFERROR(ROUND(VLOOKUP(A64,[1]eco_journals!B:E,4,0),2),"") | G64: =IFERROR(_xlfn.RANK.EQ(F64,F:F),"") | H64: =IFERROR(ROUND(VLOOKUP(A64,[1]fin_journals!B:E,4,0),2),"") | I64: =IFERROR(_xlfn.RANK.EQ(H64,H:H),"") | J64: =IFERROR(ROUND(VLOOKUP(A64,[1]bus_journals!B:E,4,0),2),"") -> 4.15 | K64: =IFERROR(_xlfn.RANK.EQ(J64,J:J),"") -> 15 | L64: =IFERROR(ROUND(VLOOKUP(A64,[1]man_journals!B:E,4,0),2),"") | M64: =IFERROR(_xlfn.RANK.EQ(L64,L:L),"") | N64: BUSINESS
A65: ANNUAL REVIEW OF FINANCIAL ECONOMICS | B65: ANNUAL REVIEWS | C65: =IFERROR(VLOOKUP(A65,[1]eco_bus_journals!$B:$D,3,0),"") -> 15 | D65: =IFERROR(ROUND(VLOOKUP(A65,[1]eco_bus_journals!$B:$X,4,0),2),"") -> 1.09 | E65: =_xlfn.RANK.EQ(D65,D:D) -> 67 | F65: =IFERROR(ROUND(VLOOKUP(A65,[1]eco_journals!B:E,4,0),2),"") | G65: =IFERROR(_xlfn.RANK.EQ(F65,F:F),"") | H65: =IFERROR(ROUND(VLOOKUP(A65,[1]fin_journals!B:E,4,0),2),"") -> 3.49 | I65: =IFERROR(_xlfn.RANK.EQ(H65,H:H),"") -> 11 | J65: =IFERROR(ROUND(VLOOKUP(A65,[1]bus_journals!B:E,4,0),2),"") | K65: =IFERROR(_xlfn.RANK.EQ(J65,J:J),"") | L65: =IFERROR(ROUND(VLOOKUP(A65,[1]man_journals!B:E,4,0),2),"") | M65: =IFERROR(_xlfn.RANK.EQ(L65,L:L),"") | N65: FINANCE
A66: JOURNAL OF FINANCIAL AND QUANTITATIVE ANALYSIS | B66: CAMBRIDGE UNIV PRESS | C66: =IFERROR(VLOOKUP(A66,[1]eco_bus_journals!$B:$D,3,0),"") -> 82 | D66: =IFERROR(ROUND(VLOOKUP(A66,[1]eco_bus_journals!$B:$X,4,0),2),"") -> 1.09 | E66: =_xlfn.RANK.EQ(D66,D:D) -> 67 | F66: =IFERROR(ROUND(VLOOKUP(A66,[1]eco_journals!B:E,4,0),2),"") -> 0.61 | G66: =IFERROR(_xlfn.RANK.EQ(F66,F:F),"") -> 61 | H66: =IFERROR(ROUND(VLOOKUP(A66,[1]fin_journals!B:E,4,0),2),"") -> 3.42 | I66: =IFERROR(_xlfn.RANK.EQ(H66,H:H),"") -> 12 | J66: =IFERROR(ROUND(VLOOKUP(A66,[1]bus_journals!B:E,4,0),2),"") | K66: =IFERROR(_xlfn.RANK.EQ(J66,J:J),"") | L66: =IFERROR(ROUND(VLOOKUP(A66,[1]man_journals!B:E,4,0),2),"") | M66: =IFERROR(_xlfn.RANK.EQ(L66,L:L),"") | N66: FINANCE | O66: ECONOMICS
A67: REVIEW OF ENVIRONMENTAL ECONOMICS AND POLICY | B67: UNIV CHICAGO PRESS | C67: =IFERROR(VLOOKUP(A67,[1]eco_bus_journals!$B:$D,3,0),"") -> 19 | D67: =IFERROR(ROUND(VLOOKUP(A67,[1]eco_bus_journals!$B:$X,4,0),2),"") -> 1.15 | E67: =_xlfn.RANK.EQ(D67,D:D) -> 63 | F67: =IFERROR(ROUND(VLOOKUP(A67,[1]eco_journals!B:E,4,0),2),"") -> 1.18 | G67: =IFERROR(_xlfn.RANK.EQ(F67,F:F),"") -> 27 | H67: =IFERROR(ROUND(VLOOKUP(A67,[1]fin_journals!B:E,4,0),2),"") | I67: =IFERROR(_xlfn.RANK.EQ(H67,H:H),"") | J67: =IFERROR(ROUND(VLOOKUP(A67,[1]bus_journals!B:E,4,0),2),"") | K67: =IFERROR(_xlfn.RANK.EQ(J67,J:J),"") | L67: =IFERROR(ROUND(VLOOKUP(A67,[1]man_journals!B:E,4,0),2),"") | M67: =IFERROR(_xlfn.RANK.EQ(L67,L:L),"") | N67: ECONOMICS | O67: ENVIRONMENTAL STUDIES
A68: JOURNAL OF RETAILING | B68: ELSEVIER | C68: =IFERROR(VLOOKUP(A68,[1]eco_bus_journals!$B:$D,3,0),"") -> 38 | D68: =IFERROR(ROUND(VLOOKUP(A68,[1]eco_bus_journals!$B:$X,4,0),2),"") -> 1.12 | E68: =_xlfn.RANK.EQ(D68,D:D) -> 65 | F68: =IFERROR(ROUND(VLOOKUP(A68,[1]eco_journals!B:E,4,0),2),"") | G68: =IFERROR(_xlfn.RANK.EQ(F68,F:F),"") | H68: =IFERROR(ROUND(VLOOKUP(A68,[1]fin_journals!B:E,4,0),2),"") | I68: =IFERROR(_xlfn.RANK.EQ(H68,H:H),"") | J68: =IFERROR(ROUND(VLOOKUP(A68,[1]bus_journals!B:E,4,0),2),"") -> 3.94 | K68: =IFERROR(_xlfn.RANK.EQ(J68,J:J),"") -> 18 | L68: =IFERROR(ROUND(VLOOKUP(A68,[1]man_journals!B:E,4,0),2),"") | M68: =IFERROR(_xlfn.RANK.EQ(L68,L:L),"") | N68: BUSINESS
A69: RAND JOURNAL OF ECONOMICS | B69: WILEY | C69: =IFERROR(VLOOKUP(A69,[1]eco_bus_journals!$B:$D,3,0),"") -> 46 | D69: =IFERROR(ROUND(VLOOKUP(A69,[1]eco_bus_journals!$B:$X,4,0),2),"") -> 1.11 | E69: =_xlfn.RANK.EQ(D69,D:D) -> 66 | F69: =IFERROR(ROUND(VLOOKUP(A69,[1]eco_journals!B:E,4,0),2),"") -> 0.95 | G69: =IFERROR(_xlfn.RANK.EQ(F69,F:F),"") -> 33 | H69: =IFERROR(ROUND(VLOOKUP(A69,[1]fin_journals!B:E,4,0),2),"") | I69: =IFERROR(_xlfn.RANK.EQ(H69,H:H),"") | J69: =IFERROR(ROUND(VLOOKUP(A69,[1]bus_journals!B:E,4,0),2),"") | K69: =IFERROR(_xlfn.RANK.EQ(J69,J:J),"") | L69: =IFERROR(ROUND(VLOOKUP(A69,[1]man_journals!B:E,4,0),2),"") | M69: =IFERROR(_xlfn.RANK.EQ(L69,L:L),"") | N69: ECONOMICS
A70: JOURNAL OF THE ASSOCIATION OF ENVIRONMENTAL AND RESOURCE ECONOMISTS | B70: UNIV CHICAGO PRESS | C70: =IFERROR(VLOOKUP(A70,[1]eco_bus_journals!$B:$D,3,0),"") -> 36 | D70: =IFERROR(ROUND(VLOOKUP(A70,[1]eco_bus_journals!$B:$X,4,0),2),"") -> 1.15 | E70: =_xlfn.RANK.EQ(D70,D:D) -> 63 | F70: =IFERROR(ROUND(VLOOKUP(A70,[1]eco_journals!B:E,4,0),2),"") -> 1.16 | G70: =IFERROR(_xlfn.RANK.EQ(F70,F:F),"") -> 29 | H70: =IFERROR(ROUND(VLOOKUP(A70,[1]fin_journals!B:E,4,0),2),"") | I70: =IFERROR(_xlfn.RANK.EQ(H70,H:H),"") | J70: =IFERROR(ROUND(VLOOKUP(A70,[1]bus_journals!B:E,4,0),2),"") | K70: =IFERROR(_xlfn.RANK.EQ(J70,J:J),"") | L70: =IFERROR(ROUND(VLOOKUP(A70,[1]man_journals!B:E,4,0),2),"") | M70: =IFERROR(_xlfn.RANK.EQ(L70,L:L),"") | N70: ECONOMICS | O70: ENVIRONMENTAL STUDIES
A71: JOURNAL OF WORLD BUSINESS | B71: ELSEVIER | C71: =IFERROR(VLOOKUP(A71,[1]eco_bus_journals!$B:$D,3,0),"") -> 62 | D71: =IFERROR(ROUND(VLOOKUP(A71,[1]eco_bus_journals!$B:$X,4,0),2),"") -> 0.98 | E71: =_xlfn.RANK.EQ(D71,D:D) -> 74 | F71: =IFERROR(ROUND(VLOOKUP(A71,[1]eco_journals!B:E,4,0),2),"") | G71: =IFERROR(_xlfn.RANK.EQ(F71,F:F),"") | H71: =IFERROR(ROUND(VLOOKUP(A71,[1]fin_journals!B:E,4,0),2),"") | I71: =IFERROR(_xlfn.RANK.EQ(H71,H:H),"") | J71: =IFERROR(ROUND(VLOOKUP(A71,[1]bus_journals!B:E,4,0),2),"") -> 2.74 | K71: =IFERROR(_xlfn.RANK.EQ(J71,J:J),"") -> 26 | L71: =IFERROR(ROUND(VLOOKUP(A71,[1]man_journals!B:E,4,0),2),"") | M71: =IFERROR(_xlfn.RANK.EQ(L71,L:L),"") | N71: BUSINESS
A72: JOURNAL OF OPERATIONS MANAGEMENT | B72: WILEY | C72: =IFERROR(VLOOKUP(A72,[1]eco_bus_journals!$B:$D,3,0),"") -> 44 | D72: =IFERROR(ROUND(VLOOKUP(A72,[1]eco_bus_journals!$B:$X,4,0),2),"") -> 1.08 | E72: =_xlfn.RANK.EQ(D72,D:D) -> 69 | F72: =IFERROR(ROUND(VLOOKUP(A72,[1]eco_journals!B:E,4,0),2),"") | G72: =IFERROR(_xlfn.RANK.EQ(F72,F:F),"") | H72: =IFERROR(ROUND(VLOOKUP(A72,[1]fin_journals!B:E,4,0),2),"") | I72: =IFERROR(_xlfn.RANK.EQ(H72,H:H),"") | J72: =IFERROR(ROUND(VLOOKUP(A72,[1]bus_journals!B:E,4,0),2),"") | K72: =IFERROR(_xlfn.RANK.EQ(J72,J:J),"") | L72: =IFERROR(ROUND(VLOOKUP(A72,[1]man_journals!B:E,4,0),2),"") -> 2.42 | M72: =IFERROR(_xlfn.RANK.EQ(L72,L:L),"") -> 18 | N72: MANAGEMENT | O72: OPERATIONS RESEARCH & MANAGEMENT SCIENCE
A73: M&SOM-MANUFACTURING & SERVICE OPERATIONS MANAGEMENT | B73: INFORMS | C73: =IFERROR(VLOOKUP(A73,[1]eco_bus_journals!$B:$D,3,0),"") -> 112 | D73: =IFERROR(ROUND(VLOOKUP(A73,[1]eco_bus_journals!$B:$X,4,0),2),"") -> 1.02 | E73: =_xlfn.RANK.EQ(D73,D:D) -> 71 | F73: =IFERROR(ROUND(VLOOKUP(A73,[1]eco_journals!B:E,4,0),2),"") | G73: =IFERROR(_xlfn.RANK.EQ(F73,F:F),"") | H73: =IFERROR(ROUND(VLOOKUP(A73,[1]fin_journals!B:E,4,0),2),"") | I73: =IFERROR(_xlfn.RANK.EQ(H73,H:H),"") | J73: =IFERROR(ROUND(VLOOKUP(A73,[1]bus_journals!B:E,4,0),2),"") | K73: =IFERROR(_xlfn.RANK.EQ(J73,J:J),"") | L73: =IFERROR(ROUND(VLOOKUP(A73,[1]man_journals!B:E,4,0),2),"") -> 2.22 | M73: =IFERROR(_xlfn.RANK.EQ(L73,L:L),"") -> 20 | N73: MANAGEMENT | O73: OPERATIONS RESEARCH & MANAGEMENT SCIENCE
A74: CONTEMPORARY ACCOUNTING RESEARCH | B74: WILEY | C74: =IFERROR(VLOOKUP(A74,[1]eco_bus_journals!$B:$D,3,0),"") -> 113 | D74: =IFERROR(ROUND(VLOOKUP(A74,[1]eco_bus_journals!$B:$X,4,0),2),"") -> 0.94 | E74: =_xlfn.RANK.EQ(D74,D:D) -> 79 | F74: =IFERROR(ROUND(VLOOKUP(A74,[1]eco_journals!B:E,4,0),2),"") | G74: =IFERROR(_xlfn.RANK.EQ(F74,F:F),"") | H74: =IFERROR(ROUND(VLOOKUP(A74,[1]fin_journals!B:E,4,0),2),"") -> 3.8 | I74: =IFERROR(_xlfn.RANK.EQ(H74,H:H),"") -> 10 | J74: =IFERROR(ROUND(VLOOKUP(A74,[1]bus_journals!B:E,4,0),2),"") | K74: =IFERROR(_xlfn.RANK.EQ(J74,J:J),"") | L74: =IFERROR(ROUND(VLOOKUP(A74,[1]man_journals!B:E,4,0),2),"") | M74: =IFERROR(_xlfn.RANK.EQ(L74,L:L),"") | N74: FINANCE
A75: ECONOMIC JOURNAL | B75: OXFORD UNIV PRESS | C75: =IFERROR(VLOOKUP(A75,[1]eco_bus_journals!$B:$D,3,0),"") -> 95 | D75: =IFERROR(ROUND(VLOOKUP(A75,[1]eco_bus_journals!$B:$X,4,0),2),"") -> 0.99 | E75: =_xlfn.RANK.EQ(D75,D:D) -> 72 | F75: =IFERROR(ROUND(VLOOKUP(A75,[1]eco_journals!B:E,4,0),2),"") -> 1.01 | G75: =IFERROR(_xlfn.RANK.EQ(F75,F:F),"") -> 31 | H75: =IFERROR(ROUND(VLOOKUP(A75,[1]fin_journals!B:E,4,0),2),"") | I75: =IFERROR(_xlfn.RANK.EQ(H75,H:H),"") | J75: =IFERROR(ROUND(VLOOKUP(A75,[1]bus_journals!B:E,4,0),2),"") | K75: =IFERROR(_xlfn.RANK.EQ(J75,J:J),"") | L75: =IFERROR(ROUND(VLOOKUP(A75,[1]man_journals!B:E,4,0),2),"") | M75: =IFERROR(_xlfn.RANK.EQ(L75,L:L),"") | N75: ECONOMICS
A76: ANNUAL REVIEW OF RESOURCE ECONOMICS | B76: ANNUAL REVIEWS | C76: =IFERROR(VLOOKUP(A76,[1]eco_bus_journals!$B:$D,3,0),"") -> 23 | D76: =IFERROR(ROUND(VLOOKUP(A76,[1]eco_bus_journals!$B:$X,4,0),2),"") -> 0.88 | E76: =_xlfn.RANK.EQ(D76,D:D) -> 84 | F76: =IFERROR(ROUND(VLOOKUP(A76,[1]eco_journals!B:E,4,0),2),"") -> 0.86 | G76: =IFERROR(_xlfn.RANK.EQ(F76,F:F),"") -> 36 | H76: =IFERROR(ROUND(VLOOKUP(A76,[1]fin_journals!B:E,4,0),2),"") | I76: =IFERROR(_xlfn.RANK.EQ(H76,H:H),"") | J76: =IFERROR(ROUND(VLOOKUP(A76,[1]bus_journals!B:E,4,0),2),"") | K76: =IFERROR(_xlfn.RANK.EQ(J76,J:J),"") | L76: =IFERROR(ROUND(VLOOKUP(A76,[1]man_journals!B:E,4,0),2),"") | M76: =IFERROR(_xlfn.RANK.EQ(L76,L:L),"") | N76: ECONOMICS
A77: AMERICAN ECONOMIC JOURNAL-MICROECONOMICS | B77: AMER ECONOMIC ASSOC | C77: =IFERROR(VLOOKUP(A77,[1]eco_bus_journals!$B:$D,3,0),"") -> 34 | D77: =IFERROR(ROUND(VLOOKUP(A77,[1]eco_bus_journals!$B:$X,4,0),2),"") -> 0.93 | E77: =_xlfn.RANK.EQ(D77,D:D) -> 80 | F77: =IFERROR(ROUND(VLOOKUP(A77,[1]eco_journals!B:E,4,0),2),"") -> 0.86 | G77: =IFERROR(_xlfn.RANK.EQ(F77,F:F),"") -> 36 | H77: =IFERROR(ROUND(VLOOKUP(A77,[1]fin_journals!B:E,4,0),2),"") | I77: =IFERROR(_xlfn.RANK.EQ(H77,H:H),"") | J77: =IFERROR(ROUND(VLOOKUP(A77,[1]bus_journals!B:E,4,0),2),"") | K77: =IFERROR(_xlfn.RANK.EQ(J77,J:J),"") | L77: =IFERROR(ROUND(VLOOKUP(A77,[1]man_journals!B:E,4,0),2),"") | M77: =IFERROR(_xlfn.RANK.EQ(L77,L:L),"") | N77: ECONOMICS
A78: INTERNATIONAL JOURNAL OF RESEARCH IN MARKETING | B78: ELSEVIER | C78: =IFERROR(VLOOKUP(A78,[1]eco_bus_journals!$B:$D,3,0),"") -> 47 | D78: =IFERROR(ROUND(VLOOKUP(A78,[1]eco_bus_journals!$B:$X,4,0),2),"") -> 0.97 | E78: =_xlfn.RANK.EQ(D78,D:D) -> 76 | F78: =IFERROR(ROUND(VLOOKUP(A78,[1]eco_journals!B:E,4,0),2),"") | G78: =IFERROR(_xlfn.RANK.EQ(F78,F:F),"") | H78: =IFERROR(ROUND(VLOOKUP(A78,[1]fin_journals!B:E,4,0),2),"") | I78: =IFERROR(_xlfn.RANK.EQ(H78,H:H),"") | J78: =IFERROR(ROUND(VLOOKUP(A78,[1]bus_journals!B:E,4,0),2),"") -> 3.29 | K78: =IFERROR(_xlfn.RANK.EQ(J78,J:J),"") -> 23 | L78: =IFERROR(ROUND(VLOOKUP(A78,[1]man_journals!B:E,4,0),2),"") | M78: =IFERROR(_xlfn.RANK.EQ(L78,L:L),"") | N78: BUSINESS
A79: LONG RANGE PLANNING | B79: ELSEVIER | C79: =IFERROR(VLOOKUP(A79,[1]eco_bus_journals!$B:$D,3,0),"") -> 56 | D79: =IFERROR(ROUND(VLOOKUP(A79,[1]eco_bus_journals!$B:$X,4,0),2),"") -> 0.98 | E79: =_xlfn.RANK.EQ(D79,D:D) -> 74 | F79: =IFERROR(ROUND(VLOOKUP(A79,[1]eco_journals!B:E,4,0),2),"") | G79: =IFERROR(_xlfn.RANK.EQ(F79,F:F),"") | H79: =IFERROR(ROUND(VLOOKUP(A79,[1]fin_journals!B:E,4,0),2),"") | I79: =IFERROR(_xlfn.RANK.EQ(H79,H:H),"") | J79: =IFERROR(ROUND(VLOOKUP(A79,[1]bus_journals!B:E,4,0),2),"") -> 2.61 | K79: =IFERROR(_xlfn.RANK.EQ(J79,J:J),"") -> 27 | L79: =IFERROR(ROUND(VLOOKUP(A79,[1]man_journals!B:E,4,0),2),"") -> 2.11 | M79: =IFERROR(_xlfn.RANK.EQ(L79,L:L),"") -> 22 | N79: BUSINESS | O79: DEVELOPMENT STUDIES | P79: MANAGEMENT | Q79: REGIONAL & URBAN PLANNING
A80: ACADEMY OF MANAGEMENT LEARNING & EDUCATION | B80: ACAD MANAGEMENT | C80: =IFERROR(VLOOKUP(A80,[1]eco_bus_journals!$B:$D,3,0),"") -> 22 | D80: =IFERROR(ROUND(VLOOKUP(A80,[1]eco_bus_journals!$B:$X,4,0),2),"") -> 0.91 | E80: =_xlfn.RANK.EQ(D80,D:D) -> 81 | F80: =IFERROR(ROUND(VLOOKUP(A80,[1]eco_journals!B:E,4,0),2),"") | G80: =IFERROR(_xlfn.RANK.EQ(F80,F:F),"") | H80: =IFERROR(ROUND(VLOOKUP(A80,[1]fin_journals!B:E,4,0),2),"") | I80: =IFERROR(_xlfn.RANK.EQ(H80,H:H),"") | J80: =IFERROR(ROUND(VLOOKUP(A80,[1]bus_journals!B:E,4,0),2),"") | K80: =IFERROR(_xlfn.RANK.EQ(J80,J:J),"") | L80: =IFERROR(ROUND(VLOOKUP(A80,[1]man_journals!B:E,4,0),2),"") -> 2.1 | M80: =IFERROR(_xlfn.RANK.EQ(L80,L:L),"") -> 23 | N80: EDUCATION & EDUCATIONAL RESEARCH | O80: MANAGEMENT
A81: ORGANIZATION STUDIES | B81: SAGE PUBLICATIONS | C81: =IFERROR(VLOOKUP(A81,[1]eco_bus_journals!$B:$D,3,0),"") -> 90 | D81: =IFERROR(ROUND(VLOOKUP(A81,[1]eco_bus_journals!$B:$X,4,0),2),"") -> 1.17 | E81: =_xlfn.RANK.EQ(D81,D:D) -> 62 | F81: =IFERROR(ROUND(VLOOKUP(A81,[1]eco_journals!B:E,4,0),2),"") | G81: =IFERROR(_xlfn.RANK.EQ(F81,F:F),"") | H81: =IFERROR(ROUND(VLOOKUP(A81,[1]fin_journals!B:E,4,0),2),"") | I81: =IFERROR(_xlfn.RANK.EQ(H81,H:H),"") | J81: =IFERROR(ROUND(VLOOKUP(A81,[1]bus_journals!B:E,4,0),2),"") | K81: =IFERROR(_xlfn.RANK.EQ(J81,J:J),"") | L81: =IFERROR(ROUND(VLOOKUP(A81,[1]man_journals!B:E,4,0),2),"") -> 2.47 | M81: =IFERROR(_xlfn.RANK.EQ(L81,L:L),"") -> 17 | N81: MANAGEMENT
A82: ACCOUNTING ORGANIZATIONS AND SOCIETY | B82: ELSEVIER | C82: =IFERROR(VLOOKUP(A82,[1]eco_bus_journals!$B:$D,3,0),"") -> 42 | D82: =IFERROR(ROUND(VLOOKUP(A82,[1]eco_bus_journals!$B:$X,4,0),2),"") -> 0.95 | E82: =_xlfn.RANK.EQ(D82,D:D) -> 77 | F82: =IFERROR(ROUND(VLOOKUP(A82,[1]eco_journals!B:E,4,0),2),"") | G82: =IFERROR(_xlfn.RANK.EQ(F82,F:F),"") | H82: =IFERROR(ROUND(VLOOKUP(A82,[1]fin_journals!B:E,4,0),2),"") -> 3.28 | I82: =IFERROR(_xlfn.RANK.EQ(H82,H:H),"") -> 13 | J82: =IFERROR(ROUND(VLOOKUP(A82,[1]bus_journals!B:E,4,0),2),"") | K82: =IFERROR(_xlfn.RANK.EQ(J82,J:J),"") | L82: =IFERROR(ROUND(VLOOKUP(A82,[1]man_journals!B:E,4,0),2),"") | M82: =IFERROR(_xlfn.RANK.EQ(L82,L:L),"") | N82: FINANCE
A83: OXFORD REVIEW OF ECONOMIC POLICY | B83: OXFORD UNIV PRESS | C83: =IFERROR(VLOOKUP(A83,[1]eco_bus_journals!$B:$D,3,0),"") -> 62 | D83: =IFERROR(ROUND(VLOOKUP(A83,[1]eco_bus_journals!$B:$X,4,0),2),"") -> 0.9 | E83: =_xlfn.RANK.EQ(D83,D:D) -> 83 | F83: =IFERROR(ROUND(VLOOKUP(A83,[1]eco_journals!B:E,4,0),2),"") -> 0.84 | G83: =IFERROR(_xlfn.RANK.EQ(F83,F:F),"") -> 39 | H83: =IFERROR(ROUND(VLOOKUP(A83,[1]fin_journals!B:E,4,0),2),"") -> 0.21 | I83: =IFERROR(_xlfn.RANK.EQ(H83,H:H),"") -> 94 | J83: =IFERROR(ROUND(VLOOKUP(A83,[1]bus_journals!B:E,4,0),2),"") | K83: =IFERROR(_xlfn.RANK.EQ(J83,J:J),"") | L83: =IFERROR(ROUND(VLOOKUP(A83,[1]man_journals!B:E,4,0),2),"") -> 1.8 | M83: =IFERROR(_xlfn.RANK.EQ(L83,L:L),"") -> 27 | N83: ECONOMICS
A84: INTERNATIONAL BUSINESS REVIEW | B84: ELSEVIER | C84: =IFERROR(VLOOKUP(A84,[1]eco_bus_journals!$B:$D,3,0),"") -> 83 | D84: =IFERROR(ROUND(VLOOKUP(A84,[1]eco_bus_journals!$B:$X,4,0),2),"") -> 0.91 | E84: =_xlfn.RANK.EQ(D84,D:D) -> 81 | F84: =IFERROR(ROUND(VLOOKUP(A84,[1]eco_journals!B:E,4,0),2),"") | G84: =IFERROR(_xlfn.RANK.EQ(F84,F:F),"") | H84: =IFERROR(ROUND(VLOOKUP(A84,[1]fin_journals!B:E,4,0),2),"") | I84: =IFERROR(_xlfn.RANK.EQ(H84,H:H),"") | J84: =IFERROR(ROUND(VLOOKUP(A84,[1]bus_journals!B:E,4,0),2),"") -> 2.45 | K84: =IFERROR(_xlfn.RANK.EQ(J84,J:J),"") -> 29 | L84: =IFERROR(ROUND(VLOOKUP(A84,[1]man_journals!B:E,4,0),2),"") | M84: =IFERROR(_xlfn.RANK.EQ(L84,L:L),"") | N84: BUSINESS
A85: JOURNAL OF RISK AND UNCERTAINTY | B85: SPRINGER | C85: =IFERROR(VLOOKUP(A85,[1]eco_bus_journals!$B:$D,3,0),"") -> 24 | D85: =IFERROR(ROUND(VLOOKUP(A85,[1]eco_bus_journals!$B:$X,4,0),2),"") -> 0.85 | E85: =_xlfn.RANK.EQ(D85,D:D) -> 85 | F85: =IFERROR(ROUND(VLOOKUP(A85,[1]eco_journals!B:E,4,0),2),"") -> 0.92 | G85: =IFERROR(_xlfn.RANK.EQ(F85,F:F),"") -> 34 | H85: =IFERROR(ROUND(VLOOKUP(A85,[1]fin_journals!B:E,4,0),2),"") -> 1.34 | I85: =IFERROR(_xlfn.RANK.EQ(H85,H:H),"") -> 27 | J85: =IFERROR(ROUND(VLOOKUP(A85,[1]bus_journals!B:E,4,0),2),"") | K85: =IFERROR(_xlfn.RANK.EQ(J85,J:J),"") | L85: =IFERROR(ROUND(VLOOKUP(A85,[1]man_journals!B:E,4,0),2),"") | M85: =IFERROR(_xlfn.RANK.EQ(L85,L:L),"") | N85: FINANCE | O85: ECONOMICS
A86: THEORETICAL ECONOMICS | B86: ECONOMETRIC SOCIETY | C86: =IFERROR(VLOOKUP(A86,[1]eco_bus_journals!$B:$D,3,0),"") -> 45 | D86: =IFERROR(ROUND(VLOOKUP(A86,[1]eco_bus_journals!$B:$X,4,0),2),"") -> 0.99 | E86: =_xlfn.RANK.EQ(D86,D:D) -> 72 | F86: =IFERROR(ROUND(VLOOKUP(A86,[1]eco_journals!B:E,4,0),2),"") -> 0.98 | G86: =IFERROR(_xlfn.RANK.EQ(F86,F:F),"") -> 32 | H86: =IFERROR(ROUND(VLOOKUP(A86,[1]fin_journals!B:E,4,0),2),"") | I86: =IFERROR(_xlfn.RANK.EQ(H86,H:H),"") | J86: =IFERROR(ROUND(VLOOKUP(A86,[1]bus_journals!B:E,4,0),2),"") | K86: =IFERROR(_xlfn.RANK.EQ(J86,J:J),"") | L86: =IFERROR(ROUND(VLOOKUP(A86,[1]man_journals!B:E,4,0),2),"") | M86: =IFERROR(_xlfn.RANK.EQ(L86,L:L),"") | N86: ECONOMICS
A87: JOURNAL OF CORPORATE FINANCE | B87: ELSEVIER | C87: =IFERROR(VLOOKUP(A87,[1]eco_bus_journals!$B:$D,3,0),"") -> 234 | D87: =IFERROR(ROUND(VLOOKUP(A87,[1]eco_bus_journals!$B:$X,4,0),2),"") -> 0.85 | E87: =_xlfn.RANK.EQ(D87,D:D) -> 85 | F87: =IFERROR(ROUND(VLOOKUP(A87,[1]eco_journals!B:E,4,0),2),"") | G87: =IFERROR(_xlfn.RANK.EQ(F87,F:F),"") | H87: =IFERROR(ROUND(VLOOKUP(A87,[1]fin_journals!B:E,4,0),2),"") -> 1.87 | I87: =IFERROR(_xlfn.RANK.EQ(H87,H:H),"") -> 17 | J87: =IFERROR(ROUND(VLOOKUP(A87,[1]bus_journals!B:E,4,0),2),"") | K87: =IFERROR(_xlfn.RANK.EQ(J87,J:J),"") | L87: =IFERROR(ROUND(VLOOKUP(A87,[1]man_journals!B:E,4,0),2),"") | M87: =IFERROR(_xlfn.RANK.EQ(L87,L:L),"") | N87: FINANCE
A88: EUROPEAN ECONOMIC REVIEW | B88: ELSEVIER | C88: =IFERROR(VLOOKUP(A88,[1]eco_bus_journals!$B:$D,3,0),"") -> 192 | D88: =IFERROR(ROUND(VLOOKUP(A88,[1]eco_bus_journals!$B:$X,4,0),2),"") -> 0.84 | E88: =_xlfn.RANK.EQ(D88,D:D) -> 87 | F88: =IFERROR(ROUND(VLOOKUP(A88,[1]eco_journals!B:E,4,0),2),"") -> 0.8 | G88: =IFERROR(_xlfn.RANK.EQ(F88,F:F),"") -> 41 | H88: =IFERROR(ROUND(VLOOKUP(A88,[1]fin_journals!B:E,4,0),2),"") | I88: =IFERROR(_xlfn.RANK.EQ(H88,H:H),"") | J88: =IFERROR(ROUND(VLOOKUP(A88,[1]bus_journals!B:E,4,0),2),"") | K88: =IFERROR(_xlfn.RANK.EQ(J88,J:J),"") | L88: =IFERROR(ROUND(VLOOKUP(A88,[1]man_journals!B:E,4,0),2),"") | M88: =IFERROR(_xlfn.RANK.EQ(L88,L:L),"") | N88: ECONOMICS
A89: JOURNAL OF FINANCIAL ECONOMETRICS | B89: OXFORD UNIV PRESS | C89: =IFERROR(VLOOKUP(A89,[1]eco_bus_journals!$B:$D,3,0),"") -> 21 | D89: =IFERROR(ROUND(VLOOKUP(A89,[1]eco_bus_journals!$B:$X,4,0),2),"") -> 0.83 | E89: =_xlfn.RANK.EQ(D89,D:D) -> 90 | F89: =IFERROR(ROUND(VLOOKUP(A89,[1]eco_journals!B:E,4,0),2),"") -> 0.63 | G89: =IFERROR(_xlfn.RANK.EQ(F89,F:F),"") -> 60 | H89: =IFERROR(ROUND(VLOOKUP(A89,[1]fin_journals!B:E,4,0),2),"") -> 1.51 | I89: =IFERROR(_xlfn.RANK.EQ(H89,H:H),"") -> 22 | J89: =IFERROR(ROUND(VLOOKUP(A89,[1]bus_journals!B:E,4,0),2),"") | K89: =IFERROR(_xlfn.RANK.EQ(J89,J:J),"") | L89: =IFERROR(ROUND(VLOOKUP(A89,[1]man_journals!B:E,4,0),2),"") | M89: =IFERROR(_xlfn.RANK.EQ(L89,L:L),"") | N89: FINANCE | O89: ECONOMICS
A90: STRATEGIC ORGANIZATION | B90: SAGE PUBLICATIONS | C90: =IFERROR(VLOOKUP(A90,[1]eco_bus_journals!$B:$D,3,0),"") -> 53 | D90: =IFERROR(ROUND(VLOOKUP(A90,[1]eco_bus_journals!$B:$X,4,0),2),"") -> 0.84 | E90: =_xlfn.RANK.EQ(D90,D:D) -> 87 | F90: =IFERROR(ROUND(VLOOKUP(A90,[1]eco_journals!B:E,4,0),2),"") | G90: =IFERROR(_xlfn.RANK.EQ(F90,F:F),"") | H90: =IFERROR(ROUND(VLOOKUP(A90,[1]fin_journals!B:E,4,0),2),"") | I90: =IFERROR(_xlfn.RANK.EQ(H90,H:H),"") | J90: =IFERROR(ROUND(VLOOKUP(A90,[1]bus_journals!B:E,4,0),2),"") -> 1.97 | K90: =IFERROR(_xlfn.RANK.EQ(J90,J:J),"") -> 35 | L90: =IFERROR(ROUND(VLOOKUP(A90,[1]man_journals!B:E,4,0),2),"") -> 1.88 | M90: =IFERROR(_xlfn.RANK.EQ(L90,L:L),"") -> 24 | N90: BUSINESS | O90: MANAGEMENT
A91: EXPERIMENTAL ECONOMICS | B91: CAMBRIDGE UNIV PRESS | C91: =IFERROR(VLOOKUP(A91,[1]eco_bus_journals!$B:$D,3,0),"") -> 70 | D91: =IFERROR(ROUND(VLOOKUP(A91,[1]eco_bus_journals!$B:$X,4,0),2),"") -> 0.73 | E91: =_xlfn.RANK.EQ(D91,D:D) -> 103 | F91: =IFERROR(ROUND(VLOOKUP(A91,[1]eco_journals!B:E,4,0),2),"") -> 0.68 | G91: =IFERROR(_xlfn.RANK.EQ(F91,F:F),"") -> 53 | H91: =IFERROR(ROUND(VLOOKUP(A91,[1]fin_journals!B:E,4,0),2),"") | I91: =IFERROR(_xlfn.RANK.EQ(H91,H:H),"") | J91: =IFERROR(ROUND(VLOOKUP(A91,[1]bus_journals!B:E,4,0),2),"") | K91: =IFERROR(_xlfn.RANK.EQ(J91,J:J),"") | L91: =IFERROR(ROUND(VLOOKUP(A91,[1]man_journals!B:E,4,0),2),"") | M91: =IFERROR(_xlfn.RANK.EQ(L91,L:L),"") | N91: ECONOMICS
A92: BRITISH JOURNAL OF MANAGEMENT | B92: WILEY | C92: =IFERROR(VLOOKUP(A92,[1]eco_bus_journals!$B:$D,3,0),"") -> 76 | D92: =IFERROR(ROUND(VLOOKUP(A92,[1]eco_bus_journals!$B:$X,4,0),2),"") -> 0.84 | E92: =_xlfn.RANK.EQ(D92,D:D) -> 87 | F92: =IFERROR(ROUND(VLOOKUP(A92,[1]eco_journals!B:E,4,0),2),"") | G92: =IFERROR(_xlfn.RANK.EQ(F92,F:F),"") | H92: =IFERROR(ROUND(VLOOKUP(A92,[1]fin_journals!B:E,4,0),2),"") | I92: =IFERROR(_xlfn.RANK.EQ(H92,H:H),"") | J92: =IFERROR(ROUND(VLOOKUP(A92,[1]bus_journals!B:E,4,0),2),"") -> 1.99 | K92: =IFERROR(_xlfn.RANK.EQ(J92,J:J),"") -> 34 | L92: =IFERROR(ROUND(VLOOKUP(A92,[1]man_journals!B:E,4,0),2),"") -> 1.54 | M92: =IFERROR(_xlfn.RANK.EQ(L92,L:L),"") -> 34 | N92: BUSINESS | O92: MANAGEMENT
A93: JOURNAL OF DEVELOPMENT ECONOMICS | B93: ELSEVIER | C93: =IFERROR(VLOOKUP(A93,[1]eco_bus_journals!$B:$D,3,0),"") -> 132 | D93: =IFERROR(ROUND(VLOOKUP(A93,[1]eco_bus_journals!$B:$X,4,0),2),"") -> 0.79 | E93: =_xlfn.RANK.EQ(D93,D:D) -> 93 | F93: =IFERROR(ROUND(VLOOKUP(A93,[1]eco_journals!B:E,4,0),2),"") -> 0.82 | G93: =IFERROR(_xlfn.RANK.EQ(F93,F:F),"") -> 40 | H93: =IFERROR(ROUND(VLOOKUP(A93,[1]fin_journals!B:E,4,0),2),"") | I93: =IFERROR(_xlfn.RANK.EQ(H93,H:H),"") | J93: =IFERROR(ROUND(VLOOKUP(A93,[1]bus_journals!B:E,4,0),2),"") | K93: =IFERROR(_xlfn.RANK.EQ(J93,J:J),"") | L93: =IFERROR(ROUND(VLOOKUP(A93,[1]man_journals!B:E,4,0),2),"") | M93: =IFERROR(_xlfn.RANK.EQ(L93,L:L),"") | N93: ECONOMICS
A94: JOURNAL OF ECONOMIC GROWTH | B94: SPRINGER | C94: =IFERROR(VLOOKUP(A94,[1]eco_bus_journals!$B:$D,3,0),"") -> 11 | D94: =IFERROR(ROUND(VLOOKUP(A94,[1]eco_bus_journals!$B:$X,4,0),2),"") -> 0.95 | E94: =_xlfn.RANK.EQ(D94,D:D) -> 77 | F94: =IFERROR(ROUND(VLOOKUP(A94,[1]eco_journals!B:E,4,0),2),"") -> 1.02 | G94: =IFERROR(_xlfn.RANK.EQ(F94,F:F),"") -> 30 | H94: =IFERROR(ROUND(VLOOKUP(A94,[1]fin_journals!B:E,4,0),2),"") | I94: =IFERROR(_xlfn.RANK.EQ(H94,H:H),"") | J94: =IFERROR(ROUND(VLOOKUP(A94,[1]bus_journals!B:E,4,0),2),"") | K94: =IFERROR(_xlfn.RANK.EQ(J94,J:J),"") | L94: =IFERROR(ROUND(VLOOKUP(A94,[1]man_journals!B:E,4,0),2),"") | M94: =IFERROR(_xlfn.RANK.EQ(L94,L:L),"") | N94: ECONOMICS
A95: HUMAN RESOURCE MANAGEMENT REVIEW | B95: ELSEVIER | C95: =IFERROR(VLOOKUP(A95,[1]eco_bus_journals!$B:$D,3,0),"") -> 35 | D95: =IFERROR(ROUND(VLOOKUP(A95,[1]eco_bus_journals!$B:$X,4,0),2),"") -> 0.76 | E95: =_xlfn.RANK.EQ(D95,D:D) -> 96 | F95: =IFERROR(ROUND(VLOOKUP(A95,[1]eco_journals!B:E,4,0),2),"") | G95: =IFERROR(_xlfn.RANK.EQ(F95,F:F),"") | H95: =IFERROR(ROUND(VLOOKUP(A95,[1]fin_journals!B:E,4,0),2),"") | I95: =IFERROR(_xlfn.RANK.EQ(H95,H:H),"") | J95: =IFERROR(ROUND(VLOOKUP(A95,[1]bus_journals!B:E,4,0),2),"") | K95: =IFERROR(_xlfn.RANK.EQ(J95,J:J),"") | L95: =IFERROR(ROUND(VLOOKUP(A95,[1]man_journals!B:E,4,0),2),"") -> 1.83 | M95: =IFERROR(_xlfn.RANK.EQ(L95,L:L),"") -> 25 | N95: MANAGEMENT
A96: LEADERSHIP QUARTERLY | B96: ELSEVIER | C96: =IFERROR(VLOOKUP(A96,[1]eco_bus_journals!$B:$D,3,0),"") -> 51 | D96: =IFERROR(ROUND(VLOOKUP(A96,[1]eco_bus_journals!$B:$X,4,0),2),"") -> 0.73 | E96: =_xlfn.RANK.EQ(D96,D:D) -> 103 | F96: =IFERROR(ROUND(VLOOKUP(A96,[1]eco_journals!B:E,4,0),2),"") | G96: =IFERROR(_xlfn.RANK.EQ(F96,F:F),"") | H96: =IFERROR(ROUND(VLOOKUP(A96,[1]fin_journals!B:E,4,0),2),"") | I96: =IFERROR(_xlfn.RANK.EQ(H96,H:H),"") | J96: =IFERROR(ROUND(VLOOKUP(A96,[1]bus_journals!B:E,4,0),2),"") | K96: =IFERROR(_xlfn.RANK.EQ(J96,J:J),"") | L96: =IFERROR(ROUND(VLOOKUP(A96,[1]man_journals!B:E,4,0),2),"") -> 1.56 | M96: =IFERROR(_xlfn.RANK.EQ(L96,L:L),"") -> 33 | N96: MANAGEMENT | O96: PSYCHOLOGY, APPLIED
A97: BUSINESS & SOCIETY | B97: SAGE PUBLICATIONS | C97: =IFERROR(VLOOKUP(A97,[1]eco_bus_journals!$B:$D,3,0),"") -> 100 | D97: =IFERROR(ROUND(VLOOKUP(A97,[1]eco_bus_journals!$B:$X,4,0),2),"") -> 0.83 | E97: =_xlfn.RANK.EQ(D97,D:D) -> 90 | F97: =IFERROR(ROUND(VLOOKUP(A97,[1]eco_journals!B:E,4,0),2),"") | G97: =IFERROR(_xlfn.RANK.EQ(F97,F:F),"") | H97: =IFERROR(ROUND(VLOOKUP(A97,[1]fin_journals!B:E,4,0),2),"") | I97: =IFERROR(_xlfn.RANK.EQ(H97,H:H),"") | J97: =IFERROR(ROUND(VLOOKUP(A97,[1]bus_journals!B:E,4,0),2),"") -> 2.22 | K97: =IFERROR(_xlfn.RANK.EQ(J97,J:J),"") -> 31 | L97: =IFERROR(ROUND(VLOOKUP(A97,[1]man_journals!B:E,4,0),2),"") | M97: =IFERROR(_xlfn.RANK.EQ(L97,L:L),"") | N97: BUSINESS
A98: JOURNAL OF LAW & ECONOMICS | B98: UNIV CHICAGO PRESS | C98: =IFERROR(VLOOKUP(A98,[1]eco_bus_journals!$B:$D,3,0),"") -> 26 | D98: =IFERROR(ROUND(VLOOKUP(A98,[1]eco_bus_journals!$B:$X,4,0),2),"") -> 0.8 | E98: =_xlfn.RANK.EQ(D98,D:D) -> 92 | F98: =IFERROR(ROUND(VLOOKUP(A98,[1]eco_journals!B:E,4,0),2),"") -> 0.64 | G98: =IFERROR(_xlfn.RANK.EQ(F98,F:F),"") -> 58 | H98: =IFERROR(ROUND(VLOOKUP(A98,[1]fin_journals!B:E,4,0),2),"") | I98: =IFERROR(_xlfn.RANK.EQ(H98,H:H),"") | J98: =IFERROR(ROUND(VLOOKUP(A98,[1]bus_journals!B:E,4,0),2),"") | K98: =IFERROR(_xlfn.RANK.EQ(J98,J:J),"") | L98: =IFERROR(ROUND(VLOOKUP(A98,[1]man_journals!B:E,4,0),2),"") | M98: =IFERROR(_xlfn.RANK.EQ(L98,L:L),"") | N98: ECONOMICS | O98: LAW
A99: AMERICAN JOURNAL OF HEALTH ECONOMICS | B99: UNIV CHICAGO PRESS | C99: =IFERROR(VLOOKUP(A99,[1]eco_bus_journals!$B:$D,3,0),"") -> 17 | D99: =IFERROR(ROUND(VLOOKUP(A99,[1]eco_bus_journals!$B:$X,4,0),2),"") -> 0.77 | E99: =_xlfn.RANK.EQ(D99,D:D) -> 95 | F99: =IFERROR(ROUND(VLOOKUP(A99,[1]eco_journals!B:E,4,0),2),"") -> 0.78 | G99: =IFERROR(_xlfn.RANK.EQ(F99,F:F),"") -> 44 | H99: =IFERROR(ROUND(VLOOKUP(A99,[1]fin_journals!B:E,4,0),2),"") | I99: =IFERROR(_xlfn.RANK.EQ(H99,H:H),"") | J99: =IFERROR(ROUND(VLOOKUP(A99,[1]bus_journals!B:E,4,0),2),"") | K99: =IFERROR(_xlfn.RANK.EQ(J99,J:J),"") | L99: =IFERROR(ROUND(VLOOKUP(A99,[1]man_journals!B:E,4,0),2),"") | M99: =IFERROR(_xlfn.RANK.EQ(L99,L:L),"") | N99: ECONOMICS | O99: HEALTH POLICY & SERVICES
A100: FISCAL STUDIES | B100: WILEY | C100: =IFERROR(VLOOKUP(A100,[1]eco_bus_journals!$B:$D,3,0),"") -> 34 | D100: =IFERROR(ROUND(VLOOKUP(A100,[1]eco_bus_journals!$B:$X,4,0),2),"") -> 0.71 | E100: =_xlfn.RANK.EQ(D100,D:D) -> 111 | F100: =IFERROR(ROUND(VLOOKUP(A100,[1]eco_journals!B:E,4,0),2),"") -> 0.75 | G100: =IFERROR(_xlfn.RANK.EQ(F100,F:F),"") -> 46 | H100: =IFERROR(ROUND(VLOOKUP(A100,[1]fin_journals!B:E,4,0),2),"") -> 0.32 | I100: =IFERROR(_xlfn.RANK.EQ(H100,H:H),"") -> 85 | J100: =IFERROR(ROUND(VLOOKUP(A100,[1]bus_journals!B:E,4,0),2),"") | K100: =IFERROR(_xlfn.RANK.EQ(J100,J:J),"") | L100: =IFERROR(ROUND(VLOOKUP(A100,[1]man_journals!B:E,4,0),2),"") | M100: =IFERROR(_xlfn.RANK.EQ(L100,L:L),"") | N100: FINANCE | O100: ECONOMICS
...

Sheet institutions
C1: eco_bus | F1: eco | I1: fin | L1: bus | O1: man
A2: institution | B2: country | C2: pub | D2: score | E2: rank | F2: pub | G2: score | H2: rank | I2: pub | J2: score | K2: rank | L2: pub | M2: score | N2: rank | O2: pub | P2: score | Q2: rank
A3: Center for Economic & Policy Research (CEPR) | B3: USA | C3: =IFERROR(VLOOKUP(A3,[1]eco_bus_institutions!B:E,2,0),"") -> 158 | D3: =IFERROR(VLOOKUP(A3,[1]eco_bus_institutions!B:E,4,0),"") -> 8 | E3: =_xlfn.RANK.EQ(D3,D:D) -> 1 | F3: =IFERROR(VLOOKUP(A3,[1]eco_institutions!B:D,2,0),"") -> 151 | G3: =IFERROR(VLOOKUP(A3,[1]eco_institutions!B:E,4,0),"") -> 6.8528581 | H3: =IFERROR(_xlfn.RANK.EQ(G3,G:G),"") -> 4 | I3: =IFERROR(VLOOKUP(A3,[1]fin_institutions!B:D,2,0),"") -> 43 | J3: =IFERROR(VLOOKUP(A3,[1]fin_institutions!B:E,4,0),"") -> 5.9098339 | K3: =IFERROR(_xlfn.RANK.EQ(J3,J:J),"") -> 6 | L3: =IFERROR(VLOOKUP(A3,[1]bus_institutions!B:D,2,0),"") | M3: =IFERROR(VLOOKUP(A3,[1]bus_institutions!B:E,4,0),"") | N3: =IFERROR(_xlfn.RANK.EQ(M3,M:M),"") | O3: =IFERROR(VLOOKUP(A3,[1]man_institutions!B:E,2,0),"") | P3: =IFERROR(VLOOKUP(A3,[1]man_institutions!B:E,4,0),"") | Q3: =IFERROR(_xlfn.RANK.EQ(P3,P:P),"")
A4: University of Chicago | B4: USA | C4: =IFERROR(VLOOKUP(A4,[1]eco_bus_institutions!B:E,2,0),"") -> 203 | D4: =IFERROR(VLOOKUP(A4,[1]eco_bus_institutions!B:E,4,0),"") -> 7.916794 | E4: =_xlfn.RANK.EQ(D4,D:D) -> 2 | F4: =IFERROR(VLOOKUP(A4,[1]eco_institutions!B:D,2,0),"") -> 157 | G4: =IFERROR(VLOOKUP(A4,[1]eco_institutions!B:E,4,0),"") -> 7.7788765 | H4: =IFERROR(_xlfn.RANK.EQ(G4,G:G),"") -> 2 | I4: =IFERROR(VLOOKUP(A4,[1]fin_institutions!B:D,2,0),"") -> 49 | J4: =IFERROR(VLOOKUP(A4,[1]fin_institutions!B:E,4,0),"") -> 6.8858104 | K4: =IFERROR(_xlfn.RANK.EQ(J4,J:J),"") -> 3 | L4: =IFERROR(VLOOKUP(A4,[1]bus_institutions!B:D,2,0),"") -> 18 | M4: =IFERROR(VLOOKUP(A4,[1]bus_institutions!B:E,4,0),"") -> 2.9859333 | N4: =IFERROR(_xlfn.RANK.EQ(M4,M:M),"") -> 118 | O4: =IFERROR(VLOOKUP(A4,[1]man_institutions!B:E,2,0),"") -> 9 | P4: =IFERROR(VLOOKUP(A4,[1]man_institutions!B:E,4,0),"") -> 1.9264411 | Q4: =IFERROR(_xlfn.RANK.EQ(P4,P:P),"") -> 422
A5: University of California Santa Barbara | B5: USA | C5: =IFERROR(VLOOKUP(A5,[1]eco_bus_institutions!B:E,2,0),"") -> 56 | D5: =IFERROR(VLOOKUP(A5,[1]eco_bus_institutions!B:E,4,0),"") -> 7.8669057 | E5: =_xlfn.RANK.EQ(D5,D:D) -> 3 | F5: =IFERROR(VLOOKUP(A5,[1]eco_institutions!B:D,2,0),"") -> 44 | G5: =IFERROR(VLOOKUP(A5,[1]eco_institutions!B:E,4,0),"") -> 8 | H5: =IFERROR(_xlfn.RANK.EQ(G5,G:G),"") -> 1 | I5: =IFERROR(VLOOKUP(A5,[1]fin_institutions!B:D,2,0),"") -> 6 | J5: =IFERROR(VLOOKUP(A5,[1]fin_institutions!B:E,4,0),"") -> 1.9501291 | K5: =IFERROR(_xlfn.RANK.EQ(J5,J:J),"") -> 170 | L5: =IFERROR(VLOOKUP(A5,[1]bus_institutions!B:D,2,0),"") -> 5 | M5: =IFERROR(VLOOKUP(A5,[1]bus_institutions!B:E,4,0),"") -> 2.0534718 | N5: =IFERROR(_xlfn.RANK.EQ(M5,M:M),"") -> 311 | O5: =IFERROR(VLOOKUP(A5,[1]man_institutions!B:E,2,0),"") -> 10 | P5: =IFERROR(VLOOKUP(A5,[1]man_institutions!B:E,4,0),"") -> 5.3733352 | Q5: =IFERROR(_xlfn.RANK.EQ(P5,P:P),"") -> 31
A6: Swiss Finance Institute (SFI) | B6: SWITZERLAND | C6: =IFERROR(VLOOKUP(A6,[1]eco_bus_institutions!B:E,2,0),"") -> 39 | D6: =IFERROR(VLOOKUP(A6,[1]eco_bus_institutions!B:E,4,0),"") -> 5.1989096 | E6: =_xlfn.RANK.EQ(D6,D:D) -> 12 | F6: =IFERROR(VLOOKUP(A6,[1]eco_institutions!B:D,2,0),"") -> 28 | G6: =IFERROR(VLOOKUP(A6,[1]eco_institutions!B:E,4,0),"") -> 4.0017151 | H6: =IFERROR(_xlfn.RANK.EQ(G6,G:G),"") -> 26 | I6: =IFERROR(VLOOKUP(A6,[1]fin_institutions!B:D,2,0),"") -> 28 | J6: =IFERROR(VLOOKUP(A6,[1]fin_institutions!B:E,4,0),"") -> 4.7617702 | K6: =IFERROR(_xlfn.RANK.EQ(J6,J:J),"") -> 17 | L6: =IFERROR(VLOOKUP(A6,[1]bus_institutions!B:D,2,0),"") | M6: =IFERROR(VLOOKUP(A6,[1]bus_institutions!B:E,4,0),"") | N6: =IFERROR(_xlfn.RANK.EQ(M6,M:M),"") | O6: =IFERROR(VLOOKUP(A6,[1]man_institutions!B:E,2,0),"") | P6: =IFERROR(VLOOKUP(A6,[1]man_institutions!B:E,4,0),"") | Q6: =IFERROR(_xlfn.RANK.EQ(P6,P:P),"")
A7: London Business School | B7: ENGLAND | C7: =IFERROR(VLOOKUP(A7,[1]eco_bus_institutions!B:E,2,0),"") -> 61 | D7: =IFERROR(VLOOKUP(A7,[1]eco_bus_institutions!B:E,4,0),"") -> 6.899268 | E7: =_xlfn.RANK.EQ(D7,D:D) -> 4 | F7: =IFERROR(VLOOKUP(A7,[1]eco_institutions!B:D,2,0),"") -> 30 | G7: =IFERROR(VLOOKUP(A7,[1]eco_institutions!B:E,4,0),"") -> 7.4382434 | H7: =IFERROR(_xlfn.RANK.EQ(G7,G:G),"") -> 3 | I7: =IFERROR(VLOOKUP(A7,[1]fin_institutions!B:D,2,0),"") -> 16 | J7: =IFERROR(VLOOKUP(A7,[1]fin_institutions!B:E,4,0),"") -> 5.043986 | K7: =IFERROR(_xlfn.RANK.EQ(J7,J:J),"") -> 13 | L7: =IFERROR(VLOOKUP(A7,[1]bus_institutions!B:D,2,0),"") -> 23 | M7: =IFERROR(VLOOKUP(A7,[1]bus_institutions!B:E,4,0),"") -> 5.1544791 | N7: =IFERROR(_xlfn.RANK.EQ(M7,M:M),"") -> 11 | O7: =IFERROR(VLOOKUP(A7,[1]man_institutions!B:E,2,0),"") -> 22 | P7: =IFERROR(VLOOKUP(A7,[1]man_institutions!B:E,4,0),"") -> 5.7121906 | Q7: =IFERROR(_xlfn.RANK.EQ(P7,P:P),"") -> 21
A8: Princeton University | B8: USA | C8: =IFERROR(VLOOKUP(A8,[1]eco_bus_institutions!B:E,2,0),"") -> 113 | D8: =IFERROR(VLOOKUP(A8,[1]eco_bus_institutions!B:E,4,0),"") -> 6.7455878 | E8: =_xlfn.RANK.EQ(D8,D:D) -> 5 | F8: =IFERROR(VLOOKUP(A8,[1]eco_institutions!B:D,2,0),"") -> 101 | G8: =IFERROR(VLOOKUP(A8,[1]eco_institutions!B:E,4,0),"") -> 6.4527793 | H8: =IFERROR(_xlfn.RANK.EQ(G8,G:G),"") -> 5 | I8: =IFERROR(VLOOKUP(A8,[1]fin_institutions!B:D,2,0),"") -> 18 | J8: =IFERROR(VLOOKUP(A8,[1]fin_institutions!B:E,4,0),"") -> 3.9390818 | K8: =IFERROR(_xlfn.RANK.EQ(J8,J:J),"") -> 36 | L8: =IFERROR(VLOOKUP(A8,[1]bus_institutions!B:D,2,0),"") | M8: =IFERROR(VLOOKUP(A8,[1]bus_institutions!B:E,4,0),"") | N8: =IFERROR(_xlfn.RANK.EQ(M8,M:M),"") | O8: =IFERROR(VLOOKUP(A8,[1]man_institutions!B:E,2,0),"") | P8: =IFERROR(VLOOKUP(A8,[1]man_institutions!B:E,4,0),"") | Q8: =IFERROR(_xlfn.RANK.EQ(P8,P:P),"")
A9: Yale University | B9: USA | C9: =IFERROR(VLOOKUP(A9,[1]eco_bus_institutions!B:E,2,0),"") -> 165 | D9: =IFERROR(VLOOKUP(A9,[1]eco_bus_institutions!B:E,4,0),"") -> 6.0289883 | E9: =_xlfn.RANK.EQ(D9,D:D) -> 6 | F9: =IFERROR(VLOOKUP(A9,[1]eco_institutions!B:D,2,0),"") -> 134 | G9: =IFERROR(VLOOKUP(A9,[1]eco_institutions!B:E,4,0),"") -> 5.6264041 | H9: =IFERROR(_xlfn.RANK.EQ(G9,G:G),"") -> 9 | I9: =IFERROR(VLOOKUP(A9,[1]fin_institutions!B:D,2,0),"") -> 27 | J9: =IFERROR(VLOOKUP(A9,[1]fin_institutions!B:E,4,0),"") -> 7.5523197 | K9: =IFERROR(_xlfn.RANK.EQ(J9,J:J),"") -> 2 | L9: =IFERROR(VLOOKUP(A9,[1]bus_institutions!B:D,2,0),"") -> 13 | M9: =IFERROR(VLOOKUP(A9,[1]bus_institutions!B:E,4,0),"") -> 5.2209887 | N9: =IFERROR(_xlfn.RANK.EQ(M9,M:M),"") -> 10 | O9: =IFERROR(VLOOKUP(A9,[1]man_institutions!B:E,2,0),"") -> 14 | P9: =IFERROR(VLOOKUP(A9,[1]man_institutions!B:E,4,0),"") -> 5.3674033 | Q9: =IFERROR(_xlfn.RANK.EQ(P9,P:P),"") -> 32
A10: National Bureau of Economic Research | B10: USA | C10: =IFERROR(VLOOKUP(A10,[1]eco_bus_institutions!B:E,2,0),"") -> 724 | D10: =IFERROR(VLOOKUP(A10,[1]eco_bus_institutions!B:E,4,0),"") -> 5.8878175 | E10: =_xlfn.RANK.EQ(D10,D:D) -> 8 | F10: =IFERROR(VLOOKUP(A10,[1]eco_institutions!B:D,2,0),"") -> 710 | G10: =IFERROR(VLOOKUP(A10,[1]eco_institutions!B:E,4,0),"") -> 5.0418361 | H10: =IFERROR(_xlfn.RANK.EQ(G10,G:G),"") -> 13 | I10: =IFERROR(VLOOKUP(A10,[1]fin_institutions!B:D,2,0),"") | J10: =IFERROR(VLOOKUP(A10,[1]fin_institutions!B:E,4,0),"") | K10: =IFERROR(_xlfn.RANK.EQ(J10,J:J),"") | L10: =IFERROR(VLOOKUP(A10,[1]bus_institutions!B:D,2,0),"") | M10: =IFERROR(VLOOKUP(A10,[1]bus_institutions!B:E,4,0),"") | N10: =IFERROR(_xlfn.RANK.EQ(M10,M:M),"") | O10: =IFERROR(VLOOKUP(A10,[1]man_institutions!B:E,2,0),"") | P10: =IFERROR(VLOOKUP(A10,[1]man_institutions!B:E,4,0),"") | Q10: =IFERROR(_xlfn.RANK.EQ(P10,P:P),"")
A11: Stanford University | B11: USA | C11: =IFERROR(VLOOKUP(A11,[1]eco_bus_institutions!B:E,2,0),"") -> 273 | D11: =IFERROR(VLOOKUP(A11,[1]eco_bus_institutions!B:E,4,0),"") -> 5.9488521 | E11: =_xlfn.RANK.EQ(D11,D:D) -> 7 | F11: =IFERROR(VLOOKUP(A11,[1]eco_institutions!B:D,2,0),"") -> 196 | G11: =IFERROR(VLOOKUP(A11,[1]eco_institutions!B:E,4,0),"") -> 5.2596414 | H11: =IFERROR(_xlfn.RANK.EQ(G11,G:G),"") -> 11 | I11: =IFERROR(VLOOKUP(A11,[1]fin_institutions!B:D,2,0),"") -> 44 | J11: =IFERROR(VLOOKUP(A11,[1]fin_institutions!B:E,4,0),"") -> 6.358214 | K11: =IFERROR(_xlfn.RANK.EQ(J11,J:J),"") -> 4 | L11: =IFERROR(VLOOKUP(A11,[1]bus_institutions!B:D,2,0),"") -> 37 | M11: =IFERROR(VLOOKUP(A11,[1]bus_institutions!B:E,4,0),"") -> 5.1481253 | N11: =IFERROR(_xlfn.RANK.EQ(M11,M:M),"") -> 12 | O11: =IFERROR(VLOOKUP(A11,[1]man_institutions!B:E,2,0),"") -> 59 | P11: =IFERROR(VLOOKUP(A11,[1]man_institutions!B:E,4,0),"") -> 7.7233049 | Q11: =IFERROR(_xlfn.RANK.EQ(P11,P:P),"") -> 3
A12: Massachusetts Institute of Technology (MIT) | B12: USA | C12: =IFERROR(VLOOKUP(A12,[1]eco_bus_institutions!B:E,2,0),"") -> 244 | D12: =IFERROR(VLOOKUP(A12,[1]eco_bus_institutions!B:E,4,0),"") -> 5.8630032 | E12: =_xlfn.RANK.EQ(D12,D:D) -> 9 | F12: =IFERROR(VLOOKUP(A12,[1]eco_institutions!B:D,2,0),"") -> 152 | G12: =IFERROR(VLOOKUP(A12,[1]eco_institutions!B:E,4,0),"") -> 6.2364645 | H12: =IFERROR(_xlfn.RANK.EQ(G12,G:G),"") -> 6 | I12: =IFERROR(VLOOKUP(A12,[1]fin_institutions!B:D,2,0),"") -> 49 | J12: =IFERROR(VLOOKUP(A12,[1]fin_institutions!B:E,4,0),"") -> 3.3225305 | K12: =IFERROR(_xlfn.RANK.EQ(J12,J:J),"") -> 60 | L12: =IFERROR(VLOOKUP(A12,[1]bus_institutions!B:D,2,0),"") -> 33 | M12: =IFERROR(VLOOKUP(A12,[1]bus_institutions!B:E,4,0),"") -> 3.0510826 | N12: =IFERROR(_xlfn.RANK.EQ(M12,M:M),"") -> 108 | O12: =IFERROR(VLOOKUP(A12,[1]man_institutions!B:E,2,0),"") -> 65 | P12: =IFERROR(VLOOKUP(A12,[1]man_institutions!B:E,4,0),"") -> 5.1443482 | Q12: =IFERROR(_xlfn.RANK.EQ(P12,P:P),"") -> 36
A13: University of California Berkeley | B13: USA | C13: =IFERROR(VLOOKUP(A13,[1]eco_bus_institutions!B:E,2,0),"") -> 207 | D13: =IFERROR(VLOOKUP(A13,[1]eco_bus_institutions!B:E,4,0),"") -> 5.3261617 | E13: =_xlfn.RANK.EQ(D13,D:D) -> 10 | F13: =IFERROR(VLOOKUP(A13,[1]eco_institutions!B:D,2,0),"") -> 156 | G13: =IFERROR(VLOOKUP(A13,[1]eco_institutions!B:E,4,0),"") -> 5.2397573 | H13: =IFERROR(_xlfn.RANK.EQ(G13,G:G),"") -> 12 | I13: =IFERROR(VLOOKUP(A13,[1]fin_institutions!B:D,2,0),"") -> 28 | J13: =IFERROR(VLOOKUP(A13,[1]fin_institutions!B:E,4,0),"") -> 4.1640943 | K13: =IFERROR(_xlfn.RANK.EQ(J13,J:J),"") -> 28 | L13: =IFERROR(VLOOKUP(A13,[1]bus_institutions!B:D,2,0),"") -> 26 | M13: =IFERROR(VLOOKUP(A13,[1]bus_institutions!B:E,4,0),"") -> 3.8922579 | N13: =IFERROR(_xlfn.RANK.EQ(M13,M:M),"") -> 40 | O13: =IFERROR(VLOOKUP(A13,[1]man_institutions!B:E,2,0),"") -> 45 | P13: =IFERROR(VLOOKUP(A13,[1]man_institutions!B:E,4,0),"") -> 4.3768843 | Q13: =IFERROR(_xlfn.RANK.EQ(P13,P:P),"") -> 60
A14: Columbia University | B14: USA | C14: =IFERROR(VLOOKUP(A14,[1]eco_bus_institutions!B:E,2,0),"") -> 256 | D14: =IFERROR(VLOOKUP(A14,[1]eco_bus_institutions!B:E,4,0),"") -> 4.9337844 | E14: =_xlfn.RANK.EQ(D14,D:D) -> 15 | F14: =IFERROR(VLOOKUP(A14,[1]eco_institutions!B:D,2,0),"") -> 165 | G14: =IFERROR(VLOOKUP(A14,[1]eco_institutions!B:E,4,0),"") -> 4.6213955 | H14: =IFERROR(_xlfn.RANK.EQ(G14,G:G),"") -> 18 | I14: =IFERROR(VLOOKUP(A14,[1]fin_institutions!B:D,2,0),"") -> 61 | J14: =IFERROR(VLOOKUP(A14,[1]fin_institutions!B:E,4,0),"") -> 4.6779708 | K14: =IFERROR(_xlfn.RANK.EQ(J14,J:J),"") -> 19 | L14: =IFERROR(VLOOKUP(A14,[1]bus_institutions!B:D,2,0),"") -> 47 | M14: =IFERROR(VLOOKUP(A14,[1]bus_institutions!B:E,4,0),"") -> 5.0050458 | N14: =IFERROR(_xlfn.RANK.EQ(M14,M:M),"") -> 14 | O14: =IFERROR(VLOOKUP(A14,[1]man_institutions!B:E,2,0),"") -> 39 | P14: =IFERROR(VLOOKUP(A14,[1]man_institutions!B:E,4,0),"") -> 3.3402901 | Q14: =IFERROR(_xlfn.RANK.EQ(P14,P:P),"") -> 153
... A602: University of Novi Sad | B602: SERBIA | C602: =IFERROR(VLOOKUP(A602,[1]eco_bus_institutions!B:E,2,0),"") -> 42 | D602: =IFERROR(VLOOKUP(A602,[1]eco_bus_institutions!B:E,4,0),"") -> 1.0420764 | E602: =_xlfn.RANK.EQ(D602,D:D) -> 598 | F602: =IFERROR(VLOOKUP(A602,[1]eco_institutions!B:D,2,0),"") -> 30 | G602: =IFERROR(VLOOKUP(A602,[1]eco_institutions!B:E,4,0),"") -> 1.0436347 | H602: =IFERROR(_xlfn.RANK.EQ(G602,G:G),"") -> 587 | I602: =IFERROR(VLOOKUP(A602,[1]fin_institutions!B:D,2,0),"") -> 4 | J602: =IFERROR(VLOOKUP(A602,[1]fin_institutions!B:E,4,0),"") -> 1.0571042 | K602: =IFERROR(_xlfn.RANK.EQ(J602,J:J),"") -> 551 | L602: =IFERROR(VLOOKUP(A602,[1]bus_institutions!B:D,2,0),"") -> 9 | M602: =IFERROR(VLOOKUP(A602,[1]bus_institutions!B:E,4,0),"") -> 1.2593262 | N602: =IFERROR(_xlfn.RANK.EQ(M602,M:M),"") -> 537 | O602: =IFERROR(VLOOKUP(A602,[1]man_institutions!B:E,2,0),"") -> 12 | P602: =IFERROR(VLOOKUP(A602,[1]man_institutions!B:E,4,0),"") -> 1.0509602 | Q602: =IFERROR(_xlfn.RANK.EQ(P602,P:P),"") -> 575

Sheet institutions_spss
T1: fra | U1: spain | V1: country | W1: acronym | Y1: For comparisons, place two countries in Y1 and Y2
A2: institution | C2: country | D2: score | E2: score | F2: score | G2: score | H2: score | I2: rank | J2: rank | K2: rank | L2: rank | M2: rank | R2: ranks | T2: deu | V2: WALES | W2: UK | Y2: For a country alone, leave Y2 blank
A3: institution | C3: country | D3: ebscore | E3: escore | F3: fscore | G3: bscore | H3: mscore | I3: ebrank | J3: erank | K3: frank | L3: brank | M3: mrank | R3: pc1 | S3: pc2 | T3: country | U3: for plot | V3: VIETNAM | W3: VTN | Y3: First Component, pc1: associated with all four categories (comprehensive institutions perform better)
A4: Center for Economic & Policy Research (CEPR) | B4: CEPR | C4: USA | D4: =IFERROR(ROUND(VLOOKUP(A4,institutions!A:E,4,0),2),"") -> 8 | E4: =IFERROR(ROUND(VLOOKUP(A4,institutions!A:X,7,0),2),"") -> 6.85 | F4: =IFERROR(ROUND(VLOOKUP(A4,institutions!A:X,10,0),2),"") -> 5.91 | G4: =IFERROR(ROUND(VLOOKUP(A4,institutions!A:X,13,0),2),"") | H4: =IFERROR(ROUND(VLOOKUP(A4,institutions!A:X,16,0),2),"") | I4: =ROUND(IFERROR((601-_xlfn.RANK.EQ(D4,D:D))/600,0),3) -> 1 | J4: =ROUND(IFERROR((601-IFERROR(_xlfn.RANK.EQ(E4,E:E),""))/600,0),3) -> 0.995 | K4: =ROUND(IFERROR((601-IFERROR(_xlfn.RANK.EQ(F4,F:F),""))/600,0),3) -> 0.992 | L4: =ROUND(IFERROR((601-IFERROR(_xlfn.RANK.EQ(G4,G:G),""))/600,0),3) -> 0 | M4: =ROUND(IFERROR((601-IFERROR(_xlfn.RANK.EQ(H4,H:H),""))/600,0),3) -> 0 | N4: =VLOOKUP(A4,#REF!,11,0) -> #REF! | O4: =VLOOKUP(A4,#REF!,12,0) -> #REF! | P4: =VLOOKUP(A4,#REF!,13,0) -> #REF! | Q4: =VLOOKUP(A4,#REF!,14,0) -> #REF! | R4: -0.17798453 | S4: 3.3912835 | T4: =VLOOKUP(C4,V:W,2,0) -> USA | U4: =IF(T4=T$1,B4,IF(T4=T$2,B4,IF(T4=U$1,B4,""))) | V4: USA | W4: USA | Y4: Second Component: North (Economics and Finance), South (Business and Management)
A5: University of Chicago | B5: Chicago | C5: USA | D5: =IFERROR(ROUND(VLOOKUP(A5,institutions!A:E,4,0),2),"") -> 7.92 | E5: =IFERROR(ROUND(VLOOKUP(A5,institutions!A:X,7,0),2),"") -> 7.78 | F5: =IFERROR(ROUND(VLOOKUP(A5,institutions!A:X,10,0),2),"") -> 6.89 | G5: =IFERROR(ROUND(VLOOKUP(A5,institutions!A:X,13,0),2),"") -> 2.99 | H5: =IFERROR(ROUND(VLOOKUP(A5,institutions!A:X,16,0),2),"") -> 1.93 | I5: =ROUND(IFERROR((601-_xlfn.RANK.EQ(D5,D:D))/600,0),3) -> 0.998 | J5: =ROUND(IFERROR((601-IFERROR(_xlfn.RANK.EQ(E5,E:E),""))/600,0),3) -> 0.998 | K5: =ROUND(IFERROR((601-IFERROR(_xlfn.RANK.EQ(F5,F:F),""))/600,0),3) -> 0.997 | L5: =ROUND(IFERROR((601-IFERROR(_xlfn.RANK.EQ(G5,G:G),""))/600,0),3) -> 0.812 | M5: =ROUND(IFERROR((601-IFERROR(_xlfn.RANK.EQ(H5,H:H),""))/600,0),3) -> 0.3 | N5: =VLOOKUP(A5,#REF!,11,0) -> #REF! | O5: =VLOOKUP(A5,#REF!,12,0) -> #REF! | P5: =VLOOKUP(A5,#REF!,13,0) -> #REF! | Q5: =VLOOKUP(A5,#REF!,14,0) -> #REF! | R5: 1.8264022 | S5: 1.5762561 | T5: =VLOOKUP(C5,V:W,2,0) -> USA | U5: =IF(T5=T$1,B5,IF(T5=T$2,B5,IF(T5=U$1,B5,""))) | V5: UNITED ARAB EMIRATES | W5: UAE | Y5: 88% of the variance explained
A6: University of California Santa Barbara | B6: UCSB | C6: USA | D6: =IFERROR(ROUND(VLOOKUP(A6,institutions!A:E,4,0),2),"") -> 7.87 | E6: =IFERROR(ROUND(VLOOKUP(A6,institutions!A:X,7,0),2),"") -> 8 | F6: =IFERROR(ROUND(VLOOKUP(A6,institutions!A:X,10,0),2),"") -> 1.95 | G6: =IFERROR(ROUND(VLOOKUP(A6,institutions!A:X,13,0),2),"") -> 2.05 | H6: =IFERROR(ROUND(VLOOKUP(A6,institutions!A:X,16,0),2),"") -> 5.37 | I6: =ROUND(IFERROR((601-_xlfn.RANK.EQ(D6,D:D))/600,0),3) -> 0.997 | J6: =ROUND(IFERROR((601-IFERROR(_xlfn.RANK.EQ(E6,E:E),""))/600,0),3) -> 1 | K6: =ROUND(IFERROR((601-IFERROR(_xlfn.RANK.EQ(F6,F:F),""))/600,0),3) -> 0.72 | L6: =ROUND(IFERROR((601-IFERROR(_xlfn.RANK.EQ(G6,G:G),""))/600,0),3) -> 0.483 | M6: =ROUND(IFERROR((601-IFERROR(_xlfn.RANK.EQ(H6,H:H),""))/600,0),3) -> 0.95 | N6: =VLOOKUP(A6,#REF!,11,0) -> #REF! | O6: =VLOOKUP(A6,#REF!,12,0) -> #REF! | P6: =VLOOKUP(A6,#REF!,13,0) -> #REF! | Q6: =VLOOKUP(A6,#REF!,14,0) -> #REF! | R6: 1.94297 | S6: 0.6946489 | T6: =VLOOKUP(C6,V:W,2,0) -> USA | U6: =IF(T6=T$1,B6,IF(T6=T$2,B6,IF(T6=U$1,B6,""))) | V6: TURKIYE | W6: TUR
A7: Princeton University | B7: Princeton | C7: USA | D7: =IFERROR(ROUND(VLOOKUP(A7,institutions!A:E,4,0),2),"") -> 6.75 | E7: =IFERROR(ROUND(VLOOKUP(A7,institutions!A:X,7,0),2),"") -> 6.45 | F7: =IFERROR(ROUND(VLOOKUP(A7,institutions!A:X,10,0),2),"") -> 3.94 | G7: =IFERROR(ROUND(VLOOKUP(A7,institutions!A:X,13,0),2),"") | H7: =IFERROR(ROUND(VLOOKUP(A7,institutions!A:X,16,0),2),"") | I7: =ROUND(IFERROR((601-_xlfn.RANK.EQ(D7,D:D))/600,0),3) -> 0.993 | J7: =ROUND(IFERROR((601-IFERROR(_xlfn.RANK.EQ(E7,E:E),""))/600,0),3) -> 0.993 | K7: =ROUND(IFERROR((601-IFERROR(_xlfn.RANK.EQ(F7,F:F),""))/600,0),3) -> 0.943 | L7: =ROUND(IFERROR((601-IFERROR(_xlfn.RANK.EQ(G7,G:G),""))/600,0),3) -> 0 | M7: =ROUND(IFERROR((601-IFERROR(_xlfn.RANK.EQ(H7,H:H),""))/600,0),3) -> 0 | N7: =VLOOKUP(A7,#REF!,11,0) -> #REF! | O7: =VLOOKUP(A7,#REF!,12,0) -> #REF! | P7: =VLOOKUP(A7,#REF!,13,0) -> #REF! | Q7: =VLOOKUP(A7,#REF!,14,0) -> #REF! | R7: -0.2648982 | S7: 3.3157124 | T7: =VLOOKUP(C7,V:W,2,0) -> USA | U7: =IF(T7=T$1,B7,IF(T7=T$2,B7,IF(T7=U$1,B7,""))) | V7: TUNISIA | W7: TUN | Y7: NorthEast Direction signals excellence
A8: London Business School | B8: LBS | C8: ENGLAND | D8: =IFERROR(ROUND(VLOOKUP(A8,institutions!A:E,4,0),2),"") -> 6.9 | E8: =IFERROR(ROUND(VLOOKUP(A8,institutions!A:X,7,0),2),"") -> 7.44 | F8: =IFERROR(ROUND(VLOOKUP(A8,institutions!A:X,10,0),2),"") -> 5.04 | G8: =IFERROR(ROUND(VLOOKUP(A8,institutions!A:X,13,0),2),"") -> 5.15 | H8: =IFERROR(ROUND(VLOOKUP(A8,institutions!A:X,16,0),2),"") -> 5.71 | I8: =ROUND(IFERROR((601-_xlfn.RANK.EQ(D8,D:D))/600,0),3) -> 0.995 | J8: =ROUND(IFERROR((601-IFERROR(_xlfn.RANK.EQ(E8,E:E),""))/600,0),3) -> 0.997 | K8: =ROUND(IFERROR((601-IFERROR(_xlfn.RANK.EQ(F8,F:F),""))/600,0),3) -> 0.98 | L8: =ROUND(IFERROR((601-IFERROR(_xlfn.RANK.EQ(G8,G:G),""))/600,0),3) -> 0.983 | M8: =ROUND(IFERROR((601-IFERROR(_xlfn.RANK.EQ(H8,H:H),""))/600,0),3) -> 0.968 | N8: =VLOOKUP(A8,#REF!,11,0) -> #REF! | O8: =VLOOKUP(A8,#REF!,12,0) -> #REF! | P8: =VLOOKUP(A8,#REF!,13,0) -> #REF! | Q8: =VLOOKUP(A8,#REF!,14,0) -> #REF! | R8: 3.3072869 | S8: 0.20496759 | T8: =VLOOKUP(C8,V:W,2,0) -> UK | U8: =IF(T8=T$1,B8,IF(T8=T$2,B8,IF(T8=U$1,B8,""))) | V8: TAIWAN | W8: TWN | Y8: To compare, move an imaginary NW to SE line: better to be on the right of that line
A9: Yale University | B9: Yale | C9: USA | D9: =IFERROR(ROUND(VLOOKUP(A9,institutions!A:E,4,0),2),"") -> 6.03 | E9: =IFERROR(ROUND(VLOOKUP(A9,institutions!A:X,7,0),2),"") -> 5.63 | F9: =IFERROR(ROUND(VLOOKUP(A9,institutions!A:X,10,0),2),"") -> 7.55 | G9: =IFERROR(ROUND(VLOOKUP(A9,institutions!A:X,13,0),2),"") -> 5.22 | H9: =IFERROR(ROUND(VLOOKUP(A9,institutions!A:X,16,0),2),"") -> 5.37 | I9: =ROUND(IFERROR((601-_xlfn.RANK.EQ(D9,D:D))/600,0),3) -> 0.992 | J9: =ROUND(IFERROR((601-IFERROR(_xlfn.RANK.EQ(E9,E:E),""))/600,0),3) -> 0.987 | K9: =ROUND(IFERROR((601-IFERROR(_xlfn.RANK.EQ(F9,F:F),""))/600,0),3) -> 0.998 | L9: =ROUND(IFERROR((601-IFERROR(_xlfn.RANK.EQ(G9,G:G),""))/600,0),3) -> 0.985 | M9: =ROUND(IFERROR((601-IFERROR(_xlfn.RANK.EQ(H9,H:H),""))/600,0),3) -> 0.95 | N9: =VLOOKUP(A9,#REF!,11,0) -> #REF! | O9: =VLOOKUP(A9,#REF!,12,0) -> #REF! | P9: =VLOOKUP(A9,#REF!,13,0) -> #REF! | Q9: =VLOOKUP(A9,#REF!,14,0) -> #REF! | R9: 3.2931033 | S9: 0.2350235 | T9: =VLOOKUP(C9,V:W,2,0) -> USA | U9: =IF(T9=T$1,B9,IF(T9=T$2,B9,IF(T9=U$1,B9,""))) | V9: SWITZERLAND | W9: CHE
A10: National Bureau of Economic Research | B10: NBER | C10: USA | D10: =IFERROR(ROUND(VLOOKUP(A10,institutions!A:E,4,0),2),"") -> 5.89 | E10: =IFERROR(ROUND(VLOOKUP(A10,institutions!A:X,7,0),2),"") -> 5.04 | F10: =IFERROR(ROUND(VLOOKUP(A10,institutions!A:X,10,0),2),"") | G10: =IFERROR(ROUND(VLOOKUP(A10,institutions!A:X,13,0),2),"") | H10: =IFERROR(ROUND(VLOOKUP(A10,institutions!A:X,16,0),2),"") | I10: =ROUND(IFERROR((601-_xlfn.RANK.EQ(D10,D:D))/600,0),3) -> 0.988 | J10: =ROUND(IFERROR((601-IFERROR(_xlfn.RANK.EQ(E10,E:E),""))/600,0),3) -> 0.98 | K10: =ROUND(IFERROR((601-IFERROR(_xlfn.RANK.EQ(F10,F:F),""))/600,0),3) -> 0 | L10: =ROUND(IFERROR((601-IFERROR(_xlfn.RANK.EQ(G10,G:G),""))/600,0),3) -> 0 | M10: =ROUND(IFERROR((601-IFERROR(_xlfn.RANK.EQ(H10,H:H),""))/600,0),3) -> 0 | N10: =VLOOKUP(A10,#REF!,11,0) -> #REF! | O10: =VLOOKUP(A10,#REF!,12,0) -> #REF! | P10: =VLOOKUP(A10,#REF!,13,0) -> #REF! | Q10: =VLOOKUP(A10,#REF!,14,0) -> #REF! | R10: -1.8967602 | S10: 1.9157826 | T10: =VLOOKUP(C10,V:W,2,0) -> USA | U10: =IF(T10=T$1,B10,IF(T10=T$2,B10,IF(T10=U$1,B10,""))) | V10: SWEDEN | W10: SWE | Y10: For Australia
A11: Stanford University | B11: Stanford | C11: USA | D11: =IFERROR(ROUND(VLOOKUP(A11,institutions!A:E,4,0),2),"") -> 5.95 | E11: =IFERROR(ROUND(VLOOKUP(A11,institutions!A:X,7,0),2),"") -> 5.26 | F11: =IFERROR(ROUND(VLOOKUP(A11,institutions!A:X,10,0),2),"") -> 6.36 | G11: =IFERROR(ROUND(VLOOKUP(A11,institutions!A:X,13,0),2),"") -> 5.15 | H11: =IFERROR(ROUND(VLOOKUP(A11,institutions!A:X,16,0),2),"") -> 7.72 | I11: =ROUND(IFERROR((601-_xlfn.RANK.EQ(D11,D:D))/600,0),3) -> 0.99 | J11: =ROUND(IFERROR((601-IFERROR(_xlfn.RANK.EQ(E11,E:E),""))/600,0),3) -> 0.983 | K11: =ROUND(IFERROR((601-IFERROR(_xlfn.RANK.EQ(F11,F:F),""))/600,0),3) -> 0.995 | L11: =ROUND(IFERROR((601-IFERROR(_xlfn.RANK.EQ(G11,G:G),""))/600,0),3) -> 0.983 | M11: =ROUND(IFERROR((601-IFERROR(_xlfn.RANK.EQ(H11,H:H),""))/600,0),3) -> 0.997 | N11: =VLOOKUP(A11,#REF!,11,0) -> #REF! | O11: =VLOOKUP(A11,#REF!,12,0) -> #REF! | P11: =VLOOKUP(A11,#REF!,13,0) -> #REF! | Q11: =VLOOKUP(A11,#REF!,14,0) -> #REF! | R11: 3.3628844 | S11: 0.15090247 | T11: =VLOOKUP(C11,V:W,2,0) -> USA | U11: =IF(T11=T$1,B11,IF(T11=T$2,B11,IF(T11=U$1,B11,""))) | V11: SPAIN | W11: SPAIN | Y11: Cluster 1: Best performers | Z11: Adelaide, ANU, Melbourne
A12: Massachusetts Institute of Technology (MIT) | B12: MIT | C12: USA | D12: =IFERROR(ROUND(VLOOKUP(A12,institutions!A:E,4,0),2),"") -> 5.86 | E12: =IFERROR(ROUND(VLOOKUP(A12,institutions!A:X,7,0),2),"") -> 6.24 | F12: =IFERROR(ROUND(VLOOKUP(A12,institutions!A:X,10,0),2),"") -> 3.32 | G12: =IFERROR(ROUND(VLOOKUP(A12,institutions!A:X,13,0),2),"") -> 3.05 | H12: =IFERROR(ROUND(VLOOKUP(A12,institutions!A:X,16,0),2),"") -> 5.14 | I12: =ROUND(IFERROR((601-_xlfn.RANK.EQ(D12,D:D))/600,0),3) -> 0.987 | J12: =ROUND(IFERROR((601-IFERROR(_xlfn.RANK.EQ(E12,E:E),""))/600,0),3) -> 0.992 | K12: =ROUND(IFERROR((601-IFERROR(_xlfn.RANK.EQ(F12,F:F),""))/600,0),3) -> 0.902 | L12: =ROUND(IFERROR((601-IFERROR(_xlfn.RANK.EQ(G12,G:G),""))/600,0),3) -> 0.822 | M12: =ROUND(IFERROR((601-IFERROR(_xlfn.RANK.EQ(H12,H:H),""))/600,0),3) -> 0.942 | N12: =VLOOKUP(A12,#REF!,11,0) -> #REF! | O12: =VLOOKUP(A12,#REF!,12,0) -> #REF! | P12: =VLOOKUP(A12,#REF!,13,0) -> #REF! | Q12: =VLOOKUP(A12,#REF!,14,0) -> #REF! | R12: 2.831718 | S12: 0.39027412 | T12: =VLOOKUP(C12,V:W,2,0) -> USA | U12: =IF(T12=T$1,B12,IF(T12=T$2,B12,IF(T12=U$1,B12,""))) | V12: SOUTH KOREA | W12: KOREA | Y12: Cluster 2: Fast followers | Z12: UTAS,Western Aus, La Trobe, Wollongong, Maquarie, RMIT, Deakin, UTS, Sifney, Queensland
A13: University of California Berkeley | B13: UCB | C13: USA | D13: =IFERROR(ROUND(VLOOKUP(A13,institutions!A:E,4,0),2),"") -> 5.33 | E13: =IFERROR(ROUND(VLOOKUP(A13,institutions!A:X,7,0),2),"") -> 5.24 | F13: =IFERROR(ROUND(VLOOKUP(A13,institutions!A:X,10,0),2),"") -> 4.16 | G13: =IFERROR(ROUND(VLOOKUP(A13,institutions!A:X,13,0),2),"") -> 3.89 | H13: =IFERROR(ROUND(VLOOKUP(A13,institutions!A:X,16,0),2),"") -> 4.38 | I13: =ROUND(IFERROR((601-_xlfn.RANK.EQ(D13,D:D))/600,0),3) -> 0.985 | J13: =ROUND(IFERROR((601-IFERROR(_xlfn.RANK.EQ(E13,E:E),""))/600,0),3) -> 0.982 | K13: =ROUND(IFERROR((601-IFERROR(_xlfn.RANK.EQ(F13,F:F),""))/600,0),3) -> 0.955 | L13: =ROUND(IFERROR((601-IFERROR(_xlfn.RANK.EQ(G13,G:G),""))/600,0),3) -> 0.935 | M13: =ROUND(IFERROR((601-IFERROR(_xlfn.RANK.EQ(H13,H:H),""))/600,0),3) -> 0.902 | N13: =VLOOKUP(A13,#REF!,11,0) -> #REF! | O13: =VLOOKUP(A13,#REF!,12,0) -> #REF! | P13: =VLOOKUP(A13,#REF!,13,0) -> #REF! | Q13: =VLOOKUP(A13,#REF!,14,0) -> #REF! | R13: 3.035717 | S13: 0.32121493 | T13: =VLOOKUP(C13,V:W,2,0) -> USA | U13: =IF(T13=T$1,B13,IF(T13=T$2,B13,IF(T13=U$1,B13,""))) | V13: SOUTH AFRICA | W13: ZAF | Y13: Cluster 3: Followers | Z13: Edith Cowan, South Australia
A14: Swiss Finance Institute (SFI) | B14: SFI | C14: SWITZERLAND | D14: =IFERROR(ROUND(VLOOKUP(A14,institutions!A:E,4,0),2),"") -> 5.2 | E14: =IFERROR(ROUND(VLOOKUP(A14,institutions!A:X,7,0),2),"") -> 4 | F14: =IFERROR(ROUND(VLOOKUP(A14,institutions!A:X,10,0),2),"") -> 4.76 | G14: =IFERROR(ROUND(VLOOKUP(A14,institutions!A:X,13,0),2),"") | H14: =IFERROR(ROUND(VLOOKUP(A14,institutions!A:X,16,0),2),"") | I14: =ROUND(IFERROR((601-_xlfn.RANK.EQ(D14,D:D))/600,0),3) -> 0.982 | J14: =ROUND(IFERROR((601-IFERROR(_xlfn.RANK.EQ(E14,E:E),""))/600,0),3) -> 0.958 | K14: =ROUND(IFERROR((601-IFERROR(_xlfn.RANK.EQ(F14,F:F),""))/600,0),3) -> 0.973 | L14: =ROUND(IFERROR((601-IFERROR(_xlfn.RANK.EQ(G14,G:G),""))/600,0),3) -> 0 | M14: =ROUND(IFERROR((601-IFERROR(_xlfn.RANK.EQ(H14,H:H),""))/600,0),3) -> 0 | N14: =VLOOKUP(A14,#REF!,11,0) -> #REF! | O14: =VLOOKUP(A14,#REF!,12,0) -> #REF! | P14: =VLOOKUP(A14,#REF!,13,0) -> #REF! | Q14: =VLOOKUP(A14,#REF!,14,0) -> #REF! | R14: -0.26964348 | S14: 3.2846281 | T14: =VLOOKUP(C14,V:W,2,0) -> CHE | U14: =IF(T14=T$1,B14,IF(T14=T$2,B14,IF(T14=U$1,B14,""))) | V14: SLOVAKIA | W14: SLK | Y14: Cluster 4: Laggers | Z14: Curtin, Griffith, QUT, Newcastle, Swinburne
A15: Harvard University | B15: Harvard | C15: USA | D15: =IFERROR(ROUND(VLOOKUP(A15,institutions!A:E,4,0),2),"") -> 5.26 | E15: =IFERROR(ROUND(VLOOKUP(A15,institutions!A:X,7,0),2),"") -> 5.71 | F15: =IFERROR(ROUND(VLOOKUP(A15,institutions!A:X,10,0),2),"") -> 4.14 | G15: =IFERROR(ROUND(VLOOKUP(A15,institutions!A:X,13,0),2),"") -> 3.39 | H15: =IFERROR(ROUND(VLOOKUP(A15,institutions!A:X,16,0),2),"") -> 4.43 | I15: =ROUND(IFERROR((601-_xlfn.RANK.EQ(D15,D:D))/600,0),3) -> 0.983 | J15: =ROUND(IFERROR((601-IFERROR(_xlfn.RANK.EQ(E15,E:E),""))/600,0),3) -> 0.988 | K15: =ROUND(IFERROR((601-IFERROR(_xlfn.RANK.EQ(F15,F:F),""))/600,0),3) -> 0.952 | L15: =ROUND(IFERROR((601-IFERROR(_xlfn.RANK.EQ(G15,G:G),""))/600,0),3) -> 0.875 | M15: =ROUND(IFERROR((601-IFERROR(_xlfn.RANK.EQ(H15,H:H),""))/600,0),3) -> 0.908 | N15: =VLOOKUP(A15,#REF!,11,0) -> #REF! | O15: =VLOOKUP(A15,#REF!,12,0) -> #REF! | P15: =VLOOKUP(A15,#REF!,13,0) -> #REF! | Q15: =VLOOKUP(A15,#REF!,14,0) -> #REF! | R15: 2.9439368 | S15: 0.42011172 | T15: =VLOOKUP(C15,V:W,2,0) -> USA | U15: =IF(T15=T$1,B15,IF(T15=T$2,B15,IF(T15=U$1,B15,""))) | V15: SINGAPORE | W15: SGP
A16: Columbia University | B16: Columbia | C16: USA | D16: =IFERROR(ROUND(VLOOKUP(A16,institutions!A:E,4,0),2),"") -> 4.93 | E16: =IFERROR(ROUND(VLOOKUP(A16,institutions!A:X,7,0),2),"") -> 4.62 | F16: =IFERROR(ROUND(VLOOKUP(A16,institutions!A:X,10,0),2),"") -> 4.68 | G16: =IFERROR(ROUND(VLOOKUP(A16,institutions!A:X,13,0),2),"") -> 5.01 | H16: =IFERROR(ROUND(VLOOKUP(A16,institutions!A:X,16,0),2),"") -> 3.34 | I16: =ROUND(IFERROR((601-_xlfn.RANK.EQ(D16,D:D))/600,0),3) -> 0.977 | J16: =ROUND(IFERROR((601-IFERROR(_xlfn.RANK.EQ(E16,E:E),""))/600,0),3) -> 0.972 | K16: =ROUND(IFERROR((601-IFERROR(_xlfn.RANK.EQ(F16,F:F),""))/600,0),3) -> 0.97 | L16: =ROUND(IFERROR((601-IFERROR(_xlfn.RANK.EQ(G16,G:G),""))/600,0),3) -> 0.978 | M16: =ROUND(IFERROR((601-IFERROR(_xlfn.RANK.EQ(H16,H:H),""))/600,0),3) -> 0.747 | N16: =VLOOKUP(A16,#REF!,11,0) -> #REF! | O16: =VLOOKUP(A16,#REF!,12,0) -> #REF! | P16: =VLOOKUP(A16,#REF!,13,0) -> #REF! | Q16: =VLOOKUP(A16,#REF!,14,0) -> #REF! | R16: 2.8421818 | S16: 0.49589009 | T16: =VLOOKUP(C16,V:W,2,0) -> USA | U16: =IF(T16=T$1,B16,IF(T16=T$2,B16,IF(T16=U$1,B16,""))) | V16: SERBIA | W16: SERBIA
A17: Boston University | B17: Boston | C17: USA | D17: =IFERROR(ROUND(VLOOKUP(A17,institutions!A:E,4,0),2),"") -> 5.13 | E17: =IFERROR(ROUND(VLOOKUP(A17,institutions!A:X,7,0),2),"") -> 4.72 | F17: =IFERROR(ROUND(VLOOKUP(A17,institutions!A:X,10,0),2),"") -> 2.82 | G17: =IFERROR(ROUND(VLOOKUP(A17,institutions!A:X,13,0),2),"") -> 6.88 | H17: =IFERROR(ROUND(VLOOKUP(A17,institutions!A:X,16,0),2),"") -> 6.77 | I17: =ROUND(IFERROR((601-_xlfn.RANK.EQ(D17,D:D))/600,0),3) -> 0.98 | J17: =ROUND(IFERROR((601-IFERROR(_xlfn.RANK.EQ(E17,E:E),""))/600,0),3) -> 0.973 | K17: =ROUND(IFERROR((601-IFERROR(_xlfn.RANK.EQ(F17,F:F),""))/600,0),3) -> 0.872 | L17: =ROUND(IFERROR((601-IFERROR(_xlfn.RANK.EQ(G17,G:G),""))/600,0),3) -> 0.998 | M17: =ROUND(IFERROR((601-IFERROR(_xlfn.RANK.EQ(H17,H:H),""))/600,0),3) -> 0.988 | N17: =VLOOKUP(A17,#REF!,11,0) -> #REF! | O17: =VLOOKUP(A17,#REF!,12,0) -> #REF! | P17: =VLOOKUP(A17,#REF!,13,0) -> #REF! | Q17: =VLOOKUP(A17,#REF!,14,0) -> #REF! | R17: 3.1472659 | S17: -0.06014661 | T17: =VLOOKUP(C17,V:W,2,0) -> USA | U17: =IF(T17=T$1,B17,IF(T17=T$2,B17,IF(T17=U$1,B17,""))) | V17: SCOTLAND | W17: UK
A18: Pompeu Fabra University | B18: Pompeu Fabra | C18: SPAIN | D18: =IFERROR(ROUND(VLOOKUP(A18,institutions!A:E,4,0),2),"") -> 5.01 | E18: =IFERROR(ROUND(VLOOKUP(A18,institutions!A:X,7,0),2),"") -> 5.75 | F18: =IFERROR(ROUND(VLOOKUP(A18,institutions!A:X,10,0),2),"") -> 1.92 | G18: =IFERROR(ROUND(VLOOKUP(A18,institutions!A:X,13,0),2),"") -> 1.08 | H18: =IFERROR(ROUND(VLOOKUP(A18,institutions!A:X,16,0),2),"") -> 1.3 | I18: =ROUND(IFERROR((601-_xlfn.RANK.EQ(D18,D:D))/600,0),3) -> 0.978 | J18: =ROUND(IFERROR((601-IFERROR(_xlfn.RANK.EQ(E18,E:E),""))/600,0),3) -> 0.99 | K18: =ROUND(IFERROR((601-IFERROR(_xlfn.RANK.EQ(F18,F:F),""))/600,0),3) -> 0.712 | L18: =ROUND(IFERROR((601-IFERROR(_xlfn.RANK.EQ(G18,G:G),""))/600,0),3) -> 0.065 | M18: =ROUND(IFERROR((601-IFERROR(_xlfn.RANK.EQ(H18,H:H),""))/600,0),3) -> 0.068 | N18: =VLOOKUP(A18,#REF!,11,0) -> #REF! | O18: =VLOOKUP(A18,#REF!,12,0) -> #REF! | P18: =VLOOKUP(A18,#REF!,13,0) -> #REF! | Q18: =VLOOKUP(A18,#REF!,14,0) -> #REF! | R18: -0.42553529 | S18: 2.757024 | T18: =VLOOKUP(C18,V:W,2,0) -> SPAIN | U18: =IF(T18=T$1,B18,IF(T18=T$2,B18,IF(T18=U$1,B18,""))) -> Pompeu Fabra | V18: SAUDI ARABIA | W18: SAU
A19: Centre for Economic Policy Research - UK | B19: CEPRUK | C19: ENGLAND | D19: =IFERROR(ROUND(VLOOKUP(A19,institutions!A:E,4,0),2),"") -> 4.84 | E19: =IFERROR(ROUND(VLOOKUP(A19,institutions!A:X,7,0),2),"") -> 4.3 | F19: =IFERROR(ROUND(VLOOKUP(A19,institutions!A:X,10,0),2),"") -> 2.88 | G19: =IFERROR(ROUND(VLOOKUP(A19,institutions!A:X,13,0),2),"") | H19: =IFERROR(ROUND(VLOOKUP(A19,institutions!A:X,16,0),2),"") | I19: =ROUND(IFERROR((601-_xlfn.RANK.EQ(D19,D:D))/600,0),3) -> 0.973 | J19: =ROUND(IFERROR((601-IFERROR(_xlfn.RANK.EQ(E19,E:E),""))/600,0),3) -> 0.967 | K19: =ROUND(IFERROR((601-IFERROR(_xlfn.RANK.EQ(F19,F:F),""))/600,0),3) -> 0.878 | L19: =ROUND(IFERROR((601-IFERROR(_xlfn.RANK.EQ(G19,G:G),""))/600,0),3) -> 0 | M19: =ROUND(IFERROR((601-IFERROR(_xlfn.RANK.EQ(H19,H:H),""))/600,0),3) -> 0 | N19: =VLOOKUP(A19,#REF!,11,0) -> #REF! | O19: =VLOOKUP(A19,#REF!,12,0) -> #REF! | P19: =VLOOKUP(A19,#REF!,13,0) -> #REF! | Q19: =VLOOKUP(A19,#REF!,14,0) -> #REF! | R19: -0.417546 | S19: 3.1656108 | T19: =VLOOKUP(C19,V:W,2,0) -> UK | U19: =IF(T19=T$1,B19,IF(T19=T$2,B19,IF(T19=U$1,B19,""))) | V19: RUSSIA | W19: RUS
A20: University of California Los Angeles | B20: UCLA | C20: USA | D20: =IFERROR(ROUND(VLOOKUP(A20,institutions!A:E,4,0),2),"") -> 4.76 | E20: =IFERROR(ROUND(VLOOKUP(A20,institutions!A:X,7,0),2),"") -> 5.44 | F20: =IFERROR(ROUND(VLOOKUP(A20,institutions!A:X,10,0),2),"") -> 3.05 | G20: =IFERROR(ROUND(VLOOKUP(A20,institutions!A:X,13,0),2),"") -> 2.66 | H20: =IFERROR(ROUND(VLOOKUP(A20,institutions!A:X,16,0),2),"") -> 3.92 | I20: =ROUND(IFERROR((601-_xlfn.RANK.EQ(D20,D:D))/600,0),3) -> 0.972 | J20: =ROUND(IFERROR((601-IFERROR(_xlfn.RANK.EQ(E20,E:E),""))/600,0),3) -> 0.985 | K20: =ROUND(IFERROR((601-IFERROR(_xlfn.RANK.EQ(F20,F:F),""))/600,0),3) -> 0.887 | L20: =ROUND(IFERROR((601-IFERROR(_xlfn.RANK.EQ(G20,G:G),""))/600,0),3) -> 0.735 | M20: =ROUND(IFERROR((601-IFERROR(_xlfn.RANK.EQ(H20,H:H),""))/600,0),3) -> 0.863 | N20: =VLOOKUP(A20,#REF!,11,0) -> #REF! | O20: =VLOOKUP(A20,#REF!,12,0) -> #REF! | P20: =VLOOKUP(A20,#REF!,13,0) -> #REF! | Q20: =VLOOKUP(A20,#REF!,14,0) -> #REF! | R20: 2.4969474 | S20: 0.62375294 | T20: =VLOOKUP(C20,V:W,2,0) -> USA | U20: =IF(T20=T$1,B20,IF(T20=T$2,B20,IF(T20=U$1,B20,""))) | V20: ROMANIA | W20: ROM
A21: Northwestern University | B21: Northwestern | C21: USA | D21: =IFERROR(ROUND(VLOOKUP(A21,institutions!A:E,4,0),2),"") -> 4.93 | E21: =IFERROR(ROUND(VLOOKUP(A21,institutions!A:X,7,0),2),"") -> 4.91 | F21: =IFERROR(ROUND(VLOOKUP(A21,institutions!A:X,10,0),2),"") -> 5.67 | G21: =IFERROR(ROUND(VLOOKUP(A21,institutions!A:X,13,0),2),"") -> 5 | H21: =IFERROR(ROUND(VLOOKUP(A21,institutions!A:X,16,0),2),"") -> 4.33 | I21: =ROUND(IFERROR((601-_xlfn.RANK.EQ(D21,D:D))/600,0),3) -> 0.977 | J21: =ROUND(IFERROR((601-IFERROR(_xlfn.RANK.EQ(E21,E:E),""))/600,0),3) -> 0.978 | K21: =ROUND(IFERROR((601-IFERROR(_xlfn.RANK.EQ(F21,F:F),""))/600,0),3) -> 0.988 | L21: =ROUND(IFERROR((601-IFERROR(_xlfn.RANK.EQ(G21,G:G),""))/600,0),3) -> 0.977 | M21: =ROUND(IFERROR((601-IFERROR(_xlfn.RANK.EQ(H21,H:H),""))/600,0),3) -> 0.898 | N21: =VLOOKUP(A21,#REF!,11,0) -> #REF! | O21: =VLOOKUP(A21,#REF!,12,0) -> #REF! | P21: =VLOOKUP(A21,#REF!,13,0) -> #REF! | Q21: =VLOOKUP(A21,#REF!,14,0) -> #REF! | R21: 3.1534353 | S21: 0.29705997 | T21: =VLOOKUP(C21,V:W,2,0) -> USA | U21: =IF(T21=T$1,B21,IF(T21=T$2,B21,IF(T21=U$1,B21,""))) | V21: QATAR | W21: QAT
A22: Institut Polytechnique de Paris | B22: IPP | C22: FRANCE | D22: =IFERROR(ROUND(VLOOKUP(A22,institutions!A:E,4,0),2),"") -> 4.66 | E22: =IFERROR(ROUND(VLOOKUP(A22,institutions!A:X,7,0),2),"") -> 4.57 | F22: =IFERROR(ROUND(VLOOKUP(A22,institutions!A:X,10,0),2),"") -> 1.73 | G22: =IFERROR(ROUND(VLOOKUP(A22,institutions!A:X,13,0),2),"") | H22: =IFERROR(ROUND(VLOOKUP(A22,institutions!A:X,16,0),2),"") -> 2.43 | I22: =ROUND(IFERROR((601-_xlfn.RANK.EQ(D22,D:D))/600,0),3) -> 0.97 | J22: =ROUND(IFERROR((601-IFERROR(_xlfn.RANK.EQ(E22,E:E),""))/600,0),3) -> 0.968 | K22: =ROUND(IFERROR((601-IFERROR(_xlfn.RANK.EQ(F22,F:F),""))/600,0),3) -> 0.655 | L22: =ROUND(IFERROR((601-IFERROR(_xlfn.RANK.EQ(G22,G:G),""))/600,0),3) -> 0 | M22: =ROUND(IFERROR((601-IFERROR(_xlfn.RANK.EQ(H22,H:H),""))/600,0),3) -> 0.515 | N22: =VLOOKUP(A22,#REF!,11,0) -> #REF! | O22: =VLOOKUP(A22,#REF!,12,0) -> #REF! | P22: =VLOOKUP(A22,#REF!,13,0) -> #REF! | Q22: =VLOOKUP(A22,#REF!,14,0) -> #REF! | R22: 0.13309472 | S22: 2.0264172 | T22: =VLOOKUP(C22,V:W,2,0) -> FRA | U22: =IF(T22=T$1,B22,IF(T22=T$2,B22,IF(T22=U$1,B22,""))) -> IPP | V22: PORTUGAL | W22: PRT
A23: University of California San Diego | B23: UCSD | C23: USA | D23: =IFERROR(ROUND(VLOOKUP(A23,institutions!A:E,4,0),2),"") -> 4.52 | E23: =IFERROR(ROUND(VLOOKUP(A23,institutions!A:X,7,0),2),"") -> 4.19 | F23: =IFERROR(ROUND(VLOOKUP(A23,institutions!A:X,10,0),2),"") -> 4.82 | G23: =IFERROR(ROUND(VLOOKUP(A23,institutions!A:X,13,0),2),"") -> 3.79 | H23: =IFERROR(ROUND(VLOOKUP(A23,institutions!A:X,16,0),2),"") -> 2.28 | I23: =ROUND(IFERROR((601-_xlfn.RANK.EQ(D23,D:D))/600,0),3) -> 0.965 | J23: =ROUND(IFERROR((601-IFERROR(_xlfn.RANK.EQ(E23,E:E),""))/600,0),3) -> 0.963 | K23: =ROUND(IFERROR((601-IFERROR(_xlfn.RANK.EQ(F23,F:F),""))/600,0),3) -> 0.975 | L23: =ROUND(IFERROR((601-IFERROR(_xlfn.RANK.EQ(G23,G:G),""))/600,0),3) -> 0.922 | M23: =ROUND(IFERROR((601-IFERROR(_xlfn.RANK.EQ(H23,H:H),""))/600,0),3) -> 0.462 | N23: =VLOOKUP(A23,#REF!,11,0) -> #REF! | O23: =VLOOKUP(A23,#REF!,12,0) -> #REF! | P23: =VLOOKUP(A23,#REF!,13,0) -> #REF! | Q23: =VLOOKUP(A23,#REF!,14,0) -> #REF! | R23: 2.2217005 | S23: 1.0292867 | T23: =VLOOKUP(C23,V:W,2,0) -> USA | U23: =IF(T23=T$1,B23,IF(T23=T$2,B23,IF(T23=U$1,B23,""))) | V23: POLAND | W23: POL
A24: Boston College | B24: Boston C | C24: USA | D24: =IFERROR(ROUND(VLOOKUP(A24,institutions!A:E,4,0),2),"") -> 4.65 | E24: =IFERROR(ROUND(VLOOKUP(A24,institutions!A:X,7,0),2),"") -> 3.76 | F24: =IFERROR(ROUND(VLOOKUP(A24,institutions!A:X,10,0),2),"") -> 5.59 | G24: =IFERROR(ROUND(VLOOKUP(A24,institutions!A:X,13,0),2),"") -> 4.63 | H24: =IFERROR(ROUND(VLOOKUP(A24,institutions!A:X,16,0),2),"") -> 6.82 | I24: =ROUND(IFERROR((601-_xlfn.RANK.EQ(D24,D:D))/600,0),3) -> 0.968 | J24: =ROUND(IFERROR((601-IFERROR(_xlfn.RANK.EQ(E24,E:E),""))/600,0),3) -> 0.955 | K24: =ROUND(IFERROR((601-IFERROR(_xlfn.RANK.EQ(F24,F:F),""))/600,0),3) -> 0.987 | L24: =ROUND(IFERROR((601-IFERROR(_xlfn.RANK.EQ(G24,G:G),""))/600,0),3) -> 0.967 | M24: =ROUND(IFERROR((601-IFERROR(_xlfn.RANK.EQ(H24,H:H),""))/600,0),3) -> 0.99 | N24: =VLOOKUP(A24,#REF!,11,0) -> #REF! | O24: =VLOOKUP(A24,#REF!,12,0) -> #REF! | P24: =VLOOKUP(A24,#REF!,13,0) -> #REF! | Q24: =VLOOKUP(A24,#REF!,14,0) -> #REF! | R24: 3.2632196 | S24: 0.11723192 | T24: =VLOOKUP(C24,V:W,2,0) -> USA | U24: =IF(T24=T$1,B24,IF(T24=T$2,B24,IF(T24=U$1,B24,""))) | V24: PAKISTAN | W24: PAK
A25: University of Zurich | B25: Zurich | C25: SWITZERLAND | D25: =IFERROR(ROUND(VLOOKUP(A25,institutions!A:E,4,0),2),"") -> 4.39 | E25: =IFERROR(ROUND(VLOOKUP(A25,institutions!A:X,7,0),2),"") -> 4.9 | F25: =IFERROR(ROUND(VLOOKUP(A25,institutions!A:X,10,0),2),"") -> 2.13 | G25: =IFERROR(ROUND(VLOOKUP(A25,institutions!A:X,13,0),2),"") -> 2.5 | H25: =IFERROR(ROUND(VLOOKUP(A25,institutions!A:X,16,0),2),"") -> 3.61 | I25: =ROUND(IFERROR((601-_xlfn.RANK.EQ(D25,D:D))/600,0),3) -> 0.962 | J25: =ROUND(IFERROR((601-IFERROR(_xlfn.RANK.EQ(E25,E:E),""))/600,0),3) -> 0.977 | K25: =ROUND(IFERROR((601-IFERROR(_xlfn.RANK.EQ(F25,F:F),""))/600,0),3) -> 0.78 | L25: =ROUND(IFERROR((601-IFERROR(_xlfn.RANK.EQ(G25,G:G),""))/600,0),3) -> 0.695 | M25: =ROUND(IFERROR((601-IFERROR(_xlfn.RANK.EQ(H25,H:H),""))/600,0),3) -> 0.817 | N25: =VLOOKUP(A25,#REF!,11,0) -> #REF! | O25: =VLOOKUP(A25,#REF!,12,0) -> #REF! | P25: =VLOOKUP(A25,#REF!,13,0) -> #REF! | Q25: =VLOOKUP(A25,#REF!,14,0) -> #REF! | R25: 2.1468809 | S25: 0.59057788 | T25: =VLOOKUP(C25,V:W,2,0) -> CHE | U25: =IF(T25=T$1,B25,IF(T25=T$2,B25,IF(T25=U$1,B25,""))) | V25: NORWAY | W25: NOR
A26: Washington University (WUSTL) | B26: WUSTL | C26: USA | D26: =IFERROR(ROUND(VLOOKUP(A26,institutions!A:E,4,0),2),"") -> 4.44 | E26: =IFERROR(ROUND(VLOOKUP(A26,institutions!A:X,7,0),2),"") -> 3.49 | F26: =IFERROR(ROUND(VLOOKUP(A26,institutions!A:X,10,0),2),"") -> 4.75 | G26: =IFERROR(ROUND(VLOOKUP(A26,institutions!A:X,13,0),2),"") -> 5.04 | H26: =IFERROR(ROUND(VLOOKUP(A26,institutions!A:X,16,0),2),"") -> 6.08 | I26: =ROUND(IFERROR((601-_xlfn.RANK.EQ(D26,D:D))/600,0),3) -> 0.963 | J26: =ROUND(IFERROR((601-IFERROR(_xlfn.RANK.EQ(E26,E:E),""))/600,0),3) -> 0.948 | K26: =ROUND(IFERROR((601-IFERROR(_xlfn.RANK.EQ(F26,F:F),""))/600,0),3) -> 0.972 | L26: =ROUND(IFERROR((601-IFERROR(_xlfn.RANK.EQ(G26,G:G),""))/600,0),3) -> 0.98 | M26: =ROUND(IFERROR((601-IFERROR(_xlfn.RANK.EQ(H26,H:H),""))/600,0),3) -> 0.978 | N26: =VLOOKUP(A26,#REF!,11,0) -> #REF! | O26: =VLOOKUP(A26,#REF!,12,0) -> #REF! | P26: =VLOOKUP(A26,#REF!,13,0) -> #REF! | Q26: =VLOOKUP(A26,#REF!,14,0) -> #REF! | R26: 3.2279256 | S26: 0.077831463 | T26: =VLOOKUP(C26,V:W,2,0) -> USA | U26: =IF(T26=T$1,B26,IF(T26=T$2,B26,IF(T26=U$1,B26,""))) | V26: NORTHERN IRELAND | W26: UK
... A45: Duke University | B45: Duke | C45: USA | D45: =IFERROR(ROUND(VLOOKUP(A45,institutions!A:E,4,0),2),"") -> 3.5 | E45: =IFERROR(ROUND(VLOOKUP(A45,institutions!A:X,7,0),2),"") -> 3.31 | F45: =IFERROR(ROUND(VLOOKUP(A45,institutions!A:X,10,0),2),"") -> 4.62 | G45: =IFERROR(ROUND(VLOOKUP(A45,institutions!A:X,13,0),2),"") -> 2.48 | H45: =IFERROR(ROUND(VLOOKUP(A45,institutions!A:X,16,0),2),"") -> 3.37 | I45: =ROUND(IFERROR((601-_xlfn.RANK.EQ(D45,D:D))/600,0),3) -> 0.918 | J45: =ROUND(IFERROR((601-IFERROR(_xlfn.RANK.EQ(E45,E:E),""))/600,0),3) -> 0.937 | K45: =ROUND(IFERROR((601-IFERROR(_xlfn.RANK.EQ(F45,F:F),""))/600,0),3) -> 0.968 | L45: =ROUND(IFERROR((601-IFERROR(_xlfn.RANK.EQ(G45,G:G),""))/600,0),3) -> 0.685 | M45: =ROUND(IFERROR((601-IFERROR(_xlfn.RANK.EQ(H45,H:H),""))/600,0),3) -> 0.76 | N45: =VLOOKUP(A45,#REF!,11,0) -> #REF! | O45: =VLOOKUP(A45,#REF!,12,0) -> #REF! | P45: =VLOOKUP(A45,#REF!,13,0) -> #REF! | Q45: =VLOOKUP(A45,#REF!,14,0) -> #REF! | R45: 2.283287 | S45: 0.88579298 | T45: =VLOOKUP(C45,V:W,2,0) -> USA | U45: =IF(T45=T$1,B45,IF(T45=T$2,B45,IF(T45=U$1,B45,""))) | V45: ESTONIA | W45: EST
A46: University of British Columbia | B46: UBC | C46: CANADA | D46: =IFERROR(ROUND(VLOOKUP(A46,institutions!A:E,4,0),2),"") -> 3.6 | E46: =IFERROR(ROUND(VLOOKUP(A46,institutions!A:X,7,0),2),"") -> 3.49 | F46: =IFERROR(ROUND(VLOOKUP(A46,institutions!A:X,10,0),2),"") -> 4.44 | G46: =IFERROR(ROUND(VLOOKUP(A46,institutions!A:X,13,0),2),"") -> 3.14 | H46: =IFERROR(ROUND(VLOOKUP(A46,institutions!A:X,16,0),2),"") -> 3.54 | I46: =ROUND(IFERROR((601-_xlfn.RANK.EQ(D46,D:D))/600,0),3) -> 0.928 | J46: =ROUND(IFERROR((601-IFERROR(_xlfn.RANK.EQ(E46,E:E),""))/600,0),3) -> 0.948 | K46: =ROUND(IFERROR((601-IFERROR(_xlfn.RANK.EQ(F46,F:F),""))/600,0),3) -> 0.963 | L46: =ROUND(IFERROR((601-IFERROR(_xlfn.RANK.EQ(G46,G:G),""))/600,0),3) -> 0.837 | M46: =ROUND(IFERROR((601-IFERROR(_xlfn.RANK.EQ(H46,H:H),""))/600,0),3) -> 0.802 | N46: 1 | O46: =VLOOKUP(A46,#REF!,12,0) -> #REF! | P46: =VLOOKUP(A46,#REF!,13,0) -> #REF! | Q46: =VLOOKUP(A46,#REF!,14,0) -> #REF! | R46: 2.6394853 | S46: 0.58214181 | T46: =VLOOKUP(C46,V:W,2,0) -> CAN | U46: =IF(T46=T$1,B46,IF(T46=T$2,B46,IF(T46=U$1,B46,""))) | V46: ENGLAND | W46: UK
A47: University of Bonn | B47: Bonn | C47: GERMANY | D47: =IFERROR(ROUND(VLOOKUP(A47,institutions!A:E,4,0),2),"") -> 3.5 | E47: =IFERROR(ROUND(VLOOKUP(A47,institutions!A:X,7,0),2),"") -> 3.33 | F47: =IFERROR(ROUND(VLOOKUP(A47,institutions!A:X,10,0),2),"") -> 2.64 | G47: =IFERROR(ROUND(VLOOKUP(A47,institutions!A:X,13,0),2),"") | H47: =IFERROR(ROUND(VLOOKUP(A47,institutions!A:X,16,0),2),"") | I47: =ROUND(IFERROR((601-_xlfn.RANK.EQ(D47,D:D))/600,0),3) -> 0.918 | J47: =ROUND(IFERROR((601-IFERROR(_xlfn.RANK.EQ(E47,E:E),""))/600,0),3) -> 0.94 | K47: =ROUND(IFERROR((601-IFERROR(_xlfn.RANK.EQ(F47,F:F),""))/600,0),3) -> 0.848 | L47: =ROUND(IFERROR((601-IFERROR(_xlfn.RANK.EQ(G47,G:G),""))/600,0),3) -> 0 | M47: =ROUND(IFERROR((601-IFERROR(_xlfn.RANK.EQ(H47,H:H),""))/600,0),3) -> 0 | N47: =VLOOKUP(A47,#REF!,11,0) -> #REF! | O47: =VLOOKUP(A47,#REF!,12,0) -> #REF! | P47: =VLOOKUP(A47,#REF!,13,0) -> #REF! | Q47: =VLOOKUP(A47,#REF!,14,0) -> #REF! | R47: -0.51199823 | S47: 3.0643027 | T47: =VLOOKUP(C47,V:W,2,0) -> DEU | U47: =IF(T47=T$1,B47,IF(T47=T$2,B47,IF(T47=U$1,B47,""))) -> Bonn | V47: DENMARK | W47: DEN
A48: University of Southern California | B48: USC | C48: USA | D48: =IFERROR(ROUND(VLOOKUP(A48,institutions!A:E,4,0),2),"") -> 3.53 | E48: =IFERROR(ROUND(VLOOKUP(A48,institutions!A:X,7,0),2),"") -> 3.03 | F48: =IFERROR(ROUND(VLOOKUP(A48,institutions!A:X,10,0),2),"") -> 3.51 | G48: =IFERROR(ROUND(VLOOKUP(A48,institutions!A:X,13,0),2),"") -> 4.58 | H48: =IFERROR(ROUND(VLOOKUP(A48,institutions!A:X,16,0),2),"") -> 4.58 | I48: =ROUND(IFERROR((601-_xlfn.RANK.EQ(D48,D:D))/600,0),3) -> 0.923 | J48: =ROUND(IFERROR((601-IFERROR(_xlfn.RANK.EQ(E48,E:E),""))/600,0),3) -> 0.92 | K48: =ROUND(IFERROR((601-IFERROR(_xlfn.RANK.EQ(F48,F:F),""))/600,0),3) -> 0.922 | L48: =ROUND(IFERROR((601-IFERROR(_xlfn.RANK.EQ(G48,G:G),""))/600,0),3) -> 0.96 | M48: =ROUND(IFERROR((601-IFERROR(_xlfn.RANK.EQ(H48,H:H),""))/600,0),3) -> 0.922 | N48: =VLOOKUP(A48,#REF!,11,0) -> #REF! | O48: =VLOOKUP(A48,#REF!,12,0) -> #REF! | P48: =VLOOKUP(A48,#REF!,13,0) -> #REF! | Q48: =VLOOKUP(A48,#REF!,14,0) -> #REF! | R48: 2.9608791 | S48: 0.067429341 | T48: =VLOOKUP(C48,V:W,2,0) -> USA | U48: =IF(T48=T$1,B48,IF(T48=T$2,B48,IF(T48=U$1,B48,""))) | V48: CZECH REPUBLIC | W48: CZE
A49: Babson College | B49: Babson C | C49: USA | D49: =IFERROR(ROUND(VLOOKUP(A49,institutions!A:E,4,0),2),"") -> 3.67 | E49: =IFERROR(ROUND(VLOOKUP(A49,institutions!A:X,7,0),2),"") -> 2.28 | F49: =IFERROR(ROUND(VLOOKUP(A49,institutions!A:X,10,0),2),"") -> 3.84 | G49: =IFERROR(ROUND(VLOOKUP(A49,institutions!A:X,13,0),2),"") -> 4.21 | H49: =IFERROR(ROUND(VLOOKUP(A49,institutions!A:X,16,0),2),"") -> 4.06 | I49: =ROUND(IFERROR((601-_xlfn.RANK.EQ(D49,D:D))/600,0),3) -> 0.935 | J49: =ROUND(IFERROR((601-IFERROR(_xlfn.RANK.EQ(E49,E:E),""))/600,0),3) -> 0.837 | K49: =ROUND(IFERROR((601-IFERROR(_xlfn.RANK.EQ(F49,F:F),""))/600,0),3) -> 0.937 | L49: =ROUND(IFERROR((601-IFERROR(_xlfn.RANK.EQ(G49,G:G),""))/600,0),3) -> 0.952 | M49: =ROUND(IFERROR((601-IFERROR(_xlfn.RANK.EQ(H49,H:H),""))/600,0),3) -> 0.88 | N49: =VLOOKUP(A49,#REF!,11,0) -> #REF! | O49: =VLOOKUP(A49,#REF!,12,0) -> #REF! | P49: =VLOOKUP(A49,#REF!,13,0) -> #REF! | Q49: =VLOOKUP(A49,#REF!,14,0) -> #REF! | R49: 2.7635838 | S49: -0.0080339468 | T49: =VLOOKUP(C49,V:W,2,0) -> USA | U49: =IF(T49=T$1,B49,IF(T49=T$2,B49,IF(T49=U$1,B49,""))) | V49: CROATIA | W49: CRO
A50: University of Cincinnati | B50: Cincinnati | C50: USA | D50: =IFERROR(ROUND(VLOOKUP(A50,institutions!A:E,4,0),2),"") -> 3.72 | E50: =IFERROR(ROUND(VLOOKUP(A50,institutions!A:X,7,0),2),"") -> 4.73 | F50: =IFERROR(ROUND(VLOOKUP(A50,institutions!A:X,10,0),2),"") -> 6.19 | G50: =IFERROR(ROUND(VLOOKUP(A50,institutions!A:X,13,0),2),"") -> 2.38 | H50: =IFERROR(ROUND(VLOOKUP(A50,institutions!A:X,16,0),2),"") -> 3.51 | I50: =ROUND(IFERROR((601-_xlfn.RANK.EQ(D50,D:D))/600,0),3) -> 0.938 | J50: =ROUND(IFERROR((601-IFERROR(_xlfn.RANK.EQ(E50,E:E),""))/600,0),3) -> 0.975 | K50: =ROUND(IFERROR((601-IFERROR(_xlfn.RANK.EQ(F50,F:F),""))/600,0),3) -> 0.993 | L50: =ROUND(IFERROR((601-IFERROR(_xlfn.RANK.EQ(G50,G:G),""))/600,0),3) -> 0.625 | M50: =ROUND(IFERROR((601-IFERROR(_xlfn.RANK.EQ(H50,H:H),""))/600,0),3) -> 0.795 | N50: =VLOOKUP(A50,#REF!,11,0) -> #REF! | O50: =VLOOKUP(A50,#REF!,12,0) -> #REF! | P50: =VLOOKUP(A50,#REF!,13,0) -> #REF! | Q50: =VLOOKUP(A50,#REF!,14,0) -> #REF! | R50: 2.3429121 | S50: 1.0477676 | T50: =VLOOKUP(C50,V:W,2,0) -> USA | U50: =IF(T50=T$1,B50,IF(T50=T$2,B50,IF(T50=U$1,B50,""))) | V50: COLOMBIA | W50: COL
A51: Hong Kong University of Science & Technology | B51: HKST | C51: HONG KONG | D51: =IFERROR(ROUND(VLOOKUP(A51,institutions!A:E,4,0),2),"") -> 3.44 | E51: =IFERROR(ROUND(VLOOKUP(A51,institutions!A:X,7,0),2),"") -> 3.06 | F51: =IFERROR(ROUND(VLOOKUP(A51,institutions!A:X,10,0),2),"") -> 3.17 | G51: =IFERROR(ROUND(VLOOKUP(A51,institutions!A:X,13,0),2),"") -> 4.46 | H51: =IFERROR(ROUND(VLOOKUP(A51,institutions!A:X,16,0),2),"") -> 3.88 | I51: =ROUND(IFERROR((601-_xlfn.RANK.EQ(D51,D:D))/600,0),3) -> 0.915 | J51: =ROUND(IFERROR((601-IFERROR(_xlfn.RANK.EQ(E51,E:E),""))/600,0),3) -> 0.925 | K51: =ROUND(IFERROR((601-IFERROR(_xlfn.RANK.EQ(F51,F:F),""))/600,0),3) -> 0.895 | L51: =ROUND(IFERROR((601-IFERROR(_xlfn.RANK.EQ(G51,G:G),""))/600,0),3) -> 0.957 | M51: =ROUND(IFERROR((601-IFERROR(_xlfn.RANK.EQ(H51,H:H),""))/600,0),3) -> 0.86 | N51: =VLOOKUP(A51,#REF!,11,0) -> #REF! | O51: =VLOOKUP(A51,#REF!,12,0) -> #REF! | P51: =VLOOKUP(A51,#REF!,13,0) -> #REF! | Q51: =VLOOKUP(A51,#REF!,14,0) -> #REF! | R51: 2.8054324 | S51: 0.14215436 | T51: =VLOOKUP(C51,V:W,2,0) -> HKG | U51: =IF(T51=T$1,B51,IF(T51=T$2,B51,IF(T51=U$1,B51,""))) | V51: CHINA MAINLAND | W51: CHN
A52: University of California Irvine | B52: UCI | C52: USA | D52: =IFERROR(ROUND(VLOOKUP(A52,institutions!A:E,4,0),2),"") -> 3.63 | E52: =IFERROR(ROUND(VLOOKUP(A52,institutions!A:X,7,0),2),"") -> 2.33 | F52: =IFERROR(ROUND(VLOOKUP(A52,institutions!A:X,10,0),2),"") -> 5.12 | G52: =IFERROR(ROUND(VLOOKUP(A52,institutions!A:X,13,0),2),"") -> 5.53 | H52: =IFERROR(ROUND(VLOOKUP(A52,institutions!A:X,16,0),2),"") -> 7.54 | I52: =ROUND(IFERROR((601-_xlfn.RANK.EQ(D52,D:D))/600,0),3) -> 0.93 | J52: =ROUND(IFERROR((601-IFERROR(_xlfn.RANK.EQ(E52,E:E),""))/600,0),3) -> 0.842 | K52: =ROUND(IFERROR((601-IFERROR(_xlfn.RANK.EQ(F52,F:F),""))/600,0),3) -> 0.982 | L52: =ROUND(IFERROR((601-IFERROR(_xlfn.RANK.EQ(G52,G:G),""))/600,0),3) -> 0.99 | M52: =ROUND(IFERROR((601-IFERROR(_xlfn.RANK.EQ(H52,H:H),""))/600,0),3) -> 0.995 | N52: =VLOOKUP(A52,#REF!,11,0) -> #REF! | O52: =VLOOKUP(A52,#REF!,12,0) -> #REF! | P52: =VLOOKUP(A52,#REF!,13,0) -> #REF! | Q52: =VLOOKUP(A52,#REF!,14,0) -> #REF! | R52: 3.1239624 | S52: -0.17759023 | T52: =VLOOKUP(C52,V:W,2,0) -> USA | U52: =IF(T52=T$1,B52,IF(T52=T$2,B52,IF(T52=U$1,B52,""))) | V52: CHILE | W52: CHL
A53: University of North Carolina Chapel Hill | B53: UNC | C53: USA | D53: =IFERROR(ROUND(VLOOKUP(A53,institutions!A:E,4,0),2),"") -> 3.54 | E53: =IFERROR(ROUND(VLOOKUP(A53,institutions!A:X,7,0),2),"") -> 2.5 | F53: =IFERROR(ROUND(VLOOKUP(A53,institutions!A:X,10,0),2),"") -> 3.78 | G53: =IFERROR(ROUND(VLOOKUP(A53,institutions!A:X,13,0),2),"") -> 5.66 | H53: =IFERROR(ROUND(VLOOKUP(A53,institutions!A:X,16,0),2),"") -> 5.34 | I53: =ROUND(IFERROR((601-_xlfn.RANK.EQ(D53,D:D))/600,0),3) -> 0.925 | J53: =ROUND(IFERROR((601-IFERROR(_xlfn.RANK.EQ(E53,E:E),""))/600,0),3) -> 0.863 | K53: =ROUND(IFERROR((601-IFERROR(_xlfn.RANK.EQ(F53,F:F),""))/600,0),3) -> 0.935 | L53: =ROUND(IFERROR((601-IFERROR(_xlfn.RANK.EQ(G53,G:G),""))/600,0),3) -> 0.995 | M53: =ROUND(IFERROR((601-IFERROR(_xlfn.RANK.EQ(H53,H:H),""))/600,0),3) -> 0.945 | N53: 1 | O53: =VLOOKUP(A53,#REF!,12,0) -> #REF! | P53: =VLOOKUP(A53,#REF!,13,0) -> #REF! | Q53: =VLOOKUP(A53,#REF!,14,0) -> #REF! | R53: 2.9958953 | S53: -0.1301637 | T53: =VLOOKUP(C53,V:W,2,0) -> USA | U53: =IF(T53=T$1,B53,IF(T53=T$2,B53,IF(T53=U$1,B53,""))) | V53: CANADA | W53: CAN
A54: University of Utah | B54: Utah | C54: USA | D54: =IFERROR(ROUND(VLOOKUP(A54,institutions!A:E,4,0),2),"") -> 3.51 | E54: =IFERROR(ROUND(VLOOKUP(A54,institutions!A:X,7,0),2),"") -> 2.63 | F54: =IFERROR(ROUND(VLOOKUP(A54,institutions!A:X,10,0),2),"") -> 3.67 | G54: =IFERROR(ROUND(VLOOKUP(A54,institutions!A:X,13,0),2),"") -> 4.08 | H54: =IFERROR(ROUND(VLOOKUP(A54,institutions!A:X,16,0),2),"") -> 5.51 | I54: =ROUND(IFERROR((601-_xlfn.RANK.EQ(D54,D:D))/600,0),3) -> 0.92 | J54: =ROUND(IFERROR((601-IFERROR(_xlfn.RANK.EQ(E54,E:E),""))/600,0),3) -> 0.878 | K54: =ROUND(IFERROR((601-IFERROR(_xlfn.RANK.EQ(F54,F:F),""))/600,0),3) -> 0.93 | L54: =ROUND(IFERROR((601-IFERROR(_xlfn.RANK.EQ(G54,G:G),""))/600,0),3) -> 0.945 | M54: =ROUND(IFERROR((601-IFERROR(_xlfn.RANK.EQ(H54,H:H),""))/600,0),3) -> 0.957 | N54: =VLOOKUP(A54,#REF!,11,0) -> #REF! | O54: =VLOOKUP(A54,#REF!,12,0) -> #REF! | P54: =VLOOKUP(A54,#REF!,13,0) -> #REF! | Q54: =VLOOKUP(A54,#REF!,14,0) -> #REF! | R54: 2.9437813 | S54: -0.041136562 | T54: =VLOOKUP(C54,V:W,2,0) -> USA | U54: =IF(T54=T$1,B54,IF(T54=T$2,B54,IF(T54=U$1,B54,""))) | V54: BRAZIL | W54: BRA
A55: Bocconi University | B55: Bocconi | C55: ITALY | D55: =IFERROR(ROUND(VLOOKUP(A55,institutions!A:E,4,0),2),"") -> 3.43 | E55: =IFERROR(ROUND(VLOOKUP(A55,institutions!A:X,7,0),2),"") -> 3.31 | F55: =IFERROR(ROUND(VLOOKUP(A55,institutions!A:X,10,0),2),"") -> 1.82 | G55: =IFERROR(ROUND(VLOOKUP(A55,institutions!A:X,13,0),2),"") -> 3.3 | H55: =IFERROR(ROUND(VLOOKUP(A55,institutions!A:X,16,0),2),"") -> 4.84 | I55: =ROUND(IFERROR((601-_xlfn.RANK.EQ(D55,D:D))/600,0),3) -> 0.913 | J55: =ROUND(IFERROR((601-IFERROR(_xlfn.RANK.EQ(E55,E:E),""))/600,0),3) -> 0.937 | K55: =ROUND(IFERROR((601-IFERROR(_xlfn.RANK.EQ(F55,F:F),""))/600,0),3) -> 0.687 | L55: =ROUND(IFERROR((601-IFERROR(_xlfn.RANK.EQ(G55,G:G),""))/600,0),3) -> 0.862 | M55: =ROUND(IFERROR((601-IFERROR(_xlfn.RANK.EQ(H55,H:H),""))/600,0),3) -> 0.93 | N55: =VLOOKUP(A55,#REF!,11,0) -> #REF! | O55: =VLOOKUP(A55,#REF!,12,0) -> #REF! | P55: =VLOOKUP(A55,#REF!,13,0) -> #REF! | Q55: =VLOOKUP(A55,#REF!,14,0) -> #REF! | R55: 2.4261276 | S55: -0.087630819 | T55: =VLOOKUP(C55,V:W,2,0) -> ITA | U55: =IF(T55=T$1,B55,IF(T55=T$2,B55,IF(T55=U$1,B55,""))) | V55: BELGIUM | W55: BEL | AG55: Varimax PCA
A56: University of Wisconsin Madison | B56: Madison | C56: USA | D56: =IFERROR(ROUND(VLOOKUP(A56,institutions!A:E,4,0),2),"") -> 3.37 | E56: =IFERROR(ROUND(VLOOKUP(A56,institutions!A:X,7,0),2),"") -> 3.12 | F56: =IFERROR(ROUND(VLOOKUP(A56,institutions!A:X,10,0),2),"") -> 3.37 | G56: =IFERROR(ROUND(VLOOKUP(A56,institutions!A:X,13,0),2),"") -> 4.6 | H56: =IFERROR(ROUND(VLOOKUP(A56,institutions!A:X,16,0),2),"") -> 3.48 | I56: =ROUND(IFERROR((601-_xlfn.RANK.EQ(D56,D:D))/600,0),3) -> 0.908 | J56: =ROUND(IFERROR((601-IFERROR(_xlfn.RANK.EQ(E56,E:E),""))/600,0),3) -> 0.93 | K56: =ROUND(IFERROR((601-IFERROR(_xlfn.RANK.EQ(F56,F:F),""))/600,0),3) -> 0.908 | L56: =ROUND(IFERROR((601-IFERROR(_xlfn.RANK.EQ(G56,G:G),""))/600,0),3) -> 0.962 | M56: =ROUND(IFERROR((601-IFERROR(_xlfn.RANK.EQ(H56,H:H),""))/600,0),3) -> 0.792 | N56: =VLOOKUP(A56,#REF!,11,0) -> #REF! | O56: =VLOOKUP(A56,#REF!,12,0) -> #REF! | P56: =VLOOKUP(A56,#REF!,13,0) -> #REF! | Q56: =VLOOKUP(A56,#REF!,14,0) -> #REF! | R56: 2.7217669 | S56: 0.27127154 | T56: =VLOOKUP(C56,V:W,2,0) -> USA | U56: =IF(T56=T$1,B56,IF(T56=T$2,B56,IF(T56=U$1,B56,""))) | V56: AUSTRIA | W56: AUT | AG56: Eigenvalues
A57: University of Colorado Boulder | B57: Boulder | C57: USA | D57: =IFERROR(ROUND(VLOOKUP(A57,institutions!A:E,4,0),2),"") -> 3.37 | E57: =IFERROR(ROUND(VLOOKUP(A57,institutions!A:X,7,0),2),"") -> 3.03 | F57: =IFERROR(ROUND(VLOOKUP(A57,institutions!A:X,10,0),2),"") -> 5.49 | G57: =IFERROR(ROUND(VLOOKUP(A57,institutions!A:X,13,0),2),"") -> 4.21 | H57: =IFERROR(ROUND(VLOOKUP(A57,institutions!A:X,16,0),2),"") -> 3.47 | I57: =ROUND(IFERROR((601-_xlfn.RANK.EQ(D57,D:D))/600,0),3) -> 0.908 | J57: =ROUND(IFERROR((601-IFERROR(_xlfn.RANK.EQ(E57,E:E),""))/600,0),3) -> 0.92 | K57: =ROUND(IFERROR((601-IFERROR(_xlfn.RANK.EQ(F57,F:F),""))/600,0),3) -> 0.983 | L57: =ROUND(IFERROR((601-IFERROR(_xlfn.RANK.EQ(G57,G:G),""))/600,0),3) -> 0.952 | M57: =ROUND(IFERROR((601-IFERROR(_xlfn.RANK.EQ(H57,H:H),""))/600,0),3) -> 0.787 | N57: =VLOOKUP(A57,#REF!,11,0) -> #REF! | O57: =VLOOKUP(A57,#REF!,12,0) -> #REF! | P57: =VLOOKUP(A57,#REF!,13,0) -> #REF! | Q57: =VLOOKUP(A57,#REF!,14,0) -> #REF! | R57: 2.8070229 | S57: 0.38364287 | T57: =VLOOKUP(C57,V:W,2,0) -> USA | U57: =IF(T57=T$1,B57,IF(T57=T$2,B57,IF(T57=U$1,B57,""))) | V57: AUSTRALIA | W57: AUS | AG57: 2.7361128 | AH57: 0.76532337
A58: University of Virginia | B58: Virginia | C58: USA | D58: =IFERROR(ROUND(VLOOKUP(A58,institutions!A:E,4,0),2),"") -> 3.53 | E58: =IFERROR(ROUND(VLOOKUP(A58,institutions!A:X,7,0),2),"") -> 2.55 | F58: =IFERROR(ROUND(VLOOKUP(A58,institutions!A:X,10,0),2),"") -> 3.47 | G58: =IFERROR(ROUND(VLOOKUP(A58,institutions!A:X,13,0),2),"") -> 5.61 | H58: =IFERROR(ROUND(VLOOKUP(A58,institutions!A:X,16,0),2),"") -> 6.3 | I58: =ROUND(IFERROR((601-_xlfn.RANK.EQ(D58,D:D))/600,0),3) -> 0.923 | J58: =ROUND(IFERROR((601-IFERROR(_xlfn.RANK.EQ(E58,E:E),""))/600,0),3) -> 0.873 | K58: =ROUND(IFERROR((601-IFERROR(_xlfn.RANK.EQ(F58,F:F),""))/600,0),3) -> 0.913 | L58: =ROUND(IFERROR((601-IFERROR(_xlfn.RANK.EQ(G58,G:G),""))/600,0),3) -> 0.993 | M58: =ROUND(IFERROR((601-IFERROR(_xlfn.RANK.EQ(H58,H:H),""))/600,0),3) -> 0.985 | N58: =VLOOKUP(A58,#REF!,11,0) -> #REF! | O58: =VLOOKUP(A58,#REF!,12,0) -> #REF! | P58: =VLOOKUP(A58,#REF!,13,0) -> #REF! | Q58: =VLOOKUP(A58,#REF!,14,0) -> #REF! | R58: 3.0429743 | S58: -0.20093415 | T58: =VLOOKUP(C58,V:W,2,0) -> USA | U58: =IF(T58=T$1,B58,IF(T58=T$2,B58,IF(T58=U$1,B58,""))) | AG58: % variance explained
A59: University of Pittsburgh | B59: Pittsburgh | C59: USA | D59: =IFERROR(ROUND(VLOOKUP(A59,institutions!A:E,4,0),2),"") -> 3.42 | E59: =IFERROR(ROUND(VLOOKUP(A59,institutions!A:X,7,0),2),"") -> 2 | F59: =IFERROR(ROUND(VLOOKUP(A59,institutions!A:X,10,0),2),"") -> 3.56 | G59: =IFERROR(ROUND(VLOOKUP(A59,institutions!A:X,13,0),2),"") -> 5.3 | H59: =IFERROR(ROUND(VLOOKUP(A59,institutions!A:X,16,0),2),"") -> 5.71 | I59: =ROUND(IFERROR((601-_xlfn.RANK.EQ(D59,D:D))/600,0),3) -> 0.912 | J59: =ROUND(IFERROR((601-IFERROR(_xlfn.RANK.EQ(E59,E:E),""))/600,0),3) -> 0.753 | K59: =ROUND(IFERROR((601-IFERROR(_xlfn.RANK.EQ(F59,F:F),""))/600,0),3) -> 0.923 | L59: =ROUND(IFERROR((601-IFERROR(_xlfn.RANK.EQ(G59,G:G),""))/600,0),3) -> 0.987 | M59: =ROUND(IFERROR((601-IFERROR(_xlfn.RANK.EQ(H59,H:H),""))/600,0),3) -> 0.968 | N59: =VLOOKUP(A59,#REF!,11,0) -> #REF! | O59: =VLOOKUP(A59,#REF!,12,0) -> #REF! | P59: =VLOOKUP(A59,#REF!,13,0) -> #REF! | Q59: =VLOOKUP(A59,#REF!,14,0) -> #REF! | R59: 2.8266547 | S59: -0.40566589 | T59: =VLOOKUP(C59,V:W,2,0) -> USA | U59: =IF(T59=T$1,B59,IF(T59=T$2,B59,IF(T59=U$1,B59,""))) | AG59: 0.68288816 | AH59: 0.19101196
A60: University of Toronto | B60: Toronto | C60: CANADA | D60: =IFERROR(ROUND(VLOOKUP(A60,institutions!A:E,4,0),2),"") -> 3.3 | E60: =IFERROR(ROUND(VLOOKUP(A60,institutions!A:X,7,0),2),"") -> 3.02 | F60: =IFERROR(ROUND(VLOOKUP(A60,institutions!A:X,10,0),2),"") -> 3.33 | G60: =IFERROR(ROUND(VLOOKUP(A60,institutions!A:X,13,0),2),"") -> 2.69 | H60: =IFERROR(ROUND(VLOOKUP(A60,institutions!A:X,16,0),2),"") -> 3.82 | I60: =ROUND(IFERROR((601-_xlfn.RANK.EQ(D60,D:D))/600,0),3) -> 0.905 | J60: =ROUND(IFERROR((601-IFERROR(_xlfn.RANK.EQ(E60,E:E),""))/600,0),3) -> 0.915 | K60: =ROUND(IFERROR((601-IFERROR(_xlfn.RANK.EQ(F60,F:F),""))/600,0),3) -> 0.903 | L60: =ROUND(IFERROR((601-IFERROR(_xlfn.RANK.EQ(G60,G:G),""))/600,0),3) -> 0.747 | M60: =ROUND(IFERROR((601-IFERROR(_xlfn.RANK.EQ(H60,H:H),""))/600,0),3) -> 0.853 | N60: =VLOOKUP(A60,#REF!,11,0) -> #REF! | O60: =VLOOKUP(A60,#REF!,12,0) -> #REF! | P60: =VLOOKUP(A60,#REF!,13,0) -> #REF! | Q60: =VLOOKUP(A60,#REF!,14,0) -> #REF! | R60: 2.4156446 | S60: 0.49342721 | T60: =VLOOKUP(C60,V:W,2,0) -> CAN | U60: =IF(T60=T$1,B60,IF(T60=T$2,B60,IF(T60=U$1,B60,"")))
A61: Carnegie Mellon University | B61: C Mellon | C61: USA | D61: =IFERROR(ROUND(VLOOKUP(A61,institutions!A:E,4,0),2),"") -> 3.38 | E61: =IFERROR(ROUND(VLOOKUP(A61,institutions!A:X,7,0),2),"") -> 2.84 | F61: =IFERROR(ROUND(VLOOKUP(A61,institutions!A:X,10,0),2),"") -> 2.59 | G61: =IFERROR(ROUND(VLOOKUP(A61,institutions!A:X,13,0),2),"") -> 2.96 | H61: =IFERROR(ROUND(VLOOKUP(A61,institutions!A:X,16,0),2),"") -> 5.5 | I61: =ROUND(IFERROR((601-_xlfn.RANK.EQ(D61,D:D))/600,0),3) -> 0.91 | J61: =ROUND(IFERROR((601-IFERROR(_xlfn.RANK.EQ(E61,E:E),""))/600,0),3) -> 0.902 | K61: =ROUND(IFERROR((601-IFERROR(_xlfn.RANK.EQ(F61,F:F),""))/600,0),3) -> 0.843 | L61: =ROUND(IFERROR((601-IFERROR(_xlfn.RANK.EQ(G61,G:G),""))/600,0),3) -> 0.802 | M61: =ROUND(IFERROR((601-IFERROR(_xlfn.RANK.EQ(H61,H:H),""))/600,0),3) -> 0.955 | N61: =VLOOKUP(A61,#REF!,11,0) -> #REF! | O61: =VLOOKUP(A61,#REF!,12,0) -> #REF! | P61: =VLOOKUP(A61,#REF!,13,0) -> #REF! | Q61: =VLOOKUP(A61,#REF!,14,0) -> #REF! | R61: 2.5747031 | S61: 0.12494314 | T61: =VLOOKUP(C61,V:W,2,0) -> USA | U61: =IF(T61=T$1,B61,IF(T61=T$2,B61,IF(T61=U$1,B61,"")))
A62: University of Illinois Chicago | B62: Illinois Ch | C62: USA | D62: =IFERROR(ROUND(VLOOKUP(A62,institutions!A:E,4,0),2),"") -> 3.24 | E62: =IFERROR(ROUND(VLOOKUP(A62,institutions!A:X,7,0),2),"") -> 3 | F62: =IFERROR(ROUND(VLOOKUP(A62,institutions!A:X,10,0),2),"") -> 3.92 | G62: =IFERROR(ROUND(VLOOKUP(A62,institutions!A:X,13,0),2),"") -> 3.52 | H62: =IFERROR(ROUND(VLOOKUP(A62,institutions!A:X,16,0),2),"") -> 3.24 | I62: =ROUND(IFERROR((601-_xlfn.RANK.EQ(D62,D:D))/600,0),3) -> 0.903 | J62: =ROUND(IFERROR((601-IFERROR(_xlfn.RANK.EQ(E62,E:E),""))/600,0),3) -> 0.913 | K62: =ROUND(IFERROR((601-IFERROR(_xlfn.RANK.EQ(F62,F:F),""))/600,0),3) -> 0.94 | L62: =ROUND(IFERROR((601-IFERROR(_xlfn.RANK.EQ(G62,G:G),""))/600,0),3) -> 0.893 | M62: =ROUND(IFERROR((601-IFERROR(_xlfn.RANK.EQ(H62,H:H),""))/600,0),3) -> 0.728 | N62: =VLOOKUP(A62,#REF!,11,0) -> #REF! | O62: =VLOOKUP(A62,#REF!,12,0) -> #REF! | P62: =VLOOKUP(A62,#REF!,13,0) -> #REF! | Q62: =VLOOKUP(A62,#REF!,14,0) -> #REF! | R62: 2.5105086 | S62: 0.49800561 | T62: =VLOOKUP(C62,V:W,2,0) -> USA | U62: =IF(T62=T$1,B62,IF(T62=T$2,B62,IF(T62=U$1,B62,"")))
A63: Georgia Institute of Technology | B63: GATECH | C63: USA | D63: =IFERROR(ROUND(VLOOKUP(A63,institutions!A:E,4,0),2),"") -> 3.22 | E63: =IFERROR(ROUND(VLOOKUP(A63,institutions!A:X,7,0),2),"") -> 2.79 | F63: =IFERROR(ROUND(VLOOKUP(A63,institutions!A:X,10,0),2),"") -> 2.24 | G63: =IFERROR(ROUND(VLOOKUP(A63,institutions!A:X,13,0),2),"") -> 4.51 | H63: =IFERROR(ROUND(VLOOKUP(A63,institutions!A:X,16,0),2),"") -> 3.83 | I63: =ROUND(IFERROR((601-_xlfn.RANK.EQ(D63,D:D))/600,0),3) -> 0.9 | J63: =ROUND(IFERROR((601-IFERROR(_xlfn.RANK.EQ(E63,E:E),""))/600,0),3) -> 0.897 | K63: =ROUND(IFERROR((601-IFERROR(_xlfn.RANK.EQ(F63,F:F),""))/600,0),3) -> 0.793 | L63: =ROUND(IFERROR((601-IFERROR(_xlfn.RANK.EQ(G63,G:G),""))/600,0),3) -> 0.958 | M63: =ROUND(IFERROR((601-IFERROR(_xlfn.RANK.EQ(H63,H:H),""))/600,0),3) -> 0.858 | N63: =VLOOKUP(A63,#REF!,11,0) -> #REF! | O63: =VLOOKUP(A63,#REF!,12,0) -> #REF! | P63: =VLOOKUP(A63,#REF!,13,0) -> #REF! | Q63: =VLOOKUP(A63,#REF!,14,0) -> #REF! | R63: 2.5845453 | S63: -0.064550988 | T63: =VLOOKUP(C63,V:W,2,0) -> USA | U63: =IF(T63=T$1,B63,IF(T63=T$2,B63,IF(T63=U$1,B63,"")))
A64: Texas Christian University | B64: Texas Christian | C64: USA | D64: =IFERROR(ROUND(VLOOKUP(A64,institutions!A:E,4,0),2),"") -> 3.24 | E64: =IFERROR(ROUND(VLOOKUP(A64,institutions!A:X,7,0),2),"") -> 1.31 | F64: =IFERROR(ROUND(VLOOKUP(A64,institutions!A:X,10,0),2),"") -> 2.43 | G64: =IFERROR(ROUND(VLOOKUP(A64,institutions!A:X,13,0),2),"") -> 4.61 | H64: =IFERROR(ROUND(VLOOKUP(A64,institutions!A:X,16,0),2),"") -> 3.3 | I64: =ROUND(IFERROR((601-_xlfn.RANK.EQ(D64,D:D))/600,0),3) -> 0.903 | J64: =ROUND(IFERROR((601-IFERROR(_xlfn.RANK.EQ(E64,E:E),""))/600,0),3) -> 0.298 | K64: =ROUND(IFERROR((601-IFERROR(_xlfn.RANK.EQ(F64,F:F),""))/600,0),3) -> 0.825 | L64: =ROUND(IFERROR((601-IFERROR(_xlfn.RANK.EQ(G64,G:G),""))/600,0),3) -> 0.963 | M64: =ROUND(IFERROR((601-IFERROR(_xlfn.RANK.EQ(H64,H:H),""))/600,0),3) -> 0.74 | N64: =VLOOKUP(A64,#REF!,11,0) -> #REF! | O64: =VLOOKUP(A64,#REF!,12,0) -> #REF! | P64: =VLOOKUP(A64,#REF!,13,0) -> #REF! | Q64: =VLOOKUP(A64,#REF!,14,0) -> #REF! | R64: 1.4766709 | S64: -1.118239 | T64: =VLOOKUP(C64,V:W,2,0) -> USA | U64: =IF(T64=T$1,B64,IF(T64=T$2,B64,IF(T64=U$1,B64,"")))
A65: Johns Hopkins University | B65: Johns Hopkins | C65: USA | D65: =IFERROR(ROUND(VLOOKUP(A65,institutions!A:E,4,0),2),"") -> 3.18 | E65: =IFERROR(ROUND(VLOOKUP(A65,institutions!A:X,7,0),2),"") -> 2.89 | F65: =IFERROR(ROUND(VLOOKUP(A65,institutions!A:X,10,0),2),"") -> 2.31 | G65: =IFERROR(ROUND(VLOOKUP(A65,institutions!A:X,13,0),2),"") -> 2.77 | H65: =IFERROR(ROUND(VLOOKUP(A65,institutions!A:X,16,0),2),"") -> 4.12 | I65: =ROUND(IFERROR((601-_xlfn.RANK.EQ(D65,D:D))/600,0),3) -> 0.895 | J65: =ROUND(IFERROR((601-IFERROR(_xlfn.RANK.EQ(E65,E:E),""))/600,0),3) -> 0.908 | K65: =ROUND(IFERROR((601-IFERROR(_xlfn.RANK.EQ(F65,F:F),""))/600,0),3) -> 0.807 | L65: =ROUND(IFERROR((601-IFERROR(_xlfn.RANK.EQ(G65,G:G),""))/600,0),3) -> 0.767 | M65: =ROUND(IFERROR((601-IFERROR(_xlfn.RANK.EQ(H65,H:H),""))/600,0),3) -> 0.885 | N65: =VLOOKUP(A65,#REF!,11,0) -> #REF! | O65: =VLOOKUP(A65,#REF!,12,0) -> #REF! | P65: =VLOOKUP(A65,#REF!,13,0) -> #REF! | Q65: =VLOOKUP(A65,#REF!,14,0) -> #REF! | R65: 2.3339188 | S65: 0.25471177 | T65: =VLOOKUP(C65,V:W,2,0) -> USA | U65: =IF(T65=T$1,B65,IF(T65=T$2,B65,IF(T65=U$1,B65,"")))
A66: Northeastern University | B66: Northeastern | C66: USA | D66: =IFERROR(ROUND(VLOOKUP(A66,institutions!A:E,4,0),2),"") -> 3.21 | E66: =IFERROR(ROUND(VLOOKUP(A66,institutions!A:X,7,0),2),"") -> 2.26 | F66: =IFERROR(ROUND(VLOOKUP(A66,institutions!A:X,10,0),2),"") -> 3.78 | G66: =IFERROR(ROUND(VLOOKUP(A66,institutions!A:X,13,0),2),"") -> 3.64 | H66: =IFERROR(ROUND(VLOOKUP(A66,institutions!A:X,16,0),2),"") -> 4.37 | I66: =ROUND(IFERROR((601-_xlfn.RANK.EQ(D66,D:D))/600,0),3) -> 0.897 | J66: =ROUND(IFERROR((601-IFERROR(_xlfn.RANK.EQ(E66,E:E),""))/600,0),3) -> 0.828 | K66: =ROUND(IFERROR((601-IFERROR(_xlfn.RANK.EQ(F66,F:F),""))/600,0),3) -> 0.935 | L66: =ROUND(IFERROR((601-IFERROR(_xlfn.RANK.EQ(G66,G:G),""))/600,0),3) -> 0.91 | M66: =ROUND(IFERROR((601-IFERROR(_xlfn.RANK.EQ(H66,H:H),""))/600,0),3) -> 0.9 | N66: =VLOOKUP(A66,#REF!,11,0) -> #REF! | O66: =VLOOKUP(A66,#REF!,12,0) -> #REF! | P66: =VLOOKUP(A66,#REF!,13,0) -> #REF! | Q66: =VLOOKUP(A66,#REF!,14,0) -> #REF! | R66: 2.7069218 | S66: 0.008092268 | T66: =VLOOKUP(C66,V:W,2,0) -> USA | U66: =IF(T66=T$1,B66,IF(T66=T$2,B66,IF(T66=U$1,B66,"")))
A67: University of Minnesota Twin Cities | B67: Minnesota | C67: USA | D67: =IFERROR(ROUND(VLOOKUP(A67,institutions!A:E,4,0),2),"") -> 3.18 | E67: =IFERROR(ROUND(VLOOKUP(A67,institutions!A:X,7,0),2),"") -> 2.86 | F67: =IFERROR(ROUND(VLOOKUP(A67,institutions!A:X,10,0),2),"") -> 3.35 | G67: =IFERROR(ROUND(VLOOKUP(A67,institutions!A:X,13,0),2),"") -> 3.41 | H67: =IFERROR(ROUND(VLOOKUP(A67,institutions!A:X,16,0),2),"") -> 4.8 | I67: =ROUND(IFERROR((601-_xlfn.RANK.EQ(D67,D:D))/600,0),3) -> 0.895 | J67: =ROUND(IFERROR((601-IFERROR(_xlfn.RANK.EQ(E67,E:E),""))/600,0),3) -> 0.905 | K67: =ROUND(IFERROR((601-IFERROR(_xlfn.RANK.EQ(F67,F:F),""))/600,0),3) -> 0.905 | L67: =ROUND(IFERROR((601-IFERROR(_xlfn.RANK.EQ(G67,G:G),""))/600,0),3) -> 0.877 | M67: =ROUND(IFERROR((601-IFERROR(_xlfn.RANK.EQ(H67,H:H),""))/600,0),3) -> 0.928 | N67: =VLOOKUP(A67,#REF!,11,0) -> #REF! | O67: =VLOOKUP(A67,#REF!,12,0) -> #REF! | P67: =VLOOKUP(A67,#REF!,13,0) -> #REF! | Q67: =VLOOKUP(A67,#REF!,14,0) -> #REF! | R67: 2.7705303 | S67: 0.13943253 | T67: =VLOOKUP(C67,V:W,2,0) -> USA | U67: =IF(T67=T$1,B67,IF(T67=T$2,B67,IF(T67=U$1,B67,"")))
A68: EDHEC Business School | B68: EDHEC | C68: FRANCE | D68: =IFERROR(ROUND(VLOOKUP(A68,institutions!A:E,4,0),2),"") -> 3.1 | E68: =IFERROR(ROUND(VLOOKUP(A68,institutions!A:X,7,0),2),"") -> 2.97 | F68: =IFERROR(ROUND(VLOOKUP(A68,institutions!A:X,10,0),2),"") -> 1.8 | G68: =IFERROR(ROUND(VLOOKUP(A68,institutions!A:X,13,0),2),"") -> 3.85 | H68: =IFERROR(ROUND(VLOOKUP(A68,institutions!A:X,16,0),2),"") -> 3.38 | I68: =ROUND(IFERROR((601-_xlfn.RANK.EQ(D68,D:D))/600,0),3) -> 0.89 | J68: =ROUND(IFERROR((601-IFERROR(_xlfn.RANK.EQ(E68,E:E),""))/600,0),3) -> 0.912 | K68: =ROUND(IFERROR((601-IFERROR(_xlfn.RANK.EQ(F68,F:F),""))/600,0),3) -> 0.68 | L68: =ROUND(IFERROR((601-IFERROR(_xlfn.RANK.EQ(G68,G:G),""))/600,0),3) -> 0.928 | M68: =ROUND(IFERROR((601-IFERROR(_xlfn.RANK.EQ(H68,H:H),""))/600,0),3) -> 0.767 | N68: =VLOOKUP(A68,#REF!,11,0) -> #REF! | O68: =VLOOKUP(A68,#REF!,12,0) -> #REF! | P68: =VLOOKUP(A68,#REF!,13,0) -> #REF! | Q68: =VLOOKUP(A68,#REF!,14,0) -> #REF! | R68: 2.1976113 | S68: -0.0026302525 | T68: =VLOOKUP(C68,V:W,2,0) -> FRA | U68: =IF(T68=T$1,B68,IF(T68=T$2,B68,IF(T68=U$1,B68,""))) -> EDHEC
A69: BI Norwegian Business School | B69: BIN | C69: NORWAY | D69: =IFERROR(ROUND(VLOOKUP(A69,institutions!A:E,4,0),2),"") -> 3.22 | E69: =IFERROR(ROUND(VLOOKUP(A69,institutions!A:X,7,0),2),"") -> 3.38 | F69: =IFERROR(ROUND(VLOOKUP(A69,institutions!A:X,10,0),2),"") -> 3.49 | G69: =IFERROR(ROUND(VLOOKUP(A69,institutions!A:X,13,0),2),"") -> 2.74 | H69: =IFERROR(ROUND(VLOOKUP(A69,institutions!A:X,16,0),2),"") -> 3.28 | I69: =ROUND(IFERROR((601-_xlfn.RANK.EQ(D69,D:D))/600,0),3) -> 0.9 | J69: =ROUND(IFERROR((601-IFERROR(_xlfn.RANK.EQ(E69,E:E),""))/600,0),3) -> 0.942 | K69: =ROUND(IFERROR((601-IFERROR(_xlfn.RANK.EQ(F69,F:F),""))/600,0),3) -> 0.915 | L69: =ROUND(IFERROR((601-IFERROR(_xlfn.RANK.EQ(G69,G:G),""))/600,0),3) -> 0.755 | M69: =ROUND(IFERROR((601-IFERROR(_xlfn.RANK.EQ(H69,H:H),""))/600,0),3) -> 0.735 | N69: =VLOOKUP(A69,#REF!,11,0) -> #REF! | O69: =VLOOKUP(A69,#REF!,12,0) -> #REF! | P69: =VLOOKUP(A69,#REF!,13,0) -> #REF! | Q69: =VLOOKUP(A69,#REF!,14,0) -> #REF! | R69: 2.2805307 | S69: 0.74237362 | T69: =VLOOKUP(C69,V:W,2,0) -> NOR | U69: =IF(T69=T$1,B69,IF(T69=T$2,B69,IF(T69=U$1,B69,"")))
A70: University of Oregon | B70: Oregon | C70: USA | D70: =IFERROR(ROUND(VLOOKUP(A70,institutions!A:E,4,0),2),"") -> 3.15 | E70: =IFERROR(ROUND(VLOOKUP(A70,institutions!A:X,7,0),2),"") -> 2.44 | F70: =IFERROR(ROUND(VLOOKUP(A70,institutions!A:X,10,0),2),"") -> 3.08 | G70: =IFERROR(ROUND(VLOOKUP(A70,institutions!A:X,13,0),2),"") -> 4.63 | H70: =IFERROR(ROUND(VLOOKUP(A70,institutions!A:X,16,0),2),"") -> 4.5 | I70: =ROUND(IFERROR((601-_xlfn.RANK.EQ(D70,D:D))/600,0),3) -> 0.892 | J70: =ROUND(IFERROR((601-IFERROR(_xlfn.RANK.EQ(E70,E:E),""))/600,0),3) -> 0.86 | K70: =ROUND(IFERROR((601-IFERROR(_xlfn.RANK.EQ(F70,F:F),""))/600,0),3) -> 0.888 | L70: =ROUND(IFERROR((601-IFERROR(_xlfn.RANK.EQ(G70,G:G),""))/600,0),3) -> 0.967 | M70: =ROUND(IFERROR((601-IFERROR(_xlfn.RANK.EQ(H70,H:H),""))/600,0),3) -> 0.917 | N70: =VLOOKUP(A70,#REF!,11,0) -> #REF! | O70: =VLOOKUP(A70,#REF!,12,0) -> #REF! | P70: =VLOOKUP(A70,#REF!,13,0) -> #REF! | Q70: =VLOOKUP(A70,#REF!,14,0) -> #REF! | R70: 2.8102589 | S70: -0.1138983 | T70: =VLOOKUP(C70,V:W,2,0) -> USA | U70: =IF(T70=T$1,B70,IF(T70=T$2,B70,IF(T70=U$1,B70,"")))
A71: University of Miami | B71: Miami | C71: USA | D71: =IFERROR(ROUND(VLOOKUP(A71,institutions!A:E,4,0),2),"") -> 3.04 | E71: =IFERROR(ROUND(VLOOKUP(A71,institutions!A:X,7,0),2),"") -> 2.18 | F71: =IFERROR(ROUND(VLOOKUP(A71,institutions!A:X,10,0),2),"") -> 3.45 | G71: =IFERROR(ROUND(VLOOKUP(A71,institutions!A:X,13,0),2),"") -> 3.8 | H71: =IFERROR(ROUND(VLOOKUP(A71,institutions!A:X,16,0),2),"") -> 4.46 | I71: =ROUND(IFERROR((601-_xlfn.RANK.EQ(D71,D:D))/600,0),3) -> 0.885 | J71: =ROUND(IFERROR((601-IFERROR(_xlfn.RANK.EQ(E71,E:E),""))/600,0),3) -> 0.812 | K71: =ROUND(IFERROR((601-IFERROR(_xlfn.RANK.EQ(F71,F:F),""))/600,0),3) -> 0.912 | L71: =ROUND(IFERROR((601-IFERROR(_xlfn.RANK.EQ(G71,G:G),""))/600,0),3) -> 0.923 | M71: =ROUND(IFERROR((601-IFERROR(_xlfn.RANK.EQ(H71,H:H),""))/600,0),3) -> 0.915 | N71: =VLOOKUP(A71,#REF!,11,0) -> #REF! | O71: =VLOOKUP(A71,#REF!,12,0) -> #REF! | P71: =VLOOKUP(A71,#REF!,13,0) -> #REF! | Q71: =VLOOKUP(A71,#REF!,14,0) -> #REF! | R71: 2.6923191 | S71: -0.10499189 | T71: =VLOOKUP(C71,V:W,2,0) -> USA | U71: =IF(T71=T$1,B71,IF(T71=T$2,B71,IF(T71=U$1,B71,"")))
... A172: ESCP Business School | B172: ESCP BS | C172: FRANCE | D172: =IFERROR(ROUND(VLOOKUP(A172,institutions!A:E,4,0),2),"") -> 2.39 | E172: =IFERROR(ROUND(VLOOKUP(A172,institutions!A:X,7,0),2),"") -> 1.29 | F172: =IFERROR(ROUND(VLOOKUP(A172,institutions!A:X,10,0),2),"") -> 1.44 | G172: =IFERROR(ROUND(VLOOKUP(A172,institutions!A:X,13,0),2),"") -> 2.8 | H172: =IFERROR(ROUND(VLOOKUP(A172,institutions!A:X,16,0),2),"") -> 2.97 | I172: =ROUND(IFERROR((601-_xlfn.RANK.EQ(D172,D:D))/600,0),3) -> 0.752 | J172: =ROUND(IFERROR((601-IFERROR(_xlfn.RANK.EQ(E172,E:E),""))/600,0),3) -> 0.268 | K172: =ROUND(IFERROR((601-IFERROR(_xlfn.RANK.EQ(F172,F:F),""))/600,0),3) -> 0.48 | L172: =ROUND(IFERROR((601-IFERROR(_xlfn.RANK.EQ(G172,G:G),""))/600,0),3) -> 0.773 | M172: =ROUND(IFERROR((601-IFERROR(_xlfn.RANK.EQ(H172,H:H),""))/600,0),3) -> 0.682 | N172: =VLOOKUP(A172,#REF!,11,0) -> #REF! | O172: =VLOOKUP(A172,#REF!,12,0) -> #REF! | P172: =VLOOKUP(A172,#REF!,13,0) -> #REF! | Q172: =VLOOKUP(A172,#REF!,14,0) -> #REF! | R172: 0.39540041 | S172: -1.275759 | T172: =VLOOKUP(C172,V:W,2,0) -> FRA | U172: =IF(T172=T$1,B172,IF(T172=T$2,B172,IF(T172=U$1,B172,""))) -> ESCP BS
A173: City St Georges, University of London | B173: City St Georges | C173: ENGLAND | D173: =IFERROR(ROUND(VLOOKUP(A173,institutions!A:E,4,0),2),"") -> 2.47 | E173: =IFERROR(ROUND(VLOOKUP(A173,institutions!A:X,7,0),2),"") -> 1.39 | F173: =IFERROR(ROUND(VLOOKUP(A173,institutions!A:X,10,0),2),"") -> 1.6 | G173: =IFERROR(ROUND(VLOOKUP(A173,institutions!A:X,13,0),2),"") -> 3.57 | H173: =IFERROR(ROUND(VLOOKUP(A173,institutions!A:X,16,0),2),"") -> 4.9 | I173: =ROUND(IFERROR((601-_xlfn.RANK.EQ(D173,D:D))/600,0),3) -> 0.777 | J173: =ROUND(IFERROR((601-IFERROR(_xlfn.RANK.EQ(E173,E:E),""))/600,0),3) -> 0.392 | K173: =ROUND(IFERROR((601-IFERROR(_xlfn.RANK.EQ(F173,F:F),""))/600,0),3) -> 0.6 | L173: =ROUND(IFERROR((601-IFERROR(_xlfn.RANK.EQ(G173,G:G),""))/600,0),3) -> 0.9 | M173: =ROUND(IFERROR((601-IFERROR(_xlfn.RANK.EQ(H173,H:H),""))/600,0),3) -> 0.937 | N173: 1 | O173: =VLOOKUP(A173,#REF!,12,0) -> #REF! | P173: =VLOOKUP(A173,#REF!,13,0) -> #REF! | Q173: =VLOOKUP(A173,#REF!,14,0) -> #REF! | R173: 1.4859795 | S173: -1.4524112 | T173: =VLOOKUP(C173,V:W,2,0) -> UK | U173: =IF(T173=T$1,B173,IF(T173=T$2,B173,IF(T173=U$1,B173,"")))
A174: Temple University | B174: Temple | C174: USA | D174: =IFERROR(ROUND(VLOOKUP(A174,institutions!A:E,4,0),2),"") -> 2.27 | E174: =IFERROR(ROUND(VLOOKUP(A174,institutions!A:X,7,0),2),"") -> 1.68 | F174: =IFERROR(ROUND(VLOOKUP(A174,institutions!A:X,10,0),2),"") -> 2.28 | G174: =IFERROR(ROUND(VLOOKUP(A174,institutions!A:X,13,0),2),"") -> 2.59 | H174: =IFERROR(ROUND(VLOOKUP(A174,institutions!A:X,16,0),2),"") -> 2.78 | I174: =ROUND(IFERROR((601-_xlfn.RANK.EQ(D174,D:D))/600,0),3) -> 0.712 | J174: =ROUND(IFERROR((601-IFERROR(_xlfn.RANK.EQ(E174,E:E),""))/600,0),3) -> 0.62 | K174: =ROUND(IFERROR((601-IFERROR(_xlfn.RANK.EQ(F174,F:F),""))/600,0),3) -> 0.798 | L174: =ROUND(IFERROR((601-IFERROR(_xlfn.RANK.EQ(G174,G:G),""))/600,0),3) -> 0.715 | M174: =ROUND(IFERROR((601-IFERROR(_xlfn.RANK.EQ(H174,H:H),""))/600,0),3) -> 0.633 | N174: =VLOOKUP(A174,#REF!,11,0) -> #REF! | O174: =VLOOKUP(A174,#REF!,12,0) -> #REF! | P174: =VLOOKUP(A174,#REF!,13,0) -> #REF! | Q174: =VLOOKUP(A174,#REF!,14,0) -> #REF! | R174: 1.3098635 | S174: 0.11296593 | T174: =VLOOKUP(C174,V:W,2,0) -> USA | U174: =IF(T174=T$1,B174,IF(T174=T$2,B174,IF(T174=U$1,B174,"")))
A175: Universitat Ramon Llull | B175: Ramon Llull | C175: SPAIN | D175: =IFERROR(ROUND(VLOOKUP(A175,institutions!A:E,4,0),2),"") -> 2.39 | E175: =IFERROR(ROUND(VLOOKUP(A175,institutions!A:X,7,0),2),"") -> 1.55 | F175: =IFERROR(ROUND(VLOOKUP(A175,institutions!A:X,10,0),2),"") -> 1.63 | G175: =IFERROR(ROUND(VLOOKUP(A175,institutions!A:X,13,0),2),"") -> 2.76 | H175: =IFERROR(ROUND(VLOOKUP(A175,institutions!A:X,16,0),2),"") -> 3.22 | I175: =ROUND(IFERROR((601-_xlfn.RANK.EQ(D175,D:D))/600,0),3) -> 0.752 | J175: =ROUND(IFERROR((601-IFERROR(_xlfn.RANK.EQ(E175,E:E),""))/600,0),3) -> 0.543 | K175: =ROUND(IFERROR((601-IFERROR(_xlfn.RANK.EQ(F175,F:F),""))/600,0),3) -> 0.613 | L175: =ROUND(IFERROR((601-IFERROR(_xlfn.RANK.EQ(G175,G:G),""))/600,0),3) -> 0.762 | M175: =ROUND(IFERROR((601-IFERROR(_xlfn.RANK.EQ(H175,H:H),""))/600,0),3) -> 0.725 | N175: =VLOOKUP(A175,#REF!,11,0) -> #REF! | O175: =VLOOKUP(A175,#REF!,12,0) -> #REF! | P175: =VLOOKUP(A175,#REF!,13,0) -> #REF! | Q175: =VLOOKUP(A175,#REF!,14,0) -> #REF! | R175: 1.1206317 | S175: -0.54488025 | T175: =VLOOKUP(C175,V:W,2,0) -> SPAIN | U175: =IF(T175=T$1,B175,IF(T175=T$2,B175,IF(T175=U$1,B175,""))) -> Ramon Llull
A176: Georgia State University | B176: Georgia State | C176: USA | D176: =IFERROR(ROUND(VLOOKUP(A176,institutions!A:E,4,0),2),"") -> 2.27 | E176: =IFERROR(ROUND(VLOOKUP(A176,institutions!A:X,7,0),2),"") -> 2 | F176: =IFERROR(ROUND(VLOOKUP(A176,institutions!A:X,10,0),2),"") -> 1.69 | G176: =IFERROR(ROUND(VLOOKUP(A176,institutions!A:X,13,0),2),"") -> 2.64 | H176: =IFERROR(ROUND(VLOOKUP(A176,institutions!A:X,16,0),2),"") -> 3.65 | I176: =ROUND(IFERROR((601-_xlfn.RANK.EQ(D176,D:D))/600,0),3) -> 0.712 | J176: =ROUND(IFERROR((601-IFERROR(_xlfn.RANK.EQ(E176,E:E),""))/600,0),3) -> 0.753 | K176: =ROUND(IFERROR((601-IFERROR(_xlfn.RANK.EQ(F176,F:F),""))/600,0),3) -> 0.63 | L176: =ROUND(IFERROR((601-IFERROR(_xlfn.RANK.EQ(G176,G:G),""))/600,0),3) -> 0.725 | M176: =ROUND(IFERROR((601-IFERROR(_xlfn.RANK.EQ(H176,H:H),""))/600,0),3) -> 0.825 | N176: =VLOOKUP(A176,#REF!,11,0) -> #REF! | O176: =VLOOKUP(A176,#REF!,12,0) -> #REF! | P176: =VLOOKUP(A176,#REF!,13,0) -> #REF! | Q176: =VLOOKUP(A176,#REF!,14,0) -> #REF! | R176: 1.6002152 | S176: -0.16868137 | T176: =VLOOKUP(C176,V:W,2,0) -> USA | U176: =IF(T176=T$1,B176,IF(T176=T$2,B176,IF(T176=U$1,B176,"")))
A177: Hanken School of Economics | B177: Hanken S Econ | C177: FINLAND | D177: =IFERROR(ROUND(VLOOKUP(A177,institutions!A:E,4,0),2),"") -> 2.39 | E177: =IFERROR(ROUND(VLOOKUP(A177,institutions!A:X,7,0),2),"") -> 1.77 | F177: =IFERROR(ROUND(VLOOKUP(A177,institutions!A:X,10,0),2),"") -> 1.76 | G177: =IFERROR(ROUND(VLOOKUP(A177,institutions!A:X,13,0),2),"") -> 2.47 | H177: =IFERROR(ROUND(VLOOKUP(A177,institutions!A:X,16,0),2),"") -> 3.37 | I177: =ROUND(IFERROR((601-_xlfn.RANK.EQ(D177,D:D))/600,0),3) -> 0.752 | J177: =ROUND(IFERROR((601-IFERROR(_xlfn.RANK.EQ(E177,E:E),""))/600,0),3) -> 0.67 | K177: =ROUND(IFERROR((601-IFERROR(_xlfn.RANK.EQ(F177,F:F),""))/600,0),3) -> 0.673 | L177: =ROUND(IFERROR((601-IFERROR(_xlfn.RANK.EQ(G177,G:G),""))/600,0),3) -> 0.677 | M177: =ROUND(IFERROR((601-IFERROR(_xlfn.RANK.EQ(H177,H:H),""))/600,0),3) -> 0.76 | N177: =VLOOKUP(A177,#REF!,11,0) -> #REF! | O177: =VLOOKUP(A177,#REF!,12,0) -> #REF! | P177: =VLOOKUP(A177,#REF!,13,0) -> #REF! | Q177: =VLOOKUP(A177,#REF!,14,0) -> #REF! | R177: 1.3378281 | S177: -0.10027699 | T177: =VLOOKUP(C177,V:W,2,0) -> FIN | U177: =IF(T177=T$1,B177,IF(T177=T$2,B177,IF(T177=U$1,B177,"")))
A178: Universite de Montreal | B178: Montreal | C178: CANADA | D178: =IFERROR(ROUND(VLOOKUP(A178,institutions!A:E,4,0),2),"") -> 2.33 | E178: =IFERROR(ROUND(VLOOKUP(A178,institutions!A:X,7,0),2),"") -> 2.21 | F178: =IFERROR(ROUND(VLOOKUP(A178,institutions!A:X,10,0),2),"") -> 1.59 | G178: =IFERROR(ROUND(VLOOKUP(A178,institutions!A:X,13,0),2),"") -> 1.09 | H178: =IFERROR(ROUND(VLOOKUP(A178,institutions!A:X,16,0),2),"") -> 2.86 | I178: =ROUND(IFERROR((601-_xlfn.RANK.EQ(D178,D:D))/600,0),3) -> 0.73 | J178: =ROUND(IFERROR((601-IFERROR(_xlfn.RANK.EQ(E178,E:E),""))/600,0),3) -> 0.82 | K178: =ROUND(IFERROR((601-IFERROR(_xlfn.RANK.EQ(F178,F:F),""))/600,0),3) -> 0.592 | L178: =ROUND(IFERROR((601-IFERROR(_xlfn.RANK.EQ(G178,G:G),""))/600,0),3) -> 0.067 | M178: =ROUND(IFERROR((601-IFERROR(_xlfn.RANK.EQ(H178,H:H),""))/600,0),3) -> 0.66 | N178: =VLOOKUP(A178,#REF!,11,0) -> #REF! | O178: =VLOOKUP(A178,#REF!,12,0) -> #REF! | P178: =VLOOKUP(A178,#REF!,13,0) -> #REF! | Q178: =VLOOKUP(A178,#REF!,14,0) -> #REF! | R178: 0.17010375 | S178: 1.2770989 | T178: =VLOOKUP(C178,V:W,2,0) -> CAN | U178: =IF(T178=T$1,B178,IF(T178=T$2,B178,IF(T178=U$1,B178,"")))
A179: University of Bath | B179: Bath | C179: ENGLAND | D179: =IFERROR(ROUND(VLOOKUP(A179,institutions!A:E,4,0),2),"") -> 2.34 | E179: =IFERROR(ROUND(VLOOKUP(A179,institutions!A:X,7,0),2),"") -> 1.46 | F179: =IFERROR(ROUND(VLOOKUP(A179,institutions!A:X,10,0),2),"") -> 1.71 | G179: =IFERROR(ROUND(VLOOKUP(A179,institutions!A:X,13,0),2),"") -> 2.95 | H179: =IFERROR(ROUND(VLOOKUP(A179,institutions!A:X,16,0),2),"") -> 3.79 | I179: =ROUND(IFERROR((601-_xlfn.RANK.EQ(D179,D:D))/600,0),3) -> 0.735 | J179: =ROUND(IFERROR((601-IFERROR(_xlfn.RANK.EQ(E179,E:E),""))/600,0),3) -> 0.468 | K179: =ROUND(IFERROR((601-IFERROR(_xlfn.RANK.EQ(F179,F:F),""))/600,0),3) -> 0.645 | L179: =ROUND(IFERROR((601-IFERROR(_xlfn.RANK.EQ(G179,G:G),""))/600,0),3) -> 0.797 | M179: =ROUND(IFERROR((601-IFERROR(_xlfn.RANK.EQ(H179,H:H),""))/600,0),3) -> 0.843 | N179: =VLOOKUP(A179,#REF!,11,0) -> #REF! | O179: =VLOOKUP(A179,#REF!,12,0) -> #REF! | P179: =VLOOKUP(A179,#REF!,13,0) -> #REF! | Q179: =VLOOKUP(A179,#REF!,14,0) -> #REF! | R179: 1.3308669 | S179: -0.90394169 | T179: =VLOOKUP(C179,V:W,2,0) -> UK | U179: =IF(T179=T$1,B179,IF(T179=T$2,B179,IF(T179=U$1,B179,"")))
A180: Hitotsubashi University | B180: Hitotsubashi | C180: JAPAN | D180: =IFERROR(ROUND(VLOOKUP(A180,institutions!A:E,4,0),2),"") -> 2.13 | E180: =IFERROR(ROUND(VLOOKUP(A180,institutions!A:X,7,0),2),"") -> 2.06 | F180: =IFERROR(ROUND(VLOOKUP(A180,institutions!A:X,10,0),2),"") -> 1.5 | G180: =IFERROR(ROUND(VLOOKUP(A180,institutions!A:X,13,0),2),"") -> 2.34 | H180: =IFERROR(ROUND(VLOOKUP(A180,institutions!A:X,16,0),2),"") -> 2.96 | I180: =ROUND(IFERROR((601-_xlfn.RANK.EQ(D180,D:D))/600,0),3) -> 0.637 | J180: =ROUND(IFERROR((601-IFERROR(_xlfn.RANK.EQ(E180,E:E),""))/600,0),3) -> 0.778 | K180: =ROUND(IFERROR((601-IFERROR(_xlfn.RANK.EQ(F180,F:F),""))/600,0),3) -> 0.527 | L180: =ROUND(IFERROR((601-IFERROR(_xlfn.RANK.EQ(G180,G:G),""))/600,0),3) -> 0.612 | M180: =ROUND(IFERROR((601-IFERROR(_xlfn.RANK.EQ(H180,H:H),""))/600,0),3) -> 0.675 | N180: =VLOOKUP(A180,#REF!,11,0) -> #REF! | O180: =VLOOKUP(A180,#REF!,12,0) -> #REF! | P180: =VLOOKUP(A180,#REF!,13,0) -> #REF! | Q180: =VLOOKUP(A180,#REF!,14,0) -> #REF! | R180: 0.99167786 | S180: 0.16101074 | T180: =VLOOKUP(C180,V:W,2,0) -> JAP | U180: =IF(T180=T$1,B180,IF(T180=T$2,B180,IF(T180=U$1,B180,"")))
A181: IESEG School of Management | B181: IESEG S Man | C181: FRANCE | D181: =IFERROR(ROUND(VLOOKUP(A181,institutions!A:E,4,0),2),"") -> 2.31 | E181: =IFERROR(ROUND(VLOOKUP(A181,institutions!A:X,7,0),2),"") -> 1.67 | F181: =IFERROR(ROUND(VLOOKUP(A181,institutions!A:X,10,0),2),"") -> 1.17 | G181: =IFERROR(ROUND(VLOOKUP(A181,institutions!A:X,13,0),2),"") -> 3.07 | H181: =IFERROR(ROUND(VLOOKUP(A181,institutions!A:X,16,0),2),"") -> 2.53 | I181: =ROUND(IFERROR((601-_xlfn.RANK.EQ(D181,D:D))/600,0),3) -> 0.723 | J181: =ROUND(IFERROR((601-IFERROR(_xlfn.RANK.EQ(E181,E:E),""))/600,0),3) -> 0.615 | K181: =ROUND(IFERROR((601-IFERROR(_xlfn.RANK.EQ(F181,F:F),""))/600,0),3) -> 0.193 | L181: =ROUND(IFERROR((601-IFERROR(_xlfn.RANK.EQ(G181,G:G),""))/600,0),3) -> 0.823 | M181: =ROUND(IFERROR((601-IFERROR(_xlfn.RANK.EQ(H181,H:H),""))/600,0),3) -> 0.558 | N181: =VLOOKUP(A181,#REF!,11,0) -> #REF! | O181: =VLOOKUP(A181,#REF!,12,0) -> #REF! | P181: =VLOOKUP(A181,#REF!,13,0) -> #REF! | Q181: =VLOOKUP(A181,#REF!,14,0) -> #REF! | R181: 0.32557668 | S181: -0.83903592 | T181: =VLOOKUP(C181,V:W,2,0) -> FRA | U181: =IF(T181=T$1,B181,IF(T181=T$2,B181,IF(T181=U$1,B181,""))) -> IESEG S Man
A182: Luiss Guido Carli University | B182: Luiss Guido Carli | C182: ITALY | D182: =IFERROR(ROUND(VLOOKUP(A182,institutions!A:E,4,0),2),"") -> 2.32 | E182: =IFERROR(ROUND(VLOOKUP(A182,institutions!A:X,7,0),2),"") -> 1.71 | F182: =IFERROR(ROUND(VLOOKUP(A182,institutions!A:X,10,0),2),"") -> 1.23 | G182: =IFERROR(ROUND(VLOOKUP(A182,institutions!A:X,13,0),2),"") -> 2.96 | H182: =IFERROR(ROUND(VLOOKUP(A182,institutions!A:X,16,0),2),"") -> 4.73 | I182: =ROUND(IFERROR((601-_xlfn.RANK.EQ(D182,D:D))/600,0),3) -> 0.727 | J182: =ROUND(IFERROR((601-IFERROR(_xlfn.RANK.EQ(E182,E:E),""))/600,0),3) -> 0.643 | K182: =ROUND(IFERROR((601-IFERROR(_xlfn.RANK.EQ(F182,F:F),""))/600,0),3) -> 0.268 | L182: =ROUND(IFERROR((601-IFERROR(_xlfn.RANK.EQ(G182,G:G),""))/600,0),3) -> 0.802 | M182: =ROUND(IFERROR((601-IFERROR(_xlfn.RANK.EQ(H182,H:H),""))/600,0),3) -> 0.927 | N182: =VLOOKUP(A182,#REF!,11,0) -> #REF! | O182: =VLOOKUP(A182,#REF!,12,0) -> #REF! | P182: =VLOOKUP(A182,#REF!,13,0) -> #REF! | Q182: =VLOOKUP(A182,#REF!,14,0) -> #REF! | R182: 1.1273939 | S182: -1.2203934 | T182: =VLOOKUP(C182,V:W,2,0) -> ITA | U182: =IF(T182=T$1,B182,IF(T182=T$2,B182,IF(T182=U$1,B182,"")))
A183: University of Amsterdam | B183: Amsterdam | C183: NETHERLANDS | D183: =IFERROR(ROUND(VLOOKUP(A183,institutions!A:E,4,0),2),"") -> 2.26 | E183: =IFERROR(ROUND(VLOOKUP(A183,institutions!A:X,7,0),2),"") -> 1.93 | F183: =IFERROR(ROUND(VLOOKUP(A183,institutions!A:X,10,0),2),"") -> 2.67 | G183: =IFERROR(ROUND(VLOOKUP(A183,institutions!A:X,13,0),2),"") -> 2.66 | H183: =IFERROR(ROUND(VLOOKUP(A183,institutions!A:X,16,0),2),"") -> 2.7 | I183: =ROUND(IFERROR((601-_xlfn.RANK.EQ(D183,D:D))/600,0),3) -> 0.703 | J183: =ROUND(IFERROR((601-IFERROR(_xlfn.RANK.EQ(E183,E:E),""))/600,0),3) -> 0.732 | K183: =ROUND(IFERROR((601-IFERROR(_xlfn.RANK.EQ(F183,F:F),""))/600,0),3) -> 0.852 | L183: =ROUND(IFERROR((601-IFERROR(_xlfn.RANK.EQ(G183,G:G),""))/600,0),3) -> 0.735 | M183: =ROUND(IFERROR((601-IFERROR(_xlfn.RANK.EQ(H183,H:H),""))/600,0),3) -> 0.61 | N183: =VLOOKUP(A183,#REF!,11,0) -> #REF! | O183: =VLOOKUP(A183,#REF!,12,0) -> #REF! | P183: =VLOOKUP(A183,#REF!,13,0) -> #REF! | Q183: =VLOOKUP(A183,#REF!,14,0) -> #REF! | R183: 1.5754766 | S183: 0.43386021 | T183: =VLOOKUP(C183,V:W,2,0) -> NED | U183: =IF(T183=T$1,B183,IF(T183=T$2,B183,IF(T183=U$1,B183,"")))
A184: Virginia Polytechnic Institute & State University | B184: Virginia Polytech | C184: USA | D184: =IFERROR(ROUND(VLOOKUP(A184,institutions!A:E,4,0),2),"") -> 2.22 | E184: =IFERROR(ROUND(VLOOKUP(A184,institutions!A:X,7,0),2),"") -> 2.02 | F184: =IFERROR(ROUND(VLOOKUP(A184,institutions!A:X,10,0),2),"") -> 3.73 | G184: =IFERROR(ROUND(VLOOKUP(A184,institutions!A:X,13,0),2),"") -> 2.06 | H184: =IFERROR(ROUND(VLOOKUP(A184,institutions!A:X,16,0),2),"") -> 2.2 | I184: =ROUND(IFERROR((601-_xlfn.RANK.EQ(D184,D:D))/600,0),3) -> 0.683 | J184: =ROUND(IFERROR((601-IFERROR(_xlfn.RANK.EQ(E184,E:E),""))/600,0),3) -> 0.763 | K184: =ROUND(IFERROR((601-IFERROR(_xlfn.RANK.EQ(F184,F:F),""))/600,0),3) -> 0.932 | L184: =ROUND(IFERROR((601-IFERROR(_xlfn.RANK.EQ(G184,G:G),""))/600,0),3) -> 0.487 | M184: =ROUND(IFERROR((601-IFERROR(_xlfn.RANK.EQ(H184,H:H),""))/600,0),3) -> 0.417 | N184: =VLOOKUP(A184,#REF!,11,0) -> #REF! | O184: =VLOOKUP(A184,#REF!,12,0) -> #REF! | P184: =VLOOKUP(A184,#REF!,13,0) -> #REF! | Q184: =VLOOKUP(A184,#REF!,14,0) -> #REF! | R184: 0.97057945 | S184: 1.3357767 | T184: =VLOOKUP(C184,V:W,2,0) -> USA | U184: =IF(T184=T$1,B184,IF(T184=T$2,B184,IF(T184=U$1,B184,"")))
A185: Bank of Italy | B185: Bank Italy | C185: ITALY | D185: =IFERROR(ROUND(VLOOKUP(A185,institutions!A:E,4,0),2),"") -> 2.14 | E185: =IFERROR(ROUND(VLOOKUP(A185,institutions!A:X,7,0),2),"") -> 2.12 | F185: =IFERROR(ROUND(VLOOKUP(A185,institutions!A:X,10,0),2),"") -> 1.49 | G185: =IFERROR(ROUND(VLOOKUP(A185,institutions!A:X,13,0),2),"") | H185: =IFERROR(ROUND(VLOOKUP(A185,institutions!A:X,16,0),2),"") | I185: =ROUND(IFERROR((601-_xlfn.RANK.EQ(D185,D:D))/600,0),3) -> 0.64 | J185: =ROUND(IFERROR((601-IFERROR(_xlfn.RANK.EQ(E185,E:E),""))/600,0),3) -> 0.8 | K185: =ROUND(IFERROR((601-IFERROR(_xlfn.RANK.EQ(F185,F:F),""))/600,0),3) -> 0.518 | L185: =ROUND(IFERROR((601-IFERROR(_xlfn.RANK.EQ(G185,G:G),""))/600,0),3) -> 0 | M185: =ROUND(IFERROR((601-IFERROR(_xlfn.RANK.EQ(H185,H:H),""))/600,0),3) -> 0 | N185: =VLOOKUP(A185,#REF!,11,0) -> #REF! | O185: =VLOOKUP(A185,#REF!,12,0) -> #REF! | P185: =VLOOKUP(A185,#REF!,13,0) -> #REF! | Q185: =VLOOKUP(A185,#REF!,14,0) -> #REF! | R185: -1.2997791 | S185: 2.2851656 | T185: =VLOOKUP(C185,V:W,2,0) -> ITA | U185: =IF(T185=T$1,B185,IF(T185=T$2,B185,IF(T185=U$1,B185,"")))
... A208: University of Surrey | B208: Surrey | C208: ENGLAND | D208: =IFERROR(ROUND(VLOOKUP(A208,institutions!A:E,4,0),2),"") -> 2.16 | E208: =IFERROR(ROUND(VLOOKUP(A208,institutions!A:X,7,0),2),"") -> 1.81 | F208: =IFERROR(ROUND(VLOOKUP(A208,institutions!A:X,10,0),2),"") -> 1.61 | G208: =IFERROR(ROUND(VLOOKUP(A208,institutions!A:X,13,0),2),"") -> 2.65 | H208: =IFERROR(ROUND(VLOOKUP(A208,institutions!A:X,16,0),2),"") -> 3.53 | I208: =ROUND(IFERROR((601-_xlfn.RANK.EQ(D208,D:D))/600,0),3) -> 0.655 | J208: =ROUND(IFERROR((601-IFERROR(_xlfn.RANK.EQ(E208,E:E),""))/600,0),3) -> 0.685 | K208: =ROUND(IFERROR((601-IFERROR(_xlfn.RANK.EQ(F208,F:F),""))/600,0),3) -> 0.605 | L208: =ROUND(IFERROR((601-IFERROR(_xlfn.RANK.EQ(G208,G:G),""))/600,0),3) -> 0.73 | M208: =ROUND(IFERROR((601-IFERROR(_xlfn.RANK.EQ(H208,H:H),""))/600,0),3) -> 0.8 | N208: =VLOOKUP(A208,#REF!,11,0) -> #REF! | O208: =VLOOKUP(A208,#REF!,12,0) -> #REF! | P208: =VLOOKUP(A208,#REF!,13,0) -> #REF! | Q208: =VLOOKUP(A208,#REF!,14,0) -> #REF! | R208: 1.4124842 | S208: -0.31894176 | T208: =VLOOKUP(C208,V:W,2,0) -> UK | U208: =IF(T208=T$1,B208,IF(T208=T$2,B208,IF(T208=U$1,B208,"")))
A209: University of Sussex | B209: Sussex | C209: ENGLAND | D209: =IFERROR(ROUND(VLOOKUP(A209,institutions!A:E,4,0),2),"") -> 2.21 | E209: =IFERROR(ROUND(VLOOKUP(A209,institutions!A:X,7,0),2),"") -> 2.06 | F209: =IFERROR(ROUND(VLOOKUP(A209,institutions!A:X,10,0),2),"") -> 1.28 | G209: =IFERROR(ROUND(VLOOKUP(A209,institutions!A:X,13,0),2),"") -> 2.21 | H209: =IFERROR(ROUND(VLOOKUP(A209,institutions!A:X,16,0),2),"") -> 3.45 | I209: =ROUND(IFERROR((601-_xlfn.RANK.EQ(D209,D:D))/600,0),3) -> 0.672 | J209: =ROUND(IFERROR((601-IFERROR(_xlfn.RANK.EQ(E209,E:E),""))/600,0),3) -> 0.778 | K209: =ROUND(IFERROR((601-IFERROR(_xlfn.RANK.EQ(F209,F:F),""))/600,0),3) -> 0.328 | L209: =ROUND(IFERROR((601-IFERROR(_xlfn.RANK.EQ(G209,G:G),""))/600,0),3) -> 0.555 | M209: =ROUND(IFERROR((601-IFERROR(_xlfn.RANK.EQ(H209,H:H),""))/600,0),3) -> 0.778 | N209: 1 | O209: =VLOOKUP(A209,#REF!,12,0) -> #REF! | P209: =VLOOKUP(A209,#REF!,13,0) -> #REF! | Q209: =VLOOKUP(A209,#REF!,14,0) -> #REF! | R209: 0.73596689 | S209: -0.19695604 | T209: =VLOOKUP(C209,V:W,2,0) -> UK | U209: =IF(T209=T$1,B209,IF(T209=T$2,B209,IF(T209=U$1,B209,"")))
A210: Purdue University | B210: Purdue | C210: USA | D210: =IFERROR(ROUND(VLOOKUP(A210,institutions!A:E,4,0),2),"") -> 2.17 | E210: =IFERROR(ROUND(VLOOKUP(A210,institutions!A:X,7,0),2),"") -> 2.09 | F210: =IFERROR(ROUND(VLOOKUP(A210,institutions!A:X,10,0),2),"") -> 2.77 | G210: =IFERROR(ROUND(VLOOKUP(A210,institutions!A:X,13,0),2),"") -> 2.08 | H210: =IFERROR(ROUND(VLOOKUP(A210,institutions!A:X,16,0),2),"") -> 2.79 | I210: =ROUND(IFERROR((601-_xlfn.RANK.EQ(D210,D:D))/600,0),3) -> 0.658 | J210: =ROUND(IFERROR((601-IFERROR(_xlfn.RANK.EQ(E210,E:E),""))/600,0),3) -> 0.787 | K210: =ROUND(IFERROR((601-IFERROR(_xlfn.RANK.EQ(F210,F:F),""))/600,0),3) -> 0.87 | L210: =ROUND(IFERROR((601-IFERROR(_xlfn.RANK.EQ(G210,G:G),""))/600,0),3) -> 0.502 | M210: =ROUND(IFERROR((601-IFERROR(_xlfn.RANK.EQ(H210,H:H),""))/600,0),3) -> 0.638 | N210: =VLOOKUP(A210,#REF!,11,0) -> #REF! | O210: =VLOOKUP(A210,#REF!,12,0) -> #REF! | P210: =VLOOKUP(A210,#REF!,13,0) -> #REF! | Q210: =VLOOKUP(A210,#REF!,14,0) -> #REF! | R210: 1.328925 | S210: 0.92128971 | T210: =VLOOKUP(C210,V:W,2,0) -> USA | U210: =IF(T210=T$1,B210,IF(T210=T$2,B210,IF(T210=U$1,B210,"")))
A211: Florida State University | B211: Florida State | C211: USA | D211: =IFERROR(ROUND(VLOOKUP(A211,institutions!A:E,4,0),2),"") -> 2.22 | E211: =IFERROR(ROUND(VLOOKUP(A211,institutions!A:X,7,0),2),"") -> 1.66 | F211: =IFERROR(ROUND(VLOOKUP(A211,institutions!A:X,10,0),2),"") -> 2.27 | G211: =IFERROR(ROUND(VLOOKUP(A211,institutions!A:X,13,0),2),"") -> 2.99 | H211: =IFERROR(ROUND(VLOOKUP(A211,institutions!A:X,16,0),2),"") -> 3.47 | I211: =ROUND(IFERROR((601-_xlfn.RANK.EQ(D211,D:D))/600,0),3) -> 0.683 | J211: =ROUND(IFERROR((601-IFERROR(_xlfn.RANK.EQ(E211,E:E),""))/600,0),3) -> 0.612 | K211: =ROUND(IFERROR((601-IFERROR(_xlfn.RANK.EQ(F211,F:F),""))/600,0),3) -> 0.795 | L211: =ROUND(IFERROR((601-IFERROR(_xlfn.RANK.EQ(G211,G:G),""))/600,0),3) -> 0.812 | M211: =ROUND(IFERROR((601-IFERROR(_xlfn.RANK.EQ(H211,H:H),""))/600,0),3) -> 0.787 | N211: =VLOOKUP(A211,#REF!,11,0) -> #REF! | O211: =VLOOKUP(A211,#REF!,12,0) -> #REF! | P211: =VLOOKUP(A211,#REF!,13,0) -> #REF! | Q211: =VLOOKUP(A211,#REF!,14,0) -> #REF! | R211: 1.7431714 | S211: -0.31435352 | T211: =VLOOKUP(C211,V:W,2,0) -> USA | U211: =IF(T211=T$1,B211,IF(T211=T$2,B211,IF(T211=U$1,B211,"")))
A212: Monash University | B212: Monash | C212: AUSTRALIA | D212: =IFERROR(ROUND(VLOOKUP(A212,institutions!A:E,4,0),2),"") -> 2.11 | E212: =IFERROR(ROUND(VLOOKUP(A212,institutions!A:X,7,0),2),"") -> 2.28 | F212: =IFERROR(ROUND(VLOOKUP(A212,institutions!A:X,10,0),2),"") -> 1.81 | G212: =IFERROR(ROUND(VLOOKUP(A212,institutions!A:X,13,0),2),"") -> 1.96 | H212: =IFERROR(ROUND(VLOOKUP(A212,institutions!A:X,16,0),2),"") -> 2.42 | I212: =ROUND(IFERROR((601-_xlfn.RANK.EQ(D212,D:D))/600,0),3) -> 0.625 | J212: =ROUND(IFERROR((601-IFERROR(_xlfn.RANK.EQ(E212,E:E),""))/600,0),3) -> 0.837 | K212: =ROUND(IFERROR((601-IFERROR(_xlfn.RANK.EQ(F212,F:F),""))/600,0),3) -> 0.682 | L212: =ROUND(IFERROR((601-IFERROR(_xlfn.RANK.EQ(G212,G:G),""))/600,0),3) -> 0.45 | M212: =ROUND(IFERROR((601-IFERROR(_xlfn.RANK.EQ(H212,H:H),""))/600,0),3) -> 0.508 | N212: =VLOOKUP(A212,#REF!,11,0) -> #REF! | O212: =VLOOKUP(A212,#REF!,12,0) -> #REF! | P212: =VLOOKUP(A212,#REF!,13,0) -> #REF! | Q212: =VLOOKUP(A212,#REF!,14,0) -> #REF! | R212: 0.76016106 | S212: 1.0473268 | T212: =VLOOKUP(C212,V:W,2,0) -> AUS | U212: =IF(T212=T$1,B212,IF(T212=T$2,B212,IF(T212=U$1,B212,"")))
A213: The World Bank | B213: The World Bank | C213: USA | D213: =IFERROR(ROUND(VLOOKUP(A213,institutions!A:E,4,0),2),"") -> 2.07 | E213: =IFERROR(ROUND(VLOOKUP(A213,institutions!A:X,7,0),2),"") -> 2.07 | F213: =IFERROR(ROUND(VLOOKUP(A213,institutions!A:X,10,0),2),"") -> 1.36 | G213: =IFERROR(ROUND(VLOOKUP(A213,institutions!A:X,13,0),2),"") | H213: =IFERROR(ROUND(VLOOKUP(A213,institutions!A:X,16,0),2),"") | I213: =ROUND(IFERROR((601-_xlfn.RANK.EQ(D213,D:D))/600,0),3) -> 0.6 | J213: =ROUND(IFERROR((601-IFERROR(_xlfn.RANK.EQ(E213,E:E),""))/600,0),3) -> 0.785 | K213: =ROUND(IFERROR((601-IFERROR(_xlfn.RANK.EQ(F213,F:F),""))/600,0),3) -> 0.412 | L213: =ROUND(IFERROR((601-IFERROR(_xlfn.RANK.EQ(G213,G:G),""))/600,0),3) -> 0 | M213: =ROUND(IFERROR((601-IFERROR(_xlfn.RANK.EQ(H213,H:H),""))/600,0),3) -> 0 | N213: =VLOOKUP(A213,#REF!,11,0) -> #REF! | O213: =VLOOKUP(A213,#REF!,12,0) -> #REF! | P213: =VLOOKUP(A213,#REF!,13,0) -> #REF! | Q213: =VLOOKUP(A213,#REF!,14,0) -> #REF! | R213: -1.5048735 | S213: 2.0988934 | T213: =VLOOKUP(C213,V:W,2,0) -> USA | U213: =IF(T213=T$1,B213,IF(T213=T$2,B213,IF(T213=U$1,B213,"")))
A214: emlyon business school | B214: emlyon BS | C214: FRANCE | D214: =IFERROR(ROUND(VLOOKUP(A214,institutions!A:E,4,0),2),"") -> 2.23 | E214: =IFERROR(ROUND(VLOOKUP(A214,institutions!A:X,7,0),2),"") -> 1.52 | F214: =IFERROR(ROUND(VLOOKUP(A214,institutions!A:X,10,0),2),"") -> 1.36 | G214: =IFERROR(ROUND(VLOOKUP(A214,institutions!A:X,13,0),2),"") -> 2.44 | H214: =IFERROR(ROUND(VLOOKUP(A214,institutions!A:X,16,0),2),"") -> 3.38 | I214: =ROUND(IFERROR((601-_xlfn.RANK.EQ(D214,D:D))/600,0),3) -> 0.685 | J214: =ROUND(IFERROR((601-IFERROR(_xlfn.RANK.EQ(E214,E:E),""))/600,0),3) -> 0.52 | K214: =ROUND(IFERROR((601-IFERROR(_xlfn.RANK.EQ(F214,F:F),""))/600,0),3) -> 0.412 | L214: =ROUND(IFERROR((601-IFERROR(_xlfn.RANK.EQ(G214,G:G),""))/600,0),3) -> 0.658 | M214: =ROUND(IFERROR((601-IFERROR(_xlfn.RANK.EQ(H214,H:H),""))/600,0),3) -> 0.767 | N214: =VLOOKUP(A214,#REF!,11,0) -> #REF! | O214: =VLOOKUP(A214,#REF!,12,0) -> #REF! | P214: =VLOOKUP(A214,#REF!,13,0) -> #REF! | Q214: =VLOOKUP(A214,#REF!,14,0) -> #REF! | R214: 0.63065957 | S214: -0.77981158 | T214: =VLOOKUP(C214,V:W,2,0) -> FRA | U214: =IF(T214=T$1,B214,IF(T214=T$2,B214,IF(T214=U$1,B214,""))) -> emlyon BS
A215: University of Birmingham | B215: Birmingham | C215: ENGLAND | D215: =IFERROR(ROUND(VLOOKUP(A215,institutions!A:E,4,0),2),"") -> 2.16 | E215: =IFERROR(ROUND(VLOOKUP(A215,institutions!A:X,7,0),2),"") -> 1.46 | F215: =IFERROR(ROUND(VLOOKUP(A215,institutions!A:X,10,0),2),"") -> 1.53 | G215: =IFERROR(ROUND(VLOOKUP(A215,institutions!A:X,13,0),2),"") -> 2.37 | H215: =IFERROR(ROUND(VLOOKUP(A215,institutions!A:X,16,0),2),"") -> 3.36 | I215: =ROUND(IFERROR((601-_xlfn.RANK.EQ(D215,D:D))/600,0),3) -> 0.655 | J215: =ROUND(IFERROR((601-IFERROR(_xlfn.RANK.EQ(E215,E:E),""))/600,0),3) -> 0.468 | K215: =ROUND(IFERROR((601-IFERROR(_xlfn.RANK.EQ(F215,F:F),""))/600,0),3) -> 0.552 | L215: =ROUND(IFERROR((601-IFERROR(_xlfn.RANK.EQ(G215,G:G),""))/600,0),3) -> 0.622 | M215: =ROUND(IFERROR((601-IFERROR(_xlfn.RANK.EQ(H215,H:H),""))/600,0),3) -> 0.753 | N215: =VLOOKUP(A215,#REF!,11,0) -> #REF! | O215: =VLOOKUP(A215,#REF!,12,0) -> #REF! | P215: =VLOOKUP(A215,#REF!,13,0) -> #REF! | Q215: =VLOOKUP(A215,#REF!,14,0) -> #REF! | R215: 0.69710765 | S215: -0.60494941 | T215: =VLOOKUP(C215,V:W,2,0) -> UK | U215: =IF(T215=T$1,B215,IF(T215=T$2,B215,IF(T215=U$1,B215,"")))
A216: Vienna University of Economics & Business | B216: Vienna Econ & Bus | C216: AUSTRIA | D216: =IFERROR(ROUND(VLOOKUP(A216,institutions!A:E,4,0),2),"") -> 2.24 | E216: =IFERROR(ROUND(VLOOKUP(A216,institutions!A:X,7,0),2),"") -> 1.82 | F216: =IFERROR(ROUND(VLOOKUP(A216,institutions!A:X,10,0),2),"") -> 2.07 | G216: =IFERROR(ROUND(VLOOKUP(A216,institutions!A:X,13,0),2),"") -> 3.33 | H216: =IFERROR(ROUND(VLOOKUP(A216,institutions!A:X,16,0),2),"") -> 3.7 | I216: =ROUND(IFERROR((601-_xlfn.RANK.EQ(D216,D:D))/600,0),3) -> 0.695 | J216: =ROUND(IFERROR((601-IFERROR(_xlfn.RANK.EQ(E216,E:E),""))/600,0),3) -> 0.692 | K216: =ROUND(IFERROR((601-IFERROR(_xlfn.RANK.EQ(F216,F:F),""))/600,0),3) -> 0.762 | L216: =ROUND(IFERROR((601-IFERROR(_xlfn.RANK.EQ(G216,G:G),""))/600,0),3) -> 0.867 | M216: =ROUND(IFERROR((601-IFERROR(_xlfn.RANK.EQ(H216,H:H),""))/600,0),3) -> 0.835 | N216: =VLOOKUP(A216,#REF!,11,0) -> #REF! | O216: =VLOOKUP(A216,#REF!,12,0) -> #REF! | P216: =VLOOKUP(A216,#REF!,13,0) -> #REF! | Q216: =VLOOKUP(A216,#REF!,14,0) -> #REF! | R216: 1.9996371 | S216: -0.35931201 | T216: =VLOOKUP(C216,V:W,2,0) -> AUT | U216: =IF(T216=T$1,B216,IF(T216=T$2,B216,IF(T216=U$1,B216,"")))
A217: Autonomous University of Barcelona | B217: Auton Barcelona | C217: SPAIN | D217: =IFERROR(ROUND(VLOOKUP(A217,institutions!A:E,4,0),2),"") -> 2.22 | E217: =IFERROR(ROUND(VLOOKUP(A217,institutions!A:X,7,0),2),"") -> 2.02 | F217: =IFERROR(ROUND(VLOOKUP(A217,institutions!A:X,10,0),2),"") -> 1.32 | G217: =IFERROR(ROUND(VLOOKUP(A217,institutions!A:X,13,0),2),"") -> 3.2 | H217: =IFERROR(ROUND(VLOOKUP(A217,institutions!A:X,16,0),2),"") -> 3.01 | I217: =ROUND(IFERROR((601-_xlfn.RANK.EQ(D217,D:D))/600,0),3) -> 0.683 | J217: =ROUND(IFERROR((601-IFERROR(_xlfn.RANK.EQ(E217,E:E),""))/600,0),3) -> 0.763 | K217: =ROUND(IFERROR((601-IFERROR(_xlfn.RANK.EQ(F217,F:F),""))/600,0),3) -> 0.365 | L217: =ROUND(IFERROR((601-IFERROR(_xlfn.RANK.EQ(G217,G:G),""))/600,0),3) -> 0.847 | M217: =ROUND(IFERROR((601-IFERROR(_xlfn.RANK.EQ(H217,H:H),""))/600,0),3) -> 0.685 | N217: =VLOOKUP(A217,#REF!,11,0) -> #REF! | O217: =VLOOKUP(A217,#REF!,12,0) -> #REF! | P217: =VLOOKUP(A217,#REF!,13,0) -> #REF! | Q217: =VLOOKUP(A217,#REF!,14,0) -> #REF! | R217: 1.1284047 | S217: -0.51414427 | T217: =VLOOKUP(C217,V:W,2,0) -> SPAIN | U217: =IF(T217=T$1,B217,IF(T217=T$2,B217,IF(T217=U$1,B217,""))) -> Auton Barcelona
A218: Chalmers University of Technology | B218: Chalmers Technology | C218: SWEDEN | D218: =IFERROR(ROUND(VLOOKUP(A218,institutions!A:E,4,0),2),"") -> 2.12 | E218: =IFERROR(ROUND(VLOOKUP(A218,institutions!A:X,7,0),2),"") | F218: =IFERROR(ROUND(VLOOKUP(A218,institutions!A:X,10,0),2),"") | G218: =IFERROR(ROUND(VLOOKUP(A218,institutions!A:X,13,0),2),"") -> 2.52 | H218: =IFERROR(ROUND(VLOOKUP(A218,institutions!A:X,16,0),2),"") -> 3.22 | I218: =ROUND(IFERROR((601-_xlfn.RANK.EQ(D218,D:D))/600,0),3) -> 0.63 | J218: =ROUND(IFERROR((601-IFERROR(_xlfn.RANK.EQ(E218,E:E),""))/600,0),3) -> 0 | K218: =ROUND(IFERROR((601-IFERROR(_xlfn.RANK.EQ(F218,F:F),""))/600,0),3) -> 0 | L218: =ROUND(IFERROR((601-IFERROR(_xlfn.RANK.EQ(G218,G:G),""))/600,0),3) -> 0.7 | M218: =ROUND(IFERROR((601-IFERROR(_xlfn.RANK.EQ(H218,H:H),""))/600,0),3) -> 0.725 | N218: =VLOOKUP(A218,#REF!,11,0) -> #REF! | O218: =VLOOKUP(A218,#REF!,12,0) -> #REF! | P218: =VLOOKUP(A218,#REF!,13,0) -> #REF! | Q218: =VLOOKUP(A218,#REF!,14,0) -> #REF! | R218: -0.90608212 | S218: -2.493065 | T218: =VLOOKUP(C218,V:W,2,0) -> SWE | U218: =IF(T218=T$1,B218,IF(T218=T$2,B218,IF(T218=U$1,B218,"")))
A219: NEOMA Business School | B219: NEOMA BS | C219: FRANCE | D219: =IFERROR(ROUND(VLOOKUP(A219,institutions!A:E,4,0),2),"") -> 2.21 | E219: =IFERROR(ROUND(VLOOKUP(A219,institutions!A:X,7,0),2),"") -> 1.55 | F219: =IFERROR(ROUND(VLOOKUP(A219,institutions!A:X,10,0),2),"") | G219: =IFERROR(ROUND(VLOOKUP(A219,institutions!A:X,13,0),2),"") -> 2 | H219: =IFERROR(ROUND(VLOOKUP(A219,institutions!A:X,16,0),2),"") -> 3.17 | I219: =ROUND(IFERROR((601-_xlfn.RANK.EQ(D219,D:D))/600,0),3) -> 0.672 | J219: =ROUND(IFERROR((601-IFERROR(_xlfn.RANK.EQ(E219,E:E),""))/600,0),3) -> 0.543 | K219: =ROUND(IFERROR((601-IFERROR(_xlfn.RANK.EQ(F219,F:F),""))/600,0),3) -> 0 | L219: =ROUND(IFERROR((601-IFERROR(_xlfn.RANK.EQ(G219,G:G),""))/600,0),3) -> 0.472 | M219: =ROUND(IFERROR((601-IFERROR(_xlfn.RANK.EQ(H219,H:H),""))/600,0),3) -> 0.715 | N219: =VLOOKUP(A219,#REF!,11,0) -> #REF! | O219: =VLOOKUP(A219,#REF!,12,0) -> #REF! | P219: =VLOOKUP(A219,#REF!,13,0) -> #REF! | Q219: =VLOOKUP(A219,#REF!,14,0) -> #REF! | R219: -0.46230418 | S219: -0.937831 | T219: =VLOOKUP(C219,V:W,2,0) -> FRA | U219: =IF(T219=T$1,B219,IF(T219=T$2,B219,IF(T219=U$1,B219,""))) -> NEOMA BS
A220: University of Essex | B220: Essex | C220: ENGLAND | D220: =IFERROR(ROUND(VLOOKUP(A220,institutions!A:E,4,0),2),"") -> 2.12 | E220: =IFERROR(ROUND(VLOOKUP(A220,institutions!A:X,7,0),2),"") -> 2.21 | F220: =IFERROR(ROUND(VLOOKUP(A220,institutions!A:X,10,0),2),"") -> 1.51 | G220: =IFERROR(ROUND(VLOOKUP(A220,institutions!A:X,13,0),2),"") -> 1.77 | H220: =IFERROR(ROUND(VLOOKUP(A220,institutions!A:X,16,0),2),"") -> 2.23 | I220: =ROUND(IFERROR((601-_xlfn.RANK.EQ(D220,D:D))/600,0),3) -> 0.63 | J220: =ROUND(IFERROR((601-IFERROR(_xlfn.RANK.EQ(E220,E:E),""))/600,0),3) -> 0.82 | K220: =ROUND(IFERROR((601-IFERROR(_xlfn.RANK.EQ(F220,F:F),""))/600,0),3) -> 0.533 | L220: =ROUND(IFERROR((601-IFERROR(_xlfn.RANK.EQ(G220,G:G),""))/600,0),3) -> 0.35 | M220: =ROUND(IFERROR((601-IFERROR(_xlfn.RANK.EQ(H220,H:H),""))/600,0),3) -> 0.432 | N220: =VLOOKUP(A220,#REF!,11,0) -> #REF! | O220: =VLOOKUP(A220,#REF!,12,0) -> #REF! | P220: =VLOOKUP(A220,#REF!,13,0) -> #REF! | Q220: =VLOOKUP(A220,#REF!,14,0) -> #REF! | R220: 0.16267424 | S220: 1.0813682 | T220: =VLOOKUP(C220,V:W,2,0) -> UK | U220: =IF(T220=T$1,B220,IF(T220=T$2,B220,IF(T220=U$1,B220,"")))
A221: Florida Atlantic University | B221: Florida Atlantic | C221: USA | D221: =IFERROR(ROUND(VLOOKUP(A221,institutions!A:E,4,0),2),"") -> 2.13 | E221: =IFERROR(ROUND(VLOOKUP(A221,institutions!A:X,7,0),2),"") -> 1.26 | F221: =IFERROR(ROUND(VLOOKUP(A221,institutions!A:X,10,0),2),"") -> 1.51 | G221: =IFERROR(ROUND(VLOOKUP(A221,institutions!A:X,13,0),2),"") -> 2.64 | H221: =IFERROR(ROUND(VLOOKUP(A221,institutions!A:X,16,0),2),"") -> 2.49 | I221: =ROUND(IFERROR((601-_xlfn.RANK.EQ(D221,D:D))/600,0),3) -> 0.637 | J221: =ROUND(IFERROR((601-IFERROR(_xlfn.RANK.EQ(E221,E:E),""))/600,0),3) -> 0.228 | K221: =ROUND(IFERROR((601-IFERROR(_xlfn.RANK.EQ(F221,F:F),""))/600,0),3) -> 0.533 | L221: =ROUND(IFERROR((601-IFERROR(_xlfn.RANK.EQ(G221,G:G),""))/600,0),3) -> 0.725 | M221: =ROUND(IFERROR((601-IFERROR(_xlfn.RANK.EQ(H221,H:H),""))/600,0),3) -> 0.545 | N221: =VLOOKUP(A221,#REF!,11,0) -> #REF! | O221: =VLOOKUP(A221,#REF!,12,0) -> #REF! | P221: =VLOOKUP(A221,#REF!,13,0) -> #REF! | Q221: =VLOOKUP(A221,#REF!,14,0) -> #REF! | R221: 0.088873248 | S221: -0.9867842 | T221: =VLOOKUP(C221,V:W,2,0) -> USA | U221: =IF(T221=T$1,B221,IF(T221=T$2,B221,IF(T221=U$1,B221,"")))
... A243: Auburn University | B243: Auburn | C243: USA | D243: =IFERROR(ROUND(VLOOKUP(A243,institutions!A:E,4,0),2),"") -> 2.12 | E243: =IFERROR(ROUND(VLOOKUP(A243,institutions!A:X,7,0),2),"") -> 1.33 | F243: =IFERROR(ROUND(VLOOKUP(A243,institutions!A:X,10,0),2),"") -> 1.83 | G243: =IFERROR(ROUND(VLOOKUP(A243,institutions!A:X,13,0),2),"") -> 2.46 | H243: =IFERROR(ROUND(VLOOKUP(A243,institutions!A:X,16,0),2),"") -> 3.65 | I243: =ROUND(IFERROR((601-_xlfn.RANK.EQ(D243,D:D))/600,0),3) -> 0.63 | J243: =ROUND(IFERROR((601-IFERROR(_xlfn.RANK.EQ(E243,E:E),""))/600,0),3) -> 0.33 | K243: =ROUND(IFERROR((601-IFERROR(_xlfn.RANK.EQ(F243,F:F),""))/600,0),3) -> 0.688 | L243: =ROUND(IFERROR((601-IFERROR(_xlfn.RANK.EQ(G243,G:G),""))/600,0),3) -> 0.672 | M243: =ROUND(IFERROR((601-IFERROR(_xlfn.RANK.EQ(H243,H:H),""))/600,0),3) -> 0.825 | N243: =VLOOKUP(A243,#REF!,11,0) -> #REF! | O243: =VLOOKUP(A243,#REF!,12,0) -> #REF! | P243: =VLOOKUP(A243,#REF!,13,0) -> #REF! | Q243: =VLOOKUP(A243,#REF!,14,0) -> #REF! | R243: 0.92792585 | S243: -0.89923816 | T243: =VLOOKUP(C243,V:W,2,0) -> USA | U243: =IF(T243=T$1,B243,IF(T243=T$2,B243,IF(T243=U$1,B243,"")))
A244: Czech Academy of Sciences | B244: Czech Acad Sci | C244: CZECH REPUBLIC | D244: =IFERROR(ROUND(VLOOKUP(A244,institutions!A:E,4,0),2),"") -> 2 | E244: =IFERROR(ROUND(VLOOKUP(A244,institutions!A:X,7,0),2),"") | F244: =IFERROR(ROUND(VLOOKUP(A244,institutions!A:X,10,0),2),"") | G244: =IFERROR(ROUND(VLOOKUP(A244,institutions!A:X,13,0),2),"") | H244: =IFERROR(ROUND(VLOOKUP(A244,institutions!A:X,16,0),2),"") | I244: =ROUND(IFERROR((601-_xlfn.RANK.EQ(D244,D:D))/600,0),3) -> 0.565 | J244: =ROUND(IFERROR((601-IFERROR(_xlfn.RANK.EQ(E244,E:E),""))/600,0),3) -> 0 | K244: =ROUND(IFERROR((601-IFERROR(_xlfn.RANK.EQ(F244,F:F),""))/600,0),3) -> 0 | L244: =ROUND(IFERROR((601-IFERROR(_xlfn.RANK.EQ(G244,G:G),""))/600,0),3) -> 0 | M244: =ROUND(IFERROR((601-IFERROR(_xlfn.RANK.EQ(H244,H:H),""))/600,0),3) -> 0 | N244: 1 | O244: =VLOOKUP(A244,#REF!,12,0) -> #REF! | P244: =VLOOKUP(A244,#REF!,13,0) -> #REF! | Q244: =VLOOKUP(A244,#REF!,14,0) -> #REF! | R244: -3.4647209 | S244: -0.17686962 | T244: =VLOOKUP(C244,V:W,2,0) -> CZE | U244: =IF(T244=T$1,B244,IF(T244=T$2,B244,IF(T244=U$1,B244,"")))
A245: Dublin City University | B245: Dublin City | C245: IRELAND | D245: =IFERROR(ROUND(VLOOKUP(A245,institutions!A:E,4,0),2),"") -> 2.09 | E245: =IFERROR(ROUND(VLOOKUP(A245,institutions!A:X,7,0),2),"") -> 1.47 | F245: =IFERROR(ROUND(VLOOKUP(A245,institutions!A:X,10,0),2),"") -> 1.75 | G245: =IFERROR(ROUND(VLOOKUP(A245,institutions!A:X,13,0),2),"") -> 1.94 | H245: =IFERROR(ROUND(VLOOKUP(A245,institutions!A:X,16,0),2),"") -> 3.71 | I245: =ROUND(IFERROR((601-_xlfn.RANK.EQ(D245,D:D))/600,0),3) -> 0.612 | J245: =ROUND(IFERROR((601-IFERROR(_xlfn.RANK.EQ(E245,E:E),""))/600,0),3) -> 0.478 | K245: =ROUND(IFERROR((601-IFERROR(_xlfn.RANK.EQ(F245,F:F),""))/600,0),3) -> 0.672 | L245: =ROUND(IFERROR((601-IFERROR(_xlfn.RANK.EQ(G245,G:G),""))/600,0),3) -> 0.44 | M245: =ROUND(IFERROR((601-IFERROR(_xlfn.RANK.EQ(H245,H:H),""))/600,0),3) -> 0.837 | N245: =VLOOKUP(A245,#REF!,11,0) -> #REF! | O245: =VLOOKUP(A245,#REF!,12,0) -> #REF! | P245: =VLOOKUP(A245,#REF!,13,0) -> #REF! | Q245: =VLOOKUP(A245,#REF!,14,0) -> #REF! | R245: 0.74497435 | S245: -0.23898261 | T245: =VLOOKUP(C245,V:W,2,0) -> IRL | U245: =IF(T245=T$1,B245,IF(T245=T$2,B245,IF(T245=U$1,B245,"")))
A246: Shanghai University of Finance & Economics | B246: Shanghai Fin & Econ | C246: CHINA MAINLAND | D246: =IFERROR(ROUND(VLOOKUP(A246,institutions!A:E,4,0),2),"") -> 2.06 | E246: =IFERROR(ROUND(VLOOKUP(A246,institutions!A:X,7,0),2),"") -> 1.59 | F246: =IFERROR(ROUND(VLOOKUP(A246,institutions!A:X,10,0),2),"") -> 2.14 | G246: =IFERROR(ROUND(VLOOKUP(A246,institutions!A:X,13,0),2),"") -> 1.93 | H246: =IFERROR(ROUND(VLOOKUP(A246,institutions!A:X,16,0),2),"") -> 4.53 | I246: =ROUND(IFERROR((601-_xlfn.RANK.EQ(D246,D:D))/600,0),3) -> 0.593 | J246: =ROUND(IFERROR((601-IFERROR(_xlfn.RANK.EQ(E246,E:E),""))/600,0),3) -> 0.563 | K246: =ROUND(IFERROR((601-IFERROR(_xlfn.RANK.EQ(F246,F:F),""))/600,0),3) -> 0.783 | L246: =ROUND(IFERROR((601-IFERROR(_xlfn.RANK.EQ(G246,G:G),""))/600,0),3) -> 0.433 | M246: =ROUND(IFERROR((601-IFERROR(_xlfn.RANK.EQ(H246,H:H),""))/600,0),3) -> 0.92 | N246: =VLOOKUP(A246,#REF!,11,0) -> #REF! | O246: =VLOOKUP(A246,#REF!,12,0) -> #REF! | P246: =VLOOKUP(A246,#REF!,13,0) -> #REF! | Q246: =VLOOKUP(A246,#REF!,14,0) -> #REF! | R246: 1.2080017 | S246: -0.015942835 | T246: =VLOOKUP(C246,V:W,2,0) -> CHN | U246: =IF(T246=T$1,B246,IF(T246=T$2,B246,IF(T246=U$1,B246,"")))
A247: Tsinghua University | B247: Tsinghua | C247: CHINA MAINLAND | D247: =IFERROR(ROUND(VLOOKUP(A247,institutions!A:E,4,0),2),"") -> 2.02 | E247: =IFERROR(ROUND(VLOOKUP(A247,institutions!A:X,7,0),2),"") -> 1.92 | F247: =IFERROR(ROUND(VLOOKUP(A247,institutions!A:X,10,0),2),"") -> 1.21 | G247: =IFERROR(ROUND(VLOOKUP(A247,institutions!A:X,13,0),2),"") -> 1.8 | H247: =IFERROR(ROUND(VLOOKUP(A247,institutions!A:X,16,0),2),"") -> 2.13 | I247: =ROUND(IFERROR((601-_xlfn.RANK.EQ(D247,D:D))/600,0),3) -> 0.578 | J247: =ROUND(IFERROR((601-IFERROR(_xlfn.RANK.EQ(E247,E:E),""))/600,0),3) -> 0.725 | K247: =ROUND(IFERROR((601-IFERROR(_xlfn.RANK.EQ(F247,F:F),""))/600,0),3) -> 0.245 | L247: =ROUND(IFERROR((601-IFERROR(_xlfn.RANK.EQ(G247,G:G),""))/600,0),3) -> 0.363 | M247: =ROUND(IFERROR((601-IFERROR(_xlfn.RANK.EQ(H247,H:H),""))/600,0),3) -> 0.387 | N247: =VLOOKUP(A247,#REF!,11,0) -> #REF! | O247: =VLOOKUP(A247,#REF!,12,0) -> #REF! | P247: =VLOOKUP(A247,#REF!,13,0) -> #REF! | Q247: =VLOOKUP(A247,#REF!,14,0) -> #REF! | R247: -0.53941517 | S247: 0.50915183 | T247: =VLOOKUP(C247,V:W,2,0) -> CHN | U247: =IF(T247=T$1,B247,IF(T247=T$2,B247,IF(T247=U$1,B247,"")))
A248: University of Bern | B248: Bern | C248: SWITZERLAND | D248: =IFERROR(ROUND(VLOOKUP(A248,institutions!A:E,4,0),2),"") -> 2.01 | E248: =IFERROR(ROUND(VLOOKUP(A248,institutions!A:X,7,0),2),"") -> 2.06 | F248: =IFERROR(ROUND(VLOOKUP(A248,institutions!A:X,10,0),2),"") -> 2.1 | G248: =IFERROR(ROUND(VLOOKUP(A248,institutions!A:X,13,0),2),"") -> 1.84 | H248: =IFERROR(ROUND(VLOOKUP(A248,institutions!A:X,16,0),2),"") -> 1.74 | I248: =ROUND(IFERROR((601-_xlfn.RANK.EQ(D248,D:D))/600,0),3) -> 0.573 | J248: =ROUND(IFERROR((601-IFERROR(_xlfn.RANK.EQ(E248,E:E),""))/600,0),3) -> 0.778 | K248: =ROUND(IFERROR((601-IFERROR(_xlfn.RANK.EQ(F248,F:F),""))/600,0),3) -> 0.772 | L248: =ROUND(IFERROR((601-IFERROR(_xlfn.RANK.EQ(G248,G:G),""))/600,0),3) -> 0.383 | M248: =ROUND(IFERROR((601-IFERROR(_xlfn.RANK.EQ(H248,H:H),""))/600,0),3) -> 0.203 | N248: =VLOOKUP(A248,#REF!,11,0) -> #REF! | O248: =VLOOKUP(A248,#REF!,12,0) -> #REF! | P248: =VLOOKUP(A248,#REF!,13,0) -> #REF! | Q248: =VLOOKUP(A248,#REF!,14,0) -> #REF! | R248: 0.1491489 | S248: 1.647689 | T248: =VLOOKUP(C248,V:W,2,0) -> CHE | U248: =IF(T248=T$1,B248,IF(T248=T$2,B248,IF(T248=U$1,B248,"")))
A249: University of Cologne | B249: Cologne | C249: GERMANY | D249: =IFERROR(ROUND(VLOOKUP(A249,institutions!A:E,4,0),2),"") -> 2.08 | E249: =IFERROR(ROUND(VLOOKUP(A249,institutions!A:X,7,0),2),"") -> 1.74 | F249: =IFERROR(ROUND(VLOOKUP(A249,institutions!A:X,10,0),2),"") -> 1.45 | G249: =IFERROR(ROUND(VLOOKUP(A249,institutions!A:X,13,0),2),"") -> 3.29 | H249: =IFERROR(ROUND(VLOOKUP(A249,institutions!A:X,16,0),2),"") -> 2.84 | I249: =ROUND(IFERROR((601-_xlfn.RANK.EQ(D249,D:D))/600,0),3) -> 0.605 | J249: =ROUND(IFERROR((601-IFERROR(_xlfn.RANK.EQ(E249,E:E),""))/600,0),3) -> 0.657 | K249: =ROUND(IFERROR((601-IFERROR(_xlfn.RANK.EQ(F249,F:F),""))/600,0),3) -> 0.485 | L249: =ROUND(IFERROR((601-IFERROR(_xlfn.RANK.EQ(G249,G:G),""))/600,0),3) -> 0.858 | M249: =ROUND(IFERROR((601-IFERROR(_xlfn.RANK.EQ(H249,H:H),""))/600,0),3) -> 0.65 | N249: =VLOOKUP(A249,#REF!,11,0) -> #REF! | O249: =VLOOKUP(A249,#REF!,12,0) -> #REF! | P249: =VLOOKUP(A249,#REF!,13,0) -> #REF! | Q249: =VLOOKUP(A249,#REF!,14,0) -> #REF! | R249: 1.1202499 | S249: -0.52869286 | T249: =VLOOKUP(C249,V:W,2,0) -> DEU | U249: =IF(T249=T$1,B249,IF(T249=T$2,B249,IF(T249=U$1,B249,""))) -> Cologne
A250: Oklahoma State University - Stillwater | B250: Stillwater | C250: USA | D250: =IFERROR(ROUND(VLOOKUP(A250,institutions!A:E,4,0),2),"") -> 2.07 | E250: =IFERROR(ROUND(VLOOKUP(A250,institutions!A:X,7,0),2),"") -> 1.27 | F250: =IFERROR(ROUND(VLOOKUP(A250,institutions!A:X,10,0),2),"") -> 1.33 | G250: =IFERROR(ROUND(VLOOKUP(A250,institutions!A:X,13,0),2),"") -> 3.33 | H250: =IFERROR(ROUND(VLOOKUP(A250,institutions!A:X,16,0),2),"") -> 5.61 | I250: =ROUND(IFERROR((601-_xlfn.RANK.EQ(D250,D:D))/600,0),3) -> 0.6 | J250: =ROUND(IFERROR((601-IFERROR(_xlfn.RANK.EQ(E250,E:E),""))/600,0),3) -> 0.242 | K250: =ROUND(IFERROR((601-IFERROR(_xlfn.RANK.EQ(F250,F:F),""))/600,0),3) -> 0.382 | L250: =ROUND(IFERROR((601-IFERROR(_xlfn.RANK.EQ(G250,G:G),""))/600,0),3) -> 0.867 | M250: =ROUND(IFERROR((601-IFERROR(_xlfn.RANK.EQ(H250,H:H),""))/600,0),3) -> 0.963 | N250: =VLOOKUP(A250,#REF!,11,0) -> #REF! | O250: =VLOOKUP(A250,#REF!,12,0) -> #REF! | P250: =VLOOKUP(A250,#REF!,13,0) -> #REF! | Q250: =VLOOKUP(A250,#REF!,14,0) -> #REF! | R250: 0.86159797 | S250: -2.0761863 | T250: =VLOOKUP(C250,V:W,2,0) -> USA | U250: =IF(T250=T$1,B250,IF(T250=T$2,B250,IF(T250=U$1,B250,"")))
A251: SKEMA Business School | B251: SKEMA BS | C251: FRANCE | D251: =IFERROR(ROUND(VLOOKUP(A251,institutions!A:E,4,0),2),"") -> 2.13 | E251: =IFERROR(ROUND(VLOOKUP(A251,institutions!A:X,7,0),2),"") -> 1.5 | F251: =IFERROR(ROUND(VLOOKUP(A251,institutions!A:X,10,0),2),"") -> 1.47 | G251: =IFERROR(ROUND(VLOOKUP(A251,institutions!A:X,13,0),2),"") -> 2.02 | H251: =IFERROR(ROUND(VLOOKUP(A251,institutions!A:X,16,0),2),"") -> 2.77 | I251: =ROUND(IFERROR((601-_xlfn.RANK.EQ(D251,D:D))/600,0),3) -> 0.637 | J251: =ROUND(IFERROR((601-IFERROR(_xlfn.RANK.EQ(E251,E:E),""))/600,0),3) -> 0.498 | K251: =ROUND(IFERROR((601-IFERROR(_xlfn.RANK.EQ(F251,F:F),""))/600,0),3) -> 0.498 | L251: =ROUND(IFERROR((601-IFERROR(_xlfn.RANK.EQ(G251,G:G),""))/600,0),3) -> 0.478 | M251: =ROUND(IFERROR((601-IFERROR(_xlfn.RANK.EQ(H251,H:H),""))/600,0),3) -> 0.627 | N251: =VLOOKUP(A251,#REF!,11,0) -> #REF! | O251: =VLOOKUP(A251,#REF!,12,0) -> #REF! | P251: =VLOOKUP(A251,#REF!,13,0) -> #REF! | Q251: =VLOOKUP(A251,#REF!,14,0) -> #REF! | R251: 0.16829495 | S251: -0.17969695 | T251: =VLOOKUP(C251,V:W,2,0) -> FRA | U251: =IF(T251=T$1,B251,IF(T251=T$2,B251,IF(T251=U$1,B251,""))) -> SKEMA BS
A252: University of Aberdeen | B252: Aberdeen | C252: SCOTLAND | D252: =IFERROR(ROUND(VLOOKUP(A252,institutions!A:E,4,0),2),"") -> 2.06 | E252: =IFERROR(ROUND(VLOOKUP(A252,institutions!A:X,7,0),2),"") -> 1.14 | F252: =IFERROR(ROUND(VLOOKUP(A252,institutions!A:X,10,0),2),"") -> 1.43 | G252: =IFERROR(ROUND(VLOOKUP(A252,institutions!A:X,13,0),2),"") -> 2.52 | H252: =IFERROR(ROUND(VLOOKUP(A252,institutions!A:X,16,0),2),"") -> 3.42 | I252: =ROUND(IFERROR((601-_xlfn.RANK.EQ(D252,D:D))/600,0),3) -> 0.593 | J252: =ROUND(IFERROR((601-IFERROR(_xlfn.RANK.EQ(E252,E:E),""))/600,0),3) -> 0.088 | K252: =ROUND(IFERROR((601-IFERROR(_xlfn.RANK.EQ(F252,F:F),""))/600,0),3) -> 0.473 | L252: =ROUND(IFERROR((601-IFERROR(_xlfn.RANK.EQ(G252,G:G),""))/600,0),3) -> 0.7 | M252: =ROUND(IFERROR((601-IFERROR(_xlfn.RANK.EQ(H252,H:H),""))/600,0),3) -> 0.773 | N252: =VLOOKUP(A252,#REF!,11,0) -> #REF! | O252: =VLOOKUP(A252,#REF!,12,0) -> #REF! | P252: =VLOOKUP(A252,#REF!,13,0) -> #REF! | Q252: =VLOOKUP(A252,#REF!,14,0) -> #REF! | R252: 0.1294901 | S252: -1.6930182 | T252: =VLOOKUP(C252,V:W,2,0) -> UK | U252: =IF(T252=T$1,B252,IF(T252=T$2,B252,IF(T252=U$1,B252,"")))
A253: University of Exeter | B253: Exeter | C253: ENGLAND | D253: =IFERROR(ROUND(VLOOKUP(A253,institutions!A:E,4,0),2),"") -> 2.06 | E253: =IFERROR(ROUND(VLOOKUP(A253,institutions!A:X,7,0),2),"") -> 1.64 | F253: =IFERROR(ROUND(VLOOKUP(A253,institutions!A:X,10,0),2),"") -> 1.57 | G253: =IFERROR(ROUND(VLOOKUP(A253,institutions!A:X,13,0),2),"") -> 2.34 | H253: =IFERROR(ROUND(VLOOKUP(A253,institutions!A:X,16,0),2),"") -> 3.32 | I253: =ROUND(IFERROR((601-_xlfn.RANK.EQ(D253,D:D))/600,0),3) -> 0.593 | J253: =ROUND(IFERROR((601-IFERROR(_xlfn.RANK.EQ(E253,E:E),""))/600,0),3) -> 0.592 | K253: =ROUND(IFERROR((601-IFERROR(_xlfn.RANK.EQ(F253,F:F),""))/600,0),3) -> 0.568 | L253: =ROUND(IFERROR((601-IFERROR(_xlfn.RANK.EQ(G253,G:G),""))/600,0),3) -> 0.612 | M253: =ROUND(IFERROR((601-IFERROR(_xlfn.RANK.EQ(H253,H:H),""))/600,0),3) -> 0.742 | N253: =VLOOKUP(A253,#REF!,11,0) -> #REF! | O253: =VLOOKUP(A253,#REF!,12,0) -> #REF! | P253: =VLOOKUP(A253,#REF!,13,0) -> #REF! | Q253: =VLOOKUP(A253,#REF!,14,0) -> #REF! | R253: 0.88512488 | S253: -0.28277493 | T253: =VLOOKUP(C253,V:W,2,0) -> UK | U253: =IF(T253=T$1,B253,IF(T253=T$2,B253,IF(T253=U$1,B253,"")))
A254: Deutsche Bundesbank | B254: Deutsche Bundesbank | C254: GERMANY | D254: =IFERROR(ROUND(VLOOKUP(A254,institutions!A:E,4,0),2),"") -> 1.97 | E254: =IFERROR(ROUND(VLOOKUP(A254,institutions!A:X,7,0),2),"") -> 1.68 | F254: =IFERROR(ROUND(VLOOKUP(A254,institutions!A:X,10,0),2),"") -> 1.86 | G254: =IFERROR(ROUND(VLOOKUP(A254,institutions!A:X,13,0),2),"") | H254: =IFERROR(ROUND(VLOOKUP(A254,institutions!A:X,16,0),2),"") | I254: =ROUND(IFERROR((601-_xlfn.RANK.EQ(D254,D:D))/600,0),3) -> 0.543 | J254: =ROUND(IFERROR((601-IFERROR(_xlfn.RANK.EQ(E254,E:E),""))/600,0),3) -> 0.62 | K254: =ROUND(IFERROR((601-IFERROR(_xlfn.RANK.EQ(F254,F:F),""))/600,0),3) -> 0.697 | L254: =ROUND(IFERROR((601-IFERROR(_xlfn.RANK.EQ(G254,G:G),""))/600,0),3) -> 0 | M254: =ROUND(IFERROR((601-IFERROR(_xlfn.RANK.EQ(H254,H:H),""))/600,0),3) -> 0 | N254: 1 | O254: =VLOOKUP(A254,#REF!,12,0) -> #REF! | P254: =VLOOKUP(A254,#REF!,13,0) -> #REF! | Q254: =VLOOKUP(A254,#REF!,14,0) -> #REF! | R254: -1.2819604 | S254: 2.1612659 | T254: =VLOOKUP(C254,V:W,2,0) -> DEU | U254: =IF(T254=T$1,B254,IF(T254=T$2,B254,IF(T254=U$1,B254,""))) -> Deutsche Bundesbank
A255: University of South Florida | B255: South Florida | C255: USA | D255: =IFERROR(ROUND(VLOOKUP(A255,institutions!A:E,4,0),2),"") -> 1.96 | E255: =IFERROR(ROUND(VLOOKUP(A255,institutions!A:X,7,0),2),"") -> 1.39 | F255: =IFERROR(ROUND(VLOOKUP(A255,institutions!A:X,10,0),2),"") -> 1.7 | G255: =IFERROR(ROUND(VLOOKUP(A255,institutions!A:X,13,0),2),"") -> 2.5 | H255: =IFERROR(ROUND(VLOOKUP(A255,institutions!A:X,16,0),2),"") -> 2.81 | I255: =ROUND(IFERROR((601-_xlfn.RANK.EQ(D255,D:D))/600,0),3) -> 0.537 | J255: =ROUND(IFERROR((601-IFERROR(_xlfn.RANK.EQ(E255,E:E),""))/600,0),3) -> 0.392 | K255: =ROUND(IFERROR((601-IFERROR(_xlfn.RANK.EQ(F255,F:F),""))/600,0),3) -> 0.633 | L255: =ROUND(IFERROR((601-IFERROR(_xlfn.RANK.EQ(G255,G:G),""))/600,0),3) -> 0.695 | M255: =ROUND(IFERROR((601-IFERROR(_xlfn.RANK.EQ(H255,H:H),""))/600,0),3) -> 0.642 | N255: =VLOOKUP(A255,#REF!,11,0) -> #REF! | O255: =VLOOKUP(A255,#REF!,12,0) -> #REF! | P255: =VLOOKUP(A255,#REF!,13,0) -> #REF! | Q255: =VLOOKUP(A255,#REF!,14,0) -> #REF! | R255: 0.64373563 | S255: -0.59494208 | T255: =VLOOKUP(C255,V:W,2,0) -> USA | U255: =IF(T255=T$1,B255,IF(T255=T$2,B255,IF(T255=U$1,B255,"")))
A256: Durham University | B256: Durham | C256: ENGLAND | D256: =IFERROR(ROUND(VLOOKUP(A256,institutions!A:E,4,0),2),"") -> 2.04 | E256: =IFERROR(ROUND(VLOOKUP(A256,institutions!A:X,7,0),2),"") -> 1.44 | F256: =IFERROR(ROUND(VLOOKUP(A256,institutions!A:X,10,0),2),"") -> 1.3 | G256: =IFERROR(ROUND(VLOOKUP(A256,institutions!A:X,13,0),2),"") -> 2.49 | H256: =IFERROR(ROUND(VLOOKUP(A256,institutions!A:X,16,0),2),"") -> 3.06 | I256: =ROUND(IFERROR((601-_xlfn.RANK.EQ(D256,D:D))/600,0),3) -> 0.585 | J256: =ROUND(IFERROR((601-IFERROR(_xlfn.RANK.EQ(E256,E:E),""))/600,0),3) -> 0.448 | K256: =ROUND(IFERROR((601-IFERROR(_xlfn.RANK.EQ(F256,F:F),""))/600,0),3) -> 0.347 | L256: =ROUND(IFERROR((601-IFERROR(_xlfn.RANK.EQ(G256,G:G),""))/600,0),3) -> 0.688 | M256: =ROUND(IFERROR((601-IFERROR(_xlfn.RANK.EQ(H256,H:H),""))/600,0),3) -> 0.693 | N256: =VLOOKUP(A256,#REF!,11,0) -> #REF! | O256: =VLOOKUP(A256,#REF!,12,0) -> #REF! | P256: =VLOOKUP(A256,#REF!,13,0) -> #REF! | Q256: =VLOOKUP(A256,#REF!,14,0) -> #REF! | R256: 0.32432408 | S256: -0.96075192 | T256: =VLOOKUP(C256,V:W,2,0) -> UK | U256: =IF(T256=T$1,B256,IF(T256=T$2,B256,IF(T256=U$1,B256,"")))
A257: Fordham University | B257: Fordham | C257: USA | D257: =IFERROR(ROUND(VLOOKUP(A257,institutions!A:E,4,0),2),"") -> 1.97 | E257: =IFERROR(ROUND(VLOOKUP(A257,institutions!A:X,7,0),2),"") -> 1.31 | F257: =IFERROR(ROUND(VLOOKUP(A257,institutions!A:X,10,0),2),"") -> 1.71 | G257: =IFERROR(ROUND(VLOOKUP(A257,institutions!A:X,13,0),2),"") -> 2.56 | H257: =IFERROR(ROUND(VLOOKUP(A257,institutions!A:X,16,0),2),"") -> 2.21 | I257: =ROUND(IFERROR((601-_xlfn.RANK.EQ(D257,D:D))/600,0),3) -> 0.543 | J257: =ROUND(IFERROR((601-IFERROR(_xlfn.RANK.EQ(E257,E:E),""))/600,0),3) -> 0.298 | K257: =ROUND(IFERROR((601-IFERROR(_xlfn.RANK.EQ(F257,F:F),""))/600,0),3) -> 0.645 | L257: =ROUND(IFERROR((601-IFERROR(_xlfn.RANK.EQ(G257,G:G),""))/600,0),3) -> 0.712 | M257: =ROUND(IFERROR((601-IFERROR(_xlfn.RANK.EQ(H257,H:H),""))/600,0),3) -> 0.427 | N257: =VLOOKUP(A257,#REF!,11,0) -> #REF! | O257: =VLOOKUP(A257,#REF!,12,0) -> #REF! | P257: =VLOOKUP(A257,#REF!,13,0) -> #REF! | Q257: =VLOOKUP(A257,#REF!,14,0) -> #REF! | R257: 0.15592052 | S257: -0.46551791 | T257: =VLOOKUP(C257,V:W,2,0) -> USA | U257: =IF(T257=T$1,B257,IF(T257=T$2,B257,IF(T257=U$1,B257,"")))
A258: North Carolina State University | B258: N Carolina State | C258: USA | D258: =IFERROR(ROUND(VLOOKUP(A258,institutions!A:E,4,0),2),"") -> 2.08 | E258: =IFERROR(ROUND(VLOOKUP(A258,institutions!A:X,7,0),2),"") -> 2.07 | F258: =IFERROR(ROUND(VLOOKUP(A258,institutions!A:X,10,0),2),"") -> 1.97 | G258: =IFERROR(ROUND(VLOOKUP(A258,institutions!A:X,13,0),2),"") -> 1.75 | H258: =IFERROR(ROUND(VLOOKUP(A258,institutions!A:X,16,0),2),"") -> 2.46 | I258: =ROUND(IFERROR((601-_xlfn.RANK.EQ(D258,D:D))/600,0),3) -> 0.605 | J258: =ROUND(IFERROR((601-IFERROR(_xlfn.RANK.EQ(E258,E:E),""))/600,0),3) -> 0.785 | K258: =ROUND(IFERROR((601-IFERROR(_xlfn.RANK.EQ(F258,F:F),""))/600,0),3) -> 0.74 | L258: =ROUND(IFERROR((601-IFERROR(_xlfn.RANK.EQ(G258,G:G),""))/600,0),3) -> 0.337 | M258: =ROUND(IFERROR((601-IFERROR(_xlfn.RANK.EQ(H258,H:H),""))/600,0),3) -> 0.53 | N258: =VLOOKUP(A258,#REF!,11,0) -> #REF! | O258: =VLOOKUP(A258,#REF!,12,0) -> #REF! | P258: =VLOOKUP(A258,#REF!,13,0) -> #REF! | Q258: =VLOOKUP(A258,#REF!,14,0) -> #REF! | R258: 0.61409608 | S258: 1.1740608 | T258: =VLOOKUP(C258,V:W,2,0) -> USA | U258: =IF(T258=T$1,B258,IF(T258=T$2,B258,IF(T258=U$1,B258,"")))
A259: University of Vaasa | B259: Vaasa | C259: FINLAND | D259: =IFERROR(ROUND(VLOOKUP(A259,institutions!A:E,4,0),2),"") -> 2.11 | E259: =IFERROR(ROUND(VLOOKUP(A259,institutions!A:X,7,0),2),"") -> 1.19 | F259: =IFERROR(ROUND(VLOOKUP(A259,institutions!A:X,10,0),2),"") -> 1.33 | G259: =IFERROR(ROUND(VLOOKUP(A259,institutions!A:X,13,0),2),"") -> 2.2 | H259: =IFERROR(ROUND(VLOOKUP(A259,institutions!A:X,16,0),2),"") -> 3.56 | I259: =ROUND(IFERROR((601-_xlfn.RANK.EQ(D259,D:D))/600,0),3) -> 0.625 | J259: =ROUND(IFERROR((601-IFERROR(_xlfn.RANK.EQ(E259,E:E),""))/600,0),3) -> 0.135 | K259: =ROUND(IFERROR((601-IFERROR(_xlfn.RANK.EQ(F259,F:F),""))/600,0),3) -> 0.382 | L259: =ROUND(IFERROR((601-IFERROR(_xlfn.RANK.EQ(G259,G:G),""))/600,0),3) -> 0.552 | M259: =ROUND(IFERROR((601-IFERROR(_xlfn.RANK.EQ(H259,H:H),""))/600,0),3) -> 0.807 | N259: =VLOOKUP(A259,#REF!,11,0) -> #REF! | O259: =VLOOKUP(A259,#REF!,12,0) -> #REF! | P259: =VLOOKUP(A259,#REF!,13,0) -> #REF! | Q259: =VLOOKUP(A259,#REF!,14,0) -> #REF! | R259: -0.15353562 | S259: -1.5324146 | T259: =VLOOKUP(C259,V:W,2,0) -> FIN | U259: =IF(T259=T$1,B259,IF(T259=T$2,B259,IF(T259=U$1,B259,"")))
A260: Australian National University | B260: ANU | C260: AUSTRALIA | D260: =IFERROR(ROUND(VLOOKUP(A260,institutions!A:E,4,0),2),"") -> 1.97 | E260: =IFERROR(ROUND(VLOOKUP(A260,institutions!A:X,7,0),2),"") -> 1.89 | F260: =IFERROR(ROUND(VLOOKUP(A260,institutions!A:X,10,0),2),"") -> 1.43 | G260: =IFERROR(ROUND(VLOOKUP(A260,institutions!A:X,13,0),2),"") -> 2.14 | H260: =IFERROR(ROUND(VLOOKUP(A260,institutions!A:X,16,0),2),"") -> 2.59 | I260: =ROUND(IFERROR((601-_xlfn.RANK.EQ(D260,D:D))/600,0),3) -> 0.543 | J260: =ROUND(IFERROR((601-IFERROR(_xlfn.RANK.EQ(E260,E:E),""))/600,0),3) -> 0.722 | K260: =ROUND(IFERROR((601-IFERROR(_xlfn.RANK.EQ(F260,F:F),""))/600,0),3) -> 0.473 | L260: =ROUND(IFERROR((601-IFERROR(_xlfn.RANK.EQ(G260,G:G),""))/600,0),3) -> 0.532 | M260: =ROUND(IFERROR((601-IFERROR(_xlfn.RANK.EQ(H260,H:H),""))/600,0),3) -> 0.578 | N260: =VLOOKUP(A260,#REF!,11,0) -> #REF! | O260: =VLOOKUP(A260,#REF!,12,0) -> #REF! | P260: =VLOOKUP(A260,#REF!,13,0) -> #REF! | Q260: =VLOOKUP(A260,#REF!,14,0) -> #REF! | R260: 0.49186809 | S260: 0.24999455 | T260: =VLOOKUP(C260,V:W,2,0) -> AUS | U260: =IF(T260=T$1,B260,IF(T260=T$2,B260,IF(T260=U$1,B260,"")))
A261: Audencia | B261: Audencia | C261: FRANCE | D261: =IFERROR(ROUND(VLOOKUP(A261,institutions!A:E,4,0),2),"") -> 2.07 | E261: =IFERROR(ROUND(VLOOKUP(A261,institutions!A:X,7,0),2),"") -> 1.17 | F261: =IFERROR(ROUND(VLOOKUP(A261,institutions!A:X,10,0),2),"") -> 1.4 | G261: =IFERROR(ROUND(VLOOKUP(A261,institutions!A:X,13,0),2),"") -> 2.77 | H261: =IFERROR(ROUND(VLOOKUP(A261,institutions!A:X,16,0),2),"") -> 2.46 | I261: =ROUND(IFERROR((601-_xlfn.RANK.EQ(D261,D:D))/600,0),3) -> 0.6 | J261: =ROUND(IFERROR((601-IFERROR(_xlfn.RANK.EQ(E261,E:E),""))/600,0),3) -> 0.117 | K261: =ROUND(IFERROR((601-IFERROR(_xlfn.RANK.EQ(F261,F:F),""))/600,0),3) -> 0.44 | L261: =ROUND(IFERROR((601-IFERROR(_xlfn.RANK.EQ(G261,G:G),""))/600,0),3) -> 0.767 | M261: =ROUND(IFERROR((601-IFERROR(_xlfn.RANK.EQ(H261,H:H),""))/600,0),3) -> 0.53 | N261: =VLOOKUP(A261,#REF!,11,0) -> #REF! | O261: =VLOOKUP(A261,#REF!,12,0) -> #REF! | P261: =VLOOKUP(A261,#REF!,13,0) -> #REF! | Q261: =VLOOKUP(A261,#REF!,14,0) -> #REF! | R261: -0.19973272 | S261: -1.4053196 | T261: =VLOOKUP(C261,V:W,2,0) -> FRA | U261: =IF(T261=T$1,B261,IF(T261=T$2,B261,IF(T261=U$1,B261,""))) -> Audencia
...

Sheet forspss
A1: id | B1: ebrank | C1: erank | D1: frank | E1: brank | F1: mrank
A2: =institutions_spss!A4 -> Center for Economic & Policy Research (CEPR) | B2: =VLOOKUP(A2,institutions_spss!A:M,9,0) -> 1 | C2: =VLOOKUP(A2,institutions_spss!A:M,10,0) -> 0.995 | D2: =VLOOKUP(A2,institutions_spss!A:M,11,0) -> 0.992 | E2: =VLOOKUP(A2,institutions_spss!A:M,12,0) -> 0 | F2: =VLOOKUP(A2,institutions_spss!A:M,13,0) -> 0
A3: =institutions_spss!A5 -> University of Chicago | B3: =VLOOKUP(A3,institutions_spss!A:M,9,0) -> 0.998 | C3: =VLOOKUP(A3,institutions_spss!A:M,10,0) -> 0.998 | D3: =VLOOKUP(A3,institutions_spss!A:M,11,0) -> 0.997 | E3: =VLOOKUP(A3,institutions_spss!A:M,12,0) -> 0.812 | F3: =VLOOKUP(A3,institutions_spss!A:M,13,0) -> 0.3
A4: =institutions_spss!A6 -> University of California Santa Barbara | B4: =VLOOKUP(A4,institutions_spss!A:M,9,0) -> 0.997 | C4: =VLOOKUP(A4,institutions_spss!A:M,10,0) -> 1 | D4: =VLOOKUP(A4,institutions_spss!A:M,11,0) -> 0.72 | E4: =VLOOKUP(A4,institutions_spss!A:M,12,0) -> 0.483 | F4: =VLOOKUP(A4,institutions_spss!A:M,13,0) -> 0.95
A5: =institutions_spss!A7 -> Princeton University | B5: =VLOOKUP(A5,institutions_spss!A:M,9,0) -> 0.993 | C5: =VLOOKUP(A5,institutions_spss!A:M,10,0) -> 0.993 | D5: =VLOOKUP(A5,institutions_spss!A:M,11,0) -> 0.943 | E5: =VLOOKUP(A5,institutions_spss!A:M,12,0) -> 0 | F5: =VLOOKUP(A5,institutions_spss!A:M,13,0) -> 0
A6: =institutions_spss!A8 -> London Business School | B6: =VLOOKUP(A6,institutions_spss!A:M,9,0) -> 0.995 | C6: =VLOOKUP(A6,institutions_spss!A:M,10,0) -> 0.997 | D6: =VLOOKUP(A6,institutions_spss!A:M,11,0) -> 0.98 | E6: =VLOOKUP(A6,institutions_spss!A:M,12,0) -> 0.983 | F6: =VLOOKUP(A6,institutions_spss!A:M,13,0) -> 0.968
A7: =institutions_spss!A9 -> Yale University | B7: =VLOOKUP(A7,institutions_spss!A:M,9,0) -> 0.992 | C7: =VLOOKUP(A7,institutions_spss!A:M,10,0) -> 0.987 | D7: =VLOOKUP(A7,institutions_spss!A:M,11,0) -> 0.998 | E7: =VLOOKUP(A7,institutions_spss!A:M,12,0) -> 0.985 | F7: =VLOOKUP(A7,institutions_spss!A:M,13,0) -> 0.95
A8: =institutions_spss!A10 -> National Bureau of Economic Research | B8: =VLOOKUP(A8,institutions_spss!A:M,9,0) -> 0.988 | C8: =VLOOKUP(A8,institutions_spss!A:M,10,0) -> 0.98 | D8: =VLOOKUP(A8,institutions_spss!A:M,11,0) -> 0 | E8: =VLOOKUP(A8,institutions_spss!A:M,12,0) -> 0 | F8: =VLOOKUP(A8,institutions_spss!A:M,13,0) -> 0
A9: =institutions_spss!A11 -> Stanford University | B9: =VLOOKUP(A9,institutions_spss!A:M,9,0) -> 0.99 | C9: =VLOOKUP(A9,institutions_spss!A:M,10,0) -> 0.983 | D9: =VLOOKUP(A9,institutions_spss!A:M,11,0) -> 0.995 | E9: =VLOOKUP(A9,institutions_spss!A:M,12,0) -> 0.983 | F9: =VLOOKUP(A9,institutions_spss!A:M,13,0) -> 0.997
A10: =institutions_spss!A12 -> Massachusetts Institute of Technology (MIT) | B10: =VLOOKUP(A10,institutions_spss!A:M,9,0) -> 0.987 | C10: =VLOOKUP(A10,institutions_spss!A:M,10,0) -> 0.992 | D10: =VLOOKUP(A10,institutions_spss!A:M,11,0) -> 0.902 | E10: =VLOOKUP(A10,institutions_spss!A:M,12,0) -> 0.822 | F10: =VLOOKUP(A10,institutions_spss!A:M,13,0) -> 0.942
A11: =institutions_spss!A13 -> University of California Berkeley | B11: =VLOOKUP(A11,institutions_spss!A:M,9,0) -> 0.985 | C11: =VLOOKUP(A11,institutions_spss!A:M,10,0) -> 0.982 | D11: =VLOOKUP(A11,institutions_spss!A:M,11,0) -> 0.955 | E11: =VLOOKUP(A11,institutions_spss!A:M,12,0) -> 0.935 | F11: =VLOOKUP(A11,institutions_spss!A:M,13,0) -> 0.902
A12: =institutions_spss!A14 -> Swiss Finance Institute (SFI) | B12: =VLOOKUP(A12,institutions_spss!A:M,9,0) -> 0.982 | C12: =VLOOKUP(A12,institutions_spss!A:M,10,0) -> 0.958 | D12: =VLOOKUP(A12,institutions_spss!A:M,11,0) -> 0.973 | E12: =VLOOKUP(A12,institutions_spss!A:M,12,0) -> 0 | F12: =VLOOKUP(A12,institutions_spss!A:M,13,0) -> 0
A13: =institutions_spss!A15 -> Harvard University | B13: =VLOOKUP(A13,institutions_spss!A:M,9,0) -> 0.983 | C13: =VLOOKUP(A13,institutions_spss!A:M,10,0) -> 0.988 | D13: =VLOOKUP(A13,institutions_spss!A:M,11,0) -> 0.952 | E13: =VLOOKUP(A13,institutions_spss!A:M,12,0) -> 0.875 | F13: =VLOOKUP(A13,institutions_spss!A:M,13,0) -> 0.908
... A601: =institutions_spss!A603 -> Vilnius Gediminas Technical University | B601: =VLOOKUP(A601,institutions_spss!A:M,9,0) -> 0.002 | C601: =VLOOKUP(A601,institutions_spss!A:M,10,0) -> 0.008 | D601: =VLOOKUP(A601,institutions_spss!A:M,11,0) -> 0 | E601: =VLOOKUP(A601,institutions_spss!A:M,12,0) -> 0.053 | F601: =VLOOKUP(A601,institutions_spss!A:M,13,0) -> 0.048
