Workbook

Sheet journals_spss
C1: eb | F1: e | H1: f | J1: b | L1: m
C2: pub | D2: ebscore | E2: ebrank | F2: score | G2: rank | H2: score | I2: rank | J2: score | K2: rank | L2: score | M2: rank | N2: wc1 | O2: wc2 | P2: wc3 | Q2: wc4 | R2: wc5 | S2: wc6
A3: journal | B3: publisher | C3: pub | D3: ebscore | E3: ebrank | F3: =CONCATENATE(F1,F2) -> escore | G3: =CONCATENATE(F1,G2) -> erank | H3: =CONCATENATE(H1,H2) -> fscore | I3: =CONCATENATE(H1,I2) -> frank | J3: =CONCATENATE(J1,J2) -> bscore | K3: =CONCATENATE(J1,K2) -> brank | L3: =CONCATENATE(L1,L2) -> mscore | M3: =CONCATENATE(L1,M2) -> mrank | N3: wc1 | O3: wc2 | P3: wc3 | Q3: wc4 | R3: wc5 | S3: wc6
A4: QUARTERLY JOURNAL OF ECONOMICS | B4: OXFORD UNIV PRESS INC | C4: 40 | D4: =IFERROR(VLOOKUP(A4,eco_bus_journals!A:D,4,0),"") -> 10 | E4: =_xlfn.RANK.EQ(D4,D:D) -> 1 | F4: =IFERROR(VLOOKUP(A4,eco_journals!A:D,4,0),"") -> 10 | G4: =IFERROR(_xlfn.RANK.EQ(F4,F:F),"") -> 1 | H4: =IFERROR(VLOOKUP(A4,fin_journals!A:D,4,0),"") | I4: =IFERROR(_xlfn.RANK.EQ(H4,H:H),"") | J4: =IFERROR(VLOOKUP(A4,bus_journals!A:D,4,0),"") | K4: =IFERROR(_xlfn.RANK.EQ(J4,J:J),"") | L4: =IFERROR(VLOOKUP(A4,man_journals!A:D,4,0),"") | M4: =IFERROR(_xlfn.RANK.EQ(L4,L:L),"") | N4: ECONOMICS | T4: journal
A5: AMERICAN ECONOMIC REVIEW | B5: AMER ECONOMIC ASSOC | C5: 116 | D5: =IFERROR(VLOOKUP(A5,eco_bus_journals!A:D,4,0),"") -> 8.4 | E5: =_xlfn.RANK.EQ(D5,D:D) -> 2 | F5: =IFERROR(VLOOKUP(A5,eco_journals!A:D,4,0),"") -> 8.32 | G5: =IFERROR(_xlfn.RANK.EQ(F5,F:F),"") -> 2 | H5: =IFERROR(VLOOKUP(A5,fin_journals!A:D,4,0),"") | I5: =IFERROR(_xlfn.RANK.EQ(H5,H:H),"") | J5: =IFERROR(VLOOKUP(A5,bus_journals!A:D,4,0),"") | K5: =IFERROR(_xlfn.RANK.EQ(J5,J:J),"") | L5: =IFERROR(VLOOKUP(A5,man_journals!A:D,4,0),"") | M5: =IFERROR(_xlfn.RANK.EQ(L5,L:L),"") | N5: ECONOMICS | T5: publisher
A6: ACADEMY OF MANAGEMENT ANNALS | B6: ACAD MANAGEMENT | C6: 31 | D6: =IFERROR(VLOOKUP(A6,eco_bus_journals!A:D,4,0),"") -> 7.04 | E6: =_xlfn.RANK.EQ(D6,D:D) -> 3 | F6: =IFERROR(VLOOKUP(A6,eco_journals!A:D,4,0),"") | G6: =IFERROR(_xlfn.RANK.EQ(F6,F:F),"") | H6: =IFERROR(VLOOKUP(A6,fin_journals!A:D,4,0),"") | I6: =IFERROR(_xlfn.RANK.EQ(H6,H:H),"") | J6: =IFERROR(VLOOKUP(A6,bus_journals!A:D,4,0),"") -> 10 | K6: =IFERROR(_xlfn.RANK.EQ(J6,J:J),"") -> 1 | L6: =IFERROR(VLOOKUP(A6,man_journals!A:D,4,0),"") -> 10 | M6: =IFERROR(_xlfn.RANK.EQ(L6,L:L),"") -> 1 | N6: BUSINESS | O6: MANAGEMENT | T6: pub
A7: NBER MACROECONOMICS ANNUAL | B7: UNIV CHICAGO PRESS | C7: 7 | D7: =IFERROR(VLOOKUP(A7,eco_bus_journals!A:D,4,0),"") -> 6.46 | E7: =_xlfn.RANK.EQ(D7,D:D) -> 4 | F7: =IFERROR(VLOOKUP(A7,eco_journals!A:D,4,0),"") -> 6.68 | G7: =IFERROR(_xlfn.RANK.EQ(F7,F:F),"") -> 3 | H7: =IFERROR(VLOOKUP(A7,fin_journals!A:D,4,0),"") | I7: =IFERROR(_xlfn.RANK.EQ(H7,H:H),"") | J7: =IFERROR(VLOOKUP(A7,bus_journals!A:D,4,0),"") | K7: =IFERROR(_xlfn.RANK.EQ(J7,J:J),"") | L7: =IFERROR(VLOOKUP(A7,man_journals!A:D,4,0),"") | M7: =IFERROR(_xlfn.RANK.EQ(L7,L:L),"") | N7: ECONOMICS | T7: ebscore
A8: ADMINISTRATIVE SCIENCE QUARTERLY | B8: SAGE PUBLICATIONS | C8: 39 | D8: =IFERROR(VLOOKUP(A8,eco_bus_journals!A:D,4,0),"") -> 6.4 | E8: =_xlfn.RANK.EQ(D8,D:D) -> 5 | F8: =IFERROR(VLOOKUP(A8,eco_journals!A:D,4,0),"") | G8: =IFERROR(_xlfn.RANK.EQ(F8,F:F),"") | H8: =IFERROR(VLOOKUP(A8,fin_journals!A:D,4,0),"") | I8: =IFERROR(_xlfn.RANK.EQ(H8,H:H),"") | J8: =IFERROR(VLOOKUP(A8,bus_journals!A:D,4,0),"") -> 9.14 | K8: =IFERROR(_xlfn.RANK.EQ(J8,J:J),"") -> 2 | L8: =IFERROR(VLOOKUP(A8,man_journals!A:D,4,0),"") -> 9.54 | M8: =IFERROR(_xlfn.RANK.EQ(L8,L:L),"") -> 2 | N8: BUSINESS | O8: MANAGEMENT | T8: ebrank
A9: REVIEW OF ECONOMIC STUDIES | B9: OXFORD UNIV PRESS | C9: 80 | D9: =IFERROR(VLOOKUP(A9,eco_bus_journals!A:D,4,0),"") -> 5.99 | E9: =_xlfn.RANK.EQ(D9,D:D) -> 6 | F9: =IFERROR(VLOOKUP(A9,eco_journals!A:D,4,0),"") -> 6.08 | G9: =IFERROR(_xlfn.RANK.EQ(F9,F:F),"") -> 4 | H9: =IFERROR(VLOOKUP(A9,fin_journals!A:D,4,0),"") | I9: =IFERROR(_xlfn.RANK.EQ(H9,H:H),"") | J9: =IFERROR(VLOOKUP(A9,bus_journals!A:D,4,0),"") | K9: =IFERROR(_xlfn.RANK.EQ(J9,J:J),"") | L9: =IFERROR(VLOOKUP(A9,man_journals!A:D,4,0),"") | M9: =IFERROR(_xlfn.RANK.EQ(L9,L:L),"") | N9: ECONOMICS | T9: escore
A10: JOURNAL OF POLITICAL ECONOMY | B10: UNIV CHICAGO PRESS | C10: 110 | D10: =IFERROR(VLOOKUP(A10,eco_bus_journals!A:D,4,0),"") -> 5.74 | E10: =_xlfn.RANK.EQ(D10,D:D) -> 7 | F10: =IFERROR(VLOOKUP(A10,eco_journals!A:D,4,0),"") -> 5.78 | G10: =IFERROR(_xlfn.RANK.EQ(F10,F:F),"") -> 5 | H10: =IFERROR(VLOOKUP(A10,fin_journals!A:D,4,0),"") | I10: =IFERROR(_xlfn.RANK.EQ(H10,H:H),"") | J10: =IFERROR(VLOOKUP(A10,bus_journals!A:D,4,0),"") | K10: =IFERROR(_xlfn.RANK.EQ(J10,J:J),"") | L10: =IFERROR(VLOOKUP(A10,man_journals!A:D,4,0),"") | M10: =IFERROR(_xlfn.RANK.EQ(L10,L:L),"") | N10: ECONOMICS | T10: erank
A11: ECONOMETRICA | B11: WILEY | C11: 76 | D11: =IFERROR(VLOOKUP(A11,eco_bus_journals!A:D,4,0),"") -> 5.32 | E11: =_xlfn.RANK.EQ(D11,D:D) -> 8 | F11: =IFERROR(VLOOKUP(A11,eco_journals!A:D,4,0),"") -> 5.73 | G11: =IFERROR(_xlfn.RANK.EQ(F11,F:F),"") -> 6 | H11: =IFERROR(VLOOKUP(A11,fin_journals!A:D,4,0),"") | I11: =IFERROR(_xlfn.RANK.EQ(H11,H:H),"") | J11: =IFERROR(VLOOKUP(A11,bus_journals!A:D,4,0),"") | K11: =IFERROR(_xlfn.RANK.EQ(J11,J:J),"") | L11: =IFERROR(VLOOKUP(A11,man_journals!A:D,4,0),"") | M11: =IFERROR(_xlfn.RANK.EQ(L11,L:L),"") | N11: ECONOMICS | O11: MATHEMATICS, INTERDISCIPLINARY APPLICATIONS | P11: SOCIAL SCIENCES, MATHEMATICAL METHODS | Q11: STATISTICS & PROBABILITY | T11: fscore
A12: JOURNAL OF FINANCE | B12: WILEY | C12: 73 | D12: =IFERROR(VLOOKUP(A12,eco_bus_journals!A:D,4,0),"") -> 5.01 | E12: =_xlfn.RANK.EQ(D12,D:D) -> 9 | F12: =IFERROR(VLOOKUP(A12,eco_journals!A:D,4,0),"") -> 3.58 | G12: =IFERROR(_xlfn.RANK.EQ(F12,F:F),"") -> 10 | H12: =IFERROR(VLOOKUP(A12,fin_journals!A:D,4,0),"") -> 8.57 | I12: =IFERROR(_xlfn.RANK.EQ(H12,H:H),"") -> 3 | J12: =IFERROR(VLOOKUP(A12,bus_journals!A:D,4,0),"") | K12: =IFERROR(_xlfn.RANK.EQ(J12,J:J),"") | L12: =IFERROR(VLOOKUP(A12,man_journals!A:D,4,0),"") | M12: =IFERROR(_xlfn.RANK.EQ(L12,L:L),"") | N12: FINANCE | O12: ECONOMICS | T12: frank
A13: AMERICAN ECONOMIC REVIEW-INSIGHTS | B13: AMER ECONOMIC ASSOC | C13: 32 | D13: =IFERROR(VLOOKUP(A13,eco_bus_journals!A:D,4,0),"") -> 4.72 | E13: =_xlfn.RANK.EQ(D13,D:D) -> 10 | F13: =IFERROR(VLOOKUP(A13,eco_journals!A:D,4,0),"") -> 4.73 | G13: =IFERROR(_xlfn.RANK.EQ(F13,F:F),"") -> 7 | H13: =IFERROR(VLOOKUP(A13,fin_journals!A:D,4,0),"") | I13: =IFERROR(_xlfn.RANK.EQ(H13,H:H),"") | J13: =IFERROR(VLOOKUP(A13,bus_journals!A:D,4,0),"") | K13: =IFERROR(_xlfn.RANK.EQ(J13,J:J),"") | L13: =IFERROR(VLOOKUP(A13,man_journals!A:D,4,0),"") | M13: =IFERROR(_xlfn.RANK.EQ(L13,L:L),"") | N13: ECONOMICS | T13: bscore
A14: ACADEMY OF MANAGEMENT JOURNAL | B14: ACAD MANAGEMENT | C14: 71 | D14: =IFERROR(VLOOKUP(A14,eco_bus_journals!A:D,4,0),"") -> 4.17 | E14: =_xlfn.RANK.EQ(D14,D:D) -> 11 | F14: =IFERROR(VLOOKUP(A14,eco_journals!A:D,4,0),"") | G14: =IFERROR(_xlfn.RANK.EQ(F14,F:F),"") | H14: =IFERROR(VLOOKUP(A14,fin_journals!A:D,4,0),"") | I14: =IFERROR(_xlfn.RANK.EQ(H14,H:H),"") | J14: =IFERROR(VLOOKUP(A14,bus_journals!A:D,4,0),"") -> 7.21 | K14: =IFERROR(_xlfn.RANK.EQ(J14,J:J),"") -> 4 | L14: =IFERROR(VLOOKUP(A14,man_journals!A:D,4,0),"") -> 6.84 | M14: =IFERROR(_xlfn.RANK.EQ(L14,L:L),"") -> 3 | N14: BUSINESS | O14: MANAGEMENT | T14: brank
A15: JOURNAL OF ECONOMIC LITERATURE | B15: AMER ECONOMIC ASSOC | C15: 16 | D15: =IFERROR(VLOOKUP(A15,eco_bus_journals!A:D,4,0),"") -> 3.8 | E15: =_xlfn.RANK.EQ(D15,D:D) -> 12 | F15: =IFERROR(VLOOKUP(A15,eco_journals!A:D,4,0),"") -> 3.56 | G15: =IFERROR(_xlfn.RANK.EQ(F15,F:F),"") -> 11 | H15: =IFERROR(VLOOKUP(A15,fin_journals!A:D,4,0),"") | I15: =IFERROR(_xlfn.RANK.EQ(H15,H:H),"") | J15: =IFERROR(VLOOKUP(A15,bus_journals!A:D,4,0),"") | K15: =IFERROR(_xlfn.RANK.EQ(J15,J:J),"") | L15: =IFERROR(VLOOKUP(A15,man_journals!A:D,4,0),"") | M15: =IFERROR(_xlfn.RANK.EQ(L15,L:L),"") | N15: ECONOMICS | T15: mscore
A16: AMERICAN ECONOMIC JOURNAL-APPLIED ECONOMICS | B16: AMER ECONOMIC ASSOC | C16: 43 | D16: =IFERROR(VLOOKUP(A16,eco_bus_journals!A:D,4,0),"") -> 3.77 | E16: =_xlfn.RANK.EQ(D16,D:D) -> 13 | F16: =IFERROR(VLOOKUP(A16,eco_journals!A:D,4,0),"") -> 3.88 | G16: =IFERROR(_xlfn.RANK.EQ(F16,F:F),"") -> 8 | H16: =IFERROR(VLOOKUP(A16,fin_journals!A:D,4,0),"") | I16: =IFERROR(_xlfn.RANK.EQ(H16,H:H),"") | J16: =IFERROR(VLOOKUP(A16,bus_journals!A:D,4,0),"") | K16: =IFERROR(_xlfn.RANK.EQ(J16,J:J),"") | L16: =IFERROR(VLOOKUP(A16,man_journals!A:D,4,0),"") | M16: =IFERROR(_xlfn.RANK.EQ(L16,L:L),"") | N16: ECONOMICS | T16: mrank
A17: AMERICAN ECONOMIC JOURNAL-MACROECONOMICS | B17: AMER ECONOMIC ASSOC | C17: 38 | D17: =IFERROR(VLOOKUP(A17,eco_bus_journals!A:D,4,0),"") -> 3.71 | E17: =_xlfn.RANK.EQ(D17,D:D) -> 14 | F17: =IFERROR(VLOOKUP(A17,eco_journals!A:D,4,0),"") -> 3.8 | G17: =IFERROR(_xlfn.RANK.EQ(F17,F:F),"") -> 9 | H17: =IFERROR(VLOOKUP(A17,fin_journals!A:D,4,0),"") | I17: =IFERROR(_xlfn.RANK.EQ(H17,H:H),"") | J17: =IFERROR(VLOOKUP(A17,bus_journals!A:D,4,0),"") | K17: =IFERROR(_xlfn.RANK.EQ(J17,J:J),"") | L17: =IFERROR(VLOOKUP(A17,man_journals!A:D,4,0),"") | M17: =IFERROR(_xlfn.RANK.EQ(L17,L:L),"") | N17: ECONOMICS | T17: wc1
A18: REVIEW OF FINANCIAL STUDIES | B18: OXFORD UNIV PRESS INC | C18: 141 | D18: =IFERROR(VLOOKUP(A18,eco_bus_journals!A:D,4,0),"") -> 3.56 | E18: =_xlfn.RANK.EQ(D18,D:D) -> 15 | F18: =IFERROR(VLOOKUP(A18,eco_journals!A:D,4,0),"") -> 1.99 | G18: =IFERROR(_xlfn.RANK.EQ(F18,F:F),"") -> 19 | H18: =IFERROR(VLOOKUP(A18,fin_journals!A:D,4,0),"") -> 7.73 | I18: =IFERROR(_xlfn.RANK.EQ(H18,H:H),"") -> 4 | J18: =IFERROR(VLOOKUP(A18,bus_journals!A:D,4,0),"") | K18: =IFERROR(_xlfn.RANK.EQ(J18,J:J),"") | L18: =IFERROR(VLOOKUP(A18,man_journals!A:D,4,0),"") | M18: =IFERROR(_xlfn.RANK.EQ(L18,L:L),"") | N18: FINANCE | O18: ECONOMICS | T18: wc2
A19: ACADEMY OF MANAGEMENT REVIEW | B19: ACAD MANAGEMENT | C19: 40 | D19: =IFERROR(VLOOKUP(A19,eco_bus_journals!A:D,4,0),"") -> 3.53 | E19: =_xlfn.RANK.EQ(D19,D:D) -> 16 | F19: =IFERROR(VLOOKUP(A19,eco_journals!A:D,4,0),"") | G19: =IFERROR(_xlfn.RANK.EQ(F19,F:F),"") | H19: =IFERROR(VLOOKUP(A19,fin_journals!A:D,4,0),"") | I19: =IFERROR(_xlfn.RANK.EQ(H19,H:H),"") | J19: =IFERROR(VLOOKUP(A19,bus_journals!A:D,4,0),"") -> 6.21 | K19: =IFERROR(_xlfn.RANK.EQ(J19,J:J),"") -> 5 | L19: =IFERROR(VLOOKUP(A19,man_journals!A:D,4,0),"") -> 5.92 | M19: =IFERROR(_xlfn.RANK.EQ(L19,L:L),"") -> 4 | N19: BUSINESS | O19: MANAGEMENT | T19: wc3
A20: ANNUAL REVIEW OF ECONOMICS | B20: ANNUAL REVIEWS | C20: 31 | D20: =IFERROR(VLOOKUP(A20,eco_bus_journals!A:D,4,0),"") -> 3.36 | E20: =_xlfn.RANK.EQ(D20,D:D) -> 17 | F20: =IFERROR(VLOOKUP(A20,eco_journals!A:D,4,0),"") -> 3.44 | G20: =IFERROR(_xlfn.RANK.EQ(F20,F:F),"") -> 12 | H20: =IFERROR(VLOOKUP(A20,fin_journals!A:D,4,0),"") | I20: =IFERROR(_xlfn.RANK.EQ(H20,H:H),"") | J20: =IFERROR(VLOOKUP(A20,bus_journals!A:D,4,0),"") | K20: =IFERROR(_xlfn.RANK.EQ(J20,J:J),"") | L20: =IFERROR(VLOOKUP(A20,man_journals!A:D,4,0),"") | M20: =IFERROR(_xlfn.RANK.EQ(L20,L:L),"") | N20: ECONOMICS | T20: wc4
A21: JOURNAL OF FINANCIAL ECONOMICS | B21: ELSEVIER | C21: 152 | D21: =IFERROR(VLOOKUP(A21,eco_bus_journals!A:D,4,0),"") -> 3.17 | E21: =_xlfn.RANK.EQ(D21,D:D) -> 18 | F21: =IFERROR(VLOOKUP(A21,eco_journals!A:D,4,0),"") -> 1.67 | G21: =IFERROR(_xlfn.RANK.EQ(F21,F:F),"") -> 22 | H21: =IFERROR(VLOOKUP(A21,fin_journals!A:D,4,0),"") -> 6.64 | I21: =IFERROR(_xlfn.RANK.EQ(H21,H:H),"") -> 5 | J21: =IFERROR(VLOOKUP(A21,bus_journals!A:D,4,0),"") | K21: =IFERROR(_xlfn.RANK.EQ(J21,J:J),"") | L21: =IFERROR(VLOOKUP(A21,man_journals!A:D,4,0),"") | M21: =IFERROR(_xlfn.RANK.EQ(L21,L:L),"") | N21: FINANCE | O21: ECONOMICS | T21: wc5
A22: STRATEGIC MANAGEMENT JOURNAL | B22: WILEY | C22: 121 | D22: =IFERROR(VLOOKUP(A22,eco_bus_journals!A:D,4,0),"") -> 2.98 | E22: =_xlfn.RANK.EQ(D22,D:D) -> 19 | F22: =IFERROR(VLOOKUP(A22,eco_journals!A:D,4,0),"") | G22: =IFERROR(_xlfn.RANK.EQ(F22,F:F),"") | H22: =IFERROR(VLOOKUP(A22,fin_journals!A:D,4,0),"") | I22: =IFERROR(_xlfn.RANK.EQ(H22,H:H),"") | J22: =IFERROR(VLOOKUP(A22,bus_journals!A:D,4,0),"") -> 4.86 | K22: =IFERROR(_xlfn.RANK.EQ(J22,J:J),"") -> 7 | L22: =IFERROR(VLOOKUP(A22,man_journals!A:D,4,0),"") -> 4.38 | M22: =IFERROR(_xlfn.RANK.EQ(L22,L:L),"") -> 5 | N22: BUSINESS | O22: MANAGEMENT | T22: wc6
A23: JOURNAL OF MARKETING | B23: SAGE PUBLICATIONS | C23: 65 | D23: =IFERROR(VLOOKUP(A23,eco_bus_journals!A:D,4,0),"") -> 2.97 | E23: =_xlfn.RANK.EQ(D23,D:D) -> 20 | F23: =IFERROR(VLOOKUP(A23,eco_journals!A:D,4,0),"") | G23: =IFERROR(_xlfn.RANK.EQ(F23,F:F),"") | H23: =IFERROR(VLOOKUP(A23,fin_journals!A:D,4,0),"") | I23: =IFERROR(_xlfn.RANK.EQ(H23,H:H),"") | J23: =IFERROR(VLOOKUP(A23,bus_journals!A:D,4,0),"") -> 7.99 | K23: =IFERROR(_xlfn.RANK.EQ(J23,J:J),"") -> 3 | L23: =IFERROR(VLOOKUP(A23,man_journals!A:D,4,0),"") | M23: =IFERROR(_xlfn.RANK.EQ(L23,L:L),"") | N23: BUSINESS
A24: JOURNAL OF ECONOMIC PERSPECTIVES | B24: AMER ECONOMIC ASSOC | C24: 41 | D24: =IFERROR(VLOOKUP(A24,eco_bus_journals!A:D,4,0),"") -> 2.9 | E24: =_xlfn.RANK.EQ(D24,D:D) -> 21 | F24: =IFERROR(VLOOKUP(A24,eco_journals!A:D,4,0),"") -> 2.67 | G24: =IFERROR(_xlfn.RANK.EQ(F24,F:F),"") -> 14 | H24: =IFERROR(VLOOKUP(A24,fin_journals!A:D,4,0),"") | I24: =IFERROR(_xlfn.RANK.EQ(H24,H:H),"") | J24: =IFERROR(VLOOKUP(A24,bus_journals!A:D,4,0),"") | K24: =IFERROR(_xlfn.RANK.EQ(J24,J:J),"") | L24: =IFERROR(VLOOKUP(A24,man_journals!A:D,4,0),"") | M24: =IFERROR(_xlfn.RANK.EQ(L24,L:L),"") | N24: ECONOMICS
A25: BROOKINGS PAPERS ON ECONOMIC ACTIVITY | B25: JOHNS HOPKINS UNIV PRESS | C25: 24 | D25: =IFERROR(VLOOKUP(A25,eco_bus_journals!A:D,4,0),"") -> 2.83 | E25: =_xlfn.RANK.EQ(D25,D:D) -> 22 | F25: =IFERROR(VLOOKUP(A25,eco_journals!A:D,4,0),"") -> 2.68 | G25: =IFERROR(_xlfn.RANK.EQ(F25,F:F),"") -> 13 | H25: =IFERROR(VLOOKUP(A25,fin_journals!A:D,4,0),"") | I25: =IFERROR(_xlfn.RANK.EQ(H25,H:H),"") | J25: =IFERROR(VLOOKUP(A25,bus_journals!A:D,4,0),"") | K25: =IFERROR(_xlfn.RANK.EQ(J25,J:J),"") | L25: =IFERROR(VLOOKUP(A25,man_journals!A:D,4,0),"") | M25: =IFERROR(_xlfn.RANK.EQ(L25,L:L),"") | N25: ECONOMICS
A26: JOURNAL OF MANAGEMENT | B26: SAGE PUBLICATIONS | C26: 88 | D26: =IFERROR(VLOOKUP(A26,eco_bus_journals!A:D,4,0),"") -> 2.8 | E26: =_xlfn.RANK.EQ(D26,D:D) -> 23 | F26: =IFERROR(VLOOKUP(A26,eco_journals!A:D,4,0),"") | G26: =IFERROR(_xlfn.RANK.EQ(F26,F:F),"") | H26: =IFERROR(VLOOKUP(A26,fin_journals!A:D,4,0),"") | I26: =IFERROR(_xlfn.RANK.EQ(H26,H:H),"") | J26: =IFERROR(VLOOKUP(A26,bus_journals!A:D,4,0),"") -> 4.79 | K26: =IFERROR(_xlfn.RANK.EQ(J26,J:J),"") -> 9 | L26: =IFERROR(VLOOKUP(A26,man_journals!A:D,4,0),"") -> 3.91 | M26: =IFERROR(_xlfn.RANK.EQ(L26,L:L),"") -> 8 | N26: BUSINESS | O26: MANAGEMENT | P26: PSYCHOLOGY, APPLIED
A27: AMERICAN ECONOMIC JOURNAL-ECONOMIC POLICY | B27: AMER ECONOMIC ASSOC | C27: 51 | D27: =IFERROR(VLOOKUP(A27,eco_bus_journals!A:D,4,0),"") -> 2.79 | E27: =_xlfn.RANK.EQ(D27,D:D) -> 24 | F27: =IFERROR(VLOOKUP(A27,eco_journals!A:D,4,0),"") -> 2.67 | G27: =IFERROR(_xlfn.RANK.EQ(F27,F:F),"") -> 14 | H27: =IFERROR(VLOOKUP(A27,fin_journals!A:D,4,0),"") | I27: =IFERROR(_xlfn.RANK.EQ(H27,H:H),"") | J27: =IFERROR(VLOOKUP(A27,bus_journals!A:D,4,0),"") | K27: =IFERROR(_xlfn.RANK.EQ(J27,J:J),"") | L27: =IFERROR(VLOOKUP(A27,man_journals!A:D,4,0),"") | M27: =IFERROR(_xlfn.RANK.EQ(L27,L:L),"") | N27: ECONOMICS
A28: ACADEMY OF MANAGEMENT PERSPECTIVES | B28: ACAD MANAGEMENT | C28: 30 | D28: =IFERROR(VLOOKUP(A28,eco_bus_journals!A:D,4,0),"") -> 2.6 | E28: =_xlfn.RANK.EQ(D28,D:D) -> 25 | F28: =IFERROR(VLOOKUP(A28,eco_journals!A:D,4,0),"") | G28: =IFERROR(_xlfn.RANK.EQ(F28,F:F),"") | H28: =IFERROR(VLOOKUP(A28,fin_journals!A:D,4,0),"") | I28: =IFERROR(_xlfn.RANK.EQ(H28,H:H),"") | J28: =IFERROR(VLOOKUP(A28,bus_journals!A:D,4,0),"") -> 4.85 | K28: =IFERROR(_xlfn.RANK.EQ(J28,J:J),"") -> 8 | L28: =IFERROR(VLOOKUP(A28,man_journals!A:D,4,0),"") -> 3.37 | M28: =IFERROR(_xlfn.RANK.EQ(L28,L:L),"") -> 9 | N28: BUSINESS | O28: MANAGEMENT
A29: ORGANIZATION SCIENCE | B29: INFORMS | C29: 74 | D29: =IFERROR(VLOOKUP(A29,eco_bus_journals!A:D,4,0),"") -> 2.55 | E29: =_xlfn.RANK.EQ(D29,D:D) -> 26 | F29: =IFERROR(VLOOKUP(A29,eco_journals!A:D,4,0),"") | G29: =IFERROR(_xlfn.RANK.EQ(F29,F:F),"") | H29: =IFERROR(VLOOKUP(A29,fin_journals!A:D,4,0),"") | I29: =IFERROR(_xlfn.RANK.EQ(H29,H:H),"") | J29: =IFERROR(VLOOKUP(A29,bus_journals!A:D,4,0),"") | K29: =IFERROR(_xlfn.RANK.EQ(J29,J:J),"") | L29: =IFERROR(VLOOKUP(A29,man_journals!A:D,4,0),"") -> 4.38 | M29: =IFERROR(_xlfn.RANK.EQ(L29,L:L),"") -> 5 | N29: MANAGEMENT
A30: JOURNAL OF ACCOUNTING & ECONOMICS | B30: ELSEVIER | C30: 35 | D30: =IFERROR(VLOOKUP(A30,eco_bus_journals!A:D,4,0),"") -> 2.46 | E30: =_xlfn.RANK.EQ(D30,D:D) -> 27 | F30: =IFERROR(VLOOKUP(A30,eco_journals!A:D,4,0),"") -> 0.54 | G30: =IFERROR(_xlfn.RANK.EQ(F30,F:F),"") -> 44 | H30: =IFERROR(VLOOKUP(A30,fin_journals!A:D,4,0),"") -> 9.8 | I30: =IFERROR(_xlfn.RANK.EQ(H30,H:H),"") -> 2 | J30: =IFERROR(VLOOKUP(A30,bus_journals!A:D,4,0),"") | K30: =IFERROR(_xlfn.RANK.EQ(J30,J:J),"") | L30: =IFERROR(VLOOKUP(A30,man_journals!A:D,4,0),"") | M30: =IFERROR(_xlfn.RANK.EQ(L30,L:L),"") | N30: FINANCE | O30: ECONOMICS
A31: ACADEMY OF MANAGEMENT DISCOVERIES | B31: ACAD MANAGEMENT | C31: 32 | D31: =IFERROR(VLOOKUP(A31,eco_bus_journals!A:D,4,0),"") -> 2.39 | E31: =_xlfn.RANK.EQ(D31,D:D) -> 28 | F31: =IFERROR(VLOOKUP(A31,eco_journals!A:D,4,0),"") | G31: =IFERROR(_xlfn.RANK.EQ(F31,F:F),"") | H31: =IFERROR(VLOOKUP(A31,fin_journals!A:D,4,0),"") | I31: =IFERROR(_xlfn.RANK.EQ(H31,H:H),"") | J31: =IFERROR(VLOOKUP(A31,bus_journals!A:D,4,0),"") | K31: =IFERROR(_xlfn.RANK.EQ(J31,J:J),"") | L31: =IFERROR(VLOOKUP(A31,man_journals!A:D,4,0),"") -> 4.03 | M31: =IFERROR(_xlfn.RANK.EQ(L31,L:L),"") -> 7 | N31: MANAGEMENT
A32: JOURNAL OF MANAGEMENT STUDIES | B32: WILEY | C32: 93 | D32: =IFERROR(VLOOKUP(A32,eco_bus_journals!A:D,4,0),"") -> 2.39 | E32: =_xlfn.RANK.EQ(D32,D:D) -> 28 | F32: =IFERROR(VLOOKUP(A32,eco_journals!A:D,4,0),"") | G32: =IFERROR(_xlfn.RANK.EQ(F32,F:F),"") | H32: =IFERROR(VLOOKUP(A32,fin_journals!A:D,4,0),"") | I32: =IFERROR(_xlfn.RANK.EQ(H32,H:H),"") | J32: =IFERROR(VLOOKUP(A32,bus_journals!A:D,4,0),"") -> 4.28 | K32: =IFERROR(_xlfn.RANK.EQ(J32,J:J),"") -> 11 | L32: =IFERROR(VLOOKUP(A32,man_journals!A:D,4,0),"") -> 3.29 | M32: =IFERROR(_xlfn.RANK.EQ(L32,L:L),"") -> 10 | N32: BUSINESS | O32: MANAGEMENT
A33: JOURNAL OF LABOR ECONOMICS | B33: UNIV CHICAGO PRESS | C33: 32 | D33: =IFERROR(VLOOKUP(A33,eco_bus_journals!A:D,4,0),"") -> 2.32 | E33: =_xlfn.RANK.EQ(D33,D:D) -> 30 | F33: =IFERROR(VLOOKUP(A33,eco_journals!A:D,4,0),"") -> 2.37 | G33: =IFERROR(_xlfn.RANK.EQ(F33,F:F),"") -> 16 | H33: =IFERROR(VLOOKUP(A33,fin_journals!A:D,4,0),"") | I33: =IFERROR(_xlfn.RANK.EQ(H33,H:H),"") | J33: =IFERROR(VLOOKUP(A33,bus_journals!A:D,4,0),"") | K33: =IFERROR(_xlfn.RANK.EQ(J33,J:J),"") | L33: =IFERROR(VLOOKUP(A33,man_journals!A:D,4,0),"") | M33: =IFERROR(_xlfn.RANK.EQ(L33,L:L),"") | N33: ECONOMICS | O33: INDUSTRIAL RELATIONS & LABOR
A34: REVIEW OF ECONOMICS AND STATISTICS | B34: MIT PRESS | C34: 65 | D34: =IFERROR(VLOOKUP(A34,eco_bus_journals!A:D,4,0),"") -> 2.31 | E34: =_xlfn.RANK.EQ(D34,D:D) -> 31 | F34: =IFERROR(VLOOKUP(A34,eco_journals!A:D,4,0),"") -> 2.37 | G34: =IFERROR(_xlfn.RANK.EQ(F34,F:F),"") -> 16 | H34: =IFERROR(VLOOKUP(A34,fin_journals!A:D,4,0),"") | I34: =IFERROR(_xlfn.RANK.EQ(H34,H:H),"") | J34: =IFERROR(VLOOKUP(A34,bus_journals!A:D,4,0),"") | K34: =IFERROR(_xlfn.RANK.EQ(J34,J:J),"") | L34: =IFERROR(VLOOKUP(A34,man_journals!A:D,4,0),"") | M34: =IFERROR(_xlfn.RANK.EQ(L34,L:L),"") | N34: ECONOMICS | O34: SOCIAL SCIENCES, MATHEMATICAL METHODS
A35: JOURNAL OF ACCOUNTING RESEARCH | B35: WILEY | C35: 34 | D35: =IFERROR(VLOOKUP(A35,eco_bus_journals!A:D,4,0),"") -> 2.21 | E35: =_xlfn.RANK.EQ(D35,D:D) -> 32 | F35: =IFERROR(VLOOKUP(A35,eco_journals!A:D,4,0),"") | G35: =IFERROR(_xlfn.RANK.EQ(F35,F:F),"") | H35: =IFERROR(VLOOKUP(A35,fin_journals!A:D,4,0),"") -> 10 | I35: =IFERROR(_xlfn.RANK.EQ(H35,H:H),"") -> 1 | J35: =IFERROR(VLOOKUP(A35,bus_journals!A:D,4,0),"") | K35: =IFERROR(_xlfn.RANK.EQ(J35,J:J),"") | L35: =IFERROR(VLOOKUP(A35,man_journals!A:D,4,0),"") | M35: =IFERROR(_xlfn.RANK.EQ(L35,L:L),"") | N35: FINANCE
A36: JOURNAL OF THE ACADEMY OF MARKETING SCIENCE | B36: SPRINGER | C36: 71 | D36: =IFERROR(VLOOKUP(A36,eco_bus_journals!A:D,4,0),"") -> 2.18 | E36: =_xlfn.RANK.EQ(D36,D:D) -> 33 | F36: =IFERROR(VLOOKUP(A36,eco_journals!A:D,4,0),"") | G36: =IFERROR(_xlfn.RANK.EQ(F36,F:F),"") | H36: =IFERROR(VLOOKUP(A36,fin_journals!A:D,4,0),"") | I36: =IFERROR(_xlfn.RANK.EQ(H36,H:H),"") | J36: =IFERROR(VLOOKUP(A36,bus_journals!A:D,4,0),"") -> 5.13 | K36: =IFERROR(_xlfn.RANK.EQ(J36,J:J),"") -> 6 | L36: =IFERROR(VLOOKUP(A36,man_journals!A:D,4,0),"") | M36: =IFERROR(_xlfn.RANK.EQ(L36,L:L),"") | N36: BUSINESS
A37: JOURNAL OF BUSINESS VENTURING | B37: ELSEVIER | C37: 60 | D37: =IFERROR(VLOOKUP(A37,eco_bus_journals!A:D,4,0),"") -> 2.16 | E37: =_xlfn.RANK.EQ(D37,D:D) -> 34 | F37: =IFERROR(VLOOKUP(A37,eco_journals!A:D,4,0),"") | G37: =IFERROR(_xlfn.RANK.EQ(F37,F:F),"") | H37: =IFERROR(VLOOKUP(A37,fin_journals!A:D,4,0),"") | I37: =IFERROR(_xlfn.RANK.EQ(H37,H:H),"") | J37: =IFERROR(VLOOKUP(A37,bus_journals!A:D,4,0),"") -> 4.31 | K37: =IFERROR(_xlfn.RANK.EQ(J37,J:J),"") -> 10 | L37: =IFERROR(VLOOKUP(A37,man_journals!A:D,4,0),"") | M37: =IFERROR(_xlfn.RANK.EQ(L37,L:L),"") | N37: BUSINESS
A38: STRATEGIC ENTREPRENEURSHIP JOURNAL | B38: WILEY | C38: 45 | D38: =IFERROR(VLOOKUP(A38,eco_bus_journals!A:D,4,0),"") -> 2.12 | E38: =_xlfn.RANK.EQ(D38,D:D) -> 35 | F38: =IFERROR(VLOOKUP(A38,eco_journals!A:D,4,0),"") | G38: =IFERROR(_xlfn.RANK.EQ(F38,F:F),"") | H38: =IFERROR(VLOOKUP(A38,fin_journals!A:D,4,0),"") | I38: =IFERROR(_xlfn.RANK.EQ(H38,H:H),"") | J38: =IFERROR(VLOOKUP(A38,bus_journals!A:D,4,0),"") -> 4.19 | K38: =IFERROR(_xlfn.RANK.EQ(J38,J:J),"") -> 12 | L38: =IFERROR(VLOOKUP(A38,man_journals!A:D,4,0),"") -> 2.49 | M38: =IFERROR(_xlfn.RANK.EQ(L38,L:L),"") -> 14 | N38: BUSINESS | O38: MANAGEMENT
A39: ENTREPRENEURSHIP THEORY AND PRACTICE | B39: SAGE PUBLICATIONS | C39: 91 | D39: =IFERROR(VLOOKUP(A39,eco_bus_journals!A:D,4,0),"") -> 2.11 | E39: =_xlfn.RANK.EQ(D39,D:D) -> 36 | F39: =IFERROR(VLOOKUP(A39,eco_journals!A:D,4,0),"") | G39: =IFERROR(_xlfn.RANK.EQ(F39,F:F),"") | H39: =IFERROR(VLOOKUP(A39,fin_journals!A:D,4,0),"") | I39: =IFERROR(_xlfn.RANK.EQ(H39,H:H),"") | J39: =IFERROR(VLOOKUP(A39,bus_journals!A:D,4,0),"") -> 4.15 | K39: =IFERROR(_xlfn.RANK.EQ(J39,J:J),"") -> 13 | L39: =IFERROR(VLOOKUP(A39,man_journals!A:D,4,0),"") | M39: =IFERROR(_xlfn.RANK.EQ(L39,L:L),"") | N39: BUSINESS
A40: ORGANIZATIONAL RESEARCH METHODS | B40: SAGE PUBLICATIONS | C40: 58 | D40: =IFERROR(VLOOKUP(A40,eco_bus_journals!A:D,4,0),"") -> 2.06 | E40: =_xlfn.RANK.EQ(D40,D:D) -> 37 | F40: =IFERROR(VLOOKUP(A40,eco_journals!A:D,4,0),"") | G40: =IFERROR(_xlfn.RANK.EQ(F40,F:F),"") | H40: =IFERROR(VLOOKUP(A40,fin_journals!A:D,4,0),"") | I40: =IFERROR(_xlfn.RANK.EQ(H40,H:H),"") | J40: =IFERROR(VLOOKUP(A40,bus_journals!A:D,4,0),"") | K40: =IFERROR(_xlfn.RANK.EQ(J40,J:J),"") | L40: =IFERROR(VLOOKUP(A40,man_journals!A:D,4,0),"") -> 3.28 | M40: =IFERROR(_xlfn.RANK.EQ(L40,L:L),"") -> 11 | N40: MANAGEMENT | O40: PSYCHOLOGY, APPLIED
A41: JOURNAL OF THE EUROPEAN ECONOMIC ASSOCIATION | B41: OXFORD UNIV PRESS | C41: 84 | D41: =IFERROR(VLOOKUP(A41,eco_bus_journals!A:D,4,0),"") -> 2.04 | E41: =_xlfn.RANK.EQ(D41,D:D) -> 38 | F41: =IFERROR(VLOOKUP(A41,eco_journals!A:D,4,0),"") -> 2.15 | G41: =IFERROR(_xlfn.RANK.EQ(F41,F:F),"") -> 18 | H41: =IFERROR(VLOOKUP(A41,fin_journals!A:D,4,0),"") | I41: =IFERROR(_xlfn.RANK.EQ(H41,H:H),"") | J41: =IFERROR(VLOOKUP(A41,bus_journals!A:D,4,0),"") | K41: =IFERROR(_xlfn.RANK.EQ(J41,J:J),"") | L41: =IFERROR(VLOOKUP(A41,man_journals!A:D,4,0),"") | M41: =IFERROR(_xlfn.RANK.EQ(L41,L:L),"") | N41: ECONOMICS
A42: JOURNAL OF PUBLIC ECONOMICS | B42: ELSEVIER | C42: 133 | D42: =IFERROR(VLOOKUP(A42,eco_bus_journals!A:D,4,0),"") -> 1.94 | E42: =_xlfn.RANK.EQ(D42,D:D) -> 39 | F42: =IFERROR(VLOOKUP(A42,eco_journals!A:D,4,0),"") -> 1.87 | G42: =IFERROR(_xlfn.RANK.EQ(F42,F:F),"") -> 20 | H42: =IFERROR(VLOOKUP(A42,fin_journals!A:D,4,0),"") | I42: =IFERROR(_xlfn.RANK.EQ(H42,H:H),"") | J42: =IFERROR(VLOOKUP(A42,bus_journals!A:D,4,0),"") | K42: =IFERROR(_xlfn.RANK.EQ(J42,J:J),"") | L42: =IFERROR(VLOOKUP(A42,man_journals!A:D,4,0),"") | M42: =IFERROR(_xlfn.RANK.EQ(L42,L:L),"") | N42: ECONOMICS
A43: JOURNAL OF INTERNATIONAL BUSINESS STUDIES | B43: PALGRAVE MACMILLAN LTD | C43: 92 | D43: =IFERROR(VLOOKUP(A43,eco_bus_journals!A:D,4,0),"") -> 1.93 | E43: =_xlfn.RANK.EQ(D43,D:D) -> 40 | F43: =IFERROR(VLOOKUP(A43,eco_journals!A:D,4,0),"") | G43: =IFERROR(_xlfn.RANK.EQ(F43,F:F),"") | H43: =IFERROR(VLOOKUP(A43,fin_journals!A:D,4,0),"") | I43: =IFERROR(_xlfn.RANK.EQ(H43,H:H),"") | J43: =IFERROR(VLOOKUP(A43,bus_journals!A:D,4,0),"") -> 3.31 | K43: =IFERROR(_xlfn.RANK.EQ(J43,J:J),"") -> 15 | L43: =IFERROR(VLOOKUP(A43,man_journals!A:D,4,0),"") -> 1.78 | M43: =IFERROR(_xlfn.RANK.EQ(L43,L:L),"") -> 19 | N43: BUSINESS | O43: MANAGEMENT
A44: JOURNAL OF MONETARY ECONOMICS | B44: ELSEVIER | C44: 102 | D44: =IFERROR(VLOOKUP(A44,eco_bus_journals!A:D,4,0),"") -> 1.8 | E44: =_xlfn.RANK.EQ(D44,D:D) -> 41 | F44: =IFERROR(VLOOKUP(A44,eco_journals!A:D,4,0),"") -> 1.75 | G44: =IFERROR(_xlfn.RANK.EQ(F44,F:F),"") -> 21 | H44: =IFERROR(VLOOKUP(A44,fin_journals!A:D,4,0),"") -> 1.1 | I44: =IFERROR(_xlfn.RANK.EQ(H44,H:H),"") -> 16 | J44: =IFERROR(VLOOKUP(A44,bus_journals!A:D,4,0),"") | K44: =IFERROR(_xlfn.RANK.EQ(J44,J:J),"") | L44: =IFERROR(VLOOKUP(A44,man_journals!A:D,4,0),"") | M44: =IFERROR(_xlfn.RANK.EQ(L44,L:L),"") | N44: FINANCE | O44: ECONOMICS
A45: JOURNAL OF PRODUCT INNOVATION MANAGEMENT | B45: WILEY | C45: 25 | D45: =IFERROR(VLOOKUP(A45,eco_bus_journals!A:D,4,0),"") -> 1.75 | E45: =_xlfn.RANK.EQ(D45,D:D) -> 42 | F45: =IFERROR(VLOOKUP(A45,eco_journals!A:D,4,0),"") | G45: =IFERROR(_xlfn.RANK.EQ(F45,F:F),"") | H45: =IFERROR(VLOOKUP(A45,fin_journals!A:D,4,0),"") | I45: =IFERROR(_xlfn.RANK.EQ(H45,H:H),"") | J45: =IFERROR(VLOOKUP(A45,bus_journals!A:D,4,0),"") -> 3.04 | K45: =IFERROR(_xlfn.RANK.EQ(J45,J:J),"") -> 20 | L45: =IFERROR(VLOOKUP(A45,man_journals!A:D,4,0),"") -> 1.83 | M45: =IFERROR(_xlfn.RANK.EQ(L45,L:L),"") -> 17 | N45: BUSINESS | O45: ENGINEERING, INDUSTRIAL | P45: MANAGEMENT
A46: ORGANIZATION STUDIES | B46: SAGE PUBLICATIONS | C46: 90 | D46: =IFERROR(VLOOKUP(A46,eco_bus_journals!A:D,4,0),"") -> 1.73 | E46: =_xlfn.RANK.EQ(D46,D:D) -> 43 | F46: =IFERROR(VLOOKUP(A46,eco_journals!A:D,4,0),"") | G46: =IFERROR(_xlfn.RANK.EQ(F46,F:F),"") | H46: =IFERROR(VLOOKUP(A46,fin_journals!A:D,4,0),"") | I46: =IFERROR(_xlfn.RANK.EQ(H46,H:H),"") | J46: =IFERROR(VLOOKUP(A46,bus_journals!A:D,4,0),"") | K46: =IFERROR(_xlfn.RANK.EQ(J46,J:J),"") | L46: =IFERROR(VLOOKUP(A46,man_journals!A:D,4,0),"") -> 3.06 | M46: =IFERROR(_xlfn.RANK.EQ(L46,L:L),"") -> 12 | N46: MANAGEMENT
A47: JOURNAL OF FINANCIAL INTERMEDIATION | B47: ELSEVIER | C47: 26 | D47: =IFERROR(VLOOKUP(A47,eco_bus_journals!A:D,4,0),"") -> 1.66 | E47: =_xlfn.RANK.EQ(D47,D:D) -> 44 | F47: =IFERROR(VLOOKUP(A47,eco_journals!A:D,4,0),"") | G47: =IFERROR(_xlfn.RANK.EQ(F47,F:F),"") | H47: =IFERROR(VLOOKUP(A47,fin_journals!A:D,4,0),"") -> 2.99 | I47: =IFERROR(_xlfn.RANK.EQ(H47,H:H),"") -> 10 | J47: =IFERROR(VLOOKUP(A47,bus_journals!A:D,4,0),"") | K47: =IFERROR(_xlfn.RANK.EQ(J47,J:J),"") | L47: =IFERROR(VLOOKUP(A47,man_journals!A:D,4,0),"") | M47: =IFERROR(_xlfn.RANK.EQ(L47,L:L),"") | N47: FINANCE
A48: REVIEW OF FINANCE | B48: OXFORD UNIV PRESS | C48: 17 | D48: =IFERROR(VLOOKUP(A48,eco_bus_journals!A:D,4,0),"") -> 1.65 | E48: =_xlfn.RANK.EQ(D48,D:D) -> 45 | F48: =IFERROR(VLOOKUP(A48,eco_journals!A:D,4,0),"") -> 0.59 | G48: =IFERROR(_xlfn.RANK.EQ(F48,F:F),"") -> 42 | H48: =IFERROR(VLOOKUP(A48,fin_journals!A:D,4,0),"") -> 3.36 | I48: =IFERROR(_xlfn.RANK.EQ(H48,H:H),"") -> 8 | J48: =IFERROR(VLOOKUP(A48,bus_journals!A:D,4,0),"") | K48: =IFERROR(_xlfn.RANK.EQ(J48,J:J),"") | L48: =IFERROR(VLOOKUP(A48,man_journals!A:D,4,0),"") | M48: =IFERROR(_xlfn.RANK.EQ(L48,L:L),"") | N48: FINANCE | O48: ECONOMICS
A49: INTERNATIONAL JOURNAL OF MANAGEMENT REVIEWS | B49: WILEY | C49: 21 | D49: =IFERROR(VLOOKUP(A49,eco_bus_journals!A:D,4,0),"") -> 1.63 | E49: =_xlfn.RANK.EQ(D49,D:D) -> 46 | F49: =IFERROR(VLOOKUP(A49,eco_journals!A:D,4,0),"") | G49: =IFERROR(_xlfn.RANK.EQ(F49,F:F),"") | H49: =IFERROR(VLOOKUP(A49,fin_journals!A:D,4,0),"") | I49: =IFERROR(_xlfn.RANK.EQ(H49,H:H),"") | J49: =IFERROR(VLOOKUP(A49,bus_journals!A:D,4,0),"") -> 2.29 | K49: =IFERROR(_xlfn.RANK.EQ(J49,J:J),"") -> 25 | L49: =IFERROR(VLOOKUP(A49,man_journals!A:D,4,0),"") -> 1.81 | M49: =IFERROR(_xlfn.RANK.EQ(L49,L:L),"") -> 18 | N49: BUSINESS | O49: MANAGEMENT
A50: JOURNAL OF SERVICE RESEARCH | B50: SAGE PUBLICATIONS | C50: 42 | D50: =IFERROR(VLOOKUP(A50,eco_bus_journals!A:D,4,0),"") -> 1.62 | E50: =_xlfn.RANK.EQ(D50,D:D) -> 47 | F50: =IFERROR(VLOOKUP(A50,eco_journals!A:D,4,0),"") | G50: =IFERROR(_xlfn.RANK.EQ(F50,F:F),"") | H50: =IFERROR(VLOOKUP(A50,fin_journals!A:D,4,0),"") | I50: =IFERROR(_xlfn.RANK.EQ(H50,H:H),"") | J50: =IFERROR(VLOOKUP(A50,bus_journals!A:D,4,0),"") -> 3.29 | K50: =IFERROR(_xlfn.RANK.EQ(J50,J:J),"") -> 16 | L50: =IFERROR(VLOOKUP(A50,man_journals!A:D,4,0),"") | M50: =IFERROR(_xlfn.RANK.EQ(L50,L:L),"") | N50: BUSINESS
A51: GLOBAL STRATEGY JOURNAL | B51: WILEY | C51: 33 | D51: =IFERROR(VLOOKUP(A51,eco_bus_journals!A:D,4,0),"") -> 1.49 | E51: =_xlfn.RANK.EQ(D51,D:D) -> 48 | F51: =IFERROR(VLOOKUP(A51,eco_journals!A:D,4,0),"") | G51: =IFERROR(_xlfn.RANK.EQ(F51,F:F),"") | H51: =IFERROR(VLOOKUP(A51,fin_journals!A:D,4,0),"") | I51: =IFERROR(_xlfn.RANK.EQ(H51,H:H),"") | J51: =IFERROR(VLOOKUP(A51,bus_journals!A:D,4,0),"") -> 2.6 | K51: =IFERROR(_xlfn.RANK.EQ(J51,J:J),"") -> 21 | L51: =IFERROR(VLOOKUP(A51,man_journals!A:D,4,0),"") -> 1.22 | M51: =IFERROR(_xlfn.RANK.EQ(L51,L:L),"") -> 25 | N51: BUSINESS | O51: MANAGEMENT
A52: IMF ECONOMIC REVIEW | B52: PALGRAVE MACMILLAN LTD | C52: 21 | D52: =IFERROR(VLOOKUP(A52,eco_bus_journals!A:D,4,0),"") -> 1.49 | E52: =_xlfn.RANK.EQ(D52,D:D) -> 48 | F52: =IFERROR(VLOOKUP(A52,eco_journals!A:D,4,0),"") -> 1.46 | G52: =IFERROR(_xlfn.RANK.EQ(F52,F:F),"") -> 25 | H52: =IFERROR(VLOOKUP(A52,fin_journals!A:D,4,0),"") -> 0.65 | I52: =IFERROR(_xlfn.RANK.EQ(H52,H:H),"") -> 25 | J52: =IFERROR(VLOOKUP(A52,bus_journals!A:D,4,0),"") | K52: =IFERROR(_xlfn.RANK.EQ(J52,J:J),"") | L52: =IFERROR(VLOOKUP(A52,man_journals!A:D,4,0),"") | M52: =IFERROR(_xlfn.RANK.EQ(L52,L:L),"") | N52: FINANCE | O52: ECONOMICS
A53: MANAGEMENT SCIENCE | B53: INFORMS | C53: 294 | D53: =IFERROR(VLOOKUP(A53,eco_bus_journals!A:D,4,0),"") -> 1.47 | E53: =_xlfn.RANK.EQ(D53,D:D) -> 50 | F53: =IFERROR(VLOOKUP(A53,eco_journals!A:D,4,0),"") | G53: =IFERROR(_xlfn.RANK.EQ(F53,F:F),"") | H53: =IFERROR(VLOOKUP(A53,fin_journals!A:D,4,0),"") | I53: =IFERROR(_xlfn.RANK.EQ(H53,H:H),"") | J53: =IFERROR(VLOOKUP(A53,bus_journals!A:D,4,0),"") | K53: =IFERROR(_xlfn.RANK.EQ(J53,J:J),"") | L53: =IFERROR(VLOOKUP(A53,man_journals!A:D,4,0),"") -> 0.97 | M53: =IFERROR(_xlfn.RANK.EQ(L53,L:L),"") -> 33 | N53: MANAGEMENT | O53: OPERATIONS RESEARCH & MANAGEMENT SCIENCE
A54: QUANTITATIVE ECONOMICS | B54: WILEY | C54: 40 | D54: =IFERROR(VLOOKUP(A54,eco_bus_journals!A:D,4,0),"") -> 1.45 | E54: =_xlfn.RANK.EQ(D54,D:D) -> 51 | F54: =IFERROR(VLOOKUP(A54,eco_journals!A:D,4,0),"") -> 1.55 | G54: =IFERROR(_xlfn.RANK.EQ(F54,F:F),"") -> 23 | H54: =IFERROR(VLOOKUP(A54,fin_journals!A:D,4,0),"") | I54: =IFERROR(_xlfn.RANK.EQ(H54,H:H),"") | J54: =IFERROR(VLOOKUP(A54,bus_journals!A:D,4,0),"") | K54: =IFERROR(_xlfn.RANK.EQ(J54,J:J),"") | L54: =IFERROR(VLOOKUP(A54,man_journals!A:D,4,0),"") | M54: =IFERROR(_xlfn.RANK.EQ(L54,L:L),"") | N54: ECONOMICS
A55: THEORETICAL ECONOMICS | B55: ECONOMETRIC SOCIETY | C55: 45 | D55: =IFERROR(VLOOKUP(A55,eco_bus_journals!A:D,4,0),"") -> 1.45 | E55: =_xlfn.RANK.EQ(D55,D:D) -> 51 | F55: =IFERROR(VLOOKUP(A55,eco_journals!A:D,4,0),"") -> 1.54 | G55: =IFERROR(_xlfn.RANK.EQ(F55,F:F),"") -> 24 | H55: =IFERROR(VLOOKUP(A55,fin_journals!A:D,4,0),"") | I55: =IFERROR(_xlfn.RANK.EQ(H55,H:H),"") | J55: =IFERROR(VLOOKUP(A55,bus_journals!A:D,4,0),"") | K55: =IFERROR(_xlfn.RANK.EQ(J55,J:J),"") | L55: =IFERROR(VLOOKUP(A55,man_journals!A:D,4,0),"") | M55: =IFERROR(_xlfn.RANK.EQ(L55,L:L),"") | N55: ECONOMICS
A56: JOURNAL OF WORLD BUSINESS | B56: ELSEVIER | C56: 62 | D56: =IFERROR(VLOOKUP(A56,eco_bus_journals!A:D,4,0),"") -> 1.44 | E56: =_xlfn.RANK.EQ(D56,D:D) -> 53 | F56: =IFERROR(VLOOKUP(A56,eco_journals!A:D,4,0),"") | G56: =IFERROR(_xlfn.RANK.EQ(F56,F:F),"") | H56: =IFERROR(VLOOKUP(A56,fin_journals!A:D,4,0),"") | I56: =IFERROR(_xlfn.RANK.EQ(H56,H:H),"") | J56: =IFERROR(VLOOKUP(A56,bus_journals!A:D,4,0),"") -> 2.38 | K56: =IFERROR(_xlfn.RANK.EQ(J56,J:J),"") -> 24 | L56: =IFERROR(VLOOKUP(A56,man_journals!A:D,4,0),"") | M56: =IFERROR(_xlfn.RANK.EQ(L56,L:L),"") | N56: BUSINESS
A57: JOURNAL OF MARKETING RESEARCH | B57: SAGE PUBLICATIONS | C57: 71 | D57: =IFERROR(VLOOKUP(A57,eco_bus_journals!A:D,4,0),"") -> 1.42 | E57: =_xlfn.RANK.EQ(D57,D:D) -> 54 | F57: =IFERROR(VLOOKUP(A57,eco_journals!A:D,4,0),"") | G57: =IFERROR(_xlfn.RANK.EQ(F57,F:F),"") | H57: =IFERROR(VLOOKUP(A57,fin_journals!A:D,4,0),"") | I57: =IFERROR(_xlfn.RANK.EQ(H57,H:H),"") | J57: =IFERROR(VLOOKUP(A57,bus_journals!A:D,4,0),"") -> 3.64 | K57: =IFERROR(_xlfn.RANK.EQ(J57,J:J),"") -> 14 | L57: =IFERROR(VLOOKUP(A57,man_journals!A:D,4,0),"") | M57: =IFERROR(_xlfn.RANK.EQ(L57,L:L),"") | N57: BUSINESS
A58: REVIEW OF ACCOUNTING STUDIES | B58: SPRINGER | C58: 51 | D58: =IFERROR(VLOOKUP(A58,eco_bus_journals!A:D,4,0),"") -> 1.41 | E58: =_xlfn.RANK.EQ(D58,D:D) -> 55 | F58: =IFERROR(VLOOKUP(A58,eco_journals!A:D,4,0),"") | G58: =IFERROR(_xlfn.RANK.EQ(F58,F:F),"") | H58: =IFERROR(VLOOKUP(A58,fin_journals!A:D,4,0),"") -> 6.24 | I58: =IFERROR(_xlfn.RANK.EQ(H58,H:H),"") -> 6 | J58: =IFERROR(VLOOKUP(A58,bus_journals!A:D,4,0),"") | K58: =IFERROR(_xlfn.RANK.EQ(J58,J:J),"") | L58: =IFERROR(VLOOKUP(A58,man_journals!A:D,4,0),"") | M58: =IFERROR(_xlfn.RANK.EQ(L58,L:L),"") | N58: FINANCE
A59: MARKETING SCIENCE | B59: INFORMS | C59: 57 | D59: =IFERROR(VLOOKUP(A59,eco_bus_journals!A:D,4,0),"") -> 1.37 | E59: =_xlfn.RANK.EQ(D59,D:D) -> 56 | F59: =IFERROR(VLOOKUP(A59,eco_journals!A:D,4,0),"") | G59: =IFERROR(_xlfn.RANK.EQ(F59,F:F),"") | H59: =IFERROR(VLOOKUP(A59,fin_journals!A:D,4,0),"") | I59: =IFERROR(_xlfn.RANK.EQ(H59,H:H),"") | J59: =IFERROR(VLOOKUP(A59,bus_journals!A:D,4,0),"") -> 2.56 | K59: =IFERROR(_xlfn.RANK.EQ(J59,J:J),"") -> 22 | L59: =IFERROR(VLOOKUP(A59,man_journals!A:D,4,0),"") | M59: =IFERROR(_xlfn.RANK.EQ(L59,L:L),"") | N59: BUSINESS
A60: STRATEGIC ORGANIZATION | B60: SAGE PUBLICATIONS | C60: 53 | D60: =IFERROR(VLOOKUP(A60,eco_bus_journals!A:D,4,0),"") -> 1.37 | E60: =_xlfn.RANK.EQ(D60,D:D) -> 56 | F60: =IFERROR(VLOOKUP(A60,eco_journals!A:D,4,0),"") | G60: =IFERROR(_xlfn.RANK.EQ(F60,F:F),"") | H60: =IFERROR(VLOOKUP(A60,fin_journals!A:D,4,0),"") | I60: =IFERROR(_xlfn.RANK.EQ(H60,H:H),"") | J60: =IFERROR(VLOOKUP(A60,bus_journals!A:D,4,0),"") -> 2.29 | K60: =IFERROR(_xlfn.RANK.EQ(J60,J:J),"") -> 25 | L60: =IFERROR(VLOOKUP(A60,man_journals!A:D,4,0),"") -> 2.2 | M60: =IFERROR(_xlfn.RANK.EQ(L60,L:L),"") -> 15 | N60: BUSINESS | O60: MANAGEMENT
A61: ACCOUNTING REVIEW | B61: AMER ACCOUNTING ASSOC | C61: 92 | D61: =IFERROR(VLOOKUP(A61,eco_bus_journals!A:D,4,0),"") -> 1.34 | E61: =_xlfn.RANK.EQ(D61,D:D) -> 58 | F61: =IFERROR(VLOOKUP(A61,eco_journals!A:D,4,0),"") | G61: =IFERROR(_xlfn.RANK.EQ(F61,F:F),"") | H61: =IFERROR(VLOOKUP(A61,fin_journals!A:D,4,0),"") -> 5.93 | I61: =IFERROR(_xlfn.RANK.EQ(H61,H:H),"") -> 7 | J61: =IFERROR(VLOOKUP(A61,bus_journals!A:D,4,0),"") | K61: =IFERROR(_xlfn.RANK.EQ(J61,J:J),"") | L61: =IFERROR(VLOOKUP(A61,man_journals!A:D,4,0),"") | M61: =IFERROR(_xlfn.RANK.EQ(L61,L:L),"") | N61: FINANCE
A62: CALIFORNIA MANAGEMENT REVIEW | B62: SAGE PUBLICATIONS | C62: 31 | D62: =IFERROR(VLOOKUP(A62,eco_bus_journals!A:D,4,0),"") -> 1.33 | E62: =_xlfn.RANK.EQ(D62,D:D) -> 59 | F62: =IFERROR(VLOOKUP(A62,eco_journals!A:D,4,0),"") | G62: =IFERROR(_xlfn.RANK.EQ(F62,F:F),"") | H62: =IFERROR(VLOOKUP(A62,fin_journals!A:D,4,0),"") | I62: =IFERROR(_xlfn.RANK.EQ(H62,H:H),"") | J62: =IFERROR(VLOOKUP(A62,bus_journals!A:D,4,0),"") -> 2.26 | K62: =IFERROR(_xlfn.RANK.EQ(J62,J:J),"") -> 27 | L62: =IFERROR(VLOOKUP(A62,man_journals!A:D,4,0),"") -> 1.44 | M62: =IFERROR(_xlfn.RANK.EQ(L62,L:L),"") -> 22 | N62: BUSINESS | O62: MANAGEMENT
A63: JOURNAL OF INTERACTIVE MARKETING | B63: SAGE PUBLICATIONS | C63: 32 | D63: =IFERROR(VLOOKUP(A63,eco_bus_journals!A:D,4,0),"") -> 1.33 | E63: =_xlfn.RANK.EQ(D63,D:D) -> 59 | F63: =IFERROR(VLOOKUP(A63,eco_journals!A:D,4,0),"") | G63: =IFERROR(_xlfn.RANK.EQ(F63,F:F),"") | H63: =IFERROR(VLOOKUP(A63,fin_journals!A:D,4,0),"") | I63: =IFERROR(_xlfn.RANK.EQ(H63,H:H),"") | J63: =IFERROR(VLOOKUP(A63,bus_journals!A:D,4,0),"") -> 3.13 | K63: =IFERROR(_xlfn.RANK.EQ(J63,J:J),"") -> 18 | L63: =IFERROR(VLOOKUP(A63,man_journals!A:D,4,0),"") | M63: =IFERROR(_xlfn.RANK.EQ(L63,L:L),"") | N63: BUSINESS
A64: JOURNAL OF HUMAN RESOURCES | B64: UNIV WISCONSIN PRESS | C64: 39 | D64: =IFERROR(VLOOKUP(A64,eco_bus_journals!A:D,4,0),"") -> 1.29 | E64: =_xlfn.RANK.EQ(D64,D:D) -> 61 | F64: =IFERROR(VLOOKUP(A64,eco_journals!A:D,4,0),"") -> 1.31 | G64: =IFERROR(_xlfn.RANK.EQ(F64,F:F),"") -> 26 | H64: =IFERROR(VLOOKUP(A64,fin_journals!A:D,4,0),"") | I64: =IFERROR(_xlfn.RANK.EQ(H64,H:H),"") | J64: =IFERROR(VLOOKUP(A64,bus_journals!A:D,4,0),"") | K64: =IFERROR(_xlfn.RANK.EQ(J64,J:J),"") | L64: =IFERROR(VLOOKUP(A64,man_journals!A:D,4,0),"") | M64: =IFERROR(_xlfn.RANK.EQ(L64,L:L),"") | N64: ECONOMICS | O64: INDUSTRIAL RELATIONS & LABOR
A65: LONG RANGE PLANNING | B65: ELSEVIER | C65: 56 | D65: =IFERROR(VLOOKUP(A65,eco_bus_journals!A:D,4,0),"") -> 1.28 | E65: =_xlfn.RANK.EQ(D65,D:D) -> 62 | F65: =IFERROR(VLOOKUP(A65,eco_journals!A:D,4,0),"") | G65: =IFERROR(_xlfn.RANK.EQ(F65,F:F),"") | H65: =IFERROR(VLOOKUP(A65,fin_journals!A:D,4,0),"") | I65: =IFERROR(_xlfn.RANK.EQ(H65,H:H),"") | J65: =IFERROR(VLOOKUP(A65,bus_journals!A:D,4,0),"") -> 2.17 | K65: =IFERROR(_xlfn.RANK.EQ(J65,J:J),"") -> 28 | L65: =IFERROR(VLOOKUP(A65,man_journals!A:D,4,0),"") -> 1.63 | M65: =IFERROR(_xlfn.RANK.EQ(L65,L:L),"") -> 20 | N65: BUSINESS | O65: DEVELOPMENT STUDIES | P65: MANAGEMENT | Q65: REGIONAL & URBAN PLANNING
A66: ANNUAL REVIEW OF FINANCIAL ECONOMICS | B66: ANNUAL REVIEWS | C66: 15 | D66: =IFERROR(VLOOKUP(A66,eco_bus_journals!A:D,4,0),"") -> 1.26 | E66: =_xlfn.RANK.EQ(D66,D:D) -> 63 | F66: =IFERROR(VLOOKUP(A66,eco_journals!A:D,4,0),"") | G66: =IFERROR(_xlfn.RANK.EQ(F66,F:F),"") | H66: =IFERROR(VLOOKUP(A66,fin_journals!A:D,4,0),"") -> 2.48 | I66: =IFERROR(_xlfn.RANK.EQ(H66,H:H),"") -> 12 | J66: =IFERROR(VLOOKUP(A66,bus_journals!A:D,4,0),"") | K66: =IFERROR(_xlfn.RANK.EQ(J66,J:J),"") | L66: =IFERROR(VLOOKUP(A66,man_journals!A:D,4,0),"") | M66: =IFERROR(_xlfn.RANK.EQ(L66,L:L),"") | N66: FINANCE
A67: JOURNAL OF INTERNATIONAL ECONOMICS | B67: ELSEVIER | C67: 92 | D67: =IFERROR(VLOOKUP(A67,eco_bus_journals!A:D,4,0),"") -> 1.25 | E67: =_xlfn.RANK.EQ(D67,D:D) -> 64 | F67: =IFERROR(VLOOKUP(A67,eco_journals!A:D,4,0),"") -> 1.25 | G67: =IFERROR(_xlfn.RANK.EQ(F67,F:F),"") -> 27 | H67: =IFERROR(VLOOKUP(A67,fin_journals!A:D,4,0),"") | I67: =IFERROR(_xlfn.RANK.EQ(H67,H:H),"") | J67: =IFERROR(VLOOKUP(A67,bus_journals!A:D,4,0),"") | K67: =IFERROR(_xlfn.RANK.EQ(J67,J:J),"") | L67: =IFERROR(VLOOKUP(A67,man_journals!A:D,4,0),"") | M67: =IFERROR(_xlfn.RANK.EQ(L67,L:L),"") | N67: ECONOMICS
A68: JOURNAL OF RETAILING | B68: ELSEVIER | C68: 38 | D68: =IFERROR(VLOOKUP(A68,eco_bus_journals!A:D,4,0),"") -> 1.22 | E68: =_xlfn.RANK.EQ(D68,D:D) -> 65 | F68: =IFERROR(VLOOKUP(A68,eco_journals!A:D,4,0),"") | G68: =IFERROR(_xlfn.RANK.EQ(F68,F:F),"") | H68: =IFERROR(VLOOKUP(A68,fin_journals!A:D,4,0),"") | I68: =IFERROR(_xlfn.RANK.EQ(H68,H:H),"") | J68: =IFERROR(VLOOKUP(A68,bus_journals!A:D,4,0),"") -> 3.12 | K68: =IFERROR(_xlfn.RANK.EQ(J68,J:J),"") -> 19 | L68: =IFERROR(VLOOKUP(A68,man_journals!A:D,4,0),"") | M68: =IFERROR(_xlfn.RANK.EQ(L68,L:L),"") | N68: BUSINESS
A69: PROCEEDINGS OF THE NATIONAL ACADEMY OF SCIENCES OF THE UNITED STATES OF AMERICA | B69: NATL ACAD SCIENCES | C69: 44 | D69: =IFERROR(VLOOKUP(A69,eco_bus_journals!A:D,4,0),"") -> 1.2 | E69: =_xlfn.RANK.EQ(D69,D:D) -> 66 | F69: =IFERROR(VLOOKUP(A69,eco_journals!A:D,4,0),"") | G69: =IFERROR(_xlfn.RANK.EQ(F69,F:F),"") | H69: =IFERROR(VLOOKUP(A69,fin_journals!A:D,4,0),"") | I69: =IFERROR(_xlfn.RANK.EQ(H69,H:H),"") | J69: =IFERROR(VLOOKUP(A69,bus_journals!A:D,4,0),"") | K69: =IFERROR(_xlfn.RANK.EQ(J69,J:J),"") | L69: =IFERROR(VLOOKUP(A69,man_journals!A:D,4,0),"") | M69: =IFERROR(_xlfn.RANK.EQ(L69,L:L),"") | N69: MULTIDISCIPLINARY SCIENCES
A70: INTERNATIONAL BUSINESS REVIEW | B70: ELSEVIER | C70: 83 | D70: =IFERROR(VLOOKUP(A70,eco_bus_journals!A:D,4,0),"") -> 1.18 | E70: =_xlfn.RANK.EQ(D70,D:D) -> 67 | F70: =IFERROR(VLOOKUP(A70,eco_journals!A:D,4,0),"") | G70: =IFERROR(_xlfn.RANK.EQ(F70,F:F),"") | H70: =IFERROR(VLOOKUP(A70,fin_journals!A:D,4,0),"") | I70: =IFERROR(_xlfn.RANK.EQ(H70,H:H),"") | J70: =IFERROR(VLOOKUP(A70,bus_journals!A:D,4,0),"") -> 1.73 | K70: =IFERROR(_xlfn.RANK.EQ(J70,J:J),"") -> 29 | L70: =IFERROR(VLOOKUP(A70,man_journals!A:D,4,0),"") | M70: =IFERROR(_xlfn.RANK.EQ(L70,L:L),"") | N70: BUSINESS
A71: ACADEMY OF MANAGEMENT LEARNING & EDUCATION | B71: ACAD MANAGEMENT | C71: 22 | D71: =IFERROR(VLOOKUP(A71,eco_bus_journals!A:D,4,0),"") -> 1.17 | E71: =_xlfn.RANK.EQ(D71,D:D) -> 68 | F71: =IFERROR(VLOOKUP(A71,eco_journals!A:D,4,0),"") | G71: =IFERROR(_xlfn.RANK.EQ(F71,F:F),"") | H71: =IFERROR(VLOOKUP(A71,fin_journals!A:D,4,0),"") | I71: =IFERROR(_xlfn.RANK.EQ(H71,H:H),"") | J71: =IFERROR(VLOOKUP(A71,bus_journals!A:D,4,0),"") | K71: =IFERROR(_xlfn.RANK.EQ(J71,J:J),"") | L71: =IFERROR(VLOOKUP(A71,man_journals!A:D,4,0),"") -> 2.01 | M71: =IFERROR(_xlfn.RANK.EQ(L71,L:L),"") -> 16 | N71: EDUCATION & EDUCATIONAL RESEARCH | O71: MANAGEMENT
A72: RAND JOURNAL OF ECONOMICS | B72: WILEY | C72: 46 | D72: =IFERROR(VLOOKUP(A72,eco_bus_journals!A:D,4,0),"") -> 1.17 | E72: =_xlfn.RANK.EQ(D72,D:D) -> 68 | F72: =IFERROR(VLOOKUP(A72,eco_journals!A:D,4,0),"") -> 0.93 | G72: =IFERROR(_xlfn.RANK.EQ(F72,F:F),"") -> 31 | H72: =IFERROR(VLOOKUP(A72,fin_journals!A:D,4,0),"") | I72: =IFERROR(_xlfn.RANK.EQ(H72,H:H),"") | J72: =IFERROR(VLOOKUP(A72,bus_journals!A:D,4,0),"") | K72: =IFERROR(_xlfn.RANK.EQ(J72,J:J),"") | L72: =IFERROR(VLOOKUP(A72,man_journals!A:D,4,0),"") | M72: =IFERROR(_xlfn.RANK.EQ(L72,L:L),"") | N72: ECONOMICS
A73: JOURNAL OF CONSUMER RESEARCH | B73: OXFORD UNIV PRESS INC | C73: 48 | D73: =IFERROR(VLOOKUP(A73,eco_bus_journals!A:D,4,0),"") -> 1.16 | E73: =_xlfn.RANK.EQ(D73,D:D) -> 70 | F73: =IFERROR(VLOOKUP(A73,eco_journals!A:D,4,0),"") | G73: =IFERROR(_xlfn.RANK.EQ(F73,F:F),"") | H73: =IFERROR(VLOOKUP(A73,fin_journals!A:D,4,0),"") | I73: =IFERROR(_xlfn.RANK.EQ(H73,H:H),"") | J73: =IFERROR(VLOOKUP(A73,bus_journals!A:D,4,0),"") -> 3.17 | K73: =IFERROR(_xlfn.RANK.EQ(J73,J:J),"") -> 17 | L73: =IFERROR(VLOOKUP(A73,man_journals!A:D,4,0),"") | M73: =IFERROR(_xlfn.RANK.EQ(L73,L:L),"") | N73: BUSINESS
A74: AMERICAN ECONOMIC JOURNAL-MICROECONOMICS | B74: AMER ECONOMIC ASSOC | C74: 34 | D74: =IFERROR(VLOOKUP(A74,eco_bus_journals!A:D,4,0),"") -> 1.15 | E74: =_xlfn.RANK.EQ(D74,D:D) -> 71 | F74: =IFERROR(VLOOKUP(A74,eco_journals!A:D,4,0),"") -> 1.07 | G74: =IFERROR(_xlfn.RANK.EQ(F74,F:F),"") -> 29 | H74: =IFERROR(VLOOKUP(A74,fin_journals!A:D,4,0),"") | I74: =IFERROR(_xlfn.RANK.EQ(H74,H:H),"") | J74: =IFERROR(VLOOKUP(A74,bus_journals!A:D,4,0),"") | K74: =IFERROR(_xlfn.RANK.EQ(J74,J:J),"") | L74: =IFERROR(VLOOKUP(A74,man_journals!A:D,4,0),"") | M74: =IFERROR(_xlfn.RANK.EQ(L74,L:L),"") | N74: ECONOMICS
A75: JOURNAL OF FINANCIAL AND QUANTITATIVE ANALYSIS | B75: CAMBRIDGE UNIV PRESS | C75: 82 | D75: =IFERROR(VLOOKUP(A75,eco_bus_journals!A:D,4,0),"") -> 1.15 | E75: =_xlfn.RANK.EQ(D75,D:D) -> 71 | F75: =IFERROR(VLOOKUP(A75,eco_journals!A:D,4,0),"") -> 0.48 | G75: =IFERROR(_xlfn.RANK.EQ(F75,F:F),"") -> 53 | H75: =IFERROR(VLOOKUP(A75,fin_journals!A:D,4,0),"") -> 2.59 | I75: =IFERROR(_xlfn.RANK.EQ(H75,H:H),"") -> 11 | J75: =IFERROR(VLOOKUP(A75,bus_journals!A:D,4,0),"") | K75: =IFERROR(_xlfn.RANK.EQ(J75,J:J),"") | L75: =IFERROR(VLOOKUP(A75,man_journals!A:D,4,0),"") | M75: =IFERROR(_xlfn.RANK.EQ(L75,L:L),"") | N75: FINANCE | O75: ECONOMICS
A76: JOURNAL OF ECONOMIC GROWTH | B76: SPRINGER | C76: 11 | D76: =IFERROR(VLOOKUP(A76,eco_bus_journals!A:D,4,0),"") -> 1.12 | E76: =_xlfn.RANK.EQ(D76,D:D) -> 73 | F76: =IFERROR(VLOOKUP(A76,eco_journals!A:D,4,0),"") -> 1.15 | G76: =IFERROR(_xlfn.RANK.EQ(F76,F:F),"") -> 28 | H76: =IFERROR(VLOOKUP(A76,fin_journals!A:D,4,0),"") | I76: =IFERROR(_xlfn.RANK.EQ(H76,H:H),"") | J76: =IFERROR(VLOOKUP(A76,bus_journals!A:D,4,0),"") | K76: =IFERROR(_xlfn.RANK.EQ(J76,J:J),"") | L76: =IFERROR(VLOOKUP(A76,man_journals!A:D,4,0),"") | M76: =IFERROR(_xlfn.RANK.EQ(L76,L:L),"") | N76: ECONOMICS
A77: JOURNAL OF SUPPLY CHAIN MANAGEMENT | B77: WILEY | C77: 25 | D77: =IFERROR(VLOOKUP(A77,eco_bus_journals!A:D,4,0),"") -> 1.12 | E77: =_xlfn.RANK.EQ(D77,D:D) -> 73 | F77: =IFERROR(VLOOKUP(A77,eco_journals!A:D,4,0),"") | G77: =IFERROR(_xlfn.RANK.EQ(F77,F:F),"") | H77: =IFERROR(VLOOKUP(A77,fin_journals!A:D,4,0),"") | I77: =IFERROR(_xlfn.RANK.EQ(H77,H:H),"") | J77: =IFERROR(VLOOKUP(A77,bus_journals!A:D,4,0),"") | K77: =IFERROR(_xlfn.RANK.EQ(J77,J:J),"") | L77: =IFERROR(VLOOKUP(A77,man_journals!A:D,4,0),"") -> 1.58 | M77: =IFERROR(_xlfn.RANK.EQ(L77,L:L),"") -> 21 | N77: MANAGEMENT
A78: JOURNAL OF URBAN ECONOMICS | B78: ELSEVIER | C78: 39 | D78: =IFERROR(VLOOKUP(A78,eco_bus_journals!A:D,4,0),"") -> 1.09 | E78: =_xlfn.RANK.EQ(D78,D:D) -> 75 | F78: =IFERROR(VLOOKUP(A78,eco_journals!A:D,4,0),"") -> 1.03 | G78: =IFERROR(_xlfn.RANK.EQ(F78,F:F),"") -> 30 | H78: =IFERROR(VLOOKUP(A78,fin_journals!A:D,4,0),"") | I78: =IFERROR(_xlfn.RANK.EQ(H78,H:H),"") | J78: =IFERROR(VLOOKUP(A78,bus_journals!A:D,4,0),"") | K78: =IFERROR(_xlfn.RANK.EQ(J78,J:J),"") | L78: =IFERROR(VLOOKUP(A78,man_journals!A:D,4,0),"") | M78: =IFERROR(_xlfn.RANK.EQ(L78,L:L),"") | N78: ECONOMICS | O78: URBAN STUDIES
A79: INTERNATIONAL JOURNAL OF RESEARCH IN MARKETING | B79: ELSEVIER | C79: 47 | D79: =IFERROR(VLOOKUP(A79,eco_bus_journals!A:D,4,0),"") -> 1.07 | E79: =_xlfn.RANK.EQ(D79,D:D) -> 76 | F79: =IFERROR(VLOOKUP(A79,eco_journals!A:D,4,0),"") | G79: =IFERROR(_xlfn.RANK.EQ(F79,F:F),"") | H79: =IFERROR(VLOOKUP(A79,fin_journals!A:D,4,0),"") | I79: =IFERROR(_xlfn.RANK.EQ(H79,H:H),"") | J79: =IFERROR(VLOOKUP(A79,bus_journals!A:D,4,0),"") -> 2.54 | K79: =IFERROR(_xlfn.RANK.EQ(J79,J:J),"") -> 23 | L79: =IFERROR(VLOOKUP(A79,man_journals!A:D,4,0),"") | M79: =IFERROR(_xlfn.RANK.EQ(L79,L:L),"") | N79: BUSINESS
A80: BUSINESS & SOCIETY | B80: SAGE PUBLICATIONS | C80: 100 | D80: =IFERROR(VLOOKUP(A80,eco_bus_journals!A:D,4,0),"") -> 0.97 | E80: =_xlfn.RANK.EQ(D80,D:D) -> 77 | F80: =IFERROR(VLOOKUP(A80,eco_journals!A:D,4,0),"") | G80: =IFERROR(_xlfn.RANK.EQ(F80,F:F),"") | H80: =IFERROR(VLOOKUP(A80,fin_journals!A:D,4,0),"") | I80: =IFERROR(_xlfn.RANK.EQ(H80,H:H),"") | J80: =IFERROR(VLOOKUP(A80,bus_journals!A:D,4,0),"") -> 1.59 | K80: =IFERROR(_xlfn.RANK.EQ(J80,J:J),"") -> 32 | L80: =IFERROR(VLOOKUP(A80,man_journals!A:D,4,0),"") | M80: =IFERROR(_xlfn.RANK.EQ(L80,L:L),"") | N80: BUSINESS
A81: ECONOMIC JOURNAL | B81: OXFORD UNIV PRESS | C81: 95 | D81: =IFERROR(VLOOKUP(A81,eco_bus_journals!A:D,4,0),"") -> 0.97 | E81: =_xlfn.RANK.EQ(D81,D:D) -> 77 | F81: =IFERROR(VLOOKUP(A81,eco_journals!A:D,4,0),"") -> 0.93 | G81: =IFERROR(_xlfn.RANK.EQ(F81,F:F),"") -> 31 | H81: =IFERROR(VLOOKUP(A81,fin_journals!A:D,4,0),"") | I81: =IFERROR(_xlfn.RANK.EQ(H81,H:H),"") | J81: =IFERROR(VLOOKUP(A81,bus_journals!A:D,4,0),"") | K81: =IFERROR(_xlfn.RANK.EQ(J81,J:J),"") | L81: =IFERROR(VLOOKUP(A81,man_journals!A:D,4,0),"") | M81: =IFERROR(_xlfn.RANK.EQ(L81,L:L),"") | N81: ECONOMICS
A82: FAMILY BUSINESS REVIEW | B82: SAGE PUBLICATIONS | C82: 25 | D82: =IFERROR(VLOOKUP(A82,eco_bus_journals!A:D,4,0),"") -> 0.92 | E82: =_xlfn.RANK.EQ(D82,D:D) -> 79 | F82: =IFERROR(VLOOKUP(A82,eco_journals!A:D,4,0),"") | G82: =IFERROR(_xlfn.RANK.EQ(F82,F:F),"") | H82: =IFERROR(VLOOKUP(A82,fin_journals!A:D,4,0),"") | I82: =IFERROR(_xlfn.RANK.EQ(H82,H:H),"") | J82: =IFERROR(VLOOKUP(A82,bus_journals!A:D,4,0),"") -> 1.68 | K82: =IFERROR(_xlfn.RANK.EQ(J82,J:J),"") -> 30 | L82: =IFERROR(VLOOKUP(A82,man_journals!A:D,4,0),"") | M82: =IFERROR(_xlfn.RANK.EQ(L82,L:L),"") | N82: BUSINESS
A83: JOURNAL OF OPERATIONS MANAGEMENT | B83: WILEY | C83: 44 | D83: =IFERROR(VLOOKUP(A83,eco_bus_journals!A:D,4,0),"") -> 0.92 | E83: =_xlfn.RANK.EQ(D83,D:D) -> 79 | F83: =IFERROR(VLOOKUP(A83,eco_journals!A:D,4,0),"") | G83: =IFERROR(_xlfn.RANK.EQ(F83,F:F),"") | H83: =IFERROR(VLOOKUP(A83,fin_journals!A:D,4,0),"") | I83: =IFERROR(_xlfn.RANK.EQ(H83,H:H),"") | J83: =IFERROR(VLOOKUP(A83,bus_journals!A:D,4,0),"") | K83: =IFERROR(_xlfn.RANK.EQ(J83,J:J),"") | L83: =IFERROR(VLOOKUP(A83,man_journals!A:D,4,0),"") -> 1.25 | M83: =IFERROR(_xlfn.RANK.EQ(L83,L:L),"") -> 24 | N83: MANAGEMENT | O83: OPERATIONS RESEARCH & MANAGEMENT SCIENCE
A84: JOURNAL OF INTERNATIONAL MANAGEMENT | B84: ELSEVIER | C84: 44 | D84: =IFERROR(VLOOKUP(A84,eco_bus_journals!A:D,4,0),"") -> 0.89 | E84: =_xlfn.RANK.EQ(D84,D:D) -> 81 | F84: =IFERROR(VLOOKUP(A84,eco_journals!A:D,4,0),"") | G84: =IFERROR(_xlfn.RANK.EQ(F84,F:F),"") | H84: =IFERROR(VLOOKUP(A84,fin_journals!A:D,4,0),"") | I84: =IFERROR(_xlfn.RANK.EQ(H84,H:H),"") | J84: =IFERROR(VLOOKUP(A84,bus_journals!A:D,4,0),"") | K84: =IFERROR(_xlfn.RANK.EQ(J84,J:J),"") | L84: =IFERROR(VLOOKUP(A84,man_journals!A:D,4,0),"") -> 0.73 | M84: =IFERROR(_xlfn.RANK.EQ(L84,L:L),"") -> 39 | N84: MANAGEMENT
A85: BRITISH JOURNAL OF MANAGEMENT | B85: WILEY | C85: 76 | D85: =IFERROR(VLOOKUP(A85,eco_bus_journals!A:D,4,0),"") -> 0.87 | E85: =_xlfn.RANK.EQ(D85,D:D) -> 82 | F85: =IFERROR(VLOOKUP(A85,eco_journals!A:D,4,0),"") | G85: =IFERROR(_xlfn.RANK.EQ(F85,F:F),"") | H85: =IFERROR(VLOOKUP(A85,fin_journals!A:D,4,0),"") | I85: =IFERROR(_xlfn.RANK.EQ(H85,H:H),"") | J85: =IFERROR(VLOOKUP(A85,bus_journals!A:D,4,0),"") -> 1.25 | K85: =IFERROR(_xlfn.RANK.EQ(J85,J:J),"") -> 39 | L85: =IFERROR(VLOOKUP(A85,man_journals!A:D,4,0),"") -> 0.86 | M85: =IFERROR(_xlfn.RANK.EQ(L85,L:L),"") -> 37 | N85: BUSINESS | O85: MANAGEMENT
A86: INTERNATIONAL ECONOMIC REVIEW | B86: WILEY | C86: 75 | D86: =IFERROR(VLOOKUP(A86,eco_bus_journals!A:D,4,0),"") -> 0.87 | E86: =_xlfn.RANK.EQ(D86,D:D) -> 82 | F86: =IFERROR(VLOOKUP(A86,eco_journals!A:D,4,0),"") -> 0.87 | G86: =IFERROR(_xlfn.RANK.EQ(F86,F:F),"") -> 35 | H86: =IFERROR(VLOOKUP(A86,fin_journals!A:D,4,0),"") | I86: =IFERROR(_xlfn.RANK.EQ(H86,H:H),"") | J86: =IFERROR(VLOOKUP(A86,bus_journals!A:D,4,0),"") | K86: =IFERROR(_xlfn.RANK.EQ(J86,J:J),"") | L86: =IFERROR(VLOOKUP(A86,man_journals!A:D,4,0),"") | M86: =IFERROR(_xlfn.RANK.EQ(L86,L:L),"") | N86: ECONOMICS
A87: JOURNAL OF LAW & ECONOMICS | B87: UNIV CHICAGO PRESS | C87: 26 | D87: =IFERROR(VLOOKUP(A87,eco_bus_journals!A:D,4,0),"") -> 0.85 | E87: =_xlfn.RANK.EQ(D87,D:D) -> 84 | F87: =IFERROR(VLOOKUP(A87,eco_journals!A:D,4,0),"") -> 0.67 | G87: =IFERROR(_xlfn.RANK.EQ(F87,F:F),"") -> 39 | H87: =IFERROR(VLOOKUP(A87,fin_journals!A:D,4,0),"") | I87: =IFERROR(_xlfn.RANK.EQ(H87,H:H),"") | J87: =IFERROR(VLOOKUP(A87,bus_journals!A:D,4,0),"") | K87: =IFERROR(_xlfn.RANK.EQ(J87,J:J),"") | L87: =IFERROR(VLOOKUP(A87,man_journals!A:D,4,0),"") | M87: =IFERROR(_xlfn.RANK.EQ(L87,L:L),"") | N87: ECONOMICS | O87: LAW
A88: REVIEW OF ECONOMIC DYNAMICS | B88: ELSEVIER | C88: 67 | D88: =IFERROR(VLOOKUP(A88,eco_bus_journals!A:D,4,0),"") -> 0.85 | E88: =_xlfn.RANK.EQ(D88,D:D) -> 84 | F88: =IFERROR(VLOOKUP(A88,eco_journals!A:D,4,0),"") -> 0.88 | G88: =IFERROR(_xlfn.RANK.EQ(F88,F:F),"") -> 33 | H88: =IFERROR(VLOOKUP(A88,fin_journals!A:D,4,0),"") | I88: =IFERROR(_xlfn.RANK.EQ(H88,H:H),"") | J88: =IFERROR(VLOOKUP(A88,bus_journals!A:D,4,0),"") | K88: =IFERROR(_xlfn.RANK.EQ(J88,J:J),"") | L88: =IFERROR(VLOOKUP(A88,man_journals!A:D,4,0),"") | M88: =IFERROR(_xlfn.RANK.EQ(L88,L:L),"") | N88: ECONOMICS
A89: ENTREPRENEURSHIP AND REGIONAL DEVELOPMENT | B89: TAYLOR & FRANCIS LTD | C89: 29 | D89: =IFERROR(VLOOKUP(A89,eco_bus_journals!A:D,4,0),"") -> 0.84 | E89: =_xlfn.RANK.EQ(D89,D:D) -> 86 | F89: =IFERROR(VLOOKUP(A89,eco_journals!A:D,4,0),"") | G89: =IFERROR(_xlfn.RANK.EQ(F89,F:F),"") | H89: =IFERROR(VLOOKUP(A89,fin_journals!A:D,4,0),"") | I89: =IFERROR(_xlfn.RANK.EQ(H89,H:H),"") | J89: =IFERROR(VLOOKUP(A89,bus_journals!A:D,4,0),"") -> 1.53 | K89: =IFERROR(_xlfn.RANK.EQ(J89,J:J),"") -> 34 | L89: =IFERROR(VLOOKUP(A89,man_journals!A:D,4,0),"") | M89: =IFERROR(_xlfn.RANK.EQ(L89,L:L),"") | N89: BUSINESS | O89: DEVELOPMENT STUDIES | P89: REGIONAL & URBAN PLANNING
A90: HUMAN RELATIONS | B90: SAGE PUBLICATIONS | C90: 111 | D90: =IFERROR(VLOOKUP(A90,eco_bus_journals!A:D,4,0),"") -> 0.84 | E90: =_xlfn.RANK.EQ(D90,D:D) -> 86 | F90: =IFERROR(VLOOKUP(A90,eco_journals!A:D,4,0),"") | G90: =IFERROR(_xlfn.RANK.EQ(F90,F:F),"") | H90: =IFERROR(VLOOKUP(A90,fin_journals!A:D,4,0),"") | I90: =IFERROR(_xlfn.RANK.EQ(H90,H:H),"") | J90: =IFERROR(VLOOKUP(A90,bus_journals!A:D,4,0),"") | K90: =IFERROR(_xlfn.RANK.EQ(J90,J:J),"") | L90: =IFERROR(VLOOKUP(A90,man_journals!A:D,4,0),"") -> 1.36 | M90: =IFERROR(_xlfn.RANK.EQ(L90,L:L),"") -> 23 | N90: MANAGEMENT | O90: SOCIAL SCIENCES, INTERDISCIPLINARY
A91: HUMAN RESOURCE MANAGEMENT REVIEW | B91: ELSEVIER | C91: 35 | D91: =IFERROR(VLOOKUP(A91,eco_bus_journals!A:D,4,0),"") -> 0.84 | E91: =_xlfn.RANK.EQ(D91,D:D) -> 86 | F91: =IFERROR(VLOOKUP(A91,eco_journals!A:D,4,0),"") | G91: =IFERROR(_xlfn.RANK.EQ(F91,F:F),"") | H91: =IFERROR(VLOOKUP(A91,fin_journals!A:D,4,0),"") | I91: =IFERROR(_xlfn.RANK.EQ(H91,H:H),"") | J91: =IFERROR(VLOOKUP(A91,bus_journals!A:D,4,0),"") | K91: =IFERROR(_xlfn.RANK.EQ(J91,J:J),"") | L91: =IFERROR(VLOOKUP(A91,man_journals!A:D,4,0),"") -> 1.02 | M91: =IFERROR(_xlfn.RANK.EQ(L91,L:L),"") -> 32 | N91: MANAGEMENT
A92: EXPLORATIONS IN ECONOMIC HISTORY | B92: ELSEVIER | C92: 23 | D92: =IFERROR(VLOOKUP(A92,eco_bus_journals!A:D,4,0),"") -> 0.83 | E92: =_xlfn.RANK.EQ(D92,D:D) -> 89 | F92: =IFERROR(VLOOKUP(A92,eco_journals!A:D,4,0),"") -> 0.88 | G92: =IFERROR(_xlfn.RANK.EQ(F92,F:F),"") -> 33 | H92: =IFERROR(VLOOKUP(A92,fin_journals!A:D,4,0),"") | I92: =IFERROR(_xlfn.RANK.EQ(H92,H:H),"") | J92: =IFERROR(VLOOKUP(A92,bus_journals!A:D,4,0),"") | K92: =IFERROR(_xlfn.RANK.EQ(J92,J:J),"") | L92: =IFERROR(VLOOKUP(A92,man_journals!A:D,4,0),"") | M92: =IFERROR(_xlfn.RANK.EQ(L92,L:L),"") | N92: ECONOMICS | O92: HISTORY OF SOCIAL SCIENCES
A93: HUMAN RESOURCE MANAGEMENT | B93: WILEY | C93: 50 | D93: =IFERROR(VLOOKUP(A93,eco_bus_journals!A:D,4,0),"") -> 0.8 | E93: =_xlfn.RANK.EQ(D93,D:D) -> 90 | F93: =IFERROR(VLOOKUP(A93,eco_journals!A:D,4,0),"") | G93: =IFERROR(_xlfn.RANK.EQ(F93,F:F),"") | H93: =IFERROR(VLOOKUP(A93,fin_journals!A:D,4,0),"") | I93: =IFERROR(_xlfn.RANK.EQ(H93,H:H),"") | J93: =IFERROR(VLOOKUP(A93,bus_journals!A:D,4,0),"") | K93: =IFERROR(_xlfn.RANK.EQ(J93,J:J),"") | L93: =IFERROR(VLOOKUP(A93,man_journals!A:D,4,0),"") -> 1.14 | M93: =IFERROR(_xlfn.RANK.EQ(L93,L:L),"") -> 26 | N93: MANAGEMENT | O93: PSYCHOLOGY, APPLIED
A94: JOURNAL OF ECONOMIC THEORY | B94: ELSEVIER | C94: 114 | D94: =IFERROR(VLOOKUP(A94,eco_bus_journals!A:D,4,0),"") -> 0.8 | E94: =_xlfn.RANK.EQ(D94,D:D) -> 90 | F94: =IFERROR(VLOOKUP(A94,eco_journals!A:D,4,0),"") -> 0.84 | G94: =IFERROR(_xlfn.RANK.EQ(F94,F:F),"") -> 36 | H94: =IFERROR(VLOOKUP(A94,fin_journals!A:D,4,0),"") | I94: =IFERROR(_xlfn.RANK.EQ(H94,H:H),"") | J94: =IFERROR(VLOOKUP(A94,bus_journals!A:D,4,0),"") | K94: =IFERROR(_xlfn.RANK.EQ(J94,J:J),"") | L94: =IFERROR(VLOOKUP(A94,man_journals!A:D,4,0),"") | M94: =IFERROR(_xlfn.RANK.EQ(L94,L:L),"") | N94: ECONOMICS
A95: ORGANIZATIONAL BEHAVIOR AND HUMAN DECISION PROCESSES | B95: ELSEVIER | C95: 77 | D95: =IFERROR(VLOOKUP(A95,eco_bus_journals!A:D,4,0),"") -> 0.8 | E95: =_xlfn.RANK.EQ(D95,D:D) -> 90 | F95: =IFERROR(VLOOKUP(A95,eco_journals!A:D,4,0),"") | G95: =IFERROR(_xlfn.RANK.EQ(F95,F:F),"") | H95: =IFERROR(VLOOKUP(A95,fin_journals!A:D,4,0),"") | I95: =IFERROR(_xlfn.RANK.EQ(H95,H:H),"") | J95: =IFERROR(VLOOKUP(A95,bus_journals!A:D,4,0),"") | K95: =IFERROR(_xlfn.RANK.EQ(J95,J:J),"") | L95: =IFERROR(VLOOKUP(A95,man_journals!A:D,4,0),"") -> 1.03 | M95: =IFERROR(_xlfn.RANK.EQ(L95,L:L),"") -> 31 | N95: MANAGEMENT | O95: PSYCHOLOGY, APPLIED | P95: PSYCHOLOGY, SOCIAL
A96: JOURNAL OF DEVELOPMENT ECONOMICS | B96: ELSEVIER | C96: 132 | D96: =IFERROR(VLOOKUP(A96,eco_bus_journals!A:D,4,0),"") -> 0.78 | E96: =_xlfn.RANK.EQ(D96,D:D) -> 93 | F96: =IFERROR(VLOOKUP(A96,eco_journals!A:D,4,0),"") -> 0.77 | G96: =IFERROR(_xlfn.RANK.EQ(F96,F:F),"") -> 37 | H96: =IFERROR(VLOOKUP(A96,fin_journals!A:D,4,0),"") | I96: =IFERROR(_xlfn.RANK.EQ(H96,H:H),"") | J96: =IFERROR(VLOOKUP(A96,bus_journals!A:D,4,0),"") | K96: =IFERROR(_xlfn.RANK.EQ(J96,J:J),"") | L96: =IFERROR(VLOOKUP(A96,man_journals!A:D,4,0),"") | M96: =IFERROR(_xlfn.RANK.EQ(L96,L:L),"") | N96: ECONOMICS
A97: JOURNAL OF CORPORATE FINANCE | B97: ELSEVIER | C97: 234 | D97: =IFERROR(VLOOKUP(A97,eco_bus_journals!A:D,4,0),"") -> 0.76 | E97: =_xlfn.RANK.EQ(D97,D:D) -> 94 | F97: =IFERROR(VLOOKUP(A97,eco_journals!A:D,4,0),"") | G97: =IFERROR(_xlfn.RANK.EQ(F97,F:F),"") | H97: =IFERROR(VLOOKUP(A97,fin_journals!A:D,4,0),"") -> 1.12 | I97: =IFERROR(_xlfn.RANK.EQ(H97,H:H),"") -> 15 | J97: =IFERROR(VLOOKUP(A97,bus_journals!A:D,4,0),"") | K97: =IFERROR(_xlfn.RANK.EQ(J97,J:J),"") | L97: =IFERROR(VLOOKUP(A97,man_journals!A:D,4,0),"") | M97: =IFERROR(_xlfn.RANK.EQ(L97,L:L),"") | N97: FINANCE
A98: JOURNAL OF INTERNATIONAL MARKETING | B98: SAGE PUBLICATIONS | C98: 21 | D98: =IFERROR(VLOOKUP(A98,eco_bus_journals!A:D,4,0),"") -> 0.76 | E98: =_xlfn.RANK.EQ(D98,D:D) -> 94 | F98: =IFERROR(VLOOKUP(A98,eco_journals!A:D,4,0),"") | G98: =IFERROR(_xlfn.RANK.EQ(F98,F:F),"") | H98: =IFERROR(VLOOKUP(A98,fin_journals!A:D,4,0),"") | I98: =IFERROR(_xlfn.RANK.EQ(H98,H:H),"") | J98: =IFERROR(VLOOKUP(A98,bus_journals!A:D,4,0),"") -> 1.62 | K98: =IFERROR(_xlfn.RANK.EQ(J98,J:J),"") -> 31 | L98: =IFERROR(VLOOKUP(A98,man_journals!A:D,4,0),"") | M98: =IFERROR(_xlfn.RANK.EQ(L98,L:L),"") | N98: BUSINESS
A99: BUSINESS ETHICS QUARTERLY | B99: CAMBRIDGE UNIV PRESS | C99: 18 | D99: =IFERROR(VLOOKUP(A99,eco_bus_journals!A:D,4,0),"") -> 0.75 | E99: =_xlfn.RANK.EQ(D99,D:D) -> 96 | F99: =IFERROR(VLOOKUP(A99,eco_journals!A:D,4,0),"") | G99: =IFERROR(_xlfn.RANK.EQ(F99,F:F),"") | H99: =IFERROR(VLOOKUP(A99,fin_journals!A:D,4,0),"") | I99: =IFERROR(_xlfn.RANK.EQ(H99,H:H),"") | J99: =IFERROR(VLOOKUP(A99,bus_journals!A:D,4,0),"") -> 1.2 | K99: =IFERROR(_xlfn.RANK.EQ(J99,J:J),"") -> 40 | L99: =IFERROR(VLOOKUP(A99,man_journals!A:D,4,0),"") | M99: =IFERROR(_xlfn.RANK.EQ(L99,L:L),"") | N99: BUSINESS | O99: ETHICS
A100: CONTEMPORARY ACCOUNTING RESEARCH | B100: WILEY | C100: 113 | D100: =IFERROR(VLOOKUP(A100,eco_bus_journals!A:D,4,0),"") -> 0.74 | E100: =_xlfn.RANK.EQ(D100,D:D) -> 97 | F100: =IFERROR(VLOOKUP(A100,eco_journals!A:D,4,0),"") | G100: =IFERROR(_xlfn.RANK.EQ(F100,F:F),"") | H100: =IFERROR(VLOOKUP(A100,fin_journals!A:D,4,0),"") -> 3.11 | I100: =IFERROR(_xlfn.RANK.EQ(H100,H:H),"") -> 9 | J100: =IFERROR(VLOOKUP(A100,bus_journals!A:D,4,0),"") | K100: =IFERROR(_xlfn.RANK.EQ(J100,J:J),"") | L100: =IFERROR(VLOOKUP(A100,man_journals!A:D,4,0),"") | M100: =IFERROR(_xlfn.RANK.EQ(L100,L:L),"") | N100: FINANCE
...

Sheet institutions_spss
D1: eb | E1: e | F1: f | G1: b | H1: m | Y1: aus | AB1: For comparisons, place two countries in Y1 and Y2 | AR1: country | AT1: 0 | AU1: 1
A2: institution | C2: country | D2: pub | E2: pub | F2: pub | G2: pub | H2: pub | I2: score | J2: score | K2: score | L2: score | M2: score | N2: rank | O2: rank | P2: rank | Q2: rank | R2: rank | W2: ranks | AB2: For a country alone, leave Y2 blank | AR2: WALES | AS2: UK | AT2: -0.10518436 | AU2: 3.2209162 | AW2: institution
A3: institution | C3: country | D3: ebpub | E3: epub | F3: fpub | G3: bpub | H3: mpub | I3: ebscore | J3: escore | K3: fscore | L3: bscore | M3: mscore | N3: ebrank | O3: erank | P3: frank | Q3: brank | R3: mrank | W3: pc1 | X3: pc2 | Y3: country | Z3: for plot | AB3: First Component, pc1: associated with all four categories (comprehensive institutions perform better) | AR3: VIETNAM | AS3: VTN | AT3: 1.8566266 | AU3: 1.5835011 | AW3: institution
A4: Center for Economic & Policy Research (CEPR) | B4: CEPR | C4: USA | D4: =IFERROR(VLOOKUP(A4,eco_bus_institutions!A:D,3,0),"") -> 158 | E4: =IFERROR(VLOOKUP(A4,eco_institutions!A:D,3,0),"") -> 151 | F4: =IFERROR(VLOOKUP(A4,fin_institutions!A:D,3,0),"") -> 43 | G4: =IFERROR(VLOOKUP(A4,bus_institutions!A:D,3,0),0) -> 0 | H4: =IFERROR(VLOOKUP(A4,man_institutions!A:D,3,0),0) -> 0 | I4: =IFERROR(VLOOKUP(A4,eco_bus_institutions!A:D,4,0),0) -> 8 | J4: =IFERROR(VLOOKUP(A4,eco_institutions!A:D,4,0),0) -> 7.34 | K4: =IFERROR(VLOOKUP(A4,fin_institutions!A:D,4,0),0) -> 4.91 | L4: =IFERROR(VLOOKUP(A4,bus_institutions!A:D,4,0),0) -> 0 | M4: =IFERROR(VLOOKUP(A4,man_institutions!A:D,4,0),0) -> 0 | N4: =ROUND(IFERROR((601-_xlfn.RANK.EQ(I4,I:I))/600,0),3) -> 1 | O4: =ROUND(IFERROR((601-IFERROR(_xlfn.RANK.EQ(J4,J:J),""))/600,0),3) -> 0.997 | P4: =ROUND(IFERROR((601-IFERROR(_xlfn.RANK.EQ(K4,K:K),""))/600,0),3) -> 0.978 | Q4: =ROUND(IFERROR((601-IFERROR(_xlfn.RANK.EQ(L4,L:L),""))/600,0),3) -> 0.05 | R4: =ROUND(IFERROR((601-IFERROR(_xlfn.RANK.EQ(M4,M:M),""))/600,0),3) -> 0.04 | S4: =VLOOKUP(A4,#REF!,11,0) -> #REF! | T4: =VLOOKUP(A4,#REF!,12,0) -> #REF! | U4: =VLOOKUP(A4,#REF!,13,0) -> #REF! | V4: =VLOOKUP(A4,#REF!,14,0) -> #REF! | W4: -0.10518436 | X4: 3.2209162 | Y4: =VLOOKUP(C4,AR:AS,2,0) -> USA | Z4: =IF(Y4=Y$1,B4,IF(Y4=Y$2,B4,"")) | AB4: Second Component: North (Economics and Finance), South (Business and Management) | AR4: USA | AS4: USA | AT4: 3.3461328 | AU4: 0.29500451 | AW4: Center for Economic & Policy Research (CEPR)
A5: University of Chicago | B5: Chicago | C5: USA | D5: =IFERROR(VLOOKUP(A5,eco_bus_institutions!A:D,3,0),"") -> 203 | E5: =IFERROR(VLOOKUP(A5,eco_institutions!A:D,3,0),"") -> 157 | F5: =IFERROR(VLOOKUP(A5,fin_institutions!A:D,3,0),"") -> 49 | G5: =IFERROR(VLOOKUP(A5,bus_institutions!A:D,3,0),0) -> 18 | H5: =IFERROR(VLOOKUP(A5,man_institutions!A:D,3,0),0) -> 9 | I5: =IFERROR(VLOOKUP(A5,eco_bus_institutions!A:D,4,0),0) -> 7.88 | J5: =IFERROR(VLOOKUP(A5,eco_institutions!A:D,4,0),0) -> 7.96 | K5: =IFERROR(VLOOKUP(A5,fin_institutions!A:D,4,0),0) -> 6.92 | L5: =IFERROR(VLOOKUP(A5,bus_institutions!A:D,4,0),0) -> 3 | M5: =IFERROR(VLOOKUP(A5,man_institutions!A:D,4,0),0) -> 1.31 | N5: =ROUND(IFERROR((601-_xlfn.RANK.EQ(I5,I:I))/600,0),3) -> 0.998 | O5: =ROUND(IFERROR((601-IFERROR(_xlfn.RANK.EQ(J5,J:J),""))/600,0),3) -> 0.998 | P5: =ROUND(IFERROR((601-IFERROR(_xlfn.RANK.EQ(K5,K:K),""))/600,0),3) -> 0.995 | Q5: =ROUND(IFERROR((601-IFERROR(_xlfn.RANK.EQ(L5,L:L),""))/600,0),3) -> 0.797 | R5: =ROUND(IFERROR((601-IFERROR(_xlfn.RANK.EQ(M5,M:M),""))/600,0),3) -> 0.338 | S5: =VLOOKUP(A5,#REF!,11,0) -> #REF! | T5: =VLOOKUP(A5,#REF!,12,0) -> #REF! | U5: =VLOOKUP(A5,#REF!,13,0) -> #REF! | V5: =VLOOKUP(A5,#REF!,14,0) -> #REF! | W5: 1.8566266 | X5: 1.5835011 | Y5: =VLOOKUP(C5,AR:AS,2,0) -> USA | Z5: =IF(Y5=Y$1,B5,IF(Y5=Y$2,B5,"")) | AB5: 88% of the variance explained | AR5: UNITED ARAB EMIRATES | AS5: UAE | AT5: -0.28326645 | AU5: 3.0913155 | AW5: Chicago
A6: London Business School | B6: LBS | C6: ENGLAND | D6: =IFERROR(VLOOKUP(A6,eco_bus_institutions!A:D,3,0),"") -> 61 | E6: =IFERROR(VLOOKUP(A6,eco_institutions!A:D,3,0),"") -> 30 | F6: =IFERROR(VLOOKUP(A6,fin_institutions!A:D,3,0),"") -> 16 | G6: =IFERROR(VLOOKUP(A6,bus_institutions!A:D,3,0),0) -> 23 | H6: =IFERROR(VLOOKUP(A6,man_institutions!A:D,3,0),0) -> 22 | I6: =IFERROR(VLOOKUP(A6,eco_bus_institutions!A:D,4,0),0) -> 7.33 | J6: =IFERROR(VLOOKUP(A6,eco_institutions!A:D,4,0),0) -> 8 | K6: =IFERROR(VLOOKUP(A6,fin_institutions!A:D,4,0),0) -> 5.11 | L6: =IFERROR(VLOOKUP(A6,bus_institutions!A:D,4,0),0) -> 6.39 | M6: =IFERROR(VLOOKUP(A6,man_institutions!A:D,4,0),0) -> 5.05 | N6: =ROUND(IFERROR((601-_xlfn.RANK.EQ(I6,I:I))/600,0),3) -> 0.997 | O6: =ROUND(IFERROR((601-IFERROR(_xlfn.RANK.EQ(J6,J:J),""))/600,0),3) -> 1 | P6: =ROUND(IFERROR((601-IFERROR(_xlfn.RANK.EQ(K6,K:K),""))/600,0),3) -> 0.982 | Q6: =ROUND(IFERROR((601-IFERROR(_xlfn.RANK.EQ(L6,L:L),""))/600,0),3) -> 0.98 | R6: =ROUND(IFERROR((601-IFERROR(_xlfn.RANK.EQ(M6,M:M),""))/600,0),3) -> 0.97 | S6: =VLOOKUP(A6,#REF!,11,0) -> #REF! | T6: =VLOOKUP(A6,#REF!,12,0) -> #REF! | U6: =VLOOKUP(A6,#REF!,13,0) -> #REF! | V6: =VLOOKUP(A6,#REF!,14,0) -> #REF! | W6: 3.3461328 | X6: 0.29500451 | Y6: =VLOOKUP(C6,AR:AS,2,0) -> UK | Z6: =IF(Y6=Y$1,B6,IF(Y6=Y$2,B6,"")) | AR6: TURKIYE | AS6: TUR | AT6: 1.4781418 | AU6: -0.10513947 | AW6: London Business School
A7: Princeton University | B7: Princeton | C7: USA | D7: =IFERROR(VLOOKUP(A7,eco_bus_institutions!A:D,3,0),"") -> 113 | E7: =IFERROR(VLOOKUP(A7,eco_institutions!A:D,3,0),"") -> 101 | F7: =IFERROR(VLOOKUP(A7,fin_institutions!A:D,3,0),"") -> 18 | G7: =IFERROR(VLOOKUP(A7,bus_institutions!A:D,3,0),0) -> 0 | H7: =IFERROR(VLOOKUP(A7,man_institutions!A:D,3,0),0) -> 0 | I7: =IFERROR(VLOOKUP(A7,eco_bus_institutions!A:D,4,0),0) -> 7.19 | J7: =IFERROR(VLOOKUP(A7,eco_institutions!A:D,4,0),0) -> 7.18 | K7: =IFERROR(VLOOKUP(A7,fin_institutions!A:D,4,0),0) -> 2.75 | L7: =IFERROR(VLOOKUP(A7,bus_institutions!A:D,4,0),0) -> 0 | M7: =IFERROR(VLOOKUP(A7,man_institutions!A:D,4,0),0) -> 0 | N7: =ROUND(IFERROR((601-_xlfn.RANK.EQ(I7,I:I))/600,0),3) -> 0.995 | O7: =ROUND(IFERROR((601-IFERROR(_xlfn.RANK.EQ(J7,J:J),""))/600,0),3) -> 0.995 | P7: =ROUND(IFERROR((601-IFERROR(_xlfn.RANK.EQ(K7,K:K),""))/600,0),3) -> 0.878 | Q7: =ROUND(IFERROR((601-IFERROR(_xlfn.RANK.EQ(L7,L:L),""))/600,0),3) -> 0.05 | R7: =ROUND(IFERROR((601-IFERROR(_xlfn.RANK.EQ(M7,M:M),""))/600,0),3) -> 0.04 | S7: =VLOOKUP(A7,#REF!,11,0) -> #REF! | T7: =VLOOKUP(A7,#REF!,12,0) -> #REF! | U7: =VLOOKUP(A7,#REF!,13,0) -> #REF! | V7: =VLOOKUP(A7,#REF!,14,0) -> #REF! | W7: -0.28326645 | X7: 3.0913155 | Y7: =VLOOKUP(C7,AR:AS,2,0) -> USA | Z7: =IF(Y7=Y$1,B7,IF(Y7=Y$2,B7,"")) | AB7: NorthEast Direction signals excellence | AR7: TUNISIA | AS7: TUN | AT7: 3.4243678 | AU7: 0.21550734 | AW7: Princeton
A8: University of California Santa Barbara | B8: UCSB | C8: USA | D8: =IFERROR(VLOOKUP(A8,eco_bus_institutions!A:D,3,0),"") -> 56 | E8: =IFERROR(VLOOKUP(A8,eco_institutions!A:D,3,0),"") -> 44 | F8: =IFERROR(VLOOKUP(A8,fin_institutions!A:D,3,0),"") -> 6 | G8: =IFERROR(VLOOKUP(A8,bus_institutions!A:D,3,0),0) -> 5 | H8: =IFERROR(VLOOKUP(A8,man_institutions!A:D,3,0),0) -> 10 | I8: =IFERROR(VLOOKUP(A8,eco_bus_institutions!A:D,4,0),0) -> 6.86 | J8: =IFERROR(VLOOKUP(A8,eco_institutions!A:D,4,0),0) -> 6.93 | K8: =IFERROR(VLOOKUP(A8,fin_institutions!A:D,4,0),0) -> 1.06 | L8: =IFERROR(VLOOKUP(A8,bus_institutions!A:D,4,0),0) -> 2.31 | M8: =IFERROR(VLOOKUP(A8,man_institutions!A:D,4,0),0) -> 4.9 | N8: =ROUND(IFERROR((601-_xlfn.RANK.EQ(I8,I:I))/600,0),3) -> 0.993 | O8: =ROUND(IFERROR((601-IFERROR(_xlfn.RANK.EQ(J8,J:J),""))/600,0),3) -> 0.992 | P8: =ROUND(IFERROR((601-IFERROR(_xlfn.RANK.EQ(K8,K:K),""))/600,0),3) -> 0.262 | Q8: =ROUND(IFERROR((601-IFERROR(_xlfn.RANK.EQ(L8,L:L),""))/600,0),3) -> 0.662 | R8: =ROUND(IFERROR((601-IFERROR(_xlfn.RANK.EQ(M8,M:M),""))/600,0),3) -> 0.965 | S8: =VLOOKUP(A8,#REF!,11,0) -> #REF! | T8: =VLOOKUP(A8,#REF!,12,0) -> #REF! | U8: =VLOOKUP(A8,#REF!,13,0) -> #REF! | V8: =VLOOKUP(A8,#REF!,14,0) -> #REF! | W8: 1.4781418 | X8: -0.10513947 | Y8: =VLOOKUP(C8,AR:AS,2,0) -> USA | Z8: =IF(Y8=Y$1,B8,IF(Y8=Y$2,B8,"")) | AB8: To compare, move an imaginary NW to SE line: better to be on the right of that line | AR8: TAIWAN | AS8: TWN | AT8: 3.013365 | AU8: 0.40613106 | AW8: California Santa Barbara
A9: Stanford University | B9: Stanford | C9: USA | D9: =IFERROR(VLOOKUP(A9,eco_bus_institutions!A:D,3,0),"") -> 273 | E9: =IFERROR(VLOOKUP(A9,eco_institutions!A:D,3,0),"") -> 196 | F9: =IFERROR(VLOOKUP(A9,fin_institutions!A:D,3,0),"") -> 44 | G9: =IFERROR(VLOOKUP(A9,bus_institutions!A:D,3,0),0) -> 37 | H9: =IFERROR(VLOOKUP(A9,man_institutions!A:D,3,0),0) -> 59 | I9: =IFERROR(VLOOKUP(A9,eco_bus_institutions!A:D,4,0),0) -> 6.58 | J9: =IFERROR(VLOOKUP(A9,eco_institutions!A:D,4,0),0) -> 5.84 | K9: =IFERROR(VLOOKUP(A9,fin_institutions!A:D,4,0),0) -> 7.99 | L9: =IFERROR(VLOOKUP(A9,bus_institutions!A:D,4,0),0) -> 6.87 | M9: =IFERROR(VLOOKUP(A9,man_institutions!A:D,4,0),0) -> 6.92 | N9: =ROUND(IFERROR((601-_xlfn.RANK.EQ(I9,I:I))/600,0),3) -> 0.992 | O9: =ROUND(IFERROR((601-IFERROR(_xlfn.RANK.EQ(J9,J:J),""))/600,0),3) -> 0.985 | P9: =ROUND(IFERROR((601-IFERROR(_xlfn.RANK.EQ(K9,K:K),""))/600,0),3) -> 0.998 | Q9: =ROUND(IFERROR((601-IFERROR(_xlfn.RANK.EQ(L9,L:L),""))/600,0),3) -> 0.995 | R9: =ROUND(IFERROR((601-IFERROR(_xlfn.RANK.EQ(M9,M:M),""))/600,0),3) -> 0.995 | S9: =VLOOKUP(A9,#REF!,11,0) -> #REF! | T9: =VLOOKUP(A9,#REF!,12,0) -> #REF! | U9: =VLOOKUP(A9,#REF!,13,0) -> #REF! | V9: =VLOOKUP(A9,#REF!,14,0) -> #REF! | W9: 3.4243678 | X9: 0.21550734 | Y9: =VLOOKUP(C9,AR:AS,2,0) -> USA | Z9: =IF(Y9=Y$1,B9,IF(Y9=Y$2,B9,"")) | AR9: SWITZERLAND | AS9: CHE | AT9: 3.3847108 | AU9: 0.22807663 | AW9: Stanford
A10: Massachusetts Institute of Technology (MIT) | B10: MIT | C10: USA | D10: =IFERROR(VLOOKUP(A10,eco_bus_institutions!A:D,3,0),"") -> 244 | E10: =IFERROR(VLOOKUP(A10,eco_institutions!A:D,3,0),"") -> 152 | F10: =IFERROR(VLOOKUP(A10,fin_institutions!A:D,3,0),"") -> 49 | G10: =IFERROR(VLOOKUP(A10,bus_institutions!A:D,3,0),0) -> 33 | H10: =IFERROR(VLOOKUP(A10,man_institutions!A:D,3,0),0) -> 65 | I10: =IFERROR(VLOOKUP(A10,eco_bus_institutions!A:D,4,0),0) -> 6.37 | J10: =IFERROR(VLOOKUP(A10,eco_institutions!A:D,4,0),0) -> 6.95 | K10: =IFERROR(VLOOKUP(A10,fin_institutions!A:D,4,0),0) -> 3.57 | L10: =IFERROR(VLOOKUP(A10,bus_institutions!A:D,4,0),0) -> 3.91 | M10: =IFERROR(VLOOKUP(A10,man_institutions!A:D,4,0),0) -> 3.97 | N10: =ROUND(IFERROR((601-_xlfn.RANK.EQ(I10,I:I))/600,0),3) -> 0.99 | O10: =ROUND(IFERROR((601-IFERROR(_xlfn.RANK.EQ(J10,J:J),""))/600,0),3) -> 0.993 | P10: =ROUND(IFERROR((601-IFERROR(_xlfn.RANK.EQ(K10,K:K),""))/600,0),3) -> 0.928 | Q10: =ROUND(IFERROR((601-IFERROR(_xlfn.RANK.EQ(L10,L:L),""))/600,0),3) -> 0.892 | R10: =ROUND(IFERROR((601-IFERROR(_xlfn.RANK.EQ(M10,M:M),""))/600,0),3) -> 0.935 | S10: =VLOOKUP(A10,#REF!,11,0) -> #REF! | T10: =VLOOKUP(A10,#REF!,12,0) -> #REF! | U10: =VLOOKUP(A10,#REF!,13,0) -> #REF! | V10: =VLOOKUP(A10,#REF!,14,0) -> #REF! | W10: 3.013365 | X10: 0.40613106 | Y10: =VLOOKUP(C10,AR:AS,2,0) -> USA | Z10: =IF(Y10=Y$1,B10,IF(Y10=Y$2,B10,"")) | AB10: For Australia | AR10: SWEDEN | AS10: SWE | AT10: -1.7444902 | AU10: 2.02713 | AW10: MIT
A11: Yale University | B11: Yale | C11: USA | D11: =IFERROR(VLOOKUP(A11,eco_bus_institutions!A:D,3,0),"") -> 165 | E11: =IFERROR(VLOOKUP(A11,eco_institutions!A:D,3,0),"") -> 134 | F11: =IFERROR(VLOOKUP(A11,fin_institutions!A:D,3,0),"") -> 27 | G11: =IFERROR(VLOOKUP(A11,bus_institutions!A:D,3,0),0) -> 13 | H11: =IFERROR(VLOOKUP(A11,man_institutions!A:D,3,0),0) -> 14 | I11: =IFERROR(VLOOKUP(A11,eco_bus_institutions!A:D,4,0),0) -> 6.15 | J11: =IFERROR(VLOOKUP(A11,eco_institutions!A:D,4,0),0) -> 5.66 | K11: =IFERROR(VLOOKUP(A11,fin_institutions!A:D,4,0),0) -> 6.49 | L11: =IFERROR(VLOOKUP(A11,bus_institutions!A:D,4,0),0) -> 6.61 | M11: =IFERROR(VLOOKUP(A11,man_institutions!A:D,4,0),0) -> 6.09 | N11: =ROUND(IFERROR((601-_xlfn.RANK.EQ(I11,I:I))/600,0),3) -> 0.988 | O11: =ROUND(IFERROR((601-IFERROR(_xlfn.RANK.EQ(J11,J:J),""))/600,0),3) -> 0.983 | P11: =ROUND(IFERROR((601-IFERROR(_xlfn.RANK.EQ(K11,K:K),""))/600,0),3) -> 0.993 | Q11: =ROUND(IFERROR((601-IFERROR(_xlfn.RANK.EQ(L11,L:L),""))/600,0),3) -> 0.988 | R11: =ROUND(IFERROR((601-IFERROR(_xlfn.RANK.EQ(M11,M:M),""))/600,0),3) -> 0.987 | S11: =VLOOKUP(A11,#REF!,11,0) -> #REF! | T11: =VLOOKUP(A11,#REF!,12,0) -> #REF! | U11: =VLOOKUP(A11,#REF!,13,0) -> #REF! | V11: =VLOOKUP(A11,#REF!,14,0) -> #REF! | W11: 3.3847108 | X11: 0.22807663 | Y11: =VLOOKUP(C11,AR:AS,2,0) -> USA | Z11: =IF(Y11=Y$1,B11,IF(Y11=Y$2,B11,"")) | AB11: Cluster 1: Best performers | AC11: Adelaide, ANU, Melbourne | AR11: SPAIN | AS11: SPAIN | AT11: 3.055082 | AU11: 0.39959249 | AW11: Yale
A12: National Bureau of Economic Research | B12: NBER | C12: USA | D12: =IFERROR(VLOOKUP(A12,eco_bus_institutions!A:D,3,0),"") -> 724 | E12: =IFERROR(VLOOKUP(A12,eco_institutions!A:D,3,0),"") -> 710 | F12: =IFERROR(VLOOKUP(A12,fin_institutions!A:D,3,0),"") | G12: =IFERROR(VLOOKUP(A12,bus_institutions!A:D,3,0),0) -> 0 | H12: =IFERROR(VLOOKUP(A12,man_institutions!A:D,3,0),0) -> 0 | I12: =IFERROR(VLOOKUP(A12,eco_bus_institutions!A:D,4,0),0) -> 5.99 | J12: =IFERROR(VLOOKUP(A12,eco_institutions!A:D,4,0),0) -> 5.19 | K12: =IFERROR(VLOOKUP(A12,fin_institutions!A:D,4,0),0) -> 0 | L12: =IFERROR(VLOOKUP(A12,bus_institutions!A:D,4,0),0) -> 0 | M12: =IFERROR(VLOOKUP(A12,man_institutions!A:D,4,0),0) -> 0 | N12: =ROUND(IFERROR((601-_xlfn.RANK.EQ(I12,I:I))/600,0),3) -> 0.987 | O12: =ROUND(IFERROR((601-IFERROR(_xlfn.RANK.EQ(J12,J:J),""))/600,0),3) -> 0.978 | P12: =ROUND(IFERROR((601-IFERROR(_xlfn.RANK.EQ(K12,K:K),""))/600,0),3) -> 0.058 | Q12: =ROUND(IFERROR((601-IFERROR(_xlfn.RANK.EQ(L12,L:L),""))/600,0),3) -> 0.05 | R12: =ROUND(IFERROR((601-IFERROR(_xlfn.RANK.EQ(M12,M:M),""))/600,0),3) -> 0.04 | S12: =VLOOKUP(A12,#REF!,11,0) -> #REF! | T12: =VLOOKUP(A12,#REF!,12,0) -> #REF! | U12: =VLOOKUP(A12,#REF!,13,0) -> #REF! | V12: =VLOOKUP(A12,#REF!,14,0) -> #REF! | W12: -1.7444902 | X12: 2.02713 | Y12: =VLOOKUP(C12,AR:AS,2,0) -> USA | Z12: =IF(Y12=Y$1,B12,IF(Y12=Y$2,B12,"")) | AB12: Cluster 2: Fast followers | AC12: UTAS,Western Aus, La Trobe, Wollongong, Maquarie, RMIT, Deakin, UTS, Sifney, Queensland | AR12: SOUTH KOREA | AS12: KOREA | AT12: 2.8276361 | AU12: 0.56199511 | AW12: National Bureau of Economic Research
A13: Harvard University | B13: Harvard | C13: USA | D13: =IFERROR(VLOOKUP(A13,eco_bus_institutions!A:D,3,0),"") -> 430 | E13: =IFERROR(VLOOKUP(A13,eco_institutions!A:D,3,0),"") -> 265 | F13: =IFERROR(VLOOKUP(A13,fin_institutions!A:D,3,0),"") -> 52 | G13: =IFERROR(VLOOKUP(A13,bus_institutions!A:D,3,0),0) -> 85 | H13: =IFERROR(VLOOKUP(A13,man_institutions!A:D,3,0),0) -> 106 | I13: =IFERROR(VLOOKUP(A13,eco_bus_institutions!A:D,4,0),0) -> 5.87 | J13: =IFERROR(VLOOKUP(A13,eco_institutions!A:D,4,0),0) -> 6.65 | K13: =IFERROR(VLOOKUP(A13,fin_institutions!A:D,4,0),0) -> 3.92 | L13: =IFERROR(VLOOKUP(A13,bus_institutions!A:D,4,0),0) -> 4.04 | M13: =IFERROR(VLOOKUP(A13,man_institutions!A:D,4,0),0) -> 3.85 | N13: =ROUND(IFERROR((601-_xlfn.RANK.EQ(I13,I:I))/600,0),3) -> 0.985 | O13: =ROUND(IFERROR((601-IFERROR(_xlfn.RANK.EQ(J13,J:J),""))/600,0),3) -> 0.99 | P13: =ROUND(IFERROR((601-IFERROR(_xlfn.RANK.EQ(K13,K:K),""))/600,0),3) -> 0.943 | Q13: =ROUND(IFERROR((601-IFERROR(_xlfn.RANK.EQ(L13,L:L),""))/600,0),3) -> 0.91 | R13: =ROUND(IFERROR((601-IFERROR(_xlfn.RANK.EQ(M13,M:M),""))/600,0),3) -> 0.928 | S13: =VLOOKUP(A13,#REF!,11,0) -> #REF! | T13: =VLOOKUP(A13,#REF!,12,0) -> #REF! | U13: =VLOOKUP(A13,#REF!,13,0) -> #REF! | V13: =VLOOKUP(A13,#REF!,14,0) -> #REF! | W13: 3.055082 | X13: 0.39959249 | Y13: =VLOOKUP(C13,AR:AS,2,0) -> USA | Z13: =IF(Y13=Y$1,B13,IF(Y13=Y$2,B13,"")) | AB13: Cluster 3: Followers | AC13: Edith Cowan, South Australia | AR13: SOUTH AFRICA | AS13: ZAF | AT13: 3.2338538 | AU13: 0.068263435 | AW13: Harvard
A14: University of California Berkeley | B14: UCB | C14: USA | D14: =IFERROR(VLOOKUP(A14,eco_bus_institutions!A:D,3,0),"") -> 207 | E14: =IFERROR(VLOOKUP(A14,eco_institutions!A:D,3,0),"") -> 156 | F14: =IFERROR(VLOOKUP(A14,fin_institutions!A:D,3,0),"") -> 28 | G14: =IFERROR(VLOOKUP(A14,bus_institutions!A:D,3,0),0) -> 26 | H14: =IFERROR(VLOOKUP(A14,man_institutions!A:D,3,0),0) -> 45 | I14: =IFERROR(VLOOKUP(A14,eco_bus_institutions!A:D,4,0),0) -> 5.47 | J14: =IFERROR(VLOOKUP(A14,eco_institutions!A:D,4,0),0) -> 5.61 | K14: =IFERROR(VLOOKUP(A14,fin_institutions!A:D,4,0),0) -> 3.92 | L14: =IFERROR(VLOOKUP(A14,bus_institutions!A:D,4,0),0) -> 3.84 | M14: =IFERROR(VLOOKUP(A14,man_institutions!A:D,4,0),0) -> 2.78 | N14: =ROUND(IFERROR((601-_xlfn.RANK.EQ(I14,I:I))/600,0),3) -> 0.983 | O14: =ROUND(IFERROR((601-IFERROR(_xlfn.RANK.EQ(J14,J:J),""))/600,0),3) -> 0.982 | P14: =ROUND(IFERROR((601-IFERROR(_xlfn.RANK.EQ(K14,K:K),""))/600,0),3) -> 0.943 | Q14: =ROUND(IFERROR((601-IFERROR(_xlfn.RANK.EQ(L14,L:L),""))/600,0),3) -> 0.882 | R14: =ROUND(IFERROR((601-IFERROR(_xlfn.RANK.EQ(M14,M:M),""))/600,0),3) -> 0.84 | S14: =VLOOKUP(A14,#REF!,11,0) -> #REF! | T14: =VLOOKUP(A14,#REF!,12,0) -> #REF! | U14: =VLOOKUP(A14,#REF!,13,0) -> #REF! | V14: =VLOOKUP(A14,#REF!,14,0) -> #REF! | W14: 2.8276361 | X14: 0.56199511 | Y14: =VLOOKUP(C14,AR:AS,2,0) -> USA | Z14: =IF(Y14=Y$1,B14,IF(Y14=Y$2,B14,"")) | AB14: Cluster 4: Laggers | AC14: Curtin, Griffith, QUT, Newcastle, Swinburne | AR14: SLOVAKIA | AS14: SLK | AT14: 3.255072 | AU14: 0.29919178 | AW14: California Berkeley
A15: Boston University | B15: Boston | C15: USA | D15: =IFERROR(VLOOKUP(A15,eco_bus_institutions!A:D,3,0),"") -> 126 | E15: =IFERROR(VLOOKUP(A15,eco_institutions!A:D,3,0),"") -> 73 | F15: =IFERROR(VLOOKUP(A15,fin_institutions!A:D,3,0),"") -> 23 | G15: =IFERROR(VLOOKUP(A15,bus_institutions!A:D,3,0),0) -> 21 | H15: =IFERROR(VLOOKUP(A15,man_institutions!A:D,3,0),0) -> 30 | I15: =IFERROR(VLOOKUP(A15,eco_bus_institutions!A:D,4,0),0) -> 5.22 | J15: =IFERROR(VLOOKUP(A15,eco_institutions!A:D,4,0),0) -> 4.72 | K15: =IFERROR(VLOOKUP(A15,fin_institutions!A:D,4,0),0) -> 3.14 | L15: =IFERROR(VLOOKUP(A15,bus_institutions!A:D,4,0),0) -> 8 | M15: =IFERROR(VLOOKUP(A15,man_institutions!A:D,4,0),0) -> 6.27 | N15: =ROUND(IFERROR((601-_xlfn.RANK.EQ(I15,I:I))/600,0),3) -> 0.982 | O15: =ROUND(IFERROR((601-IFERROR(_xlfn.RANK.EQ(J15,J:J),""))/600,0),3) -> 0.972 | P15: =ROUND(IFERROR((601-IFERROR(_xlfn.RANK.EQ(K15,K:K),""))/600,0),3) -> 0.903 | Q15: =ROUND(IFERROR((601-IFERROR(_xlfn.RANK.EQ(L15,L:L),""))/600,0),3) -> 1 | R15: =ROUND(IFERROR((601-IFERROR(_xlfn.RANK.EQ(M15,M:M),""))/600,0),3) -> 0.988 | S15: =VLOOKUP(A15,#REF!,11,0) -> #REF! | T15: =VLOOKUP(A15,#REF!,12,0) -> #REF! | U15: =VLOOKUP(A15,#REF!,13,0) -> #REF! | V15: =VLOOKUP(A15,#REF!,14,0) -> #REF! | W15: 3.2338538 | X15: 0.068263435 | Y15: =VLOOKUP(C15,AR:AS,2,0) -> USA | Z15: =IF(Y15=Y$1,B15,IF(Y15=Y$2,B15,"")) | AR15: SINGAPORE | AS15: SGP | AT15: -0.17839576 | AU15: 2.5538865 | AW15: Boston
A16: Northwestern University | B16: Northwestern | C16: USA | D16: =IFERROR(VLOOKUP(A16,eco_bus_institutions!A:D,3,0),"") -> 180 | E16: =IFERROR(VLOOKUP(A16,eco_institutions!A:D,3,0),"") -> 102 | F16: =IFERROR(VLOOKUP(A16,fin_institutions!A:D,3,0),"") -> 9 | G16: =IFERROR(VLOOKUP(A16,bus_institutions!A:D,3,0),0) -> 48 | H16: =IFERROR(VLOOKUP(A16,man_institutions!A:D,3,0),0) -> 52 | I16: =IFERROR(VLOOKUP(A16,eco_bus_institutions!A:D,4,0),0) -> 5.16 | J16: =IFERROR(VLOOKUP(A16,eco_institutions!A:D,4,0),0) -> 5.24 | K16: =IFERROR(VLOOKUP(A16,fin_institutions!A:D,4,0),0) -> 5.24 | L16: =IFERROR(VLOOKUP(A16,bus_institutions!A:D,4,0),0) -> 5.76 | M16: =IFERROR(VLOOKUP(A16,man_institutions!A:D,4,0),0) -> 4.07 | N16: =ROUND(IFERROR((601-_xlfn.RANK.EQ(I16,I:I))/600,0),3) -> 0.98 | O16: =ROUND(IFERROR((601-IFERROR(_xlfn.RANK.EQ(J16,J:J),""))/600,0),3) -> 0.98 | P16: =ROUND(IFERROR((601-IFERROR(_xlfn.RANK.EQ(K16,K:K),""))/600,0),3) -> 0.983 | Q16: =ROUND(IFERROR((601-IFERROR(_xlfn.RANK.EQ(L16,L:L),""))/600,0),3) -> 0.975 | R16: =ROUND(IFERROR((601-IFERROR(_xlfn.RANK.EQ(M16,M:M),""))/600,0),3) -> 0.942 | S16: =VLOOKUP(A16,#REF!,11,0) -> #REF! | T16: =VLOOKUP(A16,#REF!,12,0) -> #REF! | U16: =VLOOKUP(A16,#REF!,13,0) -> #REF! | V16: =VLOOKUP(A16,#REF!,14,0) -> #REF! | W16: 3.255072 | X16: 0.29919178 | Y16: =VLOOKUP(C16,AR:AS,2,0) -> USA | Z16: =IF(Y16=Y$1,B16,IF(Y16=Y$2,B16,"")) | AR16: SERBIA | AS16: SERBIA | AT16: 2.941224 | AU16: 0.49513781 | AW16: Northwestern
A17: Pompeu Fabra University | B17: Pompeu Fabra | C17: SPAIN | D17: =IFERROR(VLOOKUP(A17,eco_bus_institutions!A:D,3,0),"") -> 80 | E17: =IFERROR(VLOOKUP(A17,eco_institutions!A:D,3,0),"") -> 55 | F17: =IFERROR(VLOOKUP(A17,fin_institutions!A:D,3,0),"") -> 16 | G17: =IFERROR(VLOOKUP(A17,bus_institutions!A:D,3,0),0) -> 14 | H17: =IFERROR(VLOOKUP(A17,man_institutions!A:D,3,0),0) -> 15 | I17: =IFERROR(VLOOKUP(A17,eco_bus_institutions!A:D,4,0),0) -> 5.16 | J17: =IFERROR(VLOOKUP(A17,eco_institutions!A:D,4,0),0) -> 6.16 | K17: =IFERROR(VLOOKUP(A17,fin_institutions!A:D,4,0),0) -> 1.57 | L17: =IFERROR(VLOOKUP(A17,bus_institutions!A:D,4,0),0) -> 1.08 | M17: =IFERROR(VLOOKUP(A17,man_institutions!A:D,4,0),0) -> 1.17 | N17: =ROUND(IFERROR((601-_xlfn.RANK.EQ(I17,I:I))/600,0),3) -> 0.98 | O17: =ROUND(IFERROR((601-IFERROR(_xlfn.RANK.EQ(J17,J:J),""))/600,0),3) -> 0.988 | P17: =ROUND(IFERROR((601-IFERROR(_xlfn.RANK.EQ(K17,K:K),""))/600,0),3) -> 0.723 | Q17: =ROUND(IFERROR((601-IFERROR(_xlfn.RANK.EQ(L17,L:L),""))/600,0),3) -> 0.087 | R17: =ROUND(IFERROR((601-IFERROR(_xlfn.RANK.EQ(M17,M:M),""))/600,0),3) -> 0.212 | S17: =VLOOKUP(A17,#REF!,11,0) -> #REF! | T17: =VLOOKUP(A17,#REF!,12,0) -> #REF! | U17: =VLOOKUP(A17,#REF!,13,0) -> #REF! | V17: =VLOOKUP(A17,#REF!,14,0) -> #REF! | W17: -0.17839576 | X17: 2.5538865 | Y17: =VLOOKUP(C17,AR:AS,2,0) -> SPAIN | Z17: =IF(Y17=Y$1,B17,IF(Y17=Y$2,B17,"")) | AR17: SCOTLAND | AS17: UK | AT17: -0.37184879 | AU17: 2.9955619 | AW17: Pompeu Fabra
A18: Columbia University | B18: Columbia | C18: USA | D18: =IFERROR(VLOOKUP(A18,eco_bus_institutions!A:D,3,0),"") -> 256 | E18: =IFERROR(VLOOKUP(A18,eco_institutions!A:D,3,0),"") -> 165 | F18: =IFERROR(VLOOKUP(A18,fin_institutions!A:D,3,0),"") -> 61 | G18: =IFERROR(VLOOKUP(A18,bus_institutions!A:D,3,0),0) -> 47 | H18: =IFERROR(VLOOKUP(A18,man_institutions!A:D,3,0),0) -> 39 | I18: =IFERROR(VLOOKUP(A18,eco_bus_institutions!A:D,4,0),0) -> 5.13 | J18: =IFERROR(VLOOKUP(A18,eco_institutions!A:D,4,0),0) -> 5.07 | K18: =IFERROR(VLOOKUP(A18,fin_institutions!A:D,4,0),0) -> 4.23 | L18: =IFERROR(VLOOKUP(A18,bus_institutions!A:D,4,0),0) -> 5.36 | M18: =IFERROR(VLOOKUP(A18,man_institutions!A:D,4,0),0) -> 2.62 | N18: =ROUND(IFERROR((601-_xlfn.RANK.EQ(I18,I:I))/600,0),3) -> 0.977 | O18: =ROUND(IFERROR((601-IFERROR(_xlfn.RANK.EQ(J18,J:J),""))/600,0),3) -> 0.977 | P18: =ROUND(IFERROR((601-IFERROR(_xlfn.RANK.EQ(K18,K:K),""))/600,0),3) -> 0.962 | Q18: =ROUND(IFERROR((601-IFERROR(_xlfn.RANK.EQ(L18,L:L),""))/600,0),3) -> 0.962 | R18: =ROUND(IFERROR((601-IFERROR(_xlfn.RANK.EQ(M18,M:M),""))/600,0),3) -> 0.808 | S18: =VLOOKUP(A18,#REF!,11,0) -> #REF! | T18: =VLOOKUP(A18,#REF!,12,0) -> #REF! | U18: =VLOOKUP(A18,#REF!,13,0) -> #REF! | V18: =VLOOKUP(A18,#REF!,14,0) -> #REF! | W18: 2.941224 | X18: 0.49513781 | Y18: =VLOOKUP(C18,AR:AS,2,0) -> USA | Z18: =IF(Y18=Y$1,B18,IF(Y18=Y$2,B18,"")) | AR18: SAUDI ARABIA | AS18: SAU | AT18: 2.4617441 | AU18: 0.75473318 | AW18: Columbia
A19: Centre for Economic Policy Research - UK | B19: CEPRUK | C19: ENGLAND | D19: =IFERROR(VLOOKUP(A19,eco_bus_institutions!A:D,3,0),"") -> 253 | E19: =IFERROR(VLOOKUP(A19,eco_institutions!A:D,3,0),"") -> 233 | F19: =IFERROR(VLOOKUP(A19,fin_institutions!A:D,3,0),"") -> 63 | G19: =IFERROR(VLOOKUP(A19,bus_institutions!A:D,3,0),0) -> 0 | H19: =IFERROR(VLOOKUP(A19,man_institutions!A:D,3,0),0) -> 0 | I19: =IFERROR(VLOOKUP(A19,eco_bus_institutions!A:D,4,0),0) -> 5.01 | J19: =IFERROR(VLOOKUP(A19,eco_institutions!A:D,4,0),0) -> 4.48 | K19: =IFERROR(VLOOKUP(A19,fin_institutions!A:D,4,0),0) -> 2.4 | L19: =IFERROR(VLOOKUP(A19,bus_institutions!A:D,4,0),0) -> 0 | M19: =IFERROR(VLOOKUP(A19,man_institutions!A:D,4,0),0) -> 0 | N19: =ROUND(IFERROR((601-_xlfn.RANK.EQ(I19,I:I))/600,0),3) -> 0.975 | O19: =ROUND(IFERROR((601-IFERROR(_xlfn.RANK.EQ(J19,J:J),""))/600,0),3) -> 0.97 | P19: =ROUND(IFERROR((601-IFERROR(_xlfn.RANK.EQ(K19,K:K),""))/600,0),3) -> 0.85 | Q19: =ROUND(IFERROR((601-IFERROR(_xlfn.RANK.EQ(L19,L:L),""))/600,0),3) -> 0.05 | R19: =ROUND(IFERROR((601-IFERROR(_xlfn.RANK.EQ(M19,M:M),""))/600,0),3) -> 0.04 | S19: =VLOOKUP(A19,#REF!,11,0) -> #REF! | T19: =VLOOKUP(A19,#REF!,12,0) -> #REF! | U19: =VLOOKUP(A19,#REF!,13,0) -> #REF! | V19: =VLOOKUP(A19,#REF!,14,0) -> #REF! | W19: -0.37184879 | X19: 2.9955619 | Y19: =VLOOKUP(C19,AR:AS,2,0) -> UK | Z19: =IF(Y19=Y$1,B19,IF(Y19=Y$2,B19,"")) | AR19: RUSSIA | AS19: RUS | AT19: 3.2167895 | AU19: 0.029288811 | AW19: Centre for Economic Policy Research - UK
A20: University of California Los Angeles | B20: UCLA | C20: USA | D20: =IFERROR(VLOOKUP(A20,eco_bus_institutions!A:D,3,0),"") -> 149 | E20: =IFERROR(VLOOKUP(A20,eco_institutions!A:D,3,0),"") -> 88 | F20: =IFERROR(VLOOKUP(A20,fin_institutions!A:D,3,0),"") -> 37 | G20: =IFERROR(VLOOKUP(A20,bus_institutions!A:D,3,0),0) -> 24 | H20: =IFERROR(VLOOKUP(A20,man_institutions!A:D,3,0),0) -> 38 | I20: =IFERROR(VLOOKUP(A20,eco_bus_institutions!A:D,4,0),0) -> 4.99 | J20: =IFERROR(VLOOKUP(A20,eco_institutions!A:D,4,0),0) -> 6.14 | K20: =IFERROR(VLOOKUP(A20,fin_institutions!A:D,4,0),0) -> 2.97 | L20: =IFERROR(VLOOKUP(A20,bus_institutions!A:D,4,0),0) -> 2.93 | M20: =IFERROR(VLOOKUP(A20,man_institutions!A:D,4,0),0) -> 2.46 | N20: =ROUND(IFERROR((601-_xlfn.RANK.EQ(I20,I:I))/600,0),3) -> 0.973 | O20: =ROUND(IFERROR((601-IFERROR(_xlfn.RANK.EQ(J20,J:J),""))/600,0),3) -> 0.987 | P20: =ROUND(IFERROR((601-IFERROR(_xlfn.RANK.EQ(K20,K:K),""))/600,0),3) -> 0.892 | Q20: =ROUND(IFERROR((601-IFERROR(_xlfn.RANK.EQ(L20,L:L),""))/600,0),3) -> 0.785 | R20: =ROUND(IFERROR((601-IFERROR(_xlfn.RANK.EQ(M20,M:M),""))/600,0),3) -> 0.783 | S20: =VLOOKUP(A20,#REF!,11,0) -> #REF! | T20: =VLOOKUP(A20,#REF!,12,0) -> #REF! | U20: =VLOOKUP(A20,#REF!,13,0) -> #REF! | V20: =VLOOKUP(A20,#REF!,14,0) -> #REF! | W20: 2.4617441 | X20: 0.75473318 | Y20: =VLOOKUP(C20,AR:AS,2,0) -> USA | Z20: =IF(Y20=Y$1,B20,IF(Y20=Y$2,B20,"")) | AR20: ROMANIA | AS20: ROM | AT20: -0.21512198 | AU20: 3.0851701 | AW20: California Los Angeles
A21: INSEAD Business School | B21: INSEAD | C21: FRANCE | D21: =IFERROR(VLOOKUP(A21,eco_bus_institutions!A:D,3,0),"") -> 89 | E21: =IFERROR(VLOOKUP(A21,eco_institutions!A:D,3,0),"") -> 21 | F21: =IFERROR(VLOOKUP(A21,fin_institutions!A:D,3,0),"") -> 11 | G21: =IFERROR(VLOOKUP(A21,bus_institutions!A:D,3,0),0) -> 45 | H21: =IFERROR(VLOOKUP(A21,man_institutions!A:D,3,0),0) -> 51 | I21: =IFERROR(VLOOKUP(A21,eco_bus_institutions!A:D,4,0),0) -> 4.98 | J21: =IFERROR(VLOOKUP(A21,eco_institutions!A:D,4,0),0) -> 2.79 | K21: =IFERROR(VLOOKUP(A21,fin_institutions!A:D,4,0),0) -> 4.07 | L21: =IFERROR(VLOOKUP(A21,bus_institutions!A:D,4,0),0) -> 6.65 | M21: =IFERROR(VLOOKUP(A21,man_institutions!A:D,4,0),0) -> 6 | N21: =ROUND(IFERROR((601-_xlfn.RANK.EQ(I21,I:I))/600,0),3) -> 0.972 | O21: =ROUND(IFERROR((601-IFERROR(_xlfn.RANK.EQ(J21,J:J),""))/600,0),3) -> 0.918 | P21: =ROUND(IFERROR((601-IFERROR(_xlfn.RANK.EQ(K21,K:K),""))/600,0),3) -> 0.958 | Q21: =ROUND(IFERROR((601-IFERROR(_xlfn.RANK.EQ(L21,L:L),""))/600,0),3) -> 0.99 | R21: =ROUND(IFERROR((601-IFERROR(_xlfn.RANK.EQ(M21,M:M),""))/600,0),3) -> 0.983 | S21: =VLOOKUP(A21,#REF!,11,0) -> #REF! | T21: =VLOOKUP(A21,#REF!,12,0) -> #REF! | U21: =VLOOKUP(A21,#REF!,13,0) -> #REF! | V21: =VLOOKUP(A21,#REF!,14,0) -> #REF! | W21: 3.2167895 | X21: 0.029288811 | Y21: =VLOOKUP(C21,AR:AS,2,0) -> FRA | Z21: =IF(Y21=Y$1,B21,IF(Y21=Y$2,B21,"")) | AR21: QATAR | AS21: QAT | AT21: 3.2537572 | AU21: 0.16279534 | AW21: INSEAD Business School
A22: Swiss Finance Institute (SFI) | B22: SFI | C22: SWITZERLAND | D22: =IFERROR(VLOOKUP(A22,eco_bus_institutions!A:D,3,0),"") -> 39 | E22: =IFERROR(VLOOKUP(A22,eco_institutions!A:D,3,0),"") -> 28 | F22: =IFERROR(VLOOKUP(A22,fin_institutions!A:D,3,0),"") -> 28 | G22: =IFERROR(VLOOKUP(A22,bus_institutions!A:D,3,0),0) -> 0 | H22: =IFERROR(VLOOKUP(A22,man_institutions!A:D,3,0),0) -> 0 | I22: =IFERROR(VLOOKUP(A22,eco_bus_institutions!A:D,4,0),0) -> 4.82 | J22: =IFERROR(VLOOKUP(A22,eco_institutions!A:D,4,0),0) -> 3.64 | K22: =IFERROR(VLOOKUP(A22,fin_institutions!A:D,4,0),0) -> 4.06 | L22: =IFERROR(VLOOKUP(A22,bus_institutions!A:D,4,0),0) -> 0 | M22: =IFERROR(VLOOKUP(A22,man_institutions!A:D,4,0),0) -> 0 | N22: =ROUND(IFERROR((601-_xlfn.RANK.EQ(I22,I:I))/600,0),3) -> 0.97 | O22: =ROUND(IFERROR((601-IFERROR(_xlfn.RANK.EQ(J22,J:J),""))/600,0),3) -> 0.953 | P22: =ROUND(IFERROR((601-IFERROR(_xlfn.RANK.EQ(K22,K:K),""))/600,0),3) -> 0.955 | Q22: =ROUND(IFERROR((601-IFERROR(_xlfn.RANK.EQ(L22,L:L),""))/600,0),3) -> 0.05 | R22: =ROUND(IFERROR((601-IFERROR(_xlfn.RANK.EQ(M22,M:M),""))/600,0),3) -> 0.04 | S22: =VLOOKUP(A22,#REF!,11,0) -> #REF! | T22: =VLOOKUP(A22,#REF!,12,0) -> #REF! | U22: =VLOOKUP(A22,#REF!,13,0) -> #REF! | V22: =VLOOKUP(A22,#REF!,14,0) -> #REF! | W22: -0.21512198 | X22: 3.0851701 | Y22: =VLOOKUP(C22,AR:AS,2,0) -> CHE | Z22: =IF(Y22=Y$1,B22,IF(Y22=Y$2,B22,"")) | AR22: PORTUGAL | AS22: PRT | AT22: 3.2521945 | AU22: 0.19565598 | AW22: Swiss Finance Institute (SFI)
A23: Washington University (WUSTL) | B23: WUSTL | C23: USA | D23: =IFERROR(VLOOKUP(A23,eco_bus_institutions!A:D,3,0),"") -> 83 | E23: =IFERROR(VLOOKUP(A23,eco_institutions!A:D,3,0),"") -> 46 | F23: =IFERROR(VLOOKUP(A23,fin_institutions!A:D,3,0),"") -> 29 | G23: =IFERROR(VLOOKUP(A23,bus_institutions!A:D,3,0),0) -> 11 | H23: =IFERROR(VLOOKUP(A23,man_institutions!A:D,3,0),0) -> 18 | I23: =IFERROR(VLOOKUP(A23,eco_bus_institutions!A:D,4,0),0) -> 4.59 | J23: =IFERROR(VLOOKUP(A23,eco_institutions!A:D,4,0),0) -> 3.75 | K23: =IFERROR(VLOOKUP(A23,fin_institutions!A:D,4,0),0) -> 4.33 | L23: =IFERROR(VLOOKUP(A23,bus_institutions!A:D,4,0),0) -> 6.42 | M23: =IFERROR(VLOOKUP(A23,man_institutions!A:D,4,0),0) -> 5.1 | N23: =ROUND(IFERROR((601-_xlfn.RANK.EQ(I23,I:I))/600,0),3) -> 0.968 | O23: =ROUND(IFERROR((601-IFERROR(_xlfn.RANK.EQ(J23,J:J),""))/600,0),3) -> 0.958 | P23: =ROUND(IFERROR((601-IFERROR(_xlfn.RANK.EQ(K23,K:K),""))/600,0),3) -> 0.963 | Q23: =ROUND(IFERROR((601-IFERROR(_xlfn.RANK.EQ(L23,L:L),""))/600,0),3) -> 0.982 | R23: =ROUND(IFERROR((601-IFERROR(_xlfn.RANK.EQ(M23,M:M),""))/600,0),3) -> 0.972 | S23: =VLOOKUP(A23,#REF!,11,0) -> #REF! | T23: =VLOOKUP(A23,#REF!,12,0) -> #REF! | U23: =VLOOKUP(A23,#REF!,13,0) -> #REF! | V23: =VLOOKUP(A23,#REF!,14,0) -> #REF! | W23: 3.2537572 | X23: 0.16279534 | Y23: =VLOOKUP(C23,AR:AS,2,0) -> USA | Z23: =IF(Y23=Y$1,B23,IF(Y23=Y$2,B23,"")) | AR23: POLAND | AS23: POL | AT23: 2.4268551 | AU23: 0.94449888 | AW23: Washington (WUSTL)
A24: Boston College | B24: Boston C | C24: USA | D24: =IFERROR(VLOOKUP(A24,eco_bus_institutions!A:D,3,0),"") -> 109 | E24: =IFERROR(VLOOKUP(A24,eco_institutions!A:D,3,0),"") -> 54 | F24: =IFERROR(VLOOKUP(A24,fin_institutions!A:D,3,0),"") -> 32 | G24: =IFERROR(VLOOKUP(A24,bus_institutions!A:D,3,0),0) -> 26 | H24: =IFERROR(VLOOKUP(A24,man_institutions!A:D,3,0),0) -> 29 | I24: =IFERROR(VLOOKUP(A24,eco_bus_institutions!A:D,4,0),0) -> 4.45 | J24: =IFERROR(VLOOKUP(A24,eco_institutions!A:D,4,0),0) -> 3.58 | K24: =IFERROR(VLOOKUP(A24,fin_institutions!A:D,4,0),0) -> 5.41 | L24: =IFERROR(VLOOKUP(A24,bus_institutions!A:D,4,0),0) -> 5.16 | M24: =IFERROR(VLOOKUP(A24,man_institutions!A:D,4,0),0) -> 5.79 | N24: =ROUND(IFERROR((601-_xlfn.RANK.EQ(I24,I:I))/600,0),3) -> 0.967 | O24: =ROUND(IFERROR((601-IFERROR(_xlfn.RANK.EQ(J24,J:J),""))/600,0),3) -> 0.948 | P24: =ROUND(IFERROR((601-IFERROR(_xlfn.RANK.EQ(K24,K:K),""))/600,0),3) -> 0.988 | Q24: =ROUND(IFERROR((601-IFERROR(_xlfn.RANK.EQ(L24,L:L),""))/600,0),3) -> 0.958 | R24: =ROUND(IFERROR((601-IFERROR(_xlfn.RANK.EQ(M24,M:M),""))/600,0),3) -> 0.98 | S24: =VLOOKUP(A24,#REF!,11,0) -> #REF! | T24: =VLOOKUP(A24,#REF!,12,0) -> #REF! | U24: =VLOOKUP(A24,#REF!,13,0) -> #REF! | V24: =VLOOKUP(A24,#REF!,14,0) -> #REF! | W24: 3.2521945 | X24: 0.19565598 | Y24: =VLOOKUP(C24,AR:AS,2,0) -> USA | Z24: =IF(Y24=Y$1,B24,IF(Y24=Y$2,B24,"")) | AR24: PAKISTAN | AS24: PAK | AT24: 2.8659921 | AU24: 0.57900989 | AW24: Boston College
A25: University of California San Diego | B25: UCSD | C25: USA | D25: =IFERROR(VLOOKUP(A25,eco_bus_institutions!A:D,3,0),"") -> 101 | E25: =IFERROR(VLOOKUP(A25,eco_institutions!A:D,3,0),"") -> 82 | F25: =IFERROR(VLOOKUP(A25,fin_institutions!A:D,3,0),"") -> 18 | G25: =IFERROR(VLOOKUP(A25,bus_institutions!A:D,3,0),0) -> 9 | H25: =IFERROR(VLOOKUP(A25,man_institutions!A:D,3,0),0) -> 7 | I25: =IFERROR(VLOOKUP(A25,eco_bus_institutions!A:D,4,0),0) -> 4.42 | J25: =IFERROR(VLOOKUP(A25,eco_institutions!A:D,4,0),0) -> 4.16 | K25: =IFERROR(VLOOKUP(A25,fin_institutions!A:D,4,0),0) -> 4.98 | L25: =IFERROR(VLOOKUP(A25,bus_institutions!A:D,4,0),0) -> 4.14 | M25: =IFERROR(VLOOKUP(A25,man_institutions!A:D,4,0),0) -> 1.65 | N25: =ROUND(IFERROR((601-_xlfn.RANK.EQ(I25,I:I))/600,0),3) -> 0.965 | O25: =ROUND(IFERROR((601-IFERROR(_xlfn.RANK.EQ(J25,J:J),""))/600,0),3) -> 0.968 | P25: =ROUND(IFERROR((601-IFERROR(_xlfn.RANK.EQ(K25,K:K),""))/600,0),3) -> 0.98 | Q25: =ROUND(IFERROR((601-IFERROR(_xlfn.RANK.EQ(L25,L:L),""))/600,0),3) -> 0.918 | R25: =ROUND(IFERROR((601-IFERROR(_xlfn.RANK.EQ(M25,M:M),""))/600,0),3) -> 0.565 | S25: =VLOOKUP(A25,#REF!,11,0) -> #REF! | T25: =VLOOKUP(A25,#REF!,12,0) -> #REF! | U25: =VLOOKUP(A25,#REF!,13,0) -> #REF! | V25: =VLOOKUP(A25,#REF!,14,0) -> #REF! | W25: 2.4268551 | X25: 0.94449888 | Y25: =VLOOKUP(C25,AR:AS,2,0) -> USA | Z25: =IF(Y25=Y$1,B25,IF(Y25=Y$2,B25,"")) | AR25: NORWAY | AS25: NOR | AT25: 3.0782438 | AU25: 0.28710048 | AW25: California San Diego
A26: Dartmouth College | B26: Dartmouth | C26: USA | D26: =IFERROR(VLOOKUP(A26,eco_bus_institutions!A:D,3,0),"") -> 54 | E26: =IFERROR(VLOOKUP(A26,eco_institutions!A:D,3,0),"") -> 30 | F26: =IFERROR(VLOOKUP(A26,fin_institutions!A:D,3,0),"") -> 12 | G26: =IFERROR(VLOOKUP(A26,bus_institutions!A:D,3,0),0) -> 10 | H26: =IFERROR(VLOOKUP(A26,man_institutions!A:D,3,0),0) -> 8 | I26: =IFERROR(VLOOKUP(A26,eco_bus_institutions!A:D,4,0),0) -> 4.3 | J26: =IFERROR(VLOOKUP(A26,eco_institutions!A:D,4,0),0) -> 4.82 | K26: =IFERROR(VLOOKUP(A26,fin_institutions!A:D,4,0),0) -> 4.61 | L26: =IFERROR(VLOOKUP(A26,bus_institutions!A:D,4,0),0) -> 3.35 | M26: =IFERROR(VLOOKUP(A26,man_institutions!A:D,4,0),0) -> 3.21 | N26: =ROUND(IFERROR((601-_xlfn.RANK.EQ(I26,I:I))/600,0),3) -> 0.963 | O26: =ROUND(IFERROR((601-IFERROR(_xlfn.RANK.EQ(J26,J:J),""))/600,0),3) -> 0.975 | P26: =ROUND(IFERROR((601-IFERROR(_xlfn.RANK.EQ(K26,K:K),""))/600,0),3) -> 0.97 | Q26: =ROUND(IFERROR((601-IFERROR(_xlfn.RANK.EQ(L26,L:L),""))/600,0),3) -> 0.84 | R26: =ROUND(IFERROR((601-IFERROR(_xlfn.RANK.EQ(M26,M:M),""))/600,0),3) -> 0.883 | S26: =VLOOKUP(A26,#REF!,11,0) -> #REF! | T26: =VLOOKUP(A26,#REF!,12,0) -> #REF! | U26: =VLOOKUP(A26,#REF!,13,0) -> #REF! | V26: =VLOOKUP(A26,#REF!,14,0) -> #REF! | W26: 2.8659921 | X26: 0.57900989 | Y26: =VLOOKUP(C26,AR:AS,2,0) -> USA | Z26: =IF(Y26=Y$1,B26,IF(Y26=Y$2,B26,"")) | AR26: NORTHERN IRELAND | AS26: UK | AT26: 2.965248 | AU26: 0.23678393 | AW26: Dartmouth College
... A44: University of California Irvine | B44: UCI | C44: USA | D44: =IFERROR(VLOOKUP(A44,eco_bus_institutions!A:D,3,0),"") -> 84 | E44: =IFERROR(VLOOKUP(A44,eco_institutions!A:D,3,0),"") -> 53 | F44: =IFERROR(VLOOKUP(A44,fin_institutions!A:D,3,0),"") -> 18 | G44: =IFERROR(VLOOKUP(A44,bus_institutions!A:D,3,0),0) -> 13 | H44: =IFERROR(VLOOKUP(A44,man_institutions!A:D,3,0),0) -> 21 | I44: =IFERROR(VLOOKUP(A44,eco_bus_institutions!A:D,4,0),0) -> 3.51 | J44: =IFERROR(VLOOKUP(A44,eco_institutions!A:D,4,0),0) -> 1.9 | K44: =IFERROR(VLOOKUP(A44,fin_institutions!A:D,4,0),0) -> 4.52 | L44: =IFERROR(VLOOKUP(A44,bus_institutions!A:D,4,0),0) -> 7.35 | M44: =IFERROR(VLOOKUP(A44,man_institutions!A:D,4,0),0) -> 7.32 | N44: =ROUND(IFERROR((601-_xlfn.RANK.EQ(I44,I:I))/600,0),3) -> 0.933 | O44: =ROUND(IFERROR((601-IFERROR(_xlfn.RANK.EQ(J44,J:J),""))/600,0),3) -> 0.818 | P44: =ROUND(IFERROR((601-IFERROR(_xlfn.RANK.EQ(K44,K:K),""))/600,0),3) -> 0.967 | Q44: =ROUND(IFERROR((601-IFERROR(_xlfn.RANK.EQ(L44,L:L),""))/600,0),3) -> 0.997 | R44: =ROUND(IFERROR((601-IFERROR(_xlfn.RANK.EQ(M44,M:M),""))/600,0),3) -> 0.997 | S44: =VLOOKUP(A44,#REF!,11,0) -> #REF! | T44: =VLOOKUP(A44,#REF!,12,0) -> #REF! | U44: =VLOOKUP(A44,#REF!,13,0) -> #REF! | V44: =VLOOKUP(A44,#REF!,14,0) -> #REF! | W44: 3.1129698 | X44: -0.23580961 | Y44: =VLOOKUP(C44,AR:AS,2,0) -> USA | Z44: =IF(Y44=Y$1,B44,IF(Y44=Y$2,B44,"")) | AR44: FINLAND | AS44: FIN | AT44: 3.0841456 | AU44: -0.061536574 | AW44: California Irvine
A45: University of British Columbia | B45: UBC | C45: CANADA | D45: =IFERROR(VLOOKUP(A45,eco_bus_institutions!A:D,3,0),"") -> 127 | E45: =IFERROR(VLOOKUP(A45,eco_institutions!A:D,3,0),"") -> 79 | F45: =IFERROR(VLOOKUP(A45,fin_institutions!A:D,3,0),"") -> 20 | G45: =IFERROR(VLOOKUP(A45,bus_institutions!A:D,3,0),0) -> 28 | H45: =IFERROR(VLOOKUP(A45,man_institutions!A:D,3,0),0) -> 22 | I45: =IFERROR(VLOOKUP(A45,eco_bus_institutions!A:D,4,0),0) -> 3.49 | J45: =IFERROR(VLOOKUP(A45,eco_institutions!A:D,4,0),0) -> 3.28 | K45: =IFERROR(VLOOKUP(A45,fin_institutions!A:D,4,0),0) -> 4.02 | L45: =IFERROR(VLOOKUP(A45,bus_institutions!A:D,4,0),0) -> 3.42 | M45: =IFERROR(VLOOKUP(A45,man_institutions!A:D,4,0),0) -> 2.95 | N45: =ROUND(IFERROR((601-_xlfn.RANK.EQ(I45,I:I))/600,0),3) -> 0.932 | O45: =ROUND(IFERROR((601-IFERROR(_xlfn.RANK.EQ(J45,J:J),""))/600,0),3) -> 0.94 | P45: =ROUND(IFERROR((601-IFERROR(_xlfn.RANK.EQ(K45,K:K),""))/600,0),3) -> 0.953 | Q45: =ROUND(IFERROR((601-IFERROR(_xlfn.RANK.EQ(L45,L:L),""))/600,0),3) -> 0.85 | R45: =ROUND(IFERROR((601-IFERROR(_xlfn.RANK.EQ(M45,M:M),""))/600,0),3) -> 0.857 | S45: 1 | T45: =VLOOKUP(A45,#REF!,12,0) -> #REF! | U45: =VLOOKUP(A45,#REF!,13,0) -> #REF! | V45: =VLOOKUP(A45,#REF!,14,0) -> #REF! | W45: 2.7510633 | X45: 0.49709576 | Y45: =VLOOKUP(C45,AR:AS,2,0) -> CAN | Z45: =IF(Y45=Y$1,B45,IF(Y45=Y$2,B45,"")) | AR45: ESTONIA | AS45: EST | AT45: -0.48666816 | AU45: 2.8810982 | AW45: British Columbia
A46: University of North Carolina Chapel Hill | B46: UNC | C46: USA | D46: =IFERROR(VLOOKUP(A46,eco_bus_institutions!A:D,3,0),"") -> 125 | E46: =IFERROR(VLOOKUP(A46,eco_institutions!A:D,3,0),"") -> 68 | F46: =IFERROR(VLOOKUP(A46,fin_institutions!A:D,3,0),"") -> 27 | G46: =IFERROR(VLOOKUP(A46,bus_institutions!A:D,3,0),0) -> 27 | H46: =IFERROR(VLOOKUP(A46,man_institutions!A:D,3,0),0) -> 29 | I46: =IFERROR(VLOOKUP(A46,eco_bus_institutions!A:D,4,0),0) -> 3.49 | J46: =IFERROR(VLOOKUP(A46,eco_institutions!A:D,4,0),0) -> 2.29 | K46: =IFERROR(VLOOKUP(A46,fin_institutions!A:D,4,0),0) -> 3.99 | L46: =IFERROR(VLOOKUP(A46,bus_institutions!A:D,4,0),0) -> 6.58 | M46: =IFERROR(VLOOKUP(A46,man_institutions!A:D,4,0),0) -> 4.79 | N46: =ROUND(IFERROR((601-_xlfn.RANK.EQ(I46,I:I))/600,0),3) -> 0.932 | O46: =ROUND(IFERROR((601-IFERROR(_xlfn.RANK.EQ(J46,J:J),""))/600,0),3) -> 0.87 | P46: =ROUND(IFERROR((601-IFERROR(_xlfn.RANK.EQ(K46,K:K),""))/600,0),3) -> 0.95 | Q46: =ROUND(IFERROR((601-IFERROR(_xlfn.RANK.EQ(L46,L:L),""))/600,0),3) -> 0.987 | R46: =ROUND(IFERROR((601-IFERROR(_xlfn.RANK.EQ(M46,M:M),""))/600,0),3) -> 0.963 | S46: 1 | T46: =VLOOKUP(A46,#REF!,12,0) -> #REF! | U46: =VLOOKUP(A46,#REF!,13,0) -> #REF! | V46: =VLOOKUP(A46,#REF!,14,0) -> #REF! | W46: 3.0841456 | X46: -0.061536574 | Y46: =VLOOKUP(C46,AR:AS,2,0) -> USA | Z46: =IF(Y46=Y$1,B46,IF(Y46=Y$2,B46,"")) | AR46: ENGLAND | AS46: UK | AT46: 2.2768766 | AU46: 0.79372951 | AW46: North Carolina Chapel Hill
A47: Federal Reserve System - USA | B47: FED | C47: USA | D47: =IFERROR(VLOOKUP(A47,eco_bus_institutions!A:D,3,0),"") -> 357 | E47: =IFERROR(VLOOKUP(A47,eco_institutions!A:D,3,0),"") -> 311 | F47: =IFERROR(VLOOKUP(A47,fin_institutions!A:D,3,0),"") -> 152 | G47: =IFERROR(VLOOKUP(A47,bus_institutions!A:D,3,0),0) -> 0 | H47: =IFERROR(VLOOKUP(A47,man_institutions!A:D,3,0),0) -> 0 | I47: =IFERROR(VLOOKUP(A47,eco_bus_institutions!A:D,4,0),0) -> 3.48 | J47: =IFERROR(VLOOKUP(A47,eco_institutions!A:D,4,0),0) -> 3.39 | K47: =IFERROR(VLOOKUP(A47,fin_institutions!A:D,4,0),0) -> 1.94 | L47: =IFERROR(VLOOKUP(A47,bus_institutions!A:D,4,0),0) -> 0 | M47: =IFERROR(VLOOKUP(A47,man_institutions!A:D,4,0),0) -> 0 | N47: =ROUND(IFERROR((601-_xlfn.RANK.EQ(I47,I:I))/600,0),3) -> 0.928 | O47: =ROUND(IFERROR((601-IFERROR(_xlfn.RANK.EQ(J47,J:J),""))/600,0),3) -> 0.945 | P47: =ROUND(IFERROR((601-IFERROR(_xlfn.RANK.EQ(K47,K:K),""))/600,0),3) -> 0.807 | Q47: =ROUND(IFERROR((601-IFERROR(_xlfn.RANK.EQ(L47,L:L),""))/600,0),3) -> 0.05 | R47: =ROUND(IFERROR((601-IFERROR(_xlfn.RANK.EQ(M47,M:M),""))/600,0),3) -> 0.04 | S47: =VLOOKUP(A47,#REF!,11,0) -> #REF! | T47: =VLOOKUP(A47,#REF!,12,0) -> #REF! | U47: =VLOOKUP(A47,#REF!,13,0) -> #REF! | V47: =VLOOKUP(A47,#REF!,14,0) -> #REF! | W47: -0.48666816 | X47: 2.8810982 | Y47: =VLOOKUP(C47,AR:AS,2,0) -> USA | Z47: =IF(Y47=Y$1,B47,IF(Y47=Y$2,B47,"")) | AR47: DENMARK | AS47: DEN | AT47: 2.3914634 | AU47: 0.41409176 | AW47: Federal Reserve System - USA
A48: University of Geneva | B48: Geneva | C48: SWITZERLAND | D48: =IFERROR(VLOOKUP(A48,eco_bus_institutions!A:D,3,0),"") -> 50 | E48: =IFERROR(VLOOKUP(A48,eco_institutions!A:D,3,0),"") -> 36 | F48: =IFERROR(VLOOKUP(A48,fin_institutions!A:D,3,0),"") -> 15 | G48: =IFERROR(VLOOKUP(A48,bus_institutions!A:D,3,0),0) -> 11 | H48: =IFERROR(VLOOKUP(A48,man_institutions!A:D,3,0),0) -> 7 | I48: =IFERROR(VLOOKUP(A48,eco_bus_institutions!A:D,4,0),0) -> 3.48 | J48: =IFERROR(VLOOKUP(A48,eco_institutions!A:D,4,0),0) -> 2.43 | K48: =IFERROR(VLOOKUP(A48,fin_institutions!A:D,4,0),0) -> 5.61 | L48: =IFERROR(VLOOKUP(A48,bus_institutions!A:D,4,0),0) -> 2.28 | M48: =IFERROR(VLOOKUP(A48,man_institutions!A:D,4,0),0) -> 2.63 | N48: =ROUND(IFERROR((601-_xlfn.RANK.EQ(I48,I:I))/600,0),3) -> 0.928 | O48: =ROUND(IFERROR((601-IFERROR(_xlfn.RANK.EQ(J48,J:J),""))/600,0),3) -> 0.882 | P48: =ROUND(IFERROR((601-IFERROR(_xlfn.RANK.EQ(K48,K:K),""))/600,0),3) -> 0.992 | Q48: =ROUND(IFERROR((601-IFERROR(_xlfn.RANK.EQ(L48,L:L),""))/600,0),3) -> 0.648 | R48: =ROUND(IFERROR((601-IFERROR(_xlfn.RANK.EQ(M48,M:M),""))/600,0),3) -> 0.815 | S48: =VLOOKUP(A48,#REF!,11,0) -> #REF! | T48: =VLOOKUP(A48,#REF!,12,0) -> #REF! | U48: =VLOOKUP(A48,#REF!,13,0) -> #REF! | V48: =VLOOKUP(A48,#REF!,14,0) -> #REF! | W48: 2.2768766 | X48: 0.79372951 | Y48: =VLOOKUP(C48,AR:AS,2,0) -> CHE | Z48: =IF(Y48=Y$1,B48,IF(Y48=Y$2,B48,"")) | AR48: CZECH REPUBLIC | AS48: CZE | AT48: 2.8029894 | AU48: 0.026330193 | AW48: Geneva
A49: London School Economics & Political Science | B49: LSE | C49: ENGLAND | D49: =IFERROR(VLOOKUP(A49,eco_bus_institutions!A:D,3,0),"") -> 331 | E49: =IFERROR(VLOOKUP(A49,eco_institutions!A:D,3,0),"") -> 281 | F49: =IFERROR(VLOOKUP(A49,fin_institutions!A:D,3,0),"") -> 76 | G49: =IFERROR(VLOOKUP(A49,bus_institutions!A:D,3,0),0) -> 18 | H49: =IFERROR(VLOOKUP(A49,man_institutions!A:D,3,0),0) -> 22 | I49: =IFERROR(VLOOKUP(A49,eco_bus_institutions!A:D,4,0),0) -> 3.42 | J49: =IFERROR(VLOOKUP(A49,eco_institutions!A:D,4,0),0) -> 3.35 | K49: =IFERROR(VLOOKUP(A49,fin_institutions!A:D,4,0),0) -> 1.95 | L49: =IFERROR(VLOOKUP(A49,bus_institutions!A:D,4,0),0) -> 3.2 | M49: =IFERROR(VLOOKUP(A49,man_institutions!A:D,4,0),0) -> 2.65 | N49: =ROUND(IFERROR((601-_xlfn.RANK.EQ(I49,I:I))/600,0),3) -> 0.925 | O49: =ROUND(IFERROR((601-IFERROR(_xlfn.RANK.EQ(J49,J:J),""))/600,0),3) -> 0.942 | P49: =ROUND(IFERROR((601-IFERROR(_xlfn.RANK.EQ(K49,K:K),""))/600,0),3) -> 0.808 | Q49: =ROUND(IFERROR((601-IFERROR(_xlfn.RANK.EQ(L49,L:L),""))/600,0),3) -> 0.825 | R49: =ROUND(IFERROR((601-IFERROR(_xlfn.RANK.EQ(M49,M:M),""))/600,0),3) -> 0.823 | S49: =VLOOKUP(A49,#REF!,11,0) -> #REF! | T49: =VLOOKUP(A49,#REF!,12,0) -> #REF! | U49: =VLOOKUP(A49,#REF!,13,0) -> #REF! | V49: =VLOOKUP(A49,#REF!,14,0) -> #REF! | W49: 2.3914634 | X49: 0.41409176 | Y49: =VLOOKUP(C49,AR:AS,2,0) -> UK | Z49: =IF(Y49=Y$1,B49,IF(Y49=Y$2,B49,"")) | AR49: CROATIA | AS49: CRO | AT49: 2.5375681 | AU49: 0.72782661 | AW49: London School Economics & Political Science
A50: Babson College | B50: Babson C | C50: USA | D50: =IFERROR(VLOOKUP(A50,eco_bus_institutions!A:D,3,0),"") -> 55 | E50: =IFERROR(VLOOKUP(A50,eco_institutions!A:D,3,0),"") -> 13 | F50: =IFERROR(VLOOKUP(A50,fin_institutions!A:D,3,0),"") -> 8 | G50: =IFERROR(VLOOKUP(A50,bus_institutions!A:D,3,0),0) -> 39 | H50: =IFERROR(VLOOKUP(A50,man_institutions!A:D,3,0),0) -> 19 | I50: =IFERROR(VLOOKUP(A50,eco_bus_institutions!A:D,4,0),0) -> 3.41 | J50: =IFERROR(VLOOKUP(A50,eco_institutions!A:D,4,0),0) -> 2.08 | K50: =IFERROR(VLOOKUP(A50,fin_institutions!A:D,4,0),0) -> 3.65 | L50: =IFERROR(VLOOKUP(A50,bus_institutions!A:D,4,0),0) -> 4.24 | M50: =IFERROR(VLOOKUP(A50,man_institutions!A:D,4,0),0) -> 3.59 | N50: =ROUND(IFERROR((601-_xlfn.RANK.EQ(I50,I:I))/600,0),3) -> 0.923 | O50: =ROUND(IFERROR((601-IFERROR(_xlfn.RANK.EQ(J50,J:J),""))/600,0),3) -> 0.842 | P50: =ROUND(IFERROR((601-IFERROR(_xlfn.RANK.EQ(K50,K:K),""))/600,0),3) -> 0.933 | Q50: =ROUND(IFERROR((601-IFERROR(_xlfn.RANK.EQ(L50,L:L),""))/600,0),3) -> 0.925 | R50: =ROUND(IFERROR((601-IFERROR(_xlfn.RANK.EQ(M50,M:M),""))/600,0),3) -> 0.913 | S50: =VLOOKUP(A50,#REF!,11,0) -> #REF! | T50: =VLOOKUP(A50,#REF!,12,0) -> #REF! | U50: =VLOOKUP(A50,#REF!,13,0) -> #REF! | V50: =VLOOKUP(A50,#REF!,14,0) -> #REF! | W50: 2.8029894 | X50: 0.026330193 | Y50: =VLOOKUP(C50,AR:AS,2,0) -> USA | Z50: =IF(Y50=Y$1,B50,IF(Y50=Y$2,B50,"")) | AR50: COLOMBIA | AS50: COL | AT50: 3.0308301 | AU50: -0.14217435 | AW50: Babson College
A51: Duke University | B51: Duke | C51: USA | D51: =IFERROR(VLOOKUP(A51,eco_bus_institutions!A:D,3,0),"") -> 139 | E51: =IFERROR(VLOOKUP(A51,eco_institutions!A:D,3,0),"") -> 90 | F51: =IFERROR(VLOOKUP(A51,fin_institutions!A:D,3,0),"") -> 26 | G51: =IFERROR(VLOOKUP(A51,bus_institutions!A:D,3,0),0) -> 21 | H51: =IFERROR(VLOOKUP(A51,man_institutions!A:D,3,0),0) -> 27 | I51: =IFERROR(VLOOKUP(A51,eco_bus_institutions!A:D,4,0),0) -> 3.39 | J51: =IFERROR(VLOOKUP(A51,eco_institutions!A:D,4,0),0) -> 3.1 | K51: =IFERROR(VLOOKUP(A51,fin_institutions!A:D,4,0),0) -> 4.8 | L51: =IFERROR(VLOOKUP(A51,bus_institutions!A:D,4,0),0) -> 2.7 | M51: =IFERROR(VLOOKUP(A51,man_institutions!A:D,4,0),0) -> 2.64 | N51: =ROUND(IFERROR((601-_xlfn.RANK.EQ(I51,I:I))/600,0),3) -> 0.922 | O51: =ROUND(IFERROR((601-IFERROR(_xlfn.RANK.EQ(J51,J:J),""))/600,0),3) -> 0.935 | P51: =ROUND(IFERROR((601-IFERROR(_xlfn.RANK.EQ(K51,K:K),""))/600,0),3) -> 0.977 | Q51: =ROUND(IFERROR((601-IFERROR(_xlfn.RANK.EQ(L51,L:L),""))/600,0),3) -> 0.755 | R51: =ROUND(IFERROR((601-IFERROR(_xlfn.RANK.EQ(M51,M:M),""))/600,0),3) -> 0.818 | S51: =VLOOKUP(A51,#REF!,11,0) -> #REF! | T51: =VLOOKUP(A51,#REF!,12,0) -> #REF! | U51: =VLOOKUP(A51,#REF!,13,0) -> #REF! | V51: =VLOOKUP(A51,#REF!,14,0) -> #REF! | W51: 2.5375681 | X51: 0.72782661 | Y51: =VLOOKUP(C51,AR:AS,2,0) -> USA | Z51: =IF(Y51=Y$1,B51,IF(Y51=Y$2,B51,"")) | AR51: CHINA MAINLAND | AS51: CHN | AT51: 2.9912399 | AU51: 0.1028553 | AW51: Duke
A52: University of Virginia | B52: Virginia | C52: USA | D52: =IFERROR(VLOOKUP(A52,eco_bus_institutions!A:D,3,0),"") -> 90 | E52: =IFERROR(VLOOKUP(A52,eco_institutions!A:D,3,0),"") -> 52 | F52: =IFERROR(VLOOKUP(A52,fin_institutions!A:D,3,0),"") -> 19 | G52: =IFERROR(VLOOKUP(A52,bus_institutions!A:D,3,0),0) -> 20 | H52: =IFERROR(VLOOKUP(A52,man_institutions!A:D,3,0),0) -> 21 | I52: =IFERROR(VLOOKUP(A52,eco_bus_institutions!A:D,4,0),0) -> 3.36 | J52: =IFERROR(VLOOKUP(A52,eco_institutions!A:D,4,0),0) -> 2.35 | K52: =IFERROR(VLOOKUP(A52,fin_institutions!A:D,4,0),0) -> 3.04 | L52: =IFERROR(VLOOKUP(A52,bus_institutions!A:D,4,0),0) -> 6.73 | M52: =IFERROR(VLOOKUP(A52,man_institutions!A:D,4,0),0) -> 5.26 | N52: =ROUND(IFERROR((601-_xlfn.RANK.EQ(I52,I:I))/600,0),3) -> 0.92 | O52: =ROUND(IFERROR((601-IFERROR(_xlfn.RANK.EQ(J52,J:J),""))/600,0),3) -> 0.875 | P52: =ROUND(IFERROR((601-IFERROR(_xlfn.RANK.EQ(K52,K:K),""))/600,0),3) -> 0.897 | Q52: =ROUND(IFERROR((601-IFERROR(_xlfn.RANK.EQ(L52,L:L),""))/600,0),3) -> 0.992 | R52: =ROUND(IFERROR((601-IFERROR(_xlfn.RANK.EQ(M52,M:M),""))/600,0),3) -> 0.975 | S52: =VLOOKUP(A52,#REF!,11,0) -> #REF! | T52: =VLOOKUP(A52,#REF!,12,0) -> #REF! | U52: =VLOOKUP(A52,#REF!,13,0) -> #REF! | V52: =VLOOKUP(A52,#REF!,14,0) -> #REF! | W52: 3.0308301 | X52: -0.14217435 | Y52: =VLOOKUP(C52,AR:AS,2,0) -> USA | Z52: =IF(Y52=Y$1,B52,IF(Y52=Y$2,B52,"")) | AR52: CHILE | AS52: CHL | AT52: 2.7482656 | AU52: 0.48769122 | AW52: Virginia
A53: University of Southern California | B53: USC | C53: USA | D53: =IFERROR(VLOOKUP(A53,eco_bus_institutions!A:D,3,0),"") -> 194 | E53: =IFERROR(VLOOKUP(A53,eco_institutions!A:D,3,0),"") -> 111 | F53: =IFERROR(VLOOKUP(A53,fin_institutions!A:D,3,0),"") -> 44 | G53: =IFERROR(VLOOKUP(A53,bus_institutions!A:D,3,0),0) -> 37 | H53: =IFERROR(VLOOKUP(A53,man_institutions!A:D,3,0),0) -> 47 | I53: =IFERROR(VLOOKUP(A53,eco_bus_institutions!A:D,4,0),0) -> 3.31 | J53: =IFERROR(VLOOKUP(A53,eco_institutions!A:D,4,0),0) -> 2.69 | K53: =IFERROR(VLOOKUP(A53,fin_institutions!A:D,4,0),0) -> 3.58 | L53: =IFERROR(VLOOKUP(A53,bus_institutions!A:D,4,0),0) -> 5.18 | M53: =IFERROR(VLOOKUP(A53,man_institutions!A:D,4,0),0) -> 3.81 | N53: =ROUND(IFERROR((601-_xlfn.RANK.EQ(I53,I:I))/600,0),3) -> 0.918 | O53: =ROUND(IFERROR((601-IFERROR(_xlfn.RANK.EQ(J53,J:J),""))/600,0),3) -> 0.907 | P53: =ROUND(IFERROR((601-IFERROR(_xlfn.RANK.EQ(K53,K:K),""))/600,0),3) -> 0.93 | Q53: =ROUND(IFERROR((601-IFERROR(_xlfn.RANK.EQ(L53,L:L),""))/600,0),3) -> 0.96 | R53: =ROUND(IFERROR((601-IFERROR(_xlfn.RANK.EQ(M53,M:M),""))/600,0),3) -> 0.927 | S53: =VLOOKUP(A53,#REF!,11,0) -> #REF! | T53: =VLOOKUP(A53,#REF!,12,0) -> #REF! | U53: =VLOOKUP(A53,#REF!,13,0) -> #REF! | V53: =VLOOKUP(A53,#REF!,14,0) -> #REF! | W53: 2.9912399 | X53: 0.1028553 | Y53: =VLOOKUP(C53,AR:AS,2,0) -> USA | Z53: =IF(Y53=Y$1,B53,IF(Y53=Y$2,B53,"")) | AR53: CANADA | AS53: CAN | AT53: 2.4984828 | AU53: 0.82877062 | AW53: Southern California
A54: University of Colorado Boulder | B54: Boulder | C54: USA | D54: =IFERROR(VLOOKUP(A54,eco_bus_institutions!A:D,3,0),"") -> 86 | E54: =IFERROR(VLOOKUP(A54,eco_institutions!A:D,3,0),"") -> 42 | F54: =IFERROR(VLOOKUP(A54,fin_institutions!A:D,3,0),"") -> 15 | G54: =IFERROR(VLOOKUP(A54,bus_institutions!A:D,3,0),0) -> 23 | H54: =IFERROR(VLOOKUP(A54,man_institutions!A:D,3,0),0) -> 27 | I54: =IFERROR(VLOOKUP(A54,eco_bus_institutions!A:D,4,0),0) -> 3.27 | J54: =IFERROR(VLOOKUP(A54,eco_institutions!A:D,4,0),0) -> 2.75 | K54: =IFERROR(VLOOKUP(A54,fin_institutions!A:D,4,0),0) -> 5.41 | L54: =IFERROR(VLOOKUP(A54,bus_institutions!A:D,4,0),0) -> 4.65 | M54: =IFERROR(VLOOKUP(A54,man_institutions!A:D,4,0),0) -> 2.33 | N54: =ROUND(IFERROR((601-_xlfn.RANK.EQ(I54,I:I))/600,0),3) -> 0.917 | O54: =ROUND(IFERROR((601-IFERROR(_xlfn.RANK.EQ(J54,J:J),""))/600,0),3) -> 0.913 | P54: =ROUND(IFERROR((601-IFERROR(_xlfn.RANK.EQ(K54,K:K),""))/600,0),3) -> 0.988 | Q54: =ROUND(IFERROR((601-IFERROR(_xlfn.RANK.EQ(L54,L:L),""))/600,0),3) -> 0.948 | R54: =ROUND(IFERROR((601-IFERROR(_xlfn.RANK.EQ(M54,M:M),""))/600,0),3) -> 0.748 | S54: =VLOOKUP(A54,#REF!,11,0) -> #REF! | T54: =VLOOKUP(A54,#REF!,12,0) -> #REF! | U54: =VLOOKUP(A54,#REF!,13,0) -> #REF! | V54: =VLOOKUP(A54,#REF!,14,0) -> #REF! | W54: 2.7482656 | X54: 0.48769122 | Y54: =VLOOKUP(C54,AR:AS,2,0) -> USA | Z54: =IF(Y54=Y$1,B54,IF(Y54=Y$2,B54,"")) | AR54: BRAZIL | AS54: BRA | AT54: 2.8645925 | AU54: 0.20800479 | AW54: Colorado Boulder
A55: University of Cincinnati | B55: Cincinnati | C55: USA | D55: =IFERROR(VLOOKUP(A55,eco_bus_institutions!A:D,3,0),"") -> 44 | E55: =IFERROR(VLOOKUP(A55,eco_institutions!A:D,3,0),"") -> 12 | F55: =IFERROR(VLOOKUP(A55,fin_institutions!A:D,3,0),"") -> 16 | G55: =IFERROR(VLOOKUP(A55,bus_institutions!A:D,3,0),0) -> 12 | H55: =IFERROR(VLOOKUP(A55,man_institutions!A:D,3,0),0) -> 18 | I55: =IFERROR(VLOOKUP(A55,eco_bus_institutions!A:D,4,0),0) -> 3.22 | J55: =IFERROR(VLOOKUP(A55,eco_institutions!A:D,4,0),0) -> 3.48 | K55: =IFERROR(VLOOKUP(A55,fin_institutions!A:D,4,0),0) -> 5.28 | L55: =IFERROR(VLOOKUP(A55,bus_institutions!A:D,4,0),0) -> 2.61 | M55: =IFERROR(VLOOKUP(A55,man_institutions!A:D,4,0),0) -> 2.58 | N55: =ROUND(IFERROR((601-_xlfn.RANK.EQ(I55,I:I))/600,0),3) -> 0.915 | O55: =ROUND(IFERROR((601-IFERROR(_xlfn.RANK.EQ(J55,J:J),""))/600,0),3) -> 0.947 | P55: =ROUND(IFERROR((601-IFERROR(_xlfn.RANK.EQ(K55,K:K),""))/600,0),3) -> 0.985 | Q55: =ROUND(IFERROR((601-IFERROR(_xlfn.RANK.EQ(L55,L:L),""))/600,0),3) -> 0.732 | R55: =ROUND(IFERROR((601-IFERROR(_xlfn.RANK.EQ(M55,M:M),""))/600,0),3) -> 0.802 | S55: =VLOOKUP(A55,#REF!,11,0) -> #REF! | T55: =VLOOKUP(A55,#REF!,12,0) -> #REF! | U55: =VLOOKUP(A55,#REF!,13,0) -> #REF! | V55: =VLOOKUP(A55,#REF!,14,0) -> #REF! | W55: 2.4984828 | X55: 0.82877062 | Y55: =VLOOKUP(C55,AR:AS,2,0) -> USA | Z55: =IF(Y55=Y$1,B55,IF(Y55=Y$2,B55,"")) | AR55: BELGIUM | AS55: BEL | AT55: 2.9165757 | AU55: -0.19759463 | AW55: Cincinnati
A56: University of Minnesota Twin Cities | B56: Minnesota | C56: USA | D56: =IFERROR(VLOOKUP(A56,eco_bus_institutions!A:D,3,0),"") -> 156 | E56: =IFERROR(VLOOKUP(A56,eco_institutions!A:D,3,0),"") -> 75 | F56: =IFERROR(VLOOKUP(A56,fin_institutions!A:D,3,0),"") -> 19 | G56: =IFERROR(VLOOKUP(A56,bus_institutions!A:D,3,0),0) -> 41 | H56: =IFERROR(VLOOKUP(A56,man_institutions!A:D,3,0),0) -> 53 | I56: =IFERROR(VLOOKUP(A56,eco_bus_institutions!A:D,4,0),0) -> 3.19 | J56: =IFERROR(VLOOKUP(A56,eco_institutions!A:D,4,0),0) -> 2.79 | K56: =IFERROR(VLOOKUP(A56,fin_institutions!A:D,4,0),0) -> 3.3 | L56: =IFERROR(VLOOKUP(A56,bus_institutions!A:D,4,0),0) -> 3.92 | M56: =IFERROR(VLOOKUP(A56,man_institutions!A:D,4,0),0) -> 3.88 | N56: =ROUND(IFERROR((601-_xlfn.RANK.EQ(I56,I:I))/600,0),3) -> 0.913 | O56: =ROUND(IFERROR((601-IFERROR(_xlfn.RANK.EQ(J56,J:J),""))/600,0),3) -> 0.918 | P56: =ROUND(IFERROR((601-IFERROR(_xlfn.RANK.EQ(K56,K:K),""))/600,0),3) -> 0.913 | Q56: =ROUND(IFERROR((601-IFERROR(_xlfn.RANK.EQ(L56,L:L),""))/600,0),3) -> 0.893 | R56: =ROUND(IFERROR((601-IFERROR(_xlfn.RANK.EQ(M56,M:M),""))/600,0),3) -> 0.932 | S56: =VLOOKUP(A56,#REF!,11,0) -> #REF! | T56: =VLOOKUP(A56,#REF!,12,0) -> #REF! | U56: =VLOOKUP(A56,#REF!,13,0) -> #REF! | V56: =VLOOKUP(A56,#REF!,14,0) -> #REF! | W56: 2.8645925 | X56: 0.20800479 | Y56: =VLOOKUP(C56,AR:AS,2,0) -> USA | Z56: =IF(Y56=Y$1,B56,IF(Y56=Y$2,B56,"")) | AR56: AUSTRIA | AS56: AUT | AT56: 2.7623372 | AU56: 0.2521687 | AW56: Minnesota Twin Cities
A57: University of Pittsburgh | B57: Pittsburgh | C57: USA | D57: =IFERROR(VLOOKUP(A57,eco_bus_institutions!A:D,3,0),"") -> 66 | E57: =IFERROR(VLOOKUP(A57,eco_institutions!A:D,3,0),"") -> 32 | F57: =IFERROR(VLOOKUP(A57,fin_institutions!A:D,3,0),"") -> 6 | G57: =IFERROR(VLOOKUP(A57,bus_institutions!A:D,3,0),0) -> 20 | H57: =IFERROR(VLOOKUP(A57,man_institutions!A:D,3,0),0) -> 19 | I57: =IFERROR(VLOOKUP(A57,eco_bus_institutions!A:D,4,0),0) -> 3.17 | J57: =IFERROR(VLOOKUP(A57,eco_institutions!A:D,4,0),0) -> 1.89 | K57: =IFERROR(VLOOKUP(A57,fin_institutions!A:D,4,0),0) -> 3.56 | L57: =IFERROR(VLOOKUP(A57,bus_institutions!A:D,4,0),0) -> 6.43 | M57: =IFERROR(VLOOKUP(A57,man_institutions!A:D,4,0),0) -> 4.27 | N57: =ROUND(IFERROR((601-_xlfn.RANK.EQ(I57,I:I))/600,0),3) -> 0.912 | O57: =ROUND(IFERROR((601-IFERROR(_xlfn.RANK.EQ(J57,J:J),""))/600,0),3) -> 0.813 | P57: =ROUND(IFERROR((601-IFERROR(_xlfn.RANK.EQ(K57,K:K),""))/600,0),3) -> 0.927 | Q57: =ROUND(IFERROR((601-IFERROR(_xlfn.RANK.EQ(L57,L:L),""))/600,0),3) -> 0.983 | R57: =ROUND(IFERROR((601-IFERROR(_xlfn.RANK.EQ(M57,M:M),""))/600,0),3) -> 0.947 | S57: =VLOOKUP(A57,#REF!,11,0) -> #REF! | T57: =VLOOKUP(A57,#REF!,12,0) -> #REF! | U57: =VLOOKUP(A57,#REF!,13,0) -> #REF! | V57: =VLOOKUP(A57,#REF!,14,0) -> #REF! | W57: 2.9165757 | X57: -0.19759463 | Y57: =VLOOKUP(C57,AR:AS,2,0) -> USA | Z57: =IF(Y57=Y$1,B57,IF(Y57=Y$2,B57,"")) | AR57: AUSTRALIA | AS57: AUS | AT57: 2.9700296 | AU57: -0.063079622 | AW57: Pittsburgh
A58: University of Wisconsin Madison | B58: Madison | C58: USA | D58: =IFERROR(VLOOKUP(A58,eco_bus_institutions!A:D,3,0),"") -> 144 | E58: =IFERROR(VLOOKUP(A58,eco_institutions!A:D,3,0),"") -> 97 | F58: =IFERROR(VLOOKUP(A58,fin_institutions!A:D,3,0),"") -> 34 | G58: =IFERROR(VLOOKUP(A58,bus_institutions!A:D,3,0),0) -> 18 | H58: =IFERROR(VLOOKUP(A58,man_institutions!A:D,3,0),0) -> 23 | I58: =IFERROR(VLOOKUP(A58,eco_bus_institutions!A:D,4,0),0) -> 3.16 | J58: =IFERROR(VLOOKUP(A58,eco_institutions!A:D,4,0),0) -> 2.97 | K58: =IFERROR(VLOOKUP(A58,fin_institutions!A:D,4,0),0) -> 2.86 | L58: =IFERROR(VLOOKUP(A58,bus_institutions!A:D,4,0),0) -> 4.98 | M58: =IFERROR(VLOOKUP(A58,man_institutions!A:D,4,0),0) -> 2.75 | N58: =ROUND(IFERROR((601-_xlfn.RANK.EQ(I58,I:I))/600,0),3) -> 0.91 | O58: =ROUND(IFERROR((601-IFERROR(_xlfn.RANK.EQ(J58,J:J),""))/600,0),3) -> 0.928 | P58: =ROUND(IFERROR((601-IFERROR(_xlfn.RANK.EQ(K58,K:K),""))/600,0),3) -> 0.885 | Q58: =ROUND(IFERROR((601-IFERROR(_xlfn.RANK.EQ(L58,L:L),""))/600,0),3) -> 0.955 | R58: =ROUND(IFERROR((601-IFERROR(_xlfn.RANK.EQ(M58,M:M),""))/600,0),3) -> 0.833 | S58: =VLOOKUP(A58,#REF!,11,0) -> #REF! | T58: =VLOOKUP(A58,#REF!,12,0) -> #REF! | U58: =VLOOKUP(A58,#REF!,13,0) -> #REF! | V58: =VLOOKUP(A58,#REF!,14,0) -> #REF! | W58: 2.7623372 | X58: 0.2521687 | Y58: =VLOOKUP(C58,AR:AS,2,0) -> USA | Z58: =IF(Y58=Y$1,B58,IF(Y58=Y$2,B58,"")) | AT58: 2.4615829 | AU58: 0.15055703 | AW58: Wisconsin Madison
A59: University of Oregon | B59: Oregon | C59: USA | D59: =IFERROR(VLOOKUP(A59,eco_bus_institutions!A:D,3,0),"") -> 73 | E59: =IFERROR(VLOOKUP(A59,eco_institutions!A:D,3,0),"") -> 40 | F59: =IFERROR(VLOOKUP(A59,fin_institutions!A:D,3,0),"") -> 16 | G59: =IFERROR(VLOOKUP(A59,bus_institutions!A:D,3,0),0) -> 17 | H59: =IFERROR(VLOOKUP(A59,man_institutions!A:D,3,0),0) -> 15 | I59: =IFERROR(VLOOKUP(A59,eco_bus_institutions!A:D,4,0),0) -> 3.15 | J59: =IFERROR(VLOOKUP(A59,eco_institutions!A:D,4,0),0) -> 2.38 | K59: =IFERROR(VLOOKUP(A59,fin_institutions!A:D,4,0),0) -> 3.08 | L59: =IFERROR(VLOOKUP(A59,bus_institutions!A:D,4,0),0) -> 5.55 | M59: =IFERROR(VLOOKUP(A59,man_institutions!A:D,4,0),0) -> 4.55 | N59: =ROUND(IFERROR((601-_xlfn.RANK.EQ(I59,I:I))/600,0),3) -> 0.908 | O59: =ROUND(IFERROR((601-IFERROR(_xlfn.RANK.EQ(J59,J:J),""))/600,0),3) -> 0.88 | P59: =ROUND(IFERROR((601-IFERROR(_xlfn.RANK.EQ(K59,K:K),""))/600,0),3) -> 0.9 | Q59: =ROUND(IFERROR((601-IFERROR(_xlfn.RANK.EQ(L59,L:L),""))/600,0),3) -> 0.972 | R59: =ROUND(IFERROR((601-IFERROR(_xlfn.RANK.EQ(M59,M:M),""))/600,0),3) -> 0.955 | S59: =VLOOKUP(A59,#REF!,11,0) -> #REF! | T59: =VLOOKUP(A59,#REF!,12,0) -> #REF! | U59: =VLOOKUP(A59,#REF!,13,0) -> #REF! | V59: =VLOOKUP(A59,#REF!,14,0) -> #REF! | W59: 2.9700296 | X59: -0.063079622 | Y59: =VLOOKUP(C59,AR:AS,2,0) -> USA | Z59: =IF(Y59=Y$1,B59,IF(Y59=Y$2,B59,"")) | AT59: 2.1995731 | AU59: 0.29120906 | AW59: Oregon
A60: Carnegie Mellon University | B60: C Mellon | C60: USA | D60: =IFERROR(VLOOKUP(A60,eco_bus_institutions!A:D,3,0),"") -> 65 | E60: =IFERROR(VLOOKUP(A60,eco_institutions!A:D,3,0),"") -> 31 | F60: =IFERROR(VLOOKUP(A60,fin_institutions!A:D,3,0),"") -> 10 | G60: =IFERROR(VLOOKUP(A60,bus_institutions!A:D,3,0),0) -> 14 | H60: =IFERROR(VLOOKUP(A60,man_institutions!A:D,3,0),0) -> 27 | I60: =IFERROR(VLOOKUP(A60,eco_bus_institutions!A:D,4,0),0) -> 3.13 | J60: =IFERROR(VLOOKUP(A60,eco_institutions!A:D,4,0),0) -> 2.37 | K60: =IFERROR(VLOOKUP(A60,fin_institutions!A:D,4,0),0) -> 2.02 | L60: =IFERROR(VLOOKUP(A60,bus_institutions!A:D,4,0),0) -> 2.94 | M60: =IFERROR(VLOOKUP(A60,man_institutions!A:D,4,0),0) -> 4.05 | N60: =ROUND(IFERROR((601-_xlfn.RANK.EQ(I60,I:I))/600,0),3) -> 0.907 | O60: =ROUND(IFERROR((601-IFERROR(_xlfn.RANK.EQ(J60,J:J),""))/600,0),3) -> 0.877 | P60: =ROUND(IFERROR((601-IFERROR(_xlfn.RANK.EQ(K60,K:K),""))/600,0),3) -> 0.822 | Q60: =ROUND(IFERROR((601-IFERROR(_xlfn.RANK.EQ(L60,L:L),""))/600,0),3) -> 0.788 | R60: =ROUND(IFERROR((601-IFERROR(_xlfn.RANK.EQ(M60,M:M),""))/600,0),3) -> 0.94 | S60: =VLOOKUP(A60,#REF!,11,0) -> #REF! | T60: =VLOOKUP(A60,#REF!,12,0) -> #REF! | U60: =VLOOKUP(A60,#REF!,13,0) -> #REF! | V60: =VLOOKUP(A60,#REF!,14,0) -> #REF! | W60: 2.4615829 | X60: 0.15055703 | Y60: =VLOOKUP(C60,AR:AS,2,0) -> USA | Z60: =IF(Y60=Y$1,B60,IF(Y60=Y$2,B60,"")) | AT60: 2.0130195 | AU60: -0.6902553 | AW60: Carnegie Mellon
A61: EDHEC Business School | B61: EDHEC | C61: FRANCE | D61: =IFERROR(VLOOKUP(A61,eco_bus_institutions!A:D,3,0),"") -> 44 | E61: =IFERROR(VLOOKUP(A61,eco_institutions!A:D,3,0),"") -> 19 | F61: =IFERROR(VLOOKUP(A61,fin_institutions!A:D,3,0),"") -> 18 | G61: =IFERROR(VLOOKUP(A61,bus_institutions!A:D,3,0),0) -> 9 | H61: =IFERROR(VLOOKUP(A61,man_institutions!A:D,3,0),0) -> 12 | I61: =IFERROR(VLOOKUP(A61,eco_bus_institutions!A:D,4,0),0) -> 3.1 | J61: =IFERROR(VLOOKUP(A61,eco_institutions!A:D,4,0),0) -> 3.39 | K61: =IFERROR(VLOOKUP(A61,fin_institutions!A:D,4,0),0) -> 1.52 | L61: =IFERROR(VLOOKUP(A61,bus_institutions!A:D,4,0),0) -> 3.47 | M61: =IFERROR(VLOOKUP(A61,man_institutions!A:D,4,0),0) -> 2.44 | N61: =ROUND(IFERROR((601-_xlfn.RANK.EQ(I61,I:I))/600,0),3) -> 0.905 | O61: =ROUND(IFERROR((601-IFERROR(_xlfn.RANK.EQ(J61,J:J),""))/600,0),3) -> 0.945 | P61: =ROUND(IFERROR((601-IFERROR(_xlfn.RANK.EQ(K61,K:K),""))/600,0),3) -> 0.7 | Q61: =ROUND(IFERROR((601-IFERROR(_xlfn.RANK.EQ(L61,L:L),""))/600,0),3) -> 0.862 | R61: =ROUND(IFERROR((601-IFERROR(_xlfn.RANK.EQ(M61,M:M),""))/600,0),3) -> 0.782 | S61: =VLOOKUP(A61,#REF!,11,0) -> #REF! | T61: =VLOOKUP(A61,#REF!,12,0) -> #REF! | U61: =VLOOKUP(A61,#REF!,13,0) -> #REF! | V61: =VLOOKUP(A61,#REF!,14,0) -> #REF! | W61: 2.1995731 | X61: 0.29120906 | Y61: =VLOOKUP(C61,AR:AS,2,0) -> FRA | Z61: =IF(Y61=Y$1,B61,IF(Y61=Y$2,B61,"")) | AT61: 2.6252508 | AU61: 0.36686352 | AW61: EDHEC Business School
A62: Texas Christian University | B62: Texas Christian | C62: USA | D62: =IFERROR(VLOOKUP(A62,eco_bus_institutions!A:D,3,0),"") -> 51 | E62: =IFERROR(VLOOKUP(A62,eco_institutions!A:D,3,0),"") -> 7 | F62: =IFERROR(VLOOKUP(A62,fin_institutions!A:D,3,0),"") -> 15 | G62: =IFERROR(VLOOKUP(A62,bus_institutions!A:D,3,0),0) -> 23 | H62: =IFERROR(VLOOKUP(A62,man_institutions!A:D,3,0),0) -> 18 | I62: =IFERROR(VLOOKUP(A62,eco_bus_institutions!A:D,4,0),0) -> 3.1 | J62: =IFERROR(VLOOKUP(A62,eco_institutions!A:D,4,0),0) -> 1.22 | K62: =IFERROR(VLOOKUP(A62,fin_institutions!A:D,4,0),0) -> 2.38 | L62: =IFERROR(VLOOKUP(A62,bus_institutions!A:D,4,0),0) -> 5.53 | M62: =IFERROR(VLOOKUP(A62,man_institutions!A:D,4,0),0) -> 2.47 | N62: =ROUND(IFERROR((601-_xlfn.RANK.EQ(I62,I:I))/600,0),3) -> 0.905 | O62: =ROUND(IFERROR((601-IFERROR(_xlfn.RANK.EQ(J62,J:J),""))/600,0),3) -> 0.538 | P62: =ROUND(IFERROR((601-IFERROR(_xlfn.RANK.EQ(K62,K:K),""))/600,0),3) -> 0.847 | Q62: =ROUND(IFERROR((601-IFERROR(_xlfn.RANK.EQ(L62,L:L),""))/600,0),3) -> 0.968 | R62: =ROUND(IFERROR((601-IFERROR(_xlfn.RANK.EQ(M62,M:M),""))/600,0),3) -> 0.785 | S62: =VLOOKUP(A62,#REF!,11,0) -> #REF! | T62: =VLOOKUP(A62,#REF!,12,0) -> #REF! | U62: =VLOOKUP(A62,#REF!,13,0) -> #REF! | V62: =VLOOKUP(A62,#REF!,14,0) -> #REF! | W62: 2.0130195 | X62: -0.6902553 | Y62: =VLOOKUP(C62,AR:AS,2,0) -> USA | Z62: =IF(Y62=Y$1,B62,IF(Y62=Y$2,B62,"")) | AT62: 2.69876 | AU62: -0.11200948 | AW62: Texas Christian
A63: University of Toronto | B63: Toronto | C63: CANADA | D63: =IFERROR(VLOOKUP(A63,eco_bus_institutions!A:D,3,0),"") -> 184 | E63: =IFERROR(VLOOKUP(A63,eco_institutions!A:D,3,0),"") -> 109 | F63: =IFERROR(VLOOKUP(A63,fin_institutions!A:D,3,0),"") -> 44 | G63: =IFERROR(VLOOKUP(A63,bus_institutions!A:D,3,0),0) -> 33 | H63: =IFERROR(VLOOKUP(A63,man_institutions!A:D,3,0),0) -> 51 | I63: =IFERROR(VLOOKUP(A63,eco_bus_institutions!A:D,4,0),0) -> 3.08 | J63: =IFERROR(VLOOKUP(A63,eco_institutions!A:D,4,0),0) -> 2.72 | K63: =IFERROR(VLOOKUP(A63,fin_institutions!A:D,4,0),0) -> 3.19 | L63: =IFERROR(VLOOKUP(A63,bus_institutions!A:D,4,0),0) -> 3.11 | M63: =IFERROR(VLOOKUP(A63,man_institutions!A:D,4,0),0) -> 3.34 | N63: =ROUND(IFERROR((601-_xlfn.RANK.EQ(I63,I:I))/600,0),3) -> 0.902 | O63: =ROUND(IFERROR((601-IFERROR(_xlfn.RANK.EQ(J63,J:J),""))/600,0),3) -> 0.91 | P63: =ROUND(IFERROR((601-IFERROR(_xlfn.RANK.EQ(K63,K:K),""))/600,0),3) -> 0.907 | Q63: =ROUND(IFERROR((601-IFERROR(_xlfn.RANK.EQ(L63,L:L),""))/600,0),3) -> 0.813 | R63: =ROUND(IFERROR((601-IFERROR(_xlfn.RANK.EQ(M63,M:M),""))/600,0),3) -> 0.895 | S63: =VLOOKUP(A63,#REF!,11,0) -> #REF! | T63: =VLOOKUP(A63,#REF!,12,0) -> #REF! | U63: =VLOOKUP(A63,#REF!,13,0) -> #REF! | V63: =VLOOKUP(A63,#REF!,14,0) -> #REF! | W63: 2.6252508 | X63: 0.36686352 | Y63: =VLOOKUP(C63,AR:AS,2,0) -> CAN | Z63: =IF(Y63=Y$1,B63,IF(Y63=Y$2,B63,"")) | AT63: 2.3241669 | AU63: 0.34355137 | AW63: Toronto
A64: Northeastern University | B64: Northeastern | C64: USA | D64: =IFERROR(VLOOKUP(A64,eco_bus_institutions!A:D,3,0),"") -> 79 | E64: =IFERROR(VLOOKUP(A64,eco_institutions!A:D,3,0),"") -> 19 | F64: =IFERROR(VLOOKUP(A64,fin_institutions!A:D,3,0),"") -> 15 | G64: =IFERROR(VLOOKUP(A64,bus_institutions!A:D,3,0),0) -> 42 | H64: =IFERROR(VLOOKUP(A64,man_institutions!A:D,3,0),0) -> 30 | I64: =IFERROR(VLOOKUP(A64,eco_bus_institutions!A:D,4,0),0) -> 3.05 | J64: =IFERROR(VLOOKUP(A64,eco_institutions!A:D,4,0),0) -> 1.81 | K64: =IFERROR(VLOOKUP(A64,fin_institutions!A:D,4,0),0) -> 3.23 | L64: =IFERROR(VLOOKUP(A64,bus_institutions!A:D,4,0),0) -> 4.12 | M64: =IFERROR(VLOOKUP(A64,man_institutions!A:D,4,0),0) -> 3.79 | N64: =ROUND(IFERROR((601-_xlfn.RANK.EQ(I64,I:I))/600,0),3) -> 0.9 | O64: =ROUND(IFERROR((601-IFERROR(_xlfn.RANK.EQ(J64,J:J),""))/600,0),3) -> 0.797 | P64: =ROUND(IFERROR((601-IFERROR(_xlfn.RANK.EQ(K64,K:K),""))/600,0),3) -> 0.912 | Q64: =ROUND(IFERROR((601-IFERROR(_xlfn.RANK.EQ(L64,L:L),""))/600,0),3) -> 0.915 | R64: =ROUND(IFERROR((601-IFERROR(_xlfn.RANK.EQ(M64,M:M),""))/600,0),3) -> 0.925 | S64: =VLOOKUP(A64,#REF!,11,0) -> #REF! | T64: =VLOOKUP(A64,#REF!,12,0) -> #REF! | U64: =VLOOKUP(A64,#REF!,13,0) -> #REF! | V64: =VLOOKUP(A64,#REF!,14,0) -> #REF! | W64: 2.69876 | X64: -0.11200948 | Y64: =VLOOKUP(C64,AR:AS,2,0) -> USA | Z64: =IF(Y64=Y$1,B64,IF(Y64=Y$2,B64,"")) | AT64: -0.50561482 | AU64: 2.8376099 | AW64: Northeastern
A65: Georgia Institute of Technology | B65: GATECH | C65: USA | D65: =IFERROR(VLOOKUP(A65,eco_bus_institutions!A:D,3,0),"") -> 66 | E65: =IFERROR(VLOOKUP(A65,eco_institutions!A:D,3,0),"") -> 23 | F65: =IFERROR(VLOOKUP(A65,fin_institutions!A:D,3,0),"") -> 15 | G65: =IFERROR(VLOOKUP(A65,bus_institutions!A:D,3,0),0) -> 11 | H65: =IFERROR(VLOOKUP(A65,man_institutions!A:D,3,0),0) -> 29 | I65: =IFERROR(VLOOKUP(A65,eco_bus_institutions!A:D,4,0),0) -> 2.98 | J65: =IFERROR(VLOOKUP(A65,eco_institutions!A:D,4,0),0) -> 2.63 | K65: =IFERROR(VLOOKUP(A65,fin_institutions!A:D,4,0),0) -> 2.02 | L65: =IFERROR(VLOOKUP(A65,bus_institutions!A:D,4,0),0) -> 5.06 | M65: =IFERROR(VLOOKUP(A65,man_institutions!A:D,4,0),0) -> 2.05 | N65: =ROUND(IFERROR((601-_xlfn.RANK.EQ(I65,I:I))/600,0),3) -> 0.898 | O65: =ROUND(IFERROR((601-IFERROR(_xlfn.RANK.EQ(J65,J:J),""))/600,0),3) -> 0.9 | P65: =ROUND(IFERROR((601-IFERROR(_xlfn.RANK.EQ(K65,K:K),""))/600,0),3) -> 0.822 | Q65: =ROUND(IFERROR((601-IFERROR(_xlfn.RANK.EQ(L65,L:L),""))/600,0),3) -> 0.957 | R65: =ROUND(IFERROR((601-IFERROR(_xlfn.RANK.EQ(M65,M:M),""))/600,0),3) -> 0.678 | S65: =VLOOKUP(A65,#REF!,11,0) -> #REF! | T65: =VLOOKUP(A65,#REF!,12,0) -> #REF! | U65: =VLOOKUP(A65,#REF!,13,0) -> #REF! | V65: =VLOOKUP(A65,#REF!,14,0) -> #REF! | W65: 2.3241669 | X65: 0.34355137 | Y65: =VLOOKUP(C65,AR:AS,2,0) -> USA | Z65: =IF(Y65=Y$1,B65,IF(Y65=Y$2,B65,"")) | AT65: 2.7927204 | AU65: 0.18447044 | AW65: Georgia Institute of Technology
A66: University of Bonn | B66: Bonn | C66: GERMANY | D66: =IFERROR(VLOOKUP(A66,eco_bus_institutions!A:D,3,0),"") -> 77 | E66: =IFERROR(VLOOKUP(A66,eco_institutions!A:D,3,0),"") -> 69 | F66: =IFERROR(VLOOKUP(A66,fin_institutions!A:D,3,0),"") -> 9 | G66: =IFERROR(VLOOKUP(A66,bus_institutions!A:D,3,0),0) -> 0 | H66: =IFERROR(VLOOKUP(A66,man_institutions!A:D,3,0),0) -> 0 | I66: =IFERROR(VLOOKUP(A66,eco_bus_institutions!A:D,4,0),0) -> 2.95 | J66: =IFERROR(VLOOKUP(A66,eco_institutions!A:D,4,0),0) -> 2.82 | K66: =IFERROR(VLOOKUP(A66,fin_institutions!A:D,4,0),0) -> 2.01 | L66: =IFERROR(VLOOKUP(A66,bus_institutions!A:D,4,0),0) -> 0 | M66: =IFERROR(VLOOKUP(A66,man_institutions!A:D,4,0),0) -> 0 | N66: =ROUND(IFERROR((601-_xlfn.RANK.EQ(I66,I:I))/600,0),3) -> 0.897 | O66: =ROUND(IFERROR((601-IFERROR(_xlfn.RANK.EQ(J66,J:J),""))/600,0),3) -> 0.922 | P66: =ROUND(IFERROR((601-IFERROR(_xlfn.RANK.EQ(K66,K:K),""))/600,0),3) -> 0.817 | Q66: =ROUND(IFERROR((601-IFERROR(_xlfn.RANK.EQ(L66,L:L),""))/600,0),3) -> 0.05 | R66: =ROUND(IFERROR((601-IFERROR(_xlfn.RANK.EQ(M66,M:M),""))/600,0),3) -> 0.04 | S66: =VLOOKUP(A66,#REF!,11,0) -> #REF! | T66: =VLOOKUP(A66,#REF!,12,0) -> #REF! | U66: =VLOOKUP(A66,#REF!,13,0) -> #REF! | V66: =VLOOKUP(A66,#REF!,14,0) -> #REF! | W66: -0.50561482 | X66: 2.8376099 | Y66: =VLOOKUP(C66,AR:AS,2,0) -> DEU | Z66: =IF(Y66=Y$1,B66,IF(Y66=Y$2,B66,"")) | AT66: 2.5008899 | AU66: -0.15729351 | AW66: Bonn
A67: University of Illinois Chicago | B67: Illinois Ch | C67: USA | D67: =IFERROR(VLOOKUP(A67,eco_bus_institutions!A:D,3,0),"") -> 86 | E67: =IFERROR(VLOOKUP(A67,eco_institutions!A:D,3,0),"") -> 48 | F67: =IFERROR(VLOOKUP(A67,fin_institutions!A:D,3,0),"") -> 30 | G67: =IFERROR(VLOOKUP(A67,bus_institutions!A:D,3,0),0) -> 17 | H67: =IFERROR(VLOOKUP(A67,man_institutions!A:D,3,0),0) -> 14 | I67: =IFERROR(VLOOKUP(A67,eco_bus_institutions!A:D,4,0),0) -> 2.94 | J67: =IFERROR(VLOOKUP(A67,eco_institutions!A:D,4,0),0) -> 2.38 | K67: =IFERROR(VLOOKUP(A67,fin_institutions!A:D,4,0),0) -> 3.82 | L67: =IFERROR(VLOOKUP(A67,bus_institutions!A:D,4,0),0) -> 4.02 | M67: =IFERROR(VLOOKUP(A67,man_institutions!A:D,4,0),0) -> 3.33 | N67: =ROUND(IFERROR((601-_xlfn.RANK.EQ(I67,I:I))/600,0),3) -> 0.895 | O67: =ROUND(IFERROR((601-IFERROR(_xlfn.RANK.EQ(J67,J:J),""))/600,0),3) -> 0.88 | P67: =ROUND(IFERROR((601-IFERROR(_xlfn.RANK.EQ(K67,K:K),""))/600,0),3) -> 0.935 | Q67: =ROUND(IFERROR((601-IFERROR(_xlfn.RANK.EQ(L67,L:L),""))/600,0),3) -> 0.905 | R67: =ROUND(IFERROR((601-IFERROR(_xlfn.RANK.EQ(M67,M:M),""))/600,0),3) -> 0.893 | S67: =VLOOKUP(A67,#REF!,11,0) -> #REF! | T67: =VLOOKUP(A67,#REF!,12,0) -> #REF! | U67: =VLOOKUP(A67,#REF!,13,0) -> #REF! | V67: =VLOOKUP(A67,#REF!,14,0) -> #REF! | W67: 2.7927204 | X67: 0.18447044 | Y67: =VLOOKUP(C67,AR:AS,2,0) -> USA | Z67: =IF(Y67=Y$1,B67,IF(Y67=Y$2,B67,"")) | AT67: 2.6875723 | AU67: 0.15751169 | AW67: Illinois Chicago
A68: Baylor University | B68: Baylor | C68: USA | D68: =IFERROR(VLOOKUP(A68,eco_bus_institutions!A:D,3,0),"") -> 45 | E68: =IFERROR(VLOOKUP(A68,eco_institutions!A:D,3,0),"") -> 17 | F68: =IFERROR(VLOOKUP(A68,fin_institutions!A:D,3,0),"") -> 5 | G68: =IFERROR(VLOOKUP(A68,bus_institutions!A:D,3,0),0) -> 24 | H68: =IFERROR(VLOOKUP(A68,man_institutions!A:D,3,0),0) -> 16 | I68: =IFERROR(VLOOKUP(A68,eco_bus_institutions!A:D,4,0),0) -> 2.91 | J68: =IFERROR(VLOOKUP(A68,eco_institutions!A:D,4,0),0) -> 1.82 | K68: =IFERROR(VLOOKUP(A68,fin_institutions!A:D,4,0),0) -> 2.16 | L68: =IFERROR(VLOOKUP(A68,bus_institutions!A:D,4,0),0) -> 4.25 | M68: =IFERROR(VLOOKUP(A68,man_institutions!A:D,4,0),0) -> 3.19 | N68: =ROUND(IFERROR((601-_xlfn.RANK.EQ(I68,I:I))/600,0),3) -> 0.893 | O68: =ROUND(IFERROR((601-IFERROR(_xlfn.RANK.EQ(J68,J:J),""))/600,0),3) -> 0.798 | P68: =ROUND(IFERROR((601-IFERROR(_xlfn.RANK.EQ(K68,K:K),""))/600,0),3) -> 0.833 | Q68: =ROUND(IFERROR((601-IFERROR(_xlfn.RANK.EQ(L68,L:L),""))/600,0),3) -> 0.927 | R68: =ROUND(IFERROR((601-IFERROR(_xlfn.RANK.EQ(M68,M:M),""))/600,0),3) -> 0.88 | S68: =VLOOKUP(A68,#REF!,11,0) -> #REF! | T68: =VLOOKUP(A68,#REF!,12,0) -> #REF! | U68: =VLOOKUP(A68,#REF!,13,0) -> #REF! | V68: =VLOOKUP(A68,#REF!,14,0) -> #REF! | W68: 2.5008899 | X68: -0.15729351 | Y68: =VLOOKUP(C68,AR:AS,2,0) -> USA | Z68: =IF(Y68=Y$1,B68,IF(Y68=Y$2,B68,"")) | AT68: 2.0570931 | AU68: 0.27204985 | AW68: Baylor
A69: Hong Kong University of Science & Technology | B69: HKST | C69: HONG KONG | D69: =IFERROR(VLOOKUP(A69,eco_bus_institutions!A:D,3,0),"") -> 85 | E69: =IFERROR(VLOOKUP(A69,eco_institutions!A:D,3,0),"") -> 45 | F69: =IFERROR(VLOOKUP(A69,fin_institutions!A:D,3,0),"") -> 21 | G69: =IFERROR(VLOOKUP(A69,bus_institutions!A:D,3,0),0) -> 16 | H69: =IFERROR(VLOOKUP(A69,man_institutions!A:D,3,0),0) -> 26 | I69: =IFERROR(VLOOKUP(A69,eco_bus_institutions!A:D,4,0),0) -> 2.91 | J69: =IFERROR(VLOOKUP(A69,eco_institutions!A:D,4,0),0) -> 2.26 | K69: =IFERROR(VLOOKUP(A69,fin_institutions!A:D,4,0),0) -> 3.41 | L69: =IFERROR(VLOOKUP(A69,bus_institutions!A:D,4,0),0) -> 4.75 | M69: =IFERROR(VLOOKUP(A69,man_institutions!A:D,4,0),0) -> 2.65 | N69: =ROUND(IFERROR((601-_xlfn.RANK.EQ(I69,I:I))/600,0),3) -> 0.893 | O69: =ROUND(IFERROR((601-IFERROR(_xlfn.RANK.EQ(J69,J:J),""))/600,0),3) -> 0.863 | P69: =ROUND(IFERROR((601-IFERROR(_xlfn.RANK.EQ(K69,K:K),""))/600,0),3) -> 0.917 | Q69: =ROUND(IFERROR((601-IFERROR(_xlfn.RANK.EQ(L69,L:L),""))/600,0),3) -> 0.95 | R69: =ROUND(IFERROR((601-IFERROR(_xlfn.RANK.EQ(M69,M:M),""))/600,0),3) -> 0.823 | S69: =VLOOKUP(A69,#REF!,11,0) -> #REF! | T69: =VLOOKUP(A69,#REF!,12,0) -> #REF! | U69: =VLOOKUP(A69,#REF!,13,0) -> #REF! | V69: =VLOOKUP(A69,#REF!,14,0) -> #REF! | W69: 2.6875723 | X69: 0.15751169 | Y69: =VLOOKUP(C69,AR:AS,2,0) -> HKG | Z69: =IF(Y69=Y$1,B69,IF(Y69=Y$2,B69,"")) | AT69: 2.5763724 | AU69: -0.1399316 | AW69: Hong Kong Science & Technology
... A135: University of Connecticut | B135: Connecticut | C135: USA | D135: =IFERROR(VLOOKUP(A135,eco_bus_institutions!A:D,3,0),"") -> 89 | E135: =IFERROR(VLOOKUP(A135,eco_institutions!A:D,3,0),"") -> 56 | F135: =IFERROR(VLOOKUP(A135,fin_institutions!A:D,3,0),"") -> 26 | G135: =IFERROR(VLOOKUP(A135,bus_institutions!A:D,3,0),0) -> 16 | H135: =IFERROR(VLOOKUP(A135,man_institutions!A:D,3,0),0) -> 19 | I135: =IFERROR(VLOOKUP(A135,eco_bus_institutions!A:D,4,0),0) -> 2.28 | J135: =IFERROR(VLOOKUP(A135,eco_institutions!A:D,4,0),0) -> 1.79 | K135: =IFERROR(VLOOKUP(A135,fin_institutions!A:D,4,0),0) -> 2.22 | L135: =IFERROR(VLOOKUP(A135,bus_institutions!A:D,4,0),0) -> 4.02 | M135: =IFERROR(VLOOKUP(A135,man_institutions!A:D,4,0),0) -> 3.52 | N135: =ROUND(IFERROR((601-_xlfn.RANK.EQ(I135,I:I))/600,0),3) -> 0.783 | O135: =ROUND(IFERROR((601-IFERROR(_xlfn.RANK.EQ(J135,J:J),""))/600,0),3) -> 0.788 | P135: =ROUND(IFERROR((601-IFERROR(_xlfn.RANK.EQ(K135,K:K),""))/600,0),3) -> 0.837 | Q135: =ROUND(IFERROR((601-IFERROR(_xlfn.RANK.EQ(L135,L:L),""))/600,0),3) -> 0.905 | R135: =ROUND(IFERROR((601-IFERROR(_xlfn.RANK.EQ(M135,M:M),""))/600,0),3) -> 0.908 | S135: =VLOOKUP(A135,#REF!,11,0) -> #REF! | T135: =VLOOKUP(A135,#REF!,12,0) -> #REF! | U135: =VLOOKUP(A135,#REF!,13,0) -> #REF! | V135: =VLOOKUP(A135,#REF!,14,0) -> #REF! | W135: 2.5033568 | X135: -0.1849675 | Y135: =VLOOKUP(C135,AR:AS,2,0) -> USA | Z135: =IF(Y135=Y$1,B135,IF(Y135=Y$2,B135,"")) | AT135: 1.9860607 | AU135: 0.83620626 | AW135: Connecticut
A136: City St Georges, University of London | B136: City St Georges, London | C136: ENGLAND | D136: =IFERROR(VLOOKUP(A136,eco_bus_institutions!A:D,3,0),"") -> 125 | E136: =IFERROR(VLOOKUP(A136,eco_institutions!A:D,3,0),"") -> 55 | F136: =IFERROR(VLOOKUP(A136,fin_institutions!A:D,3,0),"") -> 29 | G136: =IFERROR(VLOOKUP(A136,bus_institutions!A:D,3,0),0) -> 36 | H136: =IFERROR(VLOOKUP(A136,man_institutions!A:D,3,0),0) -> 44 | I136: =IFERROR(VLOOKUP(A136,eco_bus_institutions!A:D,4,0),0) -> 2.27 | J136: =IFERROR(VLOOKUP(A136,eco_institutions!A:D,4,0),0) -> 1.18 | K136: =IFERROR(VLOOKUP(A136,fin_institutions!A:D,4,0),0) -> 1.34 | L136: =IFERROR(VLOOKUP(A136,bus_institutions!A:D,4,0),0) -> 3.77 | M136: =IFERROR(VLOOKUP(A136,man_institutions!A:D,4,0),0) -> 3.73 | N136: =ROUND(IFERROR((601-_xlfn.RANK.EQ(I136,I:I))/600,0),3) -> 0.78 | O136: =ROUND(IFERROR((601-IFERROR(_xlfn.RANK.EQ(J136,J:J),""))/600,0),3) -> 0.498 | P136: =ROUND(IFERROR((601-IFERROR(_xlfn.RANK.EQ(K136,K:K),""))/600,0),3) -> 0.635 | Q136: =ROUND(IFERROR((601-IFERROR(_xlfn.RANK.EQ(L136,L:L),""))/600,0),3) -> 0.875 | R136: =ROUND(IFERROR((601-IFERROR(_xlfn.RANK.EQ(M136,M:M),""))/600,0),3) -> 0.922 | S136: 1 | T136: =VLOOKUP(A136,#REF!,12,0) -> #REF! | U136: =VLOOKUP(A136,#REF!,13,0) -> #REF! | V136: =VLOOKUP(A136,#REF!,14,0) -> #REF! | W136: 1.6611993 | X136: -1.1162518 | Y136: =VLOOKUP(C136,AR:AS,2,0) -> UK | Z136: =IF(Y136=Y$1,B136,IF(Y136=Y$2,B136,"")) | AT136: 2.178281 | AU136: -0.35849015 | AW136: City St Georges, London
A137: Michigan State University | B137: Michigan State | C137: USA | D137: =IFERROR(VLOOKUP(A137,eco_bus_institutions!A:D,3,0),"") -> 187 | E137: =IFERROR(VLOOKUP(A137,eco_institutions!A:D,3,0),"") -> 97 | F137: =IFERROR(VLOOKUP(A137,fin_institutions!A:D,3,0),"") -> 23 | G137: =IFERROR(VLOOKUP(A137,bus_institutions!A:D,3,0),0) -> 39 | H137: =IFERROR(VLOOKUP(A137,man_institutions!A:D,3,0),0) -> 60 | I137: =IFERROR(VLOOKUP(A137,eco_bus_institutions!A:D,4,0),0) -> 2.27 | J137: =IFERROR(VLOOKUP(A137,eco_institutions!A:D,4,0),0) -> 2.16 | K137: =IFERROR(VLOOKUP(A137,fin_institutions!A:D,4,0),0) -> 4.07 | L137: =IFERROR(VLOOKUP(A137,bus_institutions!A:D,4,0),0) -> 2.29 | M137: =IFERROR(VLOOKUP(A137,man_institutions!A:D,4,0),0) -> 2.15 | N137: =ROUND(IFERROR((601-_xlfn.RANK.EQ(I137,I:I))/600,0),3) -> 0.78 | O137: =ROUND(IFERROR((601-IFERROR(_xlfn.RANK.EQ(J137,J:J),""))/600,0),3) -> 0.853 | P137: =ROUND(IFERROR((601-IFERROR(_xlfn.RANK.EQ(K137,K:K),""))/600,0),3) -> 0.958 | Q137: =ROUND(IFERROR((601-IFERROR(_xlfn.RANK.EQ(L137,L:L),""))/600,0),3) -> 0.653 | R137: =ROUND(IFERROR((601-IFERROR(_xlfn.RANK.EQ(M137,M:M),""))/600,0),3) -> 0.71 | S137: =VLOOKUP(A137,#REF!,11,0) -> #REF! | T137: =VLOOKUP(A137,#REF!,12,0) -> #REF! | U137: =VLOOKUP(A137,#REF!,13,0) -> #REF! | V137: =VLOOKUP(A137,#REF!,14,0) -> #REF! | W137: 1.9860607 | X137: 0.83620626 | Y137: =VLOOKUP(C137,AR:AS,2,0) -> USA | Z137: =IF(Y137=Y$1,B137,IF(Y137=Y$2,B137,"")) | AT137: 1.3761363 | AU137: -0.50679755 | AW137: Michigan State
A138: University of Georgia | B138: Georgia | C138: USA | D138: =IFERROR(VLOOKUP(A138,eco_bus_institutions!A:D,3,0),"") -> 135 | E138: =IFERROR(VLOOKUP(A138,eco_institutions!A:D,3,0),"") -> 66 | F138: =IFERROR(VLOOKUP(A138,fin_institutions!A:D,3,0),"") -> 29 | G138: =IFERROR(VLOOKUP(A138,bus_institutions!A:D,3,0),0) -> 46 | H138: =IFERROR(VLOOKUP(A138,man_institutions!A:D,3,0),0) -> 27 | I138: =IFERROR(VLOOKUP(A138,eco_bus_institutions!A:D,4,0),0) -> 2.27 | J138: =IFERROR(VLOOKUP(A138,eco_institutions!A:D,4,0),0) -> 1.37 | K138: =IFERROR(VLOOKUP(A138,fin_institutions!A:D,4,0),0) -> 2.58 | L138: =IFERROR(VLOOKUP(A138,bus_institutions!A:D,4,0),0) -> 2.69 | M138: =IFERROR(VLOOKUP(A138,man_institutions!A:D,4,0),0) -> 5.71 | N138: =ROUND(IFERROR((601-_xlfn.RANK.EQ(I138,I:I))/600,0),3) -> 0.78 | O138: =ROUND(IFERROR((601-IFERROR(_xlfn.RANK.EQ(J138,J:J),""))/600,0),3) -> 0.647 | P138: =ROUND(IFERROR((601-IFERROR(_xlfn.RANK.EQ(K138,K:K),""))/600,0),3) -> 0.865 | Q138: =ROUND(IFERROR((601-IFERROR(_xlfn.RANK.EQ(L138,L:L),""))/600,0),3) -> 0.753 | R138: =ROUND(IFERROR((601-IFERROR(_xlfn.RANK.EQ(M138,M:M),""))/600,0),3) -> 0.978 | S138: =VLOOKUP(A138,#REF!,11,0) -> #REF! | T138: =VLOOKUP(A138,#REF!,12,0) -> #REF! | U138: =VLOOKUP(A138,#REF!,13,0) -> #REF! | V138: =VLOOKUP(A138,#REF!,14,0) -> #REF! | W138: 2.178281 | X138: -0.35849015 | Y138: =VLOOKUP(C138,AR:AS,2,0) -> USA | Z138: =IF(Y138=Y$1,B138,IF(Y138=Y$2,B138,"")) | AT138: 1.2661108 | AU138: 1.1172722 | AW138: Georgia
A139: University of St Gallen | B139: St Gallen | C139: SWITZERLAND | D139: =IFERROR(VLOOKUP(A139,eco_bus_institutions!A:D,3,0),"") -> 143 | E139: =IFERROR(VLOOKUP(A139,eco_institutions!A:D,3,0),"") -> 56 | F139: =IFERROR(VLOOKUP(A139,fin_institutions!A:D,3,0),"") -> 22 | G139: =IFERROR(VLOOKUP(A139,bus_institutions!A:D,3,0),0) -> 64 | H139: =IFERROR(VLOOKUP(A139,man_institutions!A:D,3,0),0) -> 50 | I139: =IFERROR(VLOOKUP(A139,eco_bus_institutions!A:D,4,0),0) -> 2.26 | J139: =IFERROR(VLOOKUP(A139,eco_institutions!A:D,4,0),0) -> 1.51 | K139: =IFERROR(VLOOKUP(A139,fin_institutions!A:D,4,0),0) -> 1.17 | L139: =IFERROR(VLOOKUP(A139,bus_institutions!A:D,4,0),0) -> 3.16 | M139: =IFERROR(VLOOKUP(A139,man_institutions!A:D,4,0),0) -> 2.5 | N139: =ROUND(IFERROR((601-_xlfn.RANK.EQ(I139,I:I))/600,0),3) -> 0.775 | O139: =ROUND(IFERROR((601-IFERROR(_xlfn.RANK.EQ(J139,J:J),""))/600,0),3) -> 0.698 | P139: =ROUND(IFERROR((601-IFERROR(_xlfn.RANK.EQ(K139,K:K),""))/600,0),3) -> 0.493 | Q139: =ROUND(IFERROR((601-IFERROR(_xlfn.RANK.EQ(L139,L:L),""))/600,0),3) -> 0.818 | R139: =ROUND(IFERROR((601-IFERROR(_xlfn.RANK.EQ(M139,M:M),""))/600,0),3) -> 0.788 | S139: =VLOOKUP(A139,#REF!,11,0) -> #REF! | T139: =VLOOKUP(A139,#REF!,12,0) -> #REF! | U139: =VLOOKUP(A139,#REF!,13,0) -> #REF! | V139: =VLOOKUP(A139,#REF!,14,0) -> #REF! | W139: 1.3761363 | X139: -0.50679755 | Y139: =VLOOKUP(C139,AR:AS,2,0) -> CHE | Z139: =IF(Y139=Y$1,B139,IF(Y139=Y$2,B139,"")) | AT139: 1.8263777 | AU139: -0.65126804 | AW139: St Gallen
A140: University of Copenhagen | B140: Copenhagen | C140: DENMARK | D140: =IFERROR(VLOOKUP(A140,eco_bus_institutions!A:D,3,0),"") -> 98 | E140: =IFERROR(VLOOKUP(A140,eco_institutions!A:D,3,0),"") -> 80 | F140: =IFERROR(VLOOKUP(A140,fin_institutions!A:D,3,0),"") -> 8 | G140: =IFERROR(VLOOKUP(A140,bus_institutions!A:D,3,0),0) -> 9 | H140: =IFERROR(VLOOKUP(A140,man_institutions!A:D,3,0),0) -> 16 | I140: =IFERROR(VLOOKUP(A140,eco_bus_institutions!A:D,4,0),0) -> 2.25 | J140: =IFERROR(VLOOKUP(A140,eco_institutions!A:D,4,0),0) -> 2.23 | K140: =IFERROR(VLOOKUP(A140,fin_institutions!A:D,4,0),0) -> 2.09 | L140: =IFERROR(VLOOKUP(A140,bus_institutions!A:D,4,0),0) -> 2.08 | M140: =IFERROR(VLOOKUP(A140,man_institutions!A:D,4,0),0) -> 1.53 | N140: =ROUND(IFERROR((601-_xlfn.RANK.EQ(I140,I:I))/600,0),3) -> 0.773 | O140: =ROUND(IFERROR((601-IFERROR(_xlfn.RANK.EQ(J140,J:J),""))/600,0),3) -> 0.86 | P140: =ROUND(IFERROR((601-IFERROR(_xlfn.RANK.EQ(K140,K:K),""))/600,0),3) -> 0.828 | Q140: =ROUND(IFERROR((601-IFERROR(_xlfn.RANK.EQ(L140,L:L),""))/600,0),3) -> 0.593 | R140: =ROUND(IFERROR((601-IFERROR(_xlfn.RANK.EQ(M140,M:M),""))/600,0),3) -> 0.498 | S140: =VLOOKUP(A140,#REF!,11,0) -> #REF! | T140: =VLOOKUP(A140,#REF!,12,0) -> #REF! | U140: =VLOOKUP(A140,#REF!,13,0) -> #REF! | V140: =VLOOKUP(A140,#REF!,14,0) -> #REF! | W140: 1.2661108 | X140: 1.1172722 | Y140: =VLOOKUP(C140,AR:AS,2,0) -> DEN | Z140: =IF(Y140=Y$1,B140,IF(Y140=Y$2,B140,"")) | AT140: 1.8093275 | AU140: -0.92835415 | AW140: Copenhagen
A141: Nanyang Technological University | B141: Nanyang Technological | C141: SINGAPORE | D141: =IFERROR(VLOOKUP(A141,eco_bus_institutions!A:D,3,0),"") -> 116 | E141: =IFERROR(VLOOKUP(A141,eco_institutions!A:D,3,0),"") -> 48 | F141: =IFERROR(VLOOKUP(A141,fin_institutions!A:D,3,0),"") -> 22 | G141: =IFERROR(VLOOKUP(A141,bus_institutions!A:D,3,0),0) -> 35 | H141: =IFERROR(VLOOKUP(A141,man_institutions!A:D,3,0),0) -> 36 | I141: =IFERROR(VLOOKUP(A141,eco_bus_institutions!A:D,4,0),0) -> 2.24 | J141: =IFERROR(VLOOKUP(A141,eco_institutions!A:D,4,0),0) -> 1.17 | K141: =IFERROR(VLOOKUP(A141,fin_institutions!A:D,4,0),0) -> 2.59 | L141: =IFERROR(VLOOKUP(A141,bus_institutions!A:D,4,0),0) -> 3.44 | M141: =IFERROR(VLOOKUP(A141,man_institutions!A:D,4,0),0) -> 2.63 | N141: =ROUND(IFERROR((601-_xlfn.RANK.EQ(I141,I:I))/600,0),3) -> 0.772 | O141: =ROUND(IFERROR((601-IFERROR(_xlfn.RANK.EQ(J141,J:J),""))/600,0),3) -> 0.49 | P141: =ROUND(IFERROR((601-IFERROR(_xlfn.RANK.EQ(K141,K:K),""))/600,0),3) -> 0.868 | Q141: =ROUND(IFERROR((601-IFERROR(_xlfn.RANK.EQ(L141,L:L),""))/600,0),3) -> 0.858 | R141: =ROUND(IFERROR((601-IFERROR(_xlfn.RANK.EQ(M141,M:M),""))/600,0),3) -> 0.815 | S141: =VLOOKUP(A141,#REF!,11,0) -> #REF! | T141: =VLOOKUP(A141,#REF!,12,0) -> #REF! | U141: =VLOOKUP(A141,#REF!,13,0) -> #REF! | V141: =VLOOKUP(A141,#REF!,14,0) -> #REF! | W141: 1.8263777 | X141: -0.65126804 | Y141: =VLOOKUP(C141,AR:AS,2,0) -> SGP | Z141: =IF(Y141=Y$1,B141,IF(Y141=Y$2,B141,"")) | AT141: 2.4102845 | AU141: -0.22638964 | AW141: Nanyang Technological
A142: University of Munich | B142: Munich | C142: GERMANY | D142: =IFERROR(VLOOKUP(A142,eco_bus_institutions!A:D,3,0),"") -> 108 | E142: =IFERROR(VLOOKUP(A142,eco_institutions!A:D,3,0),"") -> 73 | F142: =IFERROR(VLOOKUP(A142,fin_institutions!A:D,3,0),"") -> 19 | G142: =IFERROR(VLOOKUP(A142,bus_institutions!A:D,3,0),0) -> 17 | H142: =IFERROR(VLOOKUP(A142,man_institutions!A:D,3,0),0) -> 24 | I142: =IFERROR(VLOOKUP(A142,eco_bus_institutions!A:D,4,0),0) -> 2.24 | J142: =IFERROR(VLOOKUP(A142,eco_institutions!A:D,4,0),0) -> 1.7 | K142: =IFERROR(VLOOKUP(A142,fin_institutions!A:D,4,0),0) -> 1.11 | L142: =IFERROR(VLOOKUP(A142,bus_institutions!A:D,4,0),0) -> 4.37 | M142: =IFERROR(VLOOKUP(A142,man_institutions!A:D,4,0),0) -> 4.41 | N142: =ROUND(IFERROR((601-_xlfn.RANK.EQ(I142,I:I))/600,0),3) -> 0.772 | O142: =ROUND(IFERROR((601-IFERROR(_xlfn.RANK.EQ(J142,J:J),""))/600,0),3) -> 0.755 | P142: =ROUND(IFERROR((601-IFERROR(_xlfn.RANK.EQ(K142,K:K),""))/600,0),3) -> 0.395 | Q142: =ROUND(IFERROR((601-IFERROR(_xlfn.RANK.EQ(L142,L:L),""))/600,0),3) -> 0.932 | R142: =ROUND(IFERROR((601-IFERROR(_xlfn.RANK.EQ(M142,M:M),""))/600,0),3) -> 0.952 | S142: =VLOOKUP(A142,#REF!,11,0) -> #REF! | T142: =VLOOKUP(A142,#REF!,12,0) -> #REF! | U142: =VLOOKUP(A142,#REF!,13,0) -> #REF! | V142: =VLOOKUP(A142,#REF!,14,0) -> #REF! | W142: 1.8093275 | X142: -0.92835415 | Y142: =VLOOKUP(C142,AR:AS,2,0) -> DEU | Z142: =IF(Y142=Y$1,B142,IF(Y142=Y$2,B142,"")) | AT142: 1.0388803 | AU142: 0.81622189 | AW142: Munich
A143: University of Nebraska Lincoln | B143: Nebraska Lincoln | C143: USA | D143: =IFERROR(VLOOKUP(A143,eco_bus_institutions!A:D,3,0),"") -> 66 | E143: =IFERROR(VLOOKUP(A143,eco_institutions!A:D,3,0),"") -> 28 | F143: =IFERROR(VLOOKUP(A143,fin_institutions!A:D,3,0),"") -> 19 | G143: =IFERROR(VLOOKUP(A143,bus_institutions!A:D,3,0),0) -> 16 | H143: =IFERROR(VLOOKUP(A143,man_institutions!A:D,3,0),0) -> 16 | I143: =IFERROR(VLOOKUP(A143,eco_bus_institutions!A:D,4,0),0) -> 2.24 | J143: =IFERROR(VLOOKUP(A143,eco_institutions!A:D,4,0),0) -> 1.78 | K143: =IFERROR(VLOOKUP(A143,fin_institutions!A:D,4,0),0) -> 1.93 | L143: =IFERROR(VLOOKUP(A143,bus_institutions!A:D,4,0),0) -> 4.04 | M143: =IFERROR(VLOOKUP(A143,man_institutions!A:D,4,0),0) -> 3.32 | N143: =ROUND(IFERROR((601-_xlfn.RANK.EQ(I143,I:I))/600,0),3) -> 0.772 | O143: =ROUND(IFERROR((601-IFERROR(_xlfn.RANK.EQ(J143,J:J),""))/600,0),3) -> 0.783 | P143: =ROUND(IFERROR((601-IFERROR(_xlfn.RANK.EQ(K143,K:K),""))/600,0),3) -> 0.8 | Q143: =ROUND(IFERROR((601-IFERROR(_xlfn.RANK.EQ(L143,L:L),""))/600,0),3) -> 0.91 | R143: =ROUND(IFERROR((601-IFERROR(_xlfn.RANK.EQ(M143,M:M),""))/600,0),3) -> 0.892 | S143: =VLOOKUP(A143,#REF!,11,0) -> #REF! | T143: =VLOOKUP(A143,#REF!,12,0) -> #REF! | U143: =VLOOKUP(A143,#REF!,13,0) -> #REF! | V143: =VLOOKUP(A143,#REF!,14,0) -> #REF! | W143: 2.4102845 | X143: -0.22638964 | Y143: =VLOOKUP(C143,AR:AS,2,0) -> USA | Z143: =IF(Y143=Y$1,B143,IF(Y143=Y$2,B143,"")) | AT143: 0.13467116 | AU143: -1.6406148 | AW143: Nebraska Lincoln
A144: ESSEC Business School | B144: ESSEC BS | C144: FRANCE | D144: =IFERROR(VLOOKUP(A144,eco_bus_institutions!A:D,3,0),"") -> 56 | E144: =IFERROR(VLOOKUP(A144,eco_institutions!A:D,3,0),"") -> 19 | F144: =IFERROR(VLOOKUP(A144,fin_institutions!A:D,3,0),"") -> 16 | G144: =IFERROR(VLOOKUP(A144,bus_institutions!A:D,3,0),0) -> 14 | H144: =IFERROR(VLOOKUP(A144,man_institutions!A:D,3,0),0) -> 20 | I144: =IFERROR(VLOOKUP(A144,eco_bus_institutions!A:D,4,0),0) -> 2.23 | J144: =IFERROR(VLOOKUP(A144,eco_institutions!A:D,4,0),0) -> 3.04 | K144: =IFERROR(VLOOKUP(A144,fin_institutions!A:D,4,0),0) -> 1.22 | L144: =IFERROR(VLOOKUP(A144,bus_institutions!A:D,4,0),0) -> 2.04 | M144: =IFERROR(VLOOKUP(A144,man_institutions!A:D,4,0),0) -> 1.7 | N144: =ROUND(IFERROR((601-_xlfn.RANK.EQ(I144,I:I))/600,0),3) -> 0.767 | O144: =ROUND(IFERROR((601-IFERROR(_xlfn.RANK.EQ(J144,J:J),""))/600,0),3) -> 0.932 | P144: =ROUND(IFERROR((601-IFERROR(_xlfn.RANK.EQ(K144,K:K),""))/600,0),3) -> 0.547 | Q144: =ROUND(IFERROR((601-IFERROR(_xlfn.RANK.EQ(L144,L:L),""))/600,0),3) -> 0.585 | R144: =ROUND(IFERROR((601-IFERROR(_xlfn.RANK.EQ(M144,M:M),""))/600,0),3) -> 0.587 | S144: =VLOOKUP(A144,#REF!,11,0) -> #REF! | T144: =VLOOKUP(A144,#REF!,12,0) -> #REF! | U144: =VLOOKUP(A144,#REF!,13,0) -> #REF! | V144: =VLOOKUP(A144,#REF!,14,0) -> #REF! | W144: 1.0388803 | X144: 0.81622189 | Y144: =VLOOKUP(C144,AR:AS,2,0) -> FRA | Z144: =IF(Y144=Y$1,B144,IF(Y144=Y$2,B144,"")) | AT144: -0.9555157 | AU144: 2.4229353 | AW144: ESSEC Business School
A145: Jonkoping University | B145: Jonkoping | C145: SWEDEN | D145: =IFERROR(VLOOKUP(A145,eco_bus_institutions!A:D,3,0),"") -> 54 | E145: =IFERROR(VLOOKUP(A145,eco_institutions!A:D,3,0),"") -> 16 | F145: =IFERROR(VLOOKUP(A145,fin_institutions!A:D,3,0),"") -> 5 | G145: =IFERROR(VLOOKUP(A145,bus_institutions!A:D,3,0),0) -> 29 | H145: =IFERROR(VLOOKUP(A145,man_institutions!A:D,3,0),0) -> 33 | I145: =IFERROR(VLOOKUP(A145,eco_bus_institutions!A:D,4,0),0) -> 2.23 | J145: =IFERROR(VLOOKUP(A145,eco_institutions!A:D,4,0),0) -> 1.06 | K145: =IFERROR(VLOOKUP(A145,fin_institutions!A:D,4,0),0) -> 1.07 | L145: =IFERROR(VLOOKUP(A145,bus_institutions!A:D,4,0),0) -> 3.38 | M145: =IFERROR(VLOOKUP(A145,man_institutions!A:D,4,0),0) -> 1.94 | N145: =ROUND(IFERROR((601-_xlfn.RANK.EQ(I145,I:I))/600,0),3) -> 0.767 | O145: =ROUND(IFERROR((601-IFERROR(_xlfn.RANK.EQ(J145,J:J),""))/600,0),3) -> 0.263 | P145: =ROUND(IFERROR((601-IFERROR(_xlfn.RANK.EQ(K145,K:K),""))/600,0),3) -> 0.295 | Q145: =ROUND(IFERROR((601-IFERROR(_xlfn.RANK.EQ(L145,L:L),""))/600,0),3) -> 0.845 | R145: =ROUND(IFERROR((601-IFERROR(_xlfn.RANK.EQ(M145,M:M),""))/600,0),3) -> 0.65 | S145: =VLOOKUP(A145,#REF!,11,0) -> #REF! | T145: =VLOOKUP(A145,#REF!,12,0) -> #REF! | U145: =VLOOKUP(A145,#REF!,13,0) -> #REF! | V145: =VLOOKUP(A145,#REF!,14,0) -> #REF! | W145: 0.13467116 | X145: -1.6406148 | Y145: =VLOOKUP(C145,AR:AS,2,0) -> SWE | Z145: =IF(Y145=Y$1,B145,IF(Y145=Y$2,B145,"")) | AT145: -1.0105627 | AU145: -2.2153697 | AW145: Jonkoping
A146: International Monetary Fund | B146: IMF | C146: USA | D146: =IFERROR(VLOOKUP(A146,eco_bus_institutions!A:D,3,0),"") -> 159 | E146: =IFERROR(VLOOKUP(A146,eco_institutions!A:D,3,0),"") -> 135 | F146: =IFERROR(VLOOKUP(A146,fin_institutions!A:D,3,0),"") -> 62 | G146: =IFERROR(VLOOKUP(A146,bus_institutions!A:D,3,0),0) -> 0 | H146: =IFERROR(VLOOKUP(A146,man_institutions!A:D,3,0),0) -> 0 | I146: =IFERROR(VLOOKUP(A146,eco_bus_institutions!A:D,4,0),0) -> 2.22 | J146: =IFERROR(VLOOKUP(A146,eco_institutions!A:D,4,0),0) -> 2.15 | K146: =IFERROR(VLOOKUP(A146,fin_institutions!A:D,4,0),0) -> 1.33 | L146: =IFERROR(VLOOKUP(A146,bus_institutions!A:D,4,0),0) -> 0 | M146: =IFERROR(VLOOKUP(A146,man_institutions!A:D,4,0),0) -> 0 | N146: =ROUND(IFERROR((601-_xlfn.RANK.EQ(I146,I:I))/600,0),3) -> 0.763 | O146: =ROUND(IFERROR((601-IFERROR(_xlfn.RANK.EQ(J146,J:J),""))/600,0),3) -> 0.85 | P146: =ROUND(IFERROR((601-IFERROR(_xlfn.RANK.EQ(K146,K:K),""))/600,0),3) -> 0.625 | Q146: =ROUND(IFERROR((601-IFERROR(_xlfn.RANK.EQ(L146,L:L),""))/600,0),3) -> 0.05 | R146: =ROUND(IFERROR((601-IFERROR(_xlfn.RANK.EQ(M146,M:M),""))/600,0),3) -> 0.04 | S146: =VLOOKUP(A146,#REF!,11,0) -> #REF! | T146: =VLOOKUP(A146,#REF!,12,0) -> #REF! | U146: =VLOOKUP(A146,#REF!,13,0) -> #REF! | V146: =VLOOKUP(A146,#REF!,14,0) -> #REF! | W146: -0.9555157 | X146: 2.4229353 | Y146: =VLOOKUP(C146,AR:AS,2,0) -> USA | Z146: =IF(Y146=Y$1,B146,IF(Y146=Y$2,B146,"")) | AT146: 1.3462515 | AU146: -0.62523785 | AW146: International Monetary Fund
A147: Lappeenranta-Lahti University of Technology LUT | B147: LUT | C147: FINLAND | D147: =IFERROR(VLOOKUP(A147,eco_bus_institutions!A:D,3,0),"") -> 63 | E147: =IFERROR(VLOOKUP(A147,eco_institutions!A:D,3,0),"") -> 6 | F147: =IFERROR(VLOOKUP(A147,fin_institutions!A:D,3,0),"") | G147: =IFERROR(VLOOKUP(A147,bus_institutions!A:D,3,0),0) -> 48 | H147: =IFERROR(VLOOKUP(A147,man_institutions!A:D,3,0),0) -> 37 | I147: =IFERROR(VLOOKUP(A147,eco_bus_institutions!A:D,4,0),0) -> 2.22 | J147: =IFERROR(VLOOKUP(A147,eco_institutions!A:D,4,0),0) -> 1 | K147: =IFERROR(VLOOKUP(A147,fin_institutions!A:D,4,0),0) -> 0 | L147: =IFERROR(VLOOKUP(A147,bus_institutions!A:D,4,0),0) -> 2.28 | M147: =IFERROR(VLOOKUP(A147,man_institutions!A:D,4,0),0) -> 1.97 | N147: =ROUND(IFERROR((601-_xlfn.RANK.EQ(I147,I:I))/600,0),3) -> 0.763 | O147: =ROUND(IFERROR((601-IFERROR(_xlfn.RANK.EQ(J147,J:J),""))/600,0),3) -> 0.023 | P147: =ROUND(IFERROR((601-IFERROR(_xlfn.RANK.EQ(K147,K:K),""))/600,0),3) -> 0.058 | Q147: =ROUND(IFERROR((601-IFERROR(_xlfn.RANK.EQ(L147,L:L),""))/600,0),3) -> 0.648 | R147: =ROUND(IFERROR((601-IFERROR(_xlfn.RANK.EQ(M147,M:M),""))/600,0),3) -> 0.657 | S147: =VLOOKUP(A147,#REF!,11,0) -> #REF! | T147: =VLOOKUP(A147,#REF!,12,0) -> #REF! | U147: =VLOOKUP(A147,#REF!,13,0) -> #REF! | V147: =VLOOKUP(A147,#REF!,14,0) -> #REF! | W147: -1.0105627 | X147: -2.2153697 | Y147: =VLOOKUP(C147,AR:AS,2,0) -> FIN | Z147: =IF(Y147=Y$1,B147,IF(Y147=Y$2,B147,"")) | AT147: 1.4180717 | AU147: -0.42865245 | AW147: Lappeenranta-Lahti Technology LUT
A148: Luiss Guido Carli University | B148: Luiss Guido Carli | C148: ITALY | D148: =IFERROR(VLOOKUP(A148,eco_bus_institutions!A:D,3,0),"") -> 82 | E148: =IFERROR(VLOOKUP(A148,eco_institutions!A:D,3,0),"") -> 45 | F148: =IFERROR(VLOOKUP(A148,fin_institutions!A:D,3,0),"") -> 12 | G148: =IFERROR(VLOOKUP(A148,bus_institutions!A:D,3,0),0) -> 32 | H148: =IFERROR(VLOOKUP(A148,man_institutions!A:D,3,0),0) -> 26 | I148: =IFERROR(VLOOKUP(A148,eco_bus_institutions!A:D,4,0),0) -> 2.2 | J148: =IFERROR(VLOOKUP(A148,eco_institutions!A:D,4,0),0) -> 1.68 | K148: =IFERROR(VLOOKUP(A148,fin_institutions!A:D,4,0),0) -> 1.1 | L148: =IFERROR(VLOOKUP(A148,bus_institutions!A:D,4,0),0) -> 2.82 | M148: =IFERROR(VLOOKUP(A148,man_institutions!A:D,4,0),0) -> 3.31 | N148: =ROUND(IFERROR((601-_xlfn.RANK.EQ(I148,I:I))/600,0),3) -> 0.76 | O148: =ROUND(IFERROR((601-IFERROR(_xlfn.RANK.EQ(J148,J:J),""))/600,0),3) -> 0.748 | P148: =ROUND(IFERROR((601-IFERROR(_xlfn.RANK.EQ(K148,K:K),""))/600,0),3) -> 0.37 | Q148: =ROUND(IFERROR((601-IFERROR(_xlfn.RANK.EQ(L148,L:L),""))/600,0),3) -> 0.773 | R148: =ROUND(IFERROR((601-IFERROR(_xlfn.RANK.EQ(M148,M:M),""))/600,0),3) -> 0.89 | S148: =VLOOKUP(A148,#REF!,11,0) -> #REF! | T148: =VLOOKUP(A148,#REF!,12,0) -> #REF! | U148: =VLOOKUP(A148,#REF!,13,0) -> #REF! | V148: =VLOOKUP(A148,#REF!,14,0) -> #REF! | W148: 1.3462515 | X148: -0.62523785 | Y148: =VLOOKUP(C148,AR:AS,2,0) -> ITA | Z148: =IF(Y148=Y$1,B148,IF(Y148=Y$2,B148,"")) | AT148: 2.0815181 | AU148: 0.25960733 | AW148: Luiss Guido Carli
... A177: Vrije Universiteit Amsterdam | B177: Vrije Amsterdam | C177: NETHERLANDS | D177: =IFERROR(VLOOKUP(A177,eco_bus_institutions!A:D,3,0),"") -> 181 | E177: =IFERROR(VLOOKUP(A177,eco_institutions!A:D,3,0),"") -> 90 | F177: =IFERROR(VLOOKUP(A177,fin_institutions!A:D,3,0),"") -> 24 | G177: =IFERROR(VLOOKUP(A177,bus_institutions!A:D,3,0),0) -> 48 | H177: =IFERROR(VLOOKUP(A177,man_institutions!A:D,3,0),0) -> 63 | I177: =IFERROR(VLOOKUP(A177,eco_bus_institutions!A:D,4,0),0) -> 2.06 | J177: =IFERROR(VLOOKUP(A177,eco_institutions!A:D,4,0),0) -> 1.27 | K177: =IFERROR(VLOOKUP(A177,fin_institutions!A:D,4,0),0) -> 1.31 | L177: =IFERROR(VLOOKUP(A177,bus_institutions!A:D,4,0),0) -> 3.6 | M177: =IFERROR(VLOOKUP(A177,man_institutions!A:D,4,0),0) -> 3.11 | N177: =ROUND(IFERROR((601-_xlfn.RANK.EQ(I177,I:I))/600,0),3) -> 0.715 | O177: =ROUND(IFERROR((601-IFERROR(_xlfn.RANK.EQ(J177,J:J),""))/600,0),3) -> 0.575 | P177: =ROUND(IFERROR((601-IFERROR(_xlfn.RANK.EQ(K177,K:K),""))/600,0),3) -> 0.613 | Q177: =ROUND(IFERROR((601-IFERROR(_xlfn.RANK.EQ(L177,L:L),""))/600,0),3) -> 0.865 | R177: =ROUND(IFERROR((601-IFERROR(_xlfn.RANK.EQ(M177,M:M),""))/600,0),3) -> 0.877 | S177: =VLOOKUP(A177,#REF!,11,0) -> #REF! | T177: =VLOOKUP(A177,#REF!,12,0) -> #REF! | U177: =VLOOKUP(A177,#REF!,13,0) -> #REF! | V177: =VLOOKUP(A177,#REF!,14,0) -> #REF! | W177: 1.6428465 | X177: -0.87026324 | Y177: =VLOOKUP(C177,AR:AS,2,0) -> NED | Z177: =IF(Y177=Y$1,B177,IF(Y177=Y$2,B177,"")) | AT177: -1.0166065 | AU177: 2.3506966 | AW177: Vrije Universiteit Amsterdam
A178: Czech Academy of Sciences | B178: Czech Acad Sci | C178: CZECH REPUBLIC | D178: =IFERROR(VLOOKUP(A178,eco_bus_institutions!A:D,3,0),"") -> 46 | E178: =IFERROR(VLOOKUP(A178,eco_institutions!A:D,3,0),"") | F178: =IFERROR(VLOOKUP(A178,fin_institutions!A:D,3,0),"") | G178: =IFERROR(VLOOKUP(A178,bus_institutions!A:D,3,0),0) -> 0 | H178: =IFERROR(VLOOKUP(A178,man_institutions!A:D,3,0),0) -> 0 | I178: =IFERROR(VLOOKUP(A178,eco_bus_institutions!A:D,4,0),0) -> 2.05 | J178: =IFERROR(VLOOKUP(A178,eco_institutions!A:D,4,0),0) -> 0 | K178: =IFERROR(VLOOKUP(A178,fin_institutions!A:D,4,0),0) -> 0 | L178: =IFERROR(VLOOKUP(A178,bus_institutions!A:D,4,0),0) -> 0 | M178: =IFERROR(VLOOKUP(A178,man_institutions!A:D,4,0),0) -> 0 | N178: =ROUND(IFERROR((601-_xlfn.RANK.EQ(I178,I:I))/600,0),3) -> 0.71 | O178: =ROUND(IFERROR((601-IFERROR(_xlfn.RANK.EQ(J178,J:J),""))/600,0),3) -> 0.003 | P178: =ROUND(IFERROR((601-IFERROR(_xlfn.RANK.EQ(K178,K:K),""))/600,0),3) -> 0.058 | Q178: =ROUND(IFERROR((601-IFERROR(_xlfn.RANK.EQ(L178,L:L),""))/600,0),3) -> 0.05 | R178: =ROUND(IFERROR((601-IFERROR(_xlfn.RANK.EQ(M178,M:M),""))/600,0),3) -> 0.04 | S178: 1 | T178: =VLOOKUP(A178,#REF!,12,0) -> #REF! | U178: =VLOOKUP(A178,#REF!,13,0) -> #REF! | V178: =VLOOKUP(A178,#REF!,14,0) -> #REF! | W178: -3.2891451 | X178: -0.34515917 | Y178: =VLOOKUP(C178,AR:AS,2,0) -> CZE | Z178: =IF(Y178=Y$1,B178,IF(Y178=Y$2,B178,"")) | AT178: -0.72857851 | AU178: -1.9789406 | AW178: Czech Academy of Sciences
A179: European Central Bank | B179: European Central Bank | C179: GERMANY | D179: =IFERROR(VLOOKUP(A179,eco_bus_institutions!A:D,3,0),"") -> 240 | E179: =IFERROR(VLOOKUP(A179,eco_institutions!A:D,3,0),"") -> 197 | F179: =IFERROR(VLOOKUP(A179,fin_institutions!A:D,3,0),"") -> 92 | G179: =IFERROR(VLOOKUP(A179,bus_institutions!A:D,3,0),0) -> 0 | H179: =IFERROR(VLOOKUP(A179,man_institutions!A:D,3,0),0) -> 0 | I179: =IFERROR(VLOOKUP(A179,eco_bus_institutions!A:D,4,0),0) -> 2.05 | J179: =IFERROR(VLOOKUP(A179,eco_institutions!A:D,4,0),0) -> 2.02 | K179: =IFERROR(VLOOKUP(A179,fin_institutions!A:D,4,0),0) -> 1.3 | L179: =IFERROR(VLOOKUP(A179,bus_institutions!A:D,4,0),0) -> 0 | M179: =IFERROR(VLOOKUP(A179,man_institutions!A:D,4,0),0) -> 0 | N179: =ROUND(IFERROR((601-_xlfn.RANK.EQ(I179,I:I))/600,0),3) -> 0.71 | O179: =ROUND(IFERROR((601-IFERROR(_xlfn.RANK.EQ(J179,J:J),""))/600,0),3) -> 0.828 | P179: =ROUND(IFERROR((601-IFERROR(_xlfn.RANK.EQ(K179,K:K),""))/600,0),3) -> 0.61 | Q179: =ROUND(IFERROR((601-IFERROR(_xlfn.RANK.EQ(L179,L:L),""))/600,0),3) -> 0.05 | R179: =ROUND(IFERROR((601-IFERROR(_xlfn.RANK.EQ(M179,M:M),""))/600,0),3) -> 0.04 | S179: =VLOOKUP(A179,#REF!,11,0) -> #REF! | T179: =VLOOKUP(A179,#REF!,12,0) -> #REF! | U179: =VLOOKUP(A179,#REF!,13,0) -> #REF! | V179: =VLOOKUP(A179,#REF!,14,0) -> #REF! | W179: -1.0166065 | X179: 2.3506966 | Y179: =VLOOKUP(C179,AR:AS,2,0) -> DEU | Z179: =IF(Y179=Y$1,B179,IF(Y179=Y$2,B179,"")) | AT179: 0.73417834 | AU179: -0.25849402 | AW179: European Central Bank
A180: Polytechnic University of Milan | B180: Polytechnic Milan | C180: ITALY | D180: =IFERROR(VLOOKUP(A180,eco_bus_institutions!A:D,3,0),"") -> 97 | E180: =IFERROR(VLOOKUP(A180,eco_institutions!A:D,3,0),"") -> 20 | F180: =IFERROR(VLOOKUP(A180,fin_institutions!A:D,3,0),"") | G180: =IFERROR(VLOOKUP(A180,bus_institutions!A:D,3,0),0) -> 41 | H180: =IFERROR(VLOOKUP(A180,man_institutions!A:D,3,0),0) -> 66 | I180: =IFERROR(VLOOKUP(A180,eco_bus_institutions!A:D,4,0),0) -> 2.05 | J180: =IFERROR(VLOOKUP(A180,eco_institutions!A:D,4,0),0) -> 1.03 | K180: =IFERROR(VLOOKUP(A180,fin_institutions!A:D,4,0),0) -> 0 | L180: =IFERROR(VLOOKUP(A180,bus_institutions!A:D,4,0),0) -> 2.62 | M180: =IFERROR(VLOOKUP(A180,man_institutions!A:D,4,0),0) -> 1.8 | N180: =ROUND(IFERROR((601-_xlfn.RANK.EQ(I180,I:I))/600,0),3) -> 0.71 | O180: =ROUND(IFERROR((601-IFERROR(_xlfn.RANK.EQ(J180,J:J),""))/600,0),3) -> 0.15 | P180: =ROUND(IFERROR((601-IFERROR(_xlfn.RANK.EQ(K180,K:K),""))/600,0),3) -> 0.058 | Q180: =ROUND(IFERROR((601-IFERROR(_xlfn.RANK.EQ(L180,L:L),""))/600,0),3) -> 0.737 | R180: =ROUND(IFERROR((601-IFERROR(_xlfn.RANK.EQ(M180,M:M),""))/600,0),3) -> 0.612 | S180: =VLOOKUP(A180,#REF!,11,0) -> #REF! | T180: =VLOOKUP(A180,#REF!,12,0) -> #REF! | U180: =VLOOKUP(A180,#REF!,13,0) -> #REF! | V180: =VLOOKUP(A180,#REF!,14,0) -> #REF! | W180: -0.72857851 | X180: -1.9789406 | Y180: =VLOOKUP(C180,AR:AS,2,0) -> ITA | Z180: =IF(Y180=Y$1,B180,IF(Y180=Y$2,B180,"")) | AT180: 0.32736133 | AU180: 0.81204176 | AW180: Polytechnic Milan
A181: heSam Universite | B181: heSam Universite | C181: FRANCE | D181: =IFERROR(VLOOKUP(A181,eco_bus_institutions!A:D,3,0),"") -> 98 | E181: =IFERROR(VLOOKUP(A181,eco_institutions!A:D,3,0),"") -> 24 | F181: =IFERROR(VLOOKUP(A181,fin_institutions!A:D,3,0),"") -> 12 | G181: =IFERROR(VLOOKUP(A181,bus_institutions!A:D,3,0),0) -> 42 | H181: =IFERROR(VLOOKUP(A181,man_institutions!A:D,3,0),0) -> 46 | I181: =IFERROR(VLOOKUP(A181,eco_bus_institutions!A:D,4,0),0) -> 2.04 | J181: =IFERROR(VLOOKUP(A181,eco_institutions!A:D,4,0),0) -> 1.4 | K181: =IFERROR(VLOOKUP(A181,fin_institutions!A:D,4,0),0) -> 1.14 | L181: =IFERROR(VLOOKUP(A181,bus_institutions!A:D,4,0),0) -> 2.44 | M181: =IFERROR(VLOOKUP(A181,man_institutions!A:D,4,0),0) -> 1.96 | N181: =ROUND(IFERROR((601-_xlfn.RANK.EQ(I181,I:I))/600,0),3) -> 0.705 | O181: =ROUND(IFERROR((601-IFERROR(_xlfn.RANK.EQ(J181,J:J),""))/600,0),3) -> 0.655 | P181: =ROUND(IFERROR((601-IFERROR(_xlfn.RANK.EQ(K181,K:K),""))/600,0),3) -> 0.443 | Q181: =ROUND(IFERROR((601-IFERROR(_xlfn.RANK.EQ(L181,L:L),""))/600,0),3) -> 0.69 | R181: =ROUND(IFERROR((601-IFERROR(_xlfn.RANK.EQ(M181,M:M),""))/600,0),3) -> 0.653 | S181: =VLOOKUP(A181,#REF!,11,0) -> #REF! | T181: =VLOOKUP(A181,#REF!,12,0) -> #REF! | U181: =VLOOKUP(A181,#REF!,13,0) -> #REF! | V181: =VLOOKUP(A181,#REF!,14,0) -> #REF! | W181: 0.73417834 | X181: -0.25849402 | Y181: =VLOOKUP(C181,AR:AS,2,0) -> FRA | Z181: =IF(Y181=Y$1,B181,IF(Y181=Y$2,B181,"")) | AT181: 0.68562368 | AU181: 1.2876762 | AW181: heSam Universite
A182: Ifo Institut | B182: Ifo Institut | C182: GERMANY | D182: =IFERROR(VLOOKUP(A182,eco_bus_institutions!A:D,3,0),"") -> 274 | E182: =IFERROR(VLOOKUP(A182,eco_institutions!A:D,3,0),"") -> 267 | F182: =IFERROR(VLOOKUP(A182,fin_institutions!A:D,3,0),"") -> 37 | G182: =IFERROR(VLOOKUP(A182,bus_institutions!A:D,3,0),0) -> 7 | H182: =IFERROR(VLOOKUP(A182,man_institutions!A:D,3,0),0) -> 11 | I182: =IFERROR(VLOOKUP(A182,eco_bus_institutions!A:D,4,0),0) -> 2.04 | J182: =IFERROR(VLOOKUP(A182,eco_institutions!A:D,4,0),0) -> 1.92 | K182: =IFERROR(VLOOKUP(A182,fin_institutions!A:D,4,0),0) -> 1.16 | L182: =IFERROR(VLOOKUP(A182,bus_institutions!A:D,4,0),0) -> 1.92 | M182: =IFERROR(VLOOKUP(A182,man_institutions!A:D,4,0),0) -> 1.4 | N182: =ROUND(IFERROR((601-_xlfn.RANK.EQ(I182,I:I))/600,0),3) -> 0.705 | O182: =ROUND(IFERROR((601-IFERROR(_xlfn.RANK.EQ(J182,J:J),""))/600,0),3) -> 0.822 | P182: =ROUND(IFERROR((601-IFERROR(_xlfn.RANK.EQ(K182,K:K),""))/600,0),3) -> 0.477 | Q182: =ROUND(IFERROR((601-IFERROR(_xlfn.RANK.EQ(L182,L:L),""))/600,0),3) -> 0.54 | R182: =ROUND(IFERROR((601-IFERROR(_xlfn.RANK.EQ(M182,M:M),""))/600,0),3) -> 0.408 | S182: =VLOOKUP(A182,#REF!,11,0) -> #REF! | T182: =VLOOKUP(A182,#REF!,12,0) -> #REF! | U182: =VLOOKUP(A182,#REF!,13,0) -> #REF! | V182: =VLOOKUP(A182,#REF!,14,0) -> #REF! | W182: 0.32736133 | X182: 0.81204176 | Y182: =VLOOKUP(C182,AR:AS,2,0) -> DEU | Z182: =IF(Y182=Y$1,B182,IF(Y182=Y$2,B182,"")) | AT182: 1.4060179 | AU182: -0.32467699 | AW182: Ifo Institut
A183: University of Kentucky | B183: Kentucky | C183: USA | D183: =IFERROR(VLOOKUP(A183,eco_bus_institutions!A:D,3,0),"") -> 72 | E183: =IFERROR(VLOOKUP(A183,eco_institutions!A:D,3,0),"") -> 37 | F183: =IFERROR(VLOOKUP(A183,fin_institutions!A:D,3,0),"") -> 11 | G183: =IFERROR(VLOOKUP(A183,bus_institutions!A:D,3,0),0) -> 28 | H183: =IFERROR(VLOOKUP(A183,man_institutions!A:D,3,0),0) -> 12 | I183: =IFERROR(VLOOKUP(A183,eco_bus_institutions!A:D,4,0),0) -> 2.04 | J183: =IFERROR(VLOOKUP(A183,eco_institutions!A:D,4,0),0) -> 1.64 | K183: =IFERROR(VLOOKUP(A183,fin_institutions!A:D,4,0),0) -> 2.61 | L183: =IFERROR(VLOOKUP(A183,bus_institutions!A:D,4,0),0) -> 1.05 | M183: =IFERROR(VLOOKUP(A183,man_institutions!A:D,4,0),0) -> 2.42 | N183: =ROUND(IFERROR((601-_xlfn.RANK.EQ(I183,I:I))/600,0),3) -> 0.705 | O183: =ROUND(IFERROR((601-IFERROR(_xlfn.RANK.EQ(J183,J:J),""))/600,0),3) -> 0.738 | P183: =ROUND(IFERROR((601-IFERROR(_xlfn.RANK.EQ(K183,K:K),""))/600,0),3) -> 0.87 | Q183: =ROUND(IFERROR((601-IFERROR(_xlfn.RANK.EQ(L183,L:L),""))/600,0),3) -> 0.067 | R183: =ROUND(IFERROR((601-IFERROR(_xlfn.RANK.EQ(M183,M:M),""))/600,0),3) -> 0.773 | S183: =VLOOKUP(A183,#REF!,11,0) -> #REF! | T183: =VLOOKUP(A183,#REF!,12,0) -> #REF! | U183: =VLOOKUP(A183,#REF!,13,0) -> #REF! | V183: =VLOOKUP(A183,#REF!,14,0) -> #REF! | W183: 0.68562368 | X183: 1.2876762 | Y183: =VLOOKUP(C183,AR:AS,2,0) -> USA | Z183: =IF(Y183=Y$1,B183,IF(Y183=Y$2,B183,"")) | AT183: 1.1162797 | AU183: -0.48786681 | AW183: Kentucky
A184: University of Edinburgh | B184: Edinburgh | C184: SCOTLAND | D184: =IFERROR(VLOOKUP(A184,eco_bus_institutions!A:D,3,0),"") -> 138 | E184: =IFERROR(VLOOKUP(A184,eco_institutions!A:D,3,0),"") -> 55 | F184: =IFERROR(VLOOKUP(A184,fin_institutions!A:D,3,0),"") -> 40 | G184: =IFERROR(VLOOKUP(A184,bus_institutions!A:D,3,0),0) -> 36 | H184: =IFERROR(VLOOKUP(A184,man_institutions!A:D,3,0),0) -> 41 | I184: =IFERROR(VLOOKUP(A184,eco_bus_institutions!A:D,4,0),0) -> 2.03 | J184: =IFERROR(VLOOKUP(A184,eco_institutions!A:D,4,0),0) -> 1.79 | K184: =IFERROR(VLOOKUP(A184,fin_institutions!A:D,4,0),0) -> 1.14 | L184: =IFERROR(VLOOKUP(A184,bus_institutions!A:D,4,0),0) -> 2.62 | M184: =IFERROR(VLOOKUP(A184,man_institutions!A:D,4,0),0) -> 2.94 | N184: =ROUND(IFERROR((601-_xlfn.RANK.EQ(I184,I:I))/600,0),3) -> 0.7 | O184: =ROUND(IFERROR((601-IFERROR(_xlfn.RANK.EQ(J184,J:J),""))/600,0),3) -> 0.788 | P184: =ROUND(IFERROR((601-IFERROR(_xlfn.RANK.EQ(K184,K:K),""))/600,0),3) -> 0.443 | Q184: =ROUND(IFERROR((601-IFERROR(_xlfn.RANK.EQ(L184,L:L),""))/600,0),3) -> 0.737 | R184: =ROUND(IFERROR((601-IFERROR(_xlfn.RANK.EQ(M184,M:M),""))/600,0),3) -> 0.855 | S184: =VLOOKUP(A184,#REF!,11,0) -> #REF! | T184: =VLOOKUP(A184,#REF!,12,0) -> #REF! | U184: =VLOOKUP(A184,#REF!,13,0) -> #REF! | V184: =VLOOKUP(A184,#REF!,14,0) -> #REF! | W184: 1.4060179 | X184: -0.32467699 | Y184: =VLOOKUP(C184,AR:AS,2,0) -> UK | Z184: =IF(Y184=Y$1,B184,IF(Y184=Y$2,B184,"")) | AT184: 0.19055357 | AU184: 1.1876118 | AW184: Edinburgh
A185: University of Ottawa | B185: Ottawa | C185: CANADA | D185: =IFERROR(VLOOKUP(A185,eco_bus_institutions!A:D,3,0),"") -> 79 | E185: =IFERROR(VLOOKUP(A185,eco_institutions!A:D,3,0),"") -> 36 | F185: =IFERROR(VLOOKUP(A185,fin_institutions!A:D,3,0),"") -> 13 | G185: =IFERROR(VLOOKUP(A185,bus_institutions!A:D,3,0),0) -> 31 | H185: =IFERROR(VLOOKUP(A185,man_institutions!A:D,3,0),0) -> 27 | I185: =IFERROR(VLOOKUP(A185,eco_bus_institutions!A:D,4,0),0) -> 2.03 | J185: =IFERROR(VLOOKUP(A185,eco_institutions!A:D,4,0),0) -> 1.47 | K185: =IFERROR(VLOOKUP(A185,fin_institutions!A:D,4,0),0) -> 1.14 | L185: =IFERROR(VLOOKUP(A185,bus_institutions!A:D,4,0),0) -> 2.64 | M185: =IFERROR(VLOOKUP(A185,man_institutions!A:D,4,0),0) -> 2.53 | N185: =ROUND(IFERROR((601-_xlfn.RANK.EQ(I185,I:I))/600,0),3) -> 0.7 | O185: =ROUND(IFERROR((601-IFERROR(_xlfn.RANK.EQ(J185,J:J),""))/600,0),3) -> 0.68 | P185: =ROUND(IFERROR((601-IFERROR(_xlfn.RANK.EQ(K185,K:K),""))/600,0),3) -> 0.443 | Q185: =ROUND(IFERROR((601-IFERROR(_xlfn.RANK.EQ(L185,L:L),""))/600,0),3) -> 0.738 | R185: =ROUND(IFERROR((601-IFERROR(_xlfn.RANK.EQ(M185,M:M),""))/600,0),3) -> 0.79 | S185: =VLOOKUP(A185,#REF!,11,0) -> #REF! | T185: =VLOOKUP(A185,#REF!,12,0) -> #REF! | U185: =VLOOKUP(A185,#REF!,13,0) -> #REF! | V185: =VLOOKUP(A185,#REF!,14,0) -> #REF! | W185: 1.1162797 | X185: -0.48786681 | Y185: =VLOOKUP(C185,AR:AS,2,0) -> CAN | Z185: =IF(Y185=Y$1,B185,IF(Y185=Y$2,B185,"")) | AT185: 0.21963135 | AU185: -1.3226525 | AW185: Ottawa
A186: Universite de Montreal | B186: Montreal | C186: CANADA | D186: =IFERROR(VLOOKUP(A186,eco_bus_institutions!A:D,3,0),"") -> 170 | E186: =IFERROR(VLOOKUP(A186,eco_institutions!A:D,3,0),"") -> 74 | F186: =IFERROR(VLOOKUP(A186,fin_institutions!A:D,3,0),"") -> 27 | G186: =IFERROR(VLOOKUP(A186,bus_institutions!A:D,3,0),0) -> 49 | H186: =IFERROR(VLOOKUP(A186,man_institutions!A:D,3,0),0) -> 60 | I186: =IFERROR(VLOOKUP(A186,eco_bus_institutions!A:D,4,0),0) -> 2.02 | J186: =IFERROR(VLOOKUP(A186,eco_institutions!A:D,4,0),0) -> 1.88 | K186: =IFERROR(VLOOKUP(A186,fin_institutions!A:D,4,0),0) -> 1.27 | L186: =IFERROR(VLOOKUP(A186,bus_institutions!A:D,4,0),0) -> 1.1 | M186: =IFERROR(VLOOKUP(A186,man_institutions!A:D,4,0),0) -> 2.08 | N186: =ROUND(IFERROR((601-_xlfn.RANK.EQ(I186,I:I))/600,0),3) -> 0.697 | O186: =ROUND(IFERROR((601-IFERROR(_xlfn.RANK.EQ(J186,J:J),""))/600,0),3) -> 0.807 | P186: =ROUND(IFERROR((601-IFERROR(_xlfn.RANK.EQ(K186,K:K),""))/600,0),3) -> 0.585 | Q186: =ROUND(IFERROR((601-IFERROR(_xlfn.RANK.EQ(L186,L:L),""))/600,0),3) -> 0.093 | R186: =ROUND(IFERROR((601-IFERROR(_xlfn.RANK.EQ(M186,M:M),""))/600,0),3) -> 0.69 | S186: =VLOOKUP(A186,#REF!,11,0) -> #REF! | T186: =VLOOKUP(A186,#REF!,12,0) -> #REF! | U186: =VLOOKUP(A186,#REF!,13,0) -> #REF! | V186: =VLOOKUP(A186,#REF!,14,0) -> #REF! | W186: 0.19055357 | X186: 1.1876118 | Y186: =VLOOKUP(C186,AR:AS,2,0) -> CAN | Z186: =IF(Y186=Y$1,B186,IF(Y186=Y$2,B186,"")) | AT186: 1.3323335 | AU186: 0.28448204 | AW186: Universite de Montreal
A187: emlyon business school | B187: emlyon BS | C187: FRANCE | D187: =IFERROR(VLOOKUP(A187,eco_bus_institutions!A:D,3,0),"") -> 49 | E187: =IFERROR(VLOOKUP(A187,eco_institutions!A:D,3,0),"") -> 10 | F187: =IFERROR(VLOOKUP(A187,fin_institutions!A:D,3,0),"") -> 5 | G187: =IFERROR(VLOOKUP(A187,bus_institutions!A:D,3,0),0) -> 29 | H187: =IFERROR(VLOOKUP(A187,man_institutions!A:D,3,0),0) -> 26 | I187: =IFERROR(VLOOKUP(A187,eco_bus_institutions!A:D,4,0),0) -> 2.01 | J187: =IFERROR(VLOOKUP(A187,eco_institutions!A:D,4,0),0) -> 1.08 | K187: =IFERROR(VLOOKUP(A187,fin_institutions!A:D,4,0),0) -> 1.09 | L187: =IFERROR(VLOOKUP(A187,bus_institutions!A:D,4,0),0) -> 2.43 | M187: =IFERROR(VLOOKUP(A187,man_institutions!A:D,4,0),0) -> 2.35 | N187: =ROUND(IFERROR((601-_xlfn.RANK.EQ(I187,I:I))/600,0),3) -> 0.695 | O187: =ROUND(IFERROR((601-IFERROR(_xlfn.RANK.EQ(J187,J:J),""))/600,0),3) -> 0.323 | P187: =ROUND(IFERROR((601-IFERROR(_xlfn.RANK.EQ(K187,K:K),""))/600,0),3) -> 0.352 | Q187: =ROUND(IFERROR((601-IFERROR(_xlfn.RANK.EQ(L187,L:L),""))/600,0),3) -> 0.682 | R187: =ROUND(IFERROR((601-IFERROR(_xlfn.RANK.EQ(M187,M:M),""))/600,0),3) -> 0.753 | S187: =VLOOKUP(A187,#REF!,11,0) -> #REF! | T187: =VLOOKUP(A187,#REF!,12,0) -> #REF! | U187: =VLOOKUP(A187,#REF!,13,0) -> #REF! | V187: =VLOOKUP(A187,#REF!,14,0) -> #REF! | W187: 0.21963135 | X187: -1.3226525 | Y187: =VLOOKUP(C187,AR:AS,2,0) -> FRA | Z187: =IF(Y187=Y$1,B187,IF(Y187=Y$2,B187,"")) | AT187: 1.2068043 | AU187: 0.17682125 | AW187: emlyon business school
A188: University of Hong Kong | B188: Hong Kong | C188: HONG KONG | D188: =IFERROR(VLOOKUP(A188,eco_bus_institutions!A:D,3,0),"") -> 101 | E188: =IFERROR(VLOOKUP(A188,eco_institutions!A:D,3,0),"") -> 54 | F188: =IFERROR(VLOOKUP(A188,fin_institutions!A:D,3,0),"") -> 34 | G188: =IFERROR(VLOOKUP(A188,bus_institutions!A:D,3,0),0) -> 22 | H188: =IFERROR(VLOOKUP(A188,man_institutions!A:D,3,0),0) -> 25 | I188: =IFERROR(VLOOKUP(A188,eco_bus_institutions!A:D,4,0),0) -> 2.01 | J188: =IFERROR(VLOOKUP(A188,eco_institutions!A:D,4,0),0) -> 1.45 | K188: =IFERROR(VLOOKUP(A188,fin_institutions!A:D,4,0),0) -> 2.01 | L188: =IFERROR(VLOOKUP(A188,bus_institutions!A:D,4,0),0) -> 2.47 | M188: =IFERROR(VLOOKUP(A188,man_institutions!A:D,4,0),0) -> 1.78 | N188: =ROUND(IFERROR((601-_xlfn.RANK.EQ(I188,I:I))/600,0),3) -> 0.695 | O188: =ROUND(IFERROR((601-IFERROR(_xlfn.RANK.EQ(J188,J:J),""))/600,0),3) -> 0.663 | P188: =ROUND(IFERROR((601-IFERROR(_xlfn.RANK.EQ(K188,K:K),""))/600,0),3) -> 0.817 | Q188: =ROUND(IFERROR((601-IFERROR(_xlfn.RANK.EQ(L188,L:L),""))/600,0),3) -> 0.703 | R188: =ROUND(IFERROR((601-IFERROR(_xlfn.RANK.EQ(M188,M:M),""))/600,0),3) -> 0.603 | S188: =VLOOKUP(A188,#REF!,11,0) -> #REF! | T188: =VLOOKUP(A188,#REF!,12,0) -> #REF! | U188: =VLOOKUP(A188,#REF!,13,0) -> #REF! | V188: =VLOOKUP(A188,#REF!,14,0) -> #REF! | W188: 1.3323335 | X188: 0.28448204 | Y188: =VLOOKUP(C188,AR:AS,2,0) -> HKG | Z188: =IF(Y188=Y$1,B188,IF(Y188=Y$2,B188,"")) | AT188: 1.4307264 | AU188: 0.084137149 | AW188: Hong Kong
A189: Baruch College (CUNY) | B189: Baruch College | C189: USA | D189: =IFERROR(VLOOKUP(A189,eco_bus_institutions!A:D,3,0),"") -> 57 | E189: =IFERROR(VLOOKUP(A189,eco_institutions!A:D,3,0),"") -> 17 | F189: =IFERROR(VLOOKUP(A189,fin_institutions!A:D,3,0),"") -> 13 | G189: =IFERROR(VLOOKUP(A189,bus_institutions!A:D,3,0),0) -> 27 | H189: =IFERROR(VLOOKUP(A189,man_institutions!A:D,3,0),0) -> 18 | I189: =IFERROR(VLOOKUP(A189,eco_bus_institutions!A:D,4,0),0) -> 2 | J189: =IFERROR(VLOOKUP(A189,eco_institutions!A:D,4,0),0) -> 1.47 | K189: =IFERROR(VLOOKUP(A189,fin_institutions!A:D,4,0),0) -> 1.55 | L189: =IFERROR(VLOOKUP(A189,bus_institutions!A:D,4,0),0) -> 2.47 | M189: =IFERROR(VLOOKUP(A189,man_institutions!A:D,4,0),0) -> 1.82 | N189: =ROUND(IFERROR((601-_xlfn.RANK.EQ(I189,I:I))/600,0),3) -> 0.692 | O189: =ROUND(IFERROR((601-IFERROR(_xlfn.RANK.EQ(J189,J:J),""))/600,0),3) -> 0.68 | P189: =ROUND(IFERROR((601-IFERROR(_xlfn.RANK.EQ(K189,K:K),""))/600,0),3) -> 0.715 | Q189: =ROUND(IFERROR((601-IFERROR(_xlfn.RANK.EQ(L189,L:L),""))/600,0),3) -> 0.703 | R189: =ROUND(IFERROR((601-IFERROR(_xlfn.RANK.EQ(M189,M:M),""))/600,0),3) -> 0.617 | S189: =VLOOKUP(A189,#REF!,11,0) -> #REF! | T189: =VLOOKUP(A189,#REF!,12,0) -> #REF! | U189: =VLOOKUP(A189,#REF!,13,0) -> #REF! | V189: =VLOOKUP(A189,#REF!,14,0) -> #REF! | W189: 1.2068043 | X189: 0.17682125 | Y189: =VLOOKUP(C189,AR:AS,2,0) -> USA | Z189: =IF(Y189=Y$1,B189,IF(Y189=Y$2,B189,"")) | AT189: 1.2068043 | AU189: 0.17682125 | AW189: Baruch College (CUNY)
A190: Chapman University | B190: Chapman | C190: USA | D190: =IFERROR(VLOOKUP(A190,eco_bus_institutions!A:D,3,0),"") -> 40 | E190: =IFERROR(VLOOKUP(A190,eco_institutions!A:D,3,0),"") -> 30 | F190: =IFERROR(VLOOKUP(A190,fin_institutions!A:D,3,0),"") -> 5 | G190: =IFERROR(VLOOKUP(A190,bus_institutions!A:D,3,0),0) -> 5 | H190: =IFERROR(VLOOKUP(A190,man_institutions!A:D,3,0),0) -> 4 | I190: =IFERROR(VLOOKUP(A190,eco_bus_institutions!A:D,4,0),0) -> 2 | J190: =IFERROR(VLOOKUP(A190,eco_institutions!A:D,4,0),0) -> 1.76 | K190: =IFERROR(VLOOKUP(A190,fin_institutions!A:D,4,0),0) -> 1.3 | L190: =IFERROR(VLOOKUP(A190,bus_institutions!A:D,4,0),0) -> 2.75 | M190: =IFERROR(VLOOKUP(A190,man_institutions!A:D,4,0),0) -> 2.07 | N190: =ROUND(IFERROR((601-_xlfn.RANK.EQ(I190,I:I))/600,0),3) -> 0.692 | O190: =ROUND(IFERROR((601-IFERROR(_xlfn.RANK.EQ(J190,J:J),""))/600,0),3) -> 0.782 | P190: =ROUND(IFERROR((601-IFERROR(_xlfn.RANK.EQ(K190,K:K),""))/600,0),3) -> 0.61 | Q190: =ROUND(IFERROR((601-IFERROR(_xlfn.RANK.EQ(L190,L:L),""))/600,0),3) -> 0.765 | R190: =ROUND(IFERROR((601-IFERROR(_xlfn.RANK.EQ(M190,M:M),""))/600,0),3) -> 0.688 | S190: =VLOOKUP(A190,#REF!,11,0) -> #REF! | T190: =VLOOKUP(A190,#REF!,12,0) -> #REF! | U190: =VLOOKUP(A190,#REF!,13,0) -> #REF! | V190: =VLOOKUP(A190,#REF!,14,0) -> #REF! | W190: 1.4307264 | X190: 0.084137149 | Y190: =VLOOKUP(C190,AR:AS,2,0) -> USA | Z190: =IF(Y190=Y$1,B190,IF(Y190=Y$2,B190,"")) | AT190: 1.5672347 | AU190: 0.18932614 | AW190: Chapman
... A233: University of Hamburg | B233: Hamburg | C233: GERMANY | D233: =IFERROR(VLOOKUP(A233,eco_bus_institutions!A:D,3,0),"") -> 89 | E233: =IFERROR(VLOOKUP(A233,eco_institutions!A:D,3,0),"") -> 48 | F233: =IFERROR(VLOOKUP(A233,fin_institutions!A:D,3,0),"") -> 13 | G233: =IFERROR(VLOOKUP(A233,bus_institutions!A:D,3,0),0) -> 23 | H233: =IFERROR(VLOOKUP(A233,man_institutions!A:D,3,0),0) -> 17 | I233: =IFERROR(VLOOKUP(A233,eco_bus_institutions!A:D,4,0),0) -> 1.83 | J233: =IFERROR(VLOOKUP(A233,eco_institutions!A:D,4,0),0) -> 1.12 | K233: =IFERROR(VLOOKUP(A233,fin_institutions!A:D,4,0),0) -> 1.11 | L233: =IFERROR(VLOOKUP(A233,bus_institutions!A:D,4,0),0) -> 3.43 | M233: =IFERROR(VLOOKUP(A233,man_institutions!A:D,4,0),0) -> 3.47 | N233: =ROUND(IFERROR((601-_xlfn.RANK.EQ(I233,I:I))/600,0),3) -> 0.622 | O233: =ROUND(IFERROR((601-IFERROR(_xlfn.RANK.EQ(J233,J:J),""))/600,0),3) -> 0.425 | P233: =ROUND(IFERROR((601-IFERROR(_xlfn.RANK.EQ(K233,K:K),""))/600,0),3) -> 0.395 | Q233: =ROUND(IFERROR((601-IFERROR(_xlfn.RANK.EQ(L233,L:L),""))/600,0),3) -> 0.853 | R233: =ROUND(IFERROR((601-IFERROR(_xlfn.RANK.EQ(M233,M:M),""))/600,0),3) -> 0.9 | S233: =VLOOKUP(A233,#REF!,11,0) -> #REF! | T233: =VLOOKUP(A233,#REF!,12,0) -> #REF! | U233: =VLOOKUP(A233,#REF!,13,0) -> #REF! | V233: =VLOOKUP(A233,#REF!,14,0) -> #REF! | W233: 1.0443896 | X233: -1.5237263 | Y233: =VLOOKUP(C233,AR:AS,2,0) -> DEU | Z233: =IF(Y233=Y$1,B233,IF(Y233=Y$2,B233,"")) | AT233: 1.0265367 | AU233: -0.016692764 | AW233: Hamburg
A234: University of Sussex | B234: Sussex | C234: ENGLAND | D234: =IFERROR(VLOOKUP(A234,eco_bus_institutions!A:D,3,0),"") -> 128 | E234: =IFERROR(VLOOKUP(A234,eco_institutions!A:D,3,0),"") -> 49 | F234: =IFERROR(VLOOKUP(A234,fin_institutions!A:D,3,0),"") -> 19 | G234: =IFERROR(VLOOKUP(A234,bus_institutions!A:D,3,0),0) -> 43 | H234: =IFERROR(VLOOKUP(A234,man_institutions!A:D,3,0),0) -> 44 | I234: =IFERROR(VLOOKUP(A234,eco_bus_institutions!A:D,4,0),0) -> 1.83 | J234: =IFERROR(VLOOKUP(A234,eco_institutions!A:D,4,0),0) -> 1.65 | K234: =IFERROR(VLOOKUP(A234,fin_institutions!A:D,4,0),0) -> 1.08 | L234: =IFERROR(VLOOKUP(A234,bus_institutions!A:D,4,0),0) -> 1.94 | M234: =IFERROR(VLOOKUP(A234,man_institutions!A:D,4,0),0) -> 1.95 | N234: =ROUND(IFERROR((601-_xlfn.RANK.EQ(I234,I:I))/600,0),3) -> 0.622 | O234: =ROUND(IFERROR((601-IFERROR(_xlfn.RANK.EQ(J234,J:J),""))/600,0),3) -> 0.742 | P234: =ROUND(IFERROR((601-IFERROR(_xlfn.RANK.EQ(K234,K:K),""))/600,0),3) -> 0.318 | Q234: =ROUND(IFERROR((601-IFERROR(_xlfn.RANK.EQ(L234,L:L),""))/600,0),3) -> 0.548 | R234: =ROUND(IFERROR((601-IFERROR(_xlfn.RANK.EQ(M234,M:M),""))/600,0),3) -> 0.652 | S234: 1 | T234: =VLOOKUP(A234,#REF!,12,0) -> #REF! | U234: =VLOOKUP(A234,#REF!,13,0) -> #REF! | V234: =VLOOKUP(A234,#REF!,14,0) -> #REF! | W234: 0.38954083 | X234: 0.026394347 | Y234: =VLOOKUP(C234,AR:AS,2,0) -> UK | Z234: =IF(Y234=Y$1,B234,IF(Y234=Y$2,B234,"")) | AT234: -1.6119436 | AU234: 1.8896558 | AW234: Sussex
A235: American University | B235: American | C235: USA | D235: =IFERROR(VLOOKUP(A235,eco_bus_institutions!A:D,3,0),"") -> 75 | E235: =IFERROR(VLOOKUP(A235,eco_institutions!A:D,3,0),"") -> 43 | F235: =IFERROR(VLOOKUP(A235,fin_institutions!A:D,3,0),"") -> 14 | G235: =IFERROR(VLOOKUP(A235,bus_institutions!A:D,3,0),0) -> 22 | H235: =IFERROR(VLOOKUP(A235,man_institutions!A:D,3,0),0) -> 22 | I235: =IFERROR(VLOOKUP(A235,eco_bus_institutions!A:D,4,0),0) -> 1.82 | J235: =IFERROR(VLOOKUP(A235,eco_institutions!A:D,4,0),0) -> 1.35 | K235: =IFERROR(VLOOKUP(A235,fin_institutions!A:D,4,0),0) -> 1.37 | L235: =IFERROR(VLOOKUP(A235,bus_institutions!A:D,4,0),0) -> 2.66 | M235: =IFERROR(VLOOKUP(A235,man_institutions!A:D,4,0),0) -> 1.67 | N235: =ROUND(IFERROR((601-_xlfn.RANK.EQ(I235,I:I))/600,0),3) -> 0.615 | O235: =ROUND(IFERROR((601-IFERROR(_xlfn.RANK.EQ(J235,J:J),""))/600,0),3) -> 0.638 | P235: =ROUND(IFERROR((601-IFERROR(_xlfn.RANK.EQ(K235,K:K),""))/600,0),3) -> 0.647 | Q235: =ROUND(IFERROR((601-IFERROR(_xlfn.RANK.EQ(L235,L:L),""))/600,0),3) -> 0.743 | R235: =ROUND(IFERROR((601-IFERROR(_xlfn.RANK.EQ(M235,M:M),""))/600,0),3) -> 0.58 | S235: =VLOOKUP(A235,#REF!,11,0) -> #REF! | T235: =VLOOKUP(A235,#REF!,12,0) -> #REF! | U235: =VLOOKUP(A235,#REF!,13,0) -> #REF! | V235: =VLOOKUP(A235,#REF!,14,0) -> #REF! | W235: 1.0265367 | X235: -0.016692764 | Y235: =VLOOKUP(C235,AR:AS,2,0) -> USA | Z235: =IF(Y235=Y$1,B235,IF(Y235=Y$2,B235,"")) | AT235: 1.1236777 | AU235: -0.58210385 | AW235: American
A236: The World Bank | B236: The World Bank | C236: USA | D236: =IFERROR(VLOOKUP(A236,eco_bus_institutions!A:D,3,0),"") -> 165 | E236: =IFERROR(VLOOKUP(A236,eco_institutions!A:D,3,0),"") -> 148 | F236: =IFERROR(VLOOKUP(A236,fin_institutions!A:D,3,0),"") -> 32 | G236: =IFERROR(VLOOKUP(A236,bus_institutions!A:D,3,0),0) -> 0 | H236: =IFERROR(VLOOKUP(A236,man_institutions!A:D,3,0),0) -> 0 | I236: =IFERROR(VLOOKUP(A236,eco_bus_institutions!A:D,4,0),0) -> 1.82 | J236: =IFERROR(VLOOKUP(A236,eco_institutions!A:D,4,0),0) -> 1.83 | K236: =IFERROR(VLOOKUP(A236,fin_institutions!A:D,4,0),0) -> 1.07 | L236: =IFERROR(VLOOKUP(A236,bus_institutions!A:D,4,0),0) -> 0 | M236: =IFERROR(VLOOKUP(A236,man_institutions!A:D,4,0),0) -> 0 | N236: =ROUND(IFERROR((601-_xlfn.RANK.EQ(I236,I:I))/600,0),3) -> 0.615 | O236: =ROUND(IFERROR((601-IFERROR(_xlfn.RANK.EQ(J236,J:J),""))/600,0),3) -> 0.8 | P236: =ROUND(IFERROR((601-IFERROR(_xlfn.RANK.EQ(K236,K:K),""))/600,0),3) -> 0.295 | Q236: =ROUND(IFERROR((601-IFERROR(_xlfn.RANK.EQ(L236,L:L),""))/600,0),3) -> 0.05 | R236: =ROUND(IFERROR((601-IFERROR(_xlfn.RANK.EQ(M236,M:M),""))/600,0),3) -> 0.04 | S236: =VLOOKUP(A236,#REF!,11,0) -> #REF! | T236: =VLOOKUP(A236,#REF!,12,0) -> #REF! | U236: =VLOOKUP(A236,#REF!,13,0) -> #REF! | V236: =VLOOKUP(A236,#REF!,14,0) -> #REF! | W236: -1.6119436 | X236: 1.8896558 | Y236: =VLOOKUP(C236,AR:AS,2,0) -> USA | Z236: =IF(Y236=Y$1,B236,IF(Y236=Y$2,B236,"")) | AT236: 1.1760037 | AU236: 0.11539879 | AW236: The World Bank
A237: University of South Florida | B237: South Florida | C237: USA | D237: =IFERROR(VLOOKUP(A237,eco_bus_institutions!A:D,3,0),"") -> 63 | E237: =IFERROR(VLOOKUP(A237,eco_institutions!A:D,3,0),"") -> 12 | F237: =IFERROR(VLOOKUP(A237,fin_institutions!A:D,3,0),"") -> 15 | G237: =IFERROR(VLOOKUP(A237,bus_institutions!A:D,3,0),0) -> 20 | H237: =IFERROR(VLOOKUP(A237,man_institutions!A:D,3,0),0) -> 33 | I237: =IFERROR(VLOOKUP(A237,eco_bus_institutions!A:D,4,0),0) -> 1.82 | J237: =IFERROR(VLOOKUP(A237,eco_institutions!A:D,4,0),0) -> 1.18 | K237: =IFERROR(VLOOKUP(A237,fin_institutions!A:D,4,0),0) -> 1.42 | L237: =IFERROR(VLOOKUP(A237,bus_institutions!A:D,4,0),0) -> 2.68 | M237: =IFERROR(VLOOKUP(A237,man_institutions!A:D,4,0),0) -> 2.23 | N237: =ROUND(IFERROR((601-_xlfn.RANK.EQ(I237,I:I))/600,0),3) -> 0.615 | O237: =ROUND(IFERROR((601-IFERROR(_xlfn.RANK.EQ(J237,J:J),""))/600,0),3) -> 0.498 | P237: =ROUND(IFERROR((601-IFERROR(_xlfn.RANK.EQ(K237,K:K),""))/600,0),3) -> 0.663 | Q237: =ROUND(IFERROR((601-IFERROR(_xlfn.RANK.EQ(L237,L:L),""))/600,0),3) -> 0.75 | R237: =ROUND(IFERROR((601-IFERROR(_xlfn.RANK.EQ(M237,M:M),""))/600,0),3) -> 0.73 | S237: =VLOOKUP(A237,#REF!,11,0) -> #REF! | T237: =VLOOKUP(A237,#REF!,12,0) -> #REF! | U237: =VLOOKUP(A237,#REF!,13,0) -> #REF! | V237: =VLOOKUP(A237,#REF!,14,0) -> #REF! | W237: 1.1236777 | X237: -0.58210385 | Y237: =VLOOKUP(C237,AR:AS,2,0) -> USA | Z237: =IF(Y237=Y$1,B237,IF(Y237=Y$2,B237,"")) | AT237: -1.4173625 | AU237: 1.7097345 | AW237: South Florida
A238: Utah State University | B238: Utah State | C238: USA | D238: =IFERROR(VLOOKUP(A238,eco_bus_institutions!A:D,3,0),"") -> 61 | E238: =IFERROR(VLOOKUP(A238,eco_institutions!A:D,3,0),"") -> 36 | F238: =IFERROR(VLOOKUP(A238,fin_institutions!A:D,3,0),"") -> 15 | G238: =IFERROR(VLOOKUP(A238,bus_institutions!A:D,3,0),0) -> 11 | H238: =IFERROR(VLOOKUP(A238,man_institutions!A:D,3,0),0) -> 16 | I238: =IFERROR(VLOOKUP(A238,eco_bus_institutions!A:D,4,0),0) -> 1.81 | J238: =IFERROR(VLOOKUP(A238,eco_institutions!A:D,4,0),0) -> 1.67 | K238: =IFERROR(VLOOKUP(A238,fin_institutions!A:D,4,0),0) -> 1.28 | L238: =IFERROR(VLOOKUP(A238,bus_institutions!A:D,4,0),0) -> 2.51 | M238: =IFERROR(VLOOKUP(A238,man_institutions!A:D,4,0),0) -> 1.94 | N238: =ROUND(IFERROR((601-_xlfn.RANK.EQ(I238,I:I))/600,0),3) -> 0.61 | O238: =ROUND(IFERROR((601-IFERROR(_xlfn.RANK.EQ(J238,J:J),""))/600,0),3) -> 0.745 | P238: =ROUND(IFERROR((601-IFERROR(_xlfn.RANK.EQ(K238,K:K),""))/600,0),3) -> 0.593 | Q238: =ROUND(IFERROR((601-IFERROR(_xlfn.RANK.EQ(L238,L:L),""))/600,0),3) -> 0.713 | R238: =ROUND(IFERROR((601-IFERROR(_xlfn.RANK.EQ(M238,M:M),""))/600,0),3) -> 0.65 | S238: =VLOOKUP(A238,#REF!,11,0) -> #REF! | T238: =VLOOKUP(A238,#REF!,12,0) -> #REF! | U238: =VLOOKUP(A238,#REF!,13,0) -> #REF! | V238: =VLOOKUP(A238,#REF!,14,0) -> #REF! | W238: 1.1760037 | X238: 0.11539879 | Y238: =VLOOKUP(C238,AR:AS,2,0) -> USA | Z238: =IF(Y238=Y$1,B238,IF(Y238=Y$2,B238,"")) | AT238: 0.77230949 | AU238: 1.1096388 | AW238: Utah State
A239: Charles University Prague | B239: Charles Prague | C239: CZECH REPUBLIC | D239: =IFERROR(VLOOKUP(A239,eco_bus_institutions!A:D,3,0),"") -> 86 | E239: =IFERROR(VLOOKUP(A239,eco_institutions!A:D,3,0),"") -> 72 | F239: =IFERROR(VLOOKUP(A239,fin_institutions!A:D,3,0),"") -> 20 | G239: =IFERROR(VLOOKUP(A239,bus_institutions!A:D,3,0),0) -> 5 | H239: =IFERROR(VLOOKUP(A239,man_institutions!A:D,3,0),0) -> 5 | I239: =IFERROR(VLOOKUP(A239,eco_bus_institutions!A:D,4,0),0) -> 1.8 | J239: =IFERROR(VLOOKUP(A239,eco_institutions!A:D,4,0),0) -> 1.81 | K239: =IFERROR(VLOOKUP(A239,fin_institutions!A:D,4,0),0) -> 1.07 | L239: =IFERROR(VLOOKUP(A239,bus_institutions!A:D,4,0),0) -> 1.19 | M239: =IFERROR(VLOOKUP(A239,man_institutions!A:D,4,0),0) -> 1.02 | N239: =ROUND(IFERROR((601-_xlfn.RANK.EQ(I239,I:I))/600,0),3) -> 0.608 | O239: =ROUND(IFERROR((601-IFERROR(_xlfn.RANK.EQ(J239,J:J),""))/600,0),3) -> 0.797 | P239: =ROUND(IFERROR((601-IFERROR(_xlfn.RANK.EQ(K239,K:K),""))/600,0),3) -> 0.295 | Q239: =ROUND(IFERROR((601-IFERROR(_xlfn.RANK.EQ(L239,L:L),""))/600,0),3) -> 0.148 | R239: =ROUND(IFERROR((601-IFERROR(_xlfn.RANK.EQ(M239,M:M),""))/600,0),3) -> 0.05 | S239: =VLOOKUP(A239,#REF!,11,0) -> #REF! | T239: =VLOOKUP(A239,#REF!,12,0) -> #REF! | U239: =VLOOKUP(A239,#REF!,13,0) -> #REF! | V239: =VLOOKUP(A239,#REF!,14,0) -> #REF! | W239: -1.4173625 | X239: 1.7097345 | Y239: =VLOOKUP(C239,AR:AS,2,0) -> CZE | Z239: =IF(Y239=Y$1,B239,IF(Y239=Y$2,B239,"")) | AT239: 0.99042617 | AU239: -0.053248266 | AW239: Charles Prague
A240: City University of Hong Kong | B240: City Hong Kong | C240: HONG KONG | D240: =IFERROR(VLOOKUP(A240,eco_bus_institutions!A:D,3,0),"") -> 133 | E240: =IFERROR(VLOOKUP(A240,eco_institutions!A:D,3,0),"") -> 43 | F240: =IFERROR(VLOOKUP(A240,fin_institutions!A:D,3,0),"") -> 37 | G240: =IFERROR(VLOOKUP(A240,bus_institutions!A:D,3,0),0) -> 47 | H240: =IFERROR(VLOOKUP(A240,man_institutions!A:D,3,0),0) -> 38 | I240: =IFERROR(VLOOKUP(A240,eco_bus_institutions!A:D,4,0),0) -> 1.8 | J240: =IFERROR(VLOOKUP(A240,eco_institutions!A:D,4,0),0) -> 1.57 | K240: =IFERROR(VLOOKUP(A240,fin_institutions!A:D,4,0),0) -> 2.48 | L240: =IFERROR(VLOOKUP(A240,bus_institutions!A:D,4,0),0) -> 1.74 | M240: =IFERROR(VLOOKUP(A240,man_institutions!A:D,4,0),0) -> 1.45 | N240: =ROUND(IFERROR((601-_xlfn.RANK.EQ(I240,I:I))/600,0),3) -> 0.608 | O240: =ROUND(IFERROR((601-IFERROR(_xlfn.RANK.EQ(J240,J:J),""))/600,0),3) -> 0.725 | P240: =ROUND(IFERROR((601-IFERROR(_xlfn.RANK.EQ(K240,K:K),""))/600,0),3) -> 0.857 | Q240: =ROUND(IFERROR((601-IFERROR(_xlfn.RANK.EQ(L240,L:L),""))/600,0),3) -> 0.462 | R240: =ROUND(IFERROR((601-IFERROR(_xlfn.RANK.EQ(M240,M:M),""))/600,0),3) -> 0.45 | S240: =VLOOKUP(A240,#REF!,11,0) -> #REF! | T240: =VLOOKUP(A240,#REF!,12,0) -> #REF! | U240: =VLOOKUP(A240,#REF!,13,0) -> #REF! | V240: =VLOOKUP(A240,#REF!,14,0) -> #REF! | W240: 0.77230949 | X240: 1.1096388 | Y240: =VLOOKUP(C240,AR:AS,2,0) -> HKG | Z240: =IF(Y240=Y$1,B240,IF(Y240=Y$2,B240,"")) | AT240: 1.1442972 | AU240: -0.26092068 | AW240: City Hong Kong
A241: Ihsan Dogramaci Bilkent University | B241: Ihsan Dogramaci Bilkent | C241: TURKIYE | D241: =IFERROR(VLOOKUP(A241,eco_bus_institutions!A:D,3,0),"") -> 44 | E241: =IFERROR(VLOOKUP(A241,eco_institutions!A:D,3,0),"") -> 22 | F241: =IFERROR(VLOOKUP(A241,fin_institutions!A:D,3,0),"") -> 12 | G241: =IFERROR(VLOOKUP(A241,bus_institutions!A:D,3,0),0) -> 9 | H241: =IFERROR(VLOOKUP(A241,man_institutions!A:D,3,0),0) -> 11 | I241: =IFERROR(VLOOKUP(A241,eco_bus_institutions!A:D,4,0),0) -> 1.8 | J241: =IFERROR(VLOOKUP(A241,eco_institutions!A:D,4,0),0) -> 1.45 | K241: =IFERROR(VLOOKUP(A241,fin_institutions!A:D,4,0),0) -> 1.27 | L241: =IFERROR(VLOOKUP(A241,bus_institutions!A:D,4,0),0) -> 2.11 | M241: =IFERROR(VLOOKUP(A241,man_institutions!A:D,4,0),0) -> 2.3 | N241: =ROUND(IFERROR((601-_xlfn.RANK.EQ(I241,I:I))/600,0),3) -> 0.608 | O241: =ROUND(IFERROR((601-IFERROR(_xlfn.RANK.EQ(J241,J:J),""))/600,0),3) -> 0.663 | P241: =ROUND(IFERROR((601-IFERROR(_xlfn.RANK.EQ(K241,K:K),""))/600,0),3) -> 0.585 | Q241: =ROUND(IFERROR((601-IFERROR(_xlfn.RANK.EQ(L241,L:L),""))/600,0),3) -> 0.603 | R241: =ROUND(IFERROR((601-IFERROR(_xlfn.RANK.EQ(M241,M:M),""))/600,0),3) -> 0.737 | S241: =VLOOKUP(A241,#REF!,11,0) -> #REF! | T241: =VLOOKUP(A241,#REF!,12,0) -> #REF! | U241: =VLOOKUP(A241,#REF!,13,0) -> #REF! | V241: =VLOOKUP(A241,#REF!,14,0) -> #REF! | W241: 0.99042617 | X241: -0.053248266 | Y241: =VLOOKUP(C241,AR:AS,2,0) -> TUR | Z241: =IF(Y241=Y$1,B241,IF(Y241=Y$2,B241,"")) | AT241: 1.3057484 | AU241: 0.24215062 | AW241: Ihsan Dogramaci Bilkent
A242: Maastricht University | B242: Maastricht | C242: NETHERLANDS | D242: =IFERROR(VLOOKUP(A242,eco_bus_institutions!A:D,3,0),"") -> 139 | E242: =IFERROR(VLOOKUP(A242,eco_institutions!A:D,3,0),"") -> 86 | F242: =IFERROR(VLOOKUP(A242,fin_institutions!A:D,3,0),"") -> 12 | G242: =IFERROR(VLOOKUP(A242,bus_institutions!A:D,3,0),0) -> 34 | H242: =IFERROR(VLOOKUP(A242,man_institutions!A:D,3,0),0) -> 48 | I242: =IFERROR(VLOOKUP(A242,eco_bus_institutions!A:D,4,0),0) -> 1.8 | J242: =IFERROR(VLOOKUP(A242,eco_institutions!A:D,4,0),0) -> 1.23 | K242: =IFERROR(VLOOKUP(A242,fin_institutions!A:D,4,0),0) -> 1.56 | L242: =IFERROR(VLOOKUP(A242,bus_institutions!A:D,4,0),0) -> 3.33 | M242: =IFERROR(VLOOKUP(A242,man_institutions!A:D,4,0),0) -> 1.64 | N242: =ROUND(IFERROR((601-_xlfn.RANK.EQ(I242,I:I))/600,0),3) -> 0.608 | O242: =ROUND(IFERROR((601-IFERROR(_xlfn.RANK.EQ(J242,J:J),""))/600,0),3) -> 0.548 | P242: =ROUND(IFERROR((601-IFERROR(_xlfn.RANK.EQ(K242,K:K),""))/600,0),3) -> 0.72 | Q242: =ROUND(IFERROR((601-IFERROR(_xlfn.RANK.EQ(L242,L:L),""))/600,0),3) -> 0.835 | R242: =ROUND(IFERROR((601-IFERROR(_xlfn.RANK.EQ(M242,M:M),""))/600,0),3) -> 0.56 | S242: =VLOOKUP(A242,#REF!,11,0) -> #REF! | T242: =VLOOKUP(A242,#REF!,12,0) -> #REF! | U242: =VLOOKUP(A242,#REF!,13,0) -> #REF! | V242: =VLOOKUP(A242,#REF!,14,0) -> #REF! | W242: 1.1442972 | X242: -0.26092068 | Y242: =VLOOKUP(C242,AR:AS,2,0) -> NED | Z242: =IF(Y242=Y$1,B242,IF(Y242=Y$2,B242,"")) | AT242: 1.4139619 | AU242: 0.10508655 | AW242: Maastricht
A243: University of Memphis | B243: Memphis | C243: USA | D243: =IFERROR(VLOOKUP(A243,eco_bus_institutions!A:D,3,0),"") -> 49 | E243: =IFERROR(VLOOKUP(A243,eco_institutions!A:D,3,0),"") -> 12 | F243: =IFERROR(VLOOKUP(A243,fin_institutions!A:D,3,0),"") -> 21 | G243: =IFERROR(VLOOKUP(A243,bus_institutions!A:D,3,0),0) -> 15 | H243: =IFERROR(VLOOKUP(A243,man_institutions!A:D,3,0),0) -> 15 | I243: =IFERROR(VLOOKUP(A243,eco_bus_institutions!A:D,4,0),0) -> 1.8 | J243: =IFERROR(VLOOKUP(A243,eco_institutions!A:D,4,0),0) -> 1.73 | K243: =IFERROR(VLOOKUP(A243,fin_institutions!A:D,4,0),0) -> 1.36 | L243: =IFERROR(VLOOKUP(A243,bus_institutions!A:D,4,0),0) -> 2.07 | M243: =IFERROR(VLOOKUP(A243,man_institutions!A:D,4,0),0) -> 2.42 | N243: =ROUND(IFERROR((601-_xlfn.RANK.EQ(I243,I:I))/600,0),3) -> 0.608 | O243: =ROUND(IFERROR((601-IFERROR(_xlfn.RANK.EQ(J243,J:J),""))/600,0),3) -> 0.772 | P243: =ROUND(IFERROR((601-IFERROR(_xlfn.RANK.EQ(K243,K:K),""))/600,0),3) -> 0.64 | Q243: =ROUND(IFERROR((601-IFERROR(_xlfn.RANK.EQ(L243,L:L),""))/600,0),3) -> 0.592 | R243: =ROUND(IFERROR((601-IFERROR(_xlfn.RANK.EQ(M243,M:M),""))/600,0),3) -> 0.773 | S243: =VLOOKUP(A243,#REF!,11,0) -> #REF! | T243: =VLOOKUP(A243,#REF!,12,0) -> #REF! | U243: =VLOOKUP(A243,#REF!,13,0) -> #REF! | V243: =VLOOKUP(A243,#REF!,14,0) -> #REF! | W243: 1.3057484 | X243: 0.24215062 | Y243: =VLOOKUP(C243,AR:AS,2,0) -> USA | Z243: =IF(Y243=Y$1,B243,IF(Y243=Y$2,B243,"")) | AT243: 0.29049205 | AU243: 1.3735001 | AW243: Memphis
A244: Bentley University | B244: Bentley | C244: USA | D244: =IFERROR(VLOOKUP(A244,eco_bus_institutions!A:D,3,0),"") -> 51 | E244: =IFERROR(VLOOKUP(A244,eco_institutions!A:D,3,0),"") -> 18 | F244: =IFERROR(VLOOKUP(A244,fin_institutions!A:D,3,0),"") -> 18 | G244: =IFERROR(VLOOKUP(A244,bus_institutions!A:D,3,0),0) -> 18 | H244: =IFERROR(VLOOKUP(A244,man_institutions!A:D,3,0),0) -> 12 | I244: =IFERROR(VLOOKUP(A244,eco_bus_institutions!A:D,4,0),0) -> 1.79 | J244: =IFERROR(VLOOKUP(A244,eco_institutions!A:D,4,0),0) -> 1.34 | K244: =IFERROR(VLOOKUP(A244,fin_institutions!A:D,4,0),0) -> 2.07 | L244: =IFERROR(VLOOKUP(A244,bus_institutions!A:D,4,0),0) -> 2.28 | M244: =IFERROR(VLOOKUP(A244,man_institutions!A:D,4,0),0) -> 2.19 | N244: =ROUND(IFERROR((601-_xlfn.RANK.EQ(I244,I:I))/600,0),3) -> 0.6 | O244: =ROUND(IFERROR((601-IFERROR(_xlfn.RANK.EQ(J244,J:J),""))/600,0),3) -> 0.627 | P244: =ROUND(IFERROR((601-IFERROR(_xlfn.RANK.EQ(K244,K:K),""))/600,0),3) -> 0.825 | Q244: =ROUND(IFERROR((601-IFERROR(_xlfn.RANK.EQ(L244,L:L),""))/600,0),3) -> 0.648 | R244: =ROUND(IFERROR((601-IFERROR(_xlfn.RANK.EQ(M244,M:M),""))/600,0),3) -> 0.725 | S244: =VLOOKUP(A244,#REF!,11,0) -> #REF! | T244: =VLOOKUP(A244,#REF!,12,0) -> #REF! | U244: =VLOOKUP(A244,#REF!,13,0) -> #REF! | V244: =VLOOKUP(A244,#REF!,14,0) -> #REF! | W244: 1.4139619 | X244: 0.10508655 | Y244: =VLOOKUP(C244,AR:AS,2,0) -> USA | Z244: =IF(Y244=Y$1,B244,IF(Y244=Y$2,B244,"")) | AT244: 0.5178484 | AU244: 1.178727 | AW244: Bentley
A245: Humboldt University of Berlin | B245: Humboldt Berlin | C245: GERMANY | D245: =IFERROR(VLOOKUP(A245,eco_bus_institutions!A:D,3,0),"") -> 58 | E245: =IFERROR(VLOOKUP(A245,eco_institutions!A:D,3,0),"") -> 45 | F245: =IFERROR(VLOOKUP(A245,fin_institutions!A:D,3,0),"") -> 12 | G245: =IFERROR(VLOOKUP(A245,bus_institutions!A:D,3,0),0) -> 3 | H245: =IFERROR(VLOOKUP(A245,man_institutions!A:D,3,0),0) -> 8 | I245: =IFERROR(VLOOKUP(A245,eco_bus_institutions!A:D,4,0),0) -> 1.79 | J245: =IFERROR(VLOOKUP(A245,eco_institutions!A:D,4,0),0) -> 1.39 | K245: =IFERROR(VLOOKUP(A245,fin_institutions!A:D,4,0),0) -> 3.13 | L245: =IFERROR(VLOOKUP(A245,bus_institutions!A:D,4,0),0) -> 1.11 | M245: =IFERROR(VLOOKUP(A245,man_institutions!A:D,4,0),0) -> 1.66 | N245: =ROUND(IFERROR((601-_xlfn.RANK.EQ(I245,I:I))/600,0),3) -> 0.6 | O245: =ROUND(IFERROR((601-IFERROR(_xlfn.RANK.EQ(J245,J:J),""))/600,0),3) -> 0.65 | P245: =ROUND(IFERROR((601-IFERROR(_xlfn.RANK.EQ(K245,K:K),""))/600,0),3) -> 0.902 | Q245: =ROUND(IFERROR((601-IFERROR(_xlfn.RANK.EQ(L245,L:L),""))/600,0),3) -> 0.1 | R245: =ROUND(IFERROR((601-IFERROR(_xlfn.RANK.EQ(M245,M:M),""))/600,0),3) -> 0.572 | S245: =VLOOKUP(A245,#REF!,11,0) -> #REF! | T245: =VLOOKUP(A245,#REF!,12,0) -> #REF! | U245: =VLOOKUP(A245,#REF!,13,0) -> #REF! | V245: =VLOOKUP(A245,#REF!,14,0) -> #REF! | W245: 0.29049205 | X245: 1.3735001 | Y245: =VLOOKUP(C245,AR:AS,2,0) -> DEU | Z245: =IF(Y245=Y$1,B245,IF(Y245=Y$2,B245,"")) | AT245: 1.5872503 | AU245: 0.2656909 | AW245: Humboldt Berlin
A246: Monash University | B246: Monash | C246: AUSTRALIA | D246: =IFERROR(VLOOKUP(A246,eco_bus_institutions!A:D,3,0),"") -> 371 | E246: =IFERROR(VLOOKUP(A246,eco_institutions!A:D,3,0),"") -> 169 | F246: =IFERROR(VLOOKUP(A246,fin_institutions!A:D,3,0),"") -> 97 | G246: =IFERROR(VLOOKUP(A246,bus_institutions!A:D,3,0),0) -> 89 | H246: =IFERROR(VLOOKUP(A246,man_institutions!A:D,3,0),0) -> 74 | I246: =IFERROR(VLOOKUP(A246,eco_bus_institutions!A:D,4,0),0) -> 1.79 | J246: =IFERROR(VLOOKUP(A246,eco_institutions!A:D,4,0),0) -> 1.9 | K246: =IFERROR(VLOOKUP(A246,fin_institutions!A:D,4,0),0) -> 1.44 | L246: =IFERROR(VLOOKUP(A246,bus_institutions!A:D,4,0),0) -> 1.75 | M246: =IFERROR(VLOOKUP(A246,man_institutions!A:D,4,0),0) -> 1.38 | N246: =ROUND(IFERROR((601-_xlfn.RANK.EQ(I246,I:I))/600,0),3) -> 0.6 | O246: =ROUND(IFERROR((601-IFERROR(_xlfn.RANK.EQ(J246,J:J),""))/600,0),3) -> 0.818 | P246: =ROUND(IFERROR((601-IFERROR(_xlfn.RANK.EQ(K246,K:K),""))/600,0),3) -> 0.675 | Q246: =ROUND(IFERROR((601-IFERROR(_xlfn.RANK.EQ(L246,L:L),""))/600,0),3) -> 0.467 | R246: =ROUND(IFERROR((601-IFERROR(_xlfn.RANK.EQ(M246,M:M),""))/600,0),3) -> 0.4 | S246: =VLOOKUP(A246,#REF!,11,0) -> #REF! | T246: =VLOOKUP(A246,#REF!,12,0) -> #REF! | U246: =VLOOKUP(A246,#REF!,13,0) -> #REF! | V246: =VLOOKUP(A246,#REF!,14,0) -> #REF! | W246: 0.5178484 | X246: 1.178727 | Y246: =VLOOKUP(C246,AR:AS,2,0) -> AUS | Z246: =IF(Y246=Y$1,B246,IF(Y246=Y$2,B246,"")) -> Monash | AT246: 0.84954926 | AU246: 0.6499231 | AW246: Monash
... A278: Solent University | B278: Solent | C278: ENGLAND | D278: =IFERROR(VLOOKUP(A278,eco_bus_institutions!A:D,3,0),"") -> 80 | E278: =IFERROR(VLOOKUP(A278,eco_institutions!A:D,3,0),"") -> 14 | F278: =IFERROR(VLOOKUP(A278,fin_institutions!A:D,3,0),"") -> 36 | G278: =IFERROR(VLOOKUP(A278,bus_institutions!A:D,3,0),0) -> 30 | H278: =IFERROR(VLOOKUP(A278,man_institutions!A:D,3,0),0) -> 26 | I278: =IFERROR(VLOOKUP(A278,eco_bus_institutions!A:D,4,0),0) -> 1.71 | J278: =IFERROR(VLOOKUP(A278,eco_institutions!A:D,4,0),0) -> 1.09 | K278: =IFERROR(VLOOKUP(A278,fin_institutions!A:D,4,0),0) -> 1.33 | L278: =IFERROR(VLOOKUP(A278,bus_institutions!A:D,4,0),0) -> 1.69 | M278: =IFERROR(VLOOKUP(A278,man_institutions!A:D,4,0),0) -> 1.63 | N278: =ROUND(IFERROR((601-_xlfn.RANK.EQ(I278,I:I))/600,0),3) -> 0.552 | O278: =ROUND(IFERROR((601-IFERROR(_xlfn.RANK.EQ(J278,J:J),""))/600,0),3) -> 0.363 | P278: =ROUND(IFERROR((601-IFERROR(_xlfn.RANK.EQ(K278,K:K),""))/600,0),3) -> 0.625 | Q278: =ROUND(IFERROR((601-IFERROR(_xlfn.RANK.EQ(L278,L:L),""))/600,0),3) -> 0.438 | R278: =ROUND(IFERROR((601-IFERROR(_xlfn.RANK.EQ(M278,M:M),""))/600,0),3) -> 0.553 | S278: =VLOOKUP(A278,#REF!,11,0) -> #REF! | T278: =VLOOKUP(A278,#REF!,12,0) -> #REF! | U278: =VLOOKUP(A278,#REF!,13,0) -> #REF! | V278: =VLOOKUP(A278,#REF!,14,0) -> #REF! | W278: -0.060350785 | X278: -0.18241755 | Y278: =VLOOKUP(C278,AR:AS,2,0) -> UK | Z278: =IF(Y278=Y$1,B278,IF(Y278=Y$2,B278,"")) | AT278: 0.40584667 | AU278: -0.58955031 | AW278: Solent
A279: University of Munster | B279: Munster | C279: GERMANY | D279: =IFERROR(VLOOKUP(A279,eco_bus_institutions!A:D,3,0),"") -> 56 | E279: =IFERROR(VLOOKUP(A279,eco_institutions!A:D,3,0),"") -> 30 | F279: =IFERROR(VLOOKUP(A279,fin_institutions!A:D,3,0),"") -> 10 | G279: =IFERROR(VLOOKUP(A279,bus_institutions!A:D,3,0),0) -> 18 | H279: =IFERROR(VLOOKUP(A279,man_institutions!A:D,3,0),0) -> 15 | I279: =IFERROR(VLOOKUP(A279,eco_bus_institutions!A:D,4,0),0) -> 1.71 | J279: =IFERROR(VLOOKUP(A279,eco_institutions!A:D,4,0),0) -> 1.09 | K279: =IFERROR(VLOOKUP(A279,fin_institutions!A:D,4,0),0) -> 1.1 | L279: =IFERROR(VLOOKUP(A279,bus_institutions!A:D,4,0),0) -> 3.32 | M279: =IFERROR(VLOOKUP(A279,man_institutions!A:D,4,0),0) -> 1.46 | N279: =ROUND(IFERROR((601-_xlfn.RANK.EQ(I279,I:I))/600,0),3) -> 0.552 | O279: =ROUND(IFERROR((601-IFERROR(_xlfn.RANK.EQ(J279,J:J),""))/600,0),3) -> 0.363 | P279: =ROUND(IFERROR((601-IFERROR(_xlfn.RANK.EQ(K279,K:K),""))/600,0),3) -> 0.37 | Q279: =ROUND(IFERROR((601-IFERROR(_xlfn.RANK.EQ(L279,L:L),""))/600,0),3) -> 0.833 | R279: =ROUND(IFERROR((601-IFERROR(_xlfn.RANK.EQ(M279,M:M),""))/600,0),3) -> 0.455 | S279: 1 | T279: =VLOOKUP(A279,#REF!,12,0) -> #REF! | U279: =VLOOKUP(A279,#REF!,13,0) -> #REF! | V279: =VLOOKUP(A279,#REF!,14,0) -> #REF! | W279: 0.040695486 | X279: -0.9809529 | Y279: =VLOOKUP(C279,AR:AS,2,0) -> DEU | Z279: =IF(Y279=Y$1,B279,IF(Y279=Y$2,B279,"")) | AT279: 0.93602995 | AU279: -0.26744612 | AW279: Munster
